Workbook

Sheet Dashboard
A1: Demo Company Inc.
A2: FINANCIAL MODEL DASHBOARD · E£ (Egyptian Pound) · CONFIDENTIAL
A4: 📊 SCENARIO CONTROL
A5: Active Scenario | B5: Select Scenario →
A6: ▼ Scenario Selector | B6: Base Case | E6: =IF(B6="Base Case","Central planning — stable market | Revenue 10%→5% | COGS 60%",IF(B6="Optimistic","Optimistic case — strong execution | Revenue 15%→8% | COGS 55%","Conservative case — headwinds | Revenue 5%→2% | COGS 63%")) -> Central planning — stable market | Revenue 10%→5% | COGS 60%
A8: 📈 KEY METRICS — ACTIVE SCENARIO
B9: 2024 | C9: 2025 | D9: 2026E | E9: 2027E | F9: 2028E | G9: 2029E | H9: 2030E
A10: 📗 INCOME STATEMENT
A11: Revenue (E£) | B11: =IF(Dashboard!$B$6="Base Case",Scenarios!B67,IF(Dashboard!$B$6="Optimistic",Scenarios!B153,Scenarios!B239)) -> 850000 | C11: =IF(Dashboard!$B$6="Base Case",Scenarios!C67,IF(Dashboard!$B$6="Optimistic",Scenarios!C153,Scenarios!C239)) -> 950000 | D11: =IF(Dashboard!$B$6="Base Case",Scenarios!D67,IF(Dashboard!$B$6="Optimistic",Scenarios!D153,Scenarios!D239)) -> 1045000 | E11: =IF(Dashboard!$B$6="Base Case",Scenarios!E67,IF(Dashboard!$B$6="Optimistic",Scenarios!E153,Scenarios!E239)) -> 1128600 | F11: =IF(Dashboard!$B$6="Base Case",Scenarios!F67,IF(Dashboard!$B$6="Optimistic",Scenarios!F153,Scenarios!F239)) -> 1207602 | G11: =IF(Dashboard!$B$6="Base Case",Scenarios!G67,IF(Dashboard!$B$6="Optimistic",Scenarios!G153,Scenarios!G239)) -> 1280058.1 | H11: =IF(Dashboard!$B$6="Base Case",Scenarios!H67,IF(Dashboard!$B$6="Optimistic",Scenarios!H153,Scenarios!H239)) -> 1344061
A12: Revenue Growth % | B12: =IF(Dashboard!$B$6="Base Case",Scenarios!B68,IF(Dashboard!$B$6="Optimistic",Scenarios!B154,Scenarios!B240)) -> 0 | C12: =IF(Dashboard!$B$6="Base Case",Scenarios!C68,IF(Dashboard!$B$6="Optimistic",Scenarios!C154,Scenarios!C240)) -> 0.11764706 | D12: =IF(Dashboard!$B$6="Base Case",Scenarios!D68,IF(Dashboard!$B$6="Optimistic",Scenarios!D154,Scenarios!D240)) -> 0.1 | E12: =IF(Dashboard!$B$6="Base Case",Scenarios!E68,IF(Dashboard!$B$6="Optimistic",Scenarios!E154,Scenarios!E240)) -> 0.08 | F12: =IF(Dashboard!$B$6="Base Case",Scenarios!F68,IF(Dashboard!$B$6="Optimistic",Scenarios!F154,Scenarios!F240)) -> 0.07 | G12: =IF(Dashboard!$B$6="Base Case",Scenarios!G68,IF(Dashboard!$B$6="Optimistic",Scenarios!G154,Scenarios!G240)) -> 0.06 | H12: =IF(Dashboard!$B$6="Base Case",Scenarios!H68,IF(Dashboard!$B$6="Optimistic",Scenarios!H154,Scenarios!H240)) -> 0.05
A13: Gross Profit (E£) | B13: =IF(Dashboard!$B$6="Base Case",Scenarios!B69,IF(Dashboard!$B$6="Optimistic",Scenarios!B155,Scenarios!B241)) -> 340000 | C13: =IF(Dashboard!$B$6="Base Case",Scenarios!C69,IF(Dashboard!$B$6="Optimistic",Scenarios!C155,Scenarios!C241)) -> 380000 | D13: =IF(Dashboard!$B$6="Base Case",Scenarios!D69,IF(Dashboard!$B$6="Optimistic",Scenarios!D155,Scenarios!D241)) -> 418000 | E13: =IF(Dashboard!$B$6="Base Case",Scenarios!E69,IF(Dashboard!$B$6="Optimistic",Scenarios!E155,Scenarios!E241)) -> 451440 | F13: =IF(Dashboard!$B$6="Base Case",Scenarios!F69,IF(Dashboard!$B$6="Optimistic",Scenarios!F155,Scenarios!F241)) -> 483040.8 | G13: =IF(Dashboard!$B$6="Base Case",Scenarios!G69,IF(Dashboard!$B$6="Optimistic",Scenarios!G155,Scenarios!G241)) -> 512023.25 | H13: =IF(Dashboard!$B$6="Base Case",Scenarios!H69,IF(Dashboard!$B$6="Optimistic",Scenarios!H155,Scenarios!H241)) -> 537624.41
A14: Gross Margin % | B14: =IF(Dashboard!$B$6="Base Case",Scenarios!B70,IF(Dashboard!$B$6="Optimistic",Scenarios!B156,Scenarios!B242)) -> 0.4 | C14: =IF(Dashboard!$B$6="Base Case",Scenarios!C70,IF(Dashboard!$B$6="Optimistic",Scenarios!C156,Scenarios!C242)) -> 0.4 | D14: =IF(Dashboard!$B$6="Base Case",Scenarios!D70,IF(Dashboard!$B$6="Optimistic",Scenarios!D156,Scenarios!D242)) -> 0.4 | E14: =IF(Dashboard!$B$6="Base Case",Scenarios!E70,IF(Dashboard!$B$6="Optimistic",Scenarios!E156,Scenarios!E242)) -> 0.4 | F14: =IF(Dashboard!$B$6="Base Case",Scenarios!F70,IF(Dashboard!$B$6="Optimistic",Scenarios!F156,Scenarios!F242)) -> 0.4 | G14: =IF(Dashboard!$B$6="Base Case",Scenarios!G70,IF(Dashboard!$B$6="Optimistic",Scenarios!G156,Scenarios!G242)) -> 0.4 | H14: =IF(Dashboard!$B$6="Base Case",Scenarios!H70,IF(Dashboard!$B$6="Optimistic",Scenarios!H156,Scenarios!H242)) -> 0.4
A15: EBITDA (E£) | B15: =IF(Dashboard!$B$6="Base Case",Scenarios!B71,IF(Dashboard!$B$6="Optimistic",Scenarios!B157,Scenarios!B243)) -> 153000 | C15: =IF(Dashboard!$B$6="Base Case",Scenarios!C71,IF(Dashboard!$B$6="Optimistic",Scenarios!C157,Scenarios!C243)) -> 171000 | D15: =IF(Dashboard!$B$6="Base Case",Scenarios!D71,IF(Dashboard!$B$6="Optimistic",Scenarios!D157,Scenarios!D243)) -> 240350 | E15: =IF(Dashboard!$B$6="Base Case",Scenarios!E71,IF(Dashboard!$B$6="Optimistic",Scenarios!E157,Scenarios!E243)) -> 259578 | F15: =IF(Dashboard!$B$6="Base Case",Scenarios!F71,IF(Dashboard!$B$6="Optimistic",Scenarios!F157,Scenarios!F243)) -> 277748.46 | G15: =IF(Dashboard!$B$6="Base Case",Scenarios!G71,IF(Dashboard!$B$6="Optimistic",Scenarios!G157,Scenarios!G243)) -> 294413.37 | H15: =IF(Dashboard!$B$6="Base Case",Scenarios!H71,IF(Dashboard!$B$6="Optimistic",Scenarios!H157,Scenarios!H243)) -> 309134.04
A16: EBIT (E£) | B16: =IF(Dashboard!$B$6="Base Case",Scenarios!B72,IF(Dashboard!$B$6="Optimistic",Scenarios!B158,Scenarios!B244)) -> 120000 | C16: =IF(Dashboard!$B$6="Base Case",Scenarios!C72,IF(Dashboard!$B$6="Optimistic",Scenarios!C158,Scenarios!C244)) -> 134000 | D16: =IF(Dashboard!$B$6="Base Case",Scenarios!D72,IF(Dashboard!$B$6="Optimistic",Scenarios!D158,Scenarios!D244)) -> 194237.5 | E16: =IF(Dashboard!$B$6="Base Case",Scenarios!E72,IF(Dashboard!$B$6="Optimistic",Scenarios!E158,Scenarios!E244)) -> 208031.5 | F16: =IF(Dashboard!$B$6="Base Case",Scenarios!F72,IF(Dashboard!$B$6="Optimistic",Scenarios!F158,Scenarios!F244)) -> 220361.46 | G16: =IF(Dashboard!$B$6="Base Case",Scenarios!G72,IF(Dashboard!$B$6="Optimistic",Scenarios!G158,Scenarios!G244)) -> 230807.21 | H16: =IF(Dashboard!$B$6="Base Case",Scenarios!H72,IF(Dashboard!$B$6="Optimistic",Scenarios!H158,Scenarios!H244)) -> 238967.58
A17: EBIT Margin % | B17: =IF(Dashboard!$B$6="Base Case",Scenarios!B73,IF(Dashboard!$B$6="Optimistic",Scenarios!B159,Scenarios!B245)) -> 0.14117647 | C17: =IF(Dashboard!$B$6="Base Case",Scenarios!C73,IF(Dashboard!$B$6="Optimistic",Scenarios!C159,Scenarios!C245)) -> 0.14105263 | D17: =IF(Dashboard!$B$6="Base Case",Scenarios!D73,IF(Dashboard!$B$6="Optimistic",Scenarios!D159,Scenarios!D245)) -> 0.18587321 | E17: =IF(Dashboard!$B$6="Base Case",Scenarios!E73,IF(Dashboard!$B$6="Optimistic",Scenarios!E159,Scenarios!E245)) -> 0.18432704 | F17: =IF(Dashboard!$B$6="Base Case",Scenarios!F73,IF(Dashboard!$B$6="Optimistic",Scenarios!F159,Scenarios!F245)) -> 0.18247854 | G17: =IF(Dashboard!$B$6="Base Case",Scenarios!G73,IF(Dashboard!$B$6="Optimistic",Scenarios!G159,Scenarios!G245)) -> 0.18030995 | H17: =IF(Dashboard!$B$6="Base Case",Scenarios!H73,IF(Dashboard!$B$6="Optimistic",Scenarios!H159,Scenarios!H245)) -> 0.17779519
A18: Net Income (E£) | B18: =IF(Dashboard!$B$6="Base Case",Scenarios!B74,IF(Dashboard!$B$6="Optimistic",Scenarios!B160,Scenarios!B246)) -> 84087.5 | C18: =IF(Dashboard!$B$6="Base Case",Scenarios!C74,IF(Dashboard!$B$6="Optimistic",Scenarios!C160,Scenarios!C246)) -> 96100 | D18: =IF(Dashboard!$B$6="Base Case",Scenarios!D74,IF(Dashboard!$B$6="Optimistic",Scenarios!D160,Scenarios!D246)) -> 147993.7 | E18: =IF(Dashboard!$B$6="Base Case",Scenarios!E74,IF(Dashboard!$B$6="Optimistic",Scenarios!E160,Scenarios!E246)) -> 179824.99 | F18: =IF(Dashboard!$B$6="Base Case",Scenarios!F74,IF(Dashboard!$B$6="Optimistic",Scenarios!F160,Scenarios!F246)) -> 200453.05 | G18: =IF(Dashboard!$B$6="Base Case",Scenarios!G74,IF(Dashboard!$B$6="Optimistic",Scenarios!G160,Scenarios!G246)) -> 215020.22 | H18: =IF(Dashboard!$B$6="Base Case",Scenarios!H74,IF(Dashboard!$B$6="Optimistic",Scenarios!H160,Scenarios!H246)) -> 231471.1
A19: Net Margin % | B19: =IF(Dashboard!$B$6="Base Case",Scenarios!B75,IF(Dashboard!$B$6="Optimistic",Scenarios!B161,Scenarios!B247)) -> 0.098926471 | C19: =IF(Dashboard!$B$6="Base Case",Scenarios!C75,IF(Dashboard!$B$6="Optimistic",Scenarios!C161,Scenarios!C247)) -> 0.10115789 | D19: =IF(Dashboard!$B$6="Base Case",Scenarios!D75,IF(Dashboard!$B$6="Optimistic",Scenarios!D161,Scenarios!D247)) -> 0.14162077 | E19: =IF(Dashboard!$B$6="Base Case",Scenarios!E75,IF(Dashboard!$B$6="Optimistic",Scenarios!E161,Scenarios!E247)) -> 0.15933456 | F19: =IF(Dashboard!$B$6="Base Case",Scenarios!F75,IF(Dashboard!$B$6="Optimistic",Scenarios!F161,Scenarios!F247)) -> 0.16599264 | G19: =IF(Dashboard!$B$6="Base Case",Scenarios!G75,IF(Dashboard!$B$6="Optimistic",Scenarios!G161,Scenarios!G247)) -> 0.16797692 | H19: =IF(Dashboard!$B$6="Base Case",Scenarios!H75,IF(Dashboard!$B$6="Optimistic",Scenarios!H161,Scenarios!H247)) -> 0.1722177
A20: EPS (E£) | B20: =IF(Dashboard!$B$6="Base Case",Scenarios!B76,IF(Dashboard!$B$6="Optimistic",Scenarios!B162,Scenarios!B248)) -> 0.840875 | C20: =IF(Dashboard!$B$6="Base Case",Scenarios!C76,IF(Dashboard!$B$6="Optimistic",Scenarios!C162,Scenarios!C248)) -> 0.961 | D20: =IF(Dashboard!$B$6="Base Case",Scenarios!D76,IF(Dashboard!$B$6="Optimistic",Scenarios!D162,Scenarios!D248)) -> 1.3319433 | E20: =IF(Dashboard!$B$6="Base Case",Scenarios!E76,IF(Dashboard!$B$6="Optimistic",Scenarios!E162,Scenarios!E248)) -> 1.6184249 | F20: =IF(Dashboard!$B$6="Base Case",Scenarios!F76,IF(Dashboard!$B$6="Optimistic",Scenarios!F162,Scenarios!F248)) -> 1.8040774 | G20: =IF(Dashboard!$B$6="Base Case",Scenarios!G76,IF(Dashboard!$B$6="Optimistic",Scenarios!G162,Scenarios!G248)) -> 1.935182 | H20: =IF(Dashboard!$B$6="Base Case",Scenarios!H76,IF(Dashboard!$B$6="Optimistic",Scenarios!H162,Scenarios!H248)) -> 2.0832399
A21: 💵 CASH FLOW
A22: CFO (E£) | B22: — | C22: =IF(Dashboard!$B$6="Base Case",Scenarios!C77,IF(Dashboard!$B$6="Optimistic",Scenarios!C163,Scenarios!C249)) -> 126417 | D22: =IF(Dashboard!$B$6="Base Case",Scenarios!D77,IF(Dashboard!$B$6="Optimistic",Scenarios!D163,Scenarios!D249)) -> 319424.67 | E22: =IF(Dashboard!$B$6="Base Case",Scenarios!E77,IF(Dashboard!$B$6="Optimistic",Scenarios!E163,Scenarios!E249)) -> 236316.49 | F22: =IF(Dashboard!$B$6="Base Case",Scenarios!F77,IF(Dashboard!$B$6="Optimistic",Scenarios!F163,Scenarios!F249)) -> 262513.07 | G22: =IF(Dashboard!$B$6="Base Case",Scenarios!G77,IF(Dashboard!$B$6="Optimistic",Scenarios!G163,Scenarios!G249)) -> 282912.21 | H22: =IF(Dashboard!$B$6="Base Case",Scenarios!H77,IF(Dashboard!$B$6="Optimistic",Scenarios!H163,Scenarios!H249)) -> 305423.37
A23: Free Cash Flow (E£) | B23: — | C23: =IF(Dashboard!$B$6="Base Case",Scenarios!C78,IF(Dashboard!$B$6="Optimistic",Scenarios!C164,Scenarios!C250)) -> 81417 | D23: =IF(Dashboard!$B$6="Base Case",Scenarios!D78,IF(Dashboard!$B$6="Optimistic",Scenarios!D164,Scenarios!D250)) -> 267174.67 | E23: =IF(Dashboard!$B$6="Base Case",Scenarios!E78,IF(Dashboard!$B$6="Optimistic",Scenarios!E164,Scenarios!E250)) -> 179886.49 | F23: =IF(Dashboard!$B$6="Base Case",Scenarios!F78,IF(Dashboard!$B$6="Optimistic",Scenarios!F164,Scenarios!F250)) -> 202132.97 | G23: =IF(Dashboard!$B$6="Base Case",Scenarios!G78,IF(Dashboard!$B$6="Optimistic",Scenarios!G164,Scenarios!G250)) -> 218909.3 | H23: =IF(Dashboard!$B$6="Base Case",Scenarios!H78,IF(Dashboard!$B$6="Optimistic",Scenarios!H164,Scenarios!H250)) -> 238220.32
A24: Ending Cash (E£) | B24: — | C24: =IF(Dashboard!$B$6="Base Case",Scenarios!C79,IF(Dashboard!$B$6="Optimistic",Scenarios!C165,Scenarios!C251)) -> 200000 | D24: =IF(Dashboard!$B$6="Base Case",Scenarios!D79,IF(Dashboard!$B$6="Optimistic",Scenarios!D165,Scenarios!D251)) -> 413917 | E24: =IF(Dashboard!$B$6="Base Case",Scenarios!E79,IF(Dashboard!$B$6="Optimistic",Scenarios!E165,Scenarios!E251)) -> 527268.24 | F24: =IF(Dashboard!$B$6="Base Case",Scenarios!F79,IF(Dashboard!$B$6="Optimistic",Scenarios!F165,Scenarios!F251)) -> 655233.58 | G24: =IF(Dashboard!$B$6="Base Case",Scenarios!G79,IF(Dashboard!$B$6="Optimistic",Scenarios!G165,Scenarios!G251)) -> 794585.4 | H24: =IF(Dashboard!$B$6="Base Case",Scenarios!H79,IF(Dashboard!$B$6="Optimistic",Scenarios!H165,Scenarios!H251)) -> 947161.42
A25: 🏦 BALANCE SHEET
A26: Total Assets (E£) | B26: =IF(Dashboard!$B$6="Base Case",Scenarios!B80,IF(Dashboard!$B$6="Optimistic",Scenarios!B166,Scenarios!B252)) -> 717213 | C26: =IF(Dashboard!$B$6="Base Case",Scenarios!C80,IF(Dashboard!$B$6="Optimistic",Scenarios!C166,Scenarios!C252)) -> 768472 | D26: =IF(Dashboard!$B$6="Base Case",Scenarios!D80,IF(Dashboard!$B$6="Optimistic",Scenarios!D166,Scenarios!D252)) -> 1013189.4 | E26: =IF(Dashboard!$B$6="Base Case",Scenarios!E80,IF(Dashboard!$B$6="Optimistic",Scenarios!E166,Scenarios!E252)) -> 1147274.9 | F26: =IF(Dashboard!$B$6="Base Case",Scenarios!F80,IF(Dashboard!$B$6="Optimistic",Scenarios!F166,Scenarios!F252)) -> 1293212.3 | G26: =IF(Dashboard!$B$6="Base Case",Scenarios!G80,IF(Dashboard!$B$6="Optimistic",Scenarios!G166,Scenarios!G252)) -> 1446698.8 | H26: =IF(Dashboard!$B$6="Base Case",Scenarios!H80,IF(Dashboard!$B$6="Optimistic",Scenarios!H166,Scenarios!H252)) -> 1608446.5
A27: Total Debt (E£) | B27: =IF(Dashboard!$B$6="Base Case",Scenarios!B81,IF(Dashboard!$B$6="Optimistic",Scenarios!B167,Scenarios!B253)) -> 300000 | C27: =IF(Dashboard!$B$6="Base Case",Scenarios!C81,IF(Dashboard!$B$6="Optimistic",Scenarios!C167,Scenarios!C253)) -> 280000 | D27: =IF(Dashboard!$B$6="Base Case",Scenarios!D81,IF(Dashboard!$B$6="Optimistic",Scenarios!D167,Scenarios!D253)) -> 280000 | E27: =IF(Dashboard!$B$6="Base Case",Scenarios!E81,IF(Dashboard!$B$6="Optimistic",Scenarios!E167,Scenarios!E253)) -> 280000 | F27: =IF(Dashboard!$B$6="Base Case",Scenarios!F81,IF(Dashboard!$B$6="Optimistic",Scenarios!F167,Scenarios!F253)) -> 280000 | G27: =IF(Dashboard!$B$6="Base Case",Scenarios!G81,IF(Dashboard!$B$6="Optimistic",Scenarios!G167,Scenarios!G253)) -> 280000 | H27: =IF(Dashboard!$B$6="Base Case",Scenarios!H81,IF(Dashboard!$B$6="Optimistic",Scenarios!H167,Scenarios!H253)) -> 280000
A28: Total Equity (E£) | B28: =IF(Dashboard!$B$6="Base Case",Scenarios!B82,IF(Dashboard!$B$6="Optimistic",Scenarios!B168,Scenarios!B254)) -> 248823 | C28: =IF(Dashboard!$B$6="Base Case",Scenarios!C82,IF(Dashboard!$B$6="Optimistic",Scenarios!C168,Scenarios!C254)) -> 308506 | D28: =IF(Dashboard!$B$6="Base Case",Scenarios!D82,IF(Dashboard!$B$6="Optimistic",Scenarios!D168,Scenarios!D254)) -> 403242.03 | E28: =IF(Dashboard!$B$6="Base Case",Scenarios!E82,IF(Dashboard!$B$6="Optimistic",Scenarios!E168,Scenarios!E254)) -> 516531.78 | F28: =IF(Dashboard!$B$6="Base Case",Scenarios!F82,IF(Dashboard!$B$6="Optimistic",Scenarios!F168,Scenarios!F254)) -> 642817.19 | G28: =IF(Dashboard!$B$6="Base Case",Scenarios!G82,IF(Dashboard!$B$6="Optimistic",Scenarios!G168,Scenarios!G254)) -> 778279.93 | H28: =IF(Dashboard!$B$6="Base Case",Scenarios!H82,IF(Dashboard!$B$6="Optimistic",Scenarios!H168,Scenarios!H254)) -> 924106.73
A29: Cash (E£) | B29: =IF(Dashboard!$B$6="Base Case",Scenarios!B83,IF(Dashboard!$B$6="Optimistic",Scenarios!B169,Scenarios!B255)) -> 175000 | C29: =IF(Dashboard!$B$6="Base Case",Scenarios!C83,IF(Dashboard!$B$6="Optimistic",Scenarios!C169,Scenarios!C255)) -> 200000 | D29: =IF(Dashboard!$B$6="Base Case",Scenarios!D83,IF(Dashboard!$B$6="Optimistic",Scenarios!D169,Scenarios!D255)) -> 413917 | E29: =IF(Dashboard!$B$6="Base Case",Scenarios!E83,IF(Dashboard!$B$6="Optimistic",Scenarios!E169,Scenarios!E255)) -> 527268.24 | F29: =IF(Dashboard!$B$6="Base Case",Scenarios!F83,IF(Dashboard!$B$6="Optimistic",Scenarios!F169,Scenarios!F255)) -> 655233.58 | G29: =IF(Dashboard!$B$6="Base Case",Scenarios!G83,IF(Dashboard!$B$6="Optimistic",Scenarios!G169,Scenarios!G255)) -> 794585.4 | H29: =IF(Dashboard!$B$6="Base Case",Scenarios!H83,IF(Dashboard!$B$6="Optimistic",Scenarios!H169,Scenarios!H255)) -> 947161.42
A30: 📊 KEY RATIOS
A31: Current Ratio | B31: =IF(Dashboard!$B$6="Base Case",Scenarios!B84,IF(Dashboard!$B$6="Optimistic",Scenarios!B170,Scenarios!B256)) -> 1.8551339 | C31: =IF(Dashboard!$B$6="Base Case",Scenarios!C84,IF(Dashboard!$B$6="Optimistic",Scenarios!C170,Scenarios!C256)) -> 1.966866 | D31: =IF(Dashboard!$B$6="Base Case",Scenarios!D84,IF(Dashboard!$B$6="Optimistic",Scenarios!D170,Scenarios!D256)) -> 1.8033242 | E31: =IF(Dashboard!$B$6="Base Case",Scenarios!E84,IF(Dashboard!$B$6="Optimistic",Scenarios!E170,Scenarios!E256)) -> 2.0540479 | F31: =IF(Dashboard!$B$6="Base Case",Scenarios!F84,IF(Dashboard!$B$6="Optimistic",Scenarios!F170,Scenarios!F256)) -> 2.3202115 | G31: =IF(Dashboard!$B$6="Base Case",Scenarios!G84,IF(Dashboard!$B$6="Optimistic",Scenarios!G170,Scenarios!G256)) -> 2.5960313 | H31: =IF(Dashboard!$B$6="Base Case",Scenarios!H84,IF(Dashboard!$B$6="Optimistic",Scenarios!H170,Scenarios!H256)) -> 2.8902554
A32: Debt / Equity | B32: =IF(Dashboard!$B$6="Base Case",Scenarios!B85,IF(Dashboard!$B$6="Optimistic",Scenarios!B171,Scenarios!B257)) -> 1.2056763 | C32: =IF(Dashboard!$B$6="Base Case",Scenarios!C85,IF(Dashboard!$B$6="Optimistic",Scenarios!C171,Scenarios!C257)) -> 0.90759985 | D32: =IF(Dashboard!$B$6="Base Case",Scenarios!D85,IF(Dashboard!$B$6="Optimistic",Scenarios!D171,Scenarios!D257)) -> 0.69437206 | E32: =IF(Dashboard!$B$6="Base Case",Scenarios!E85,IF(Dashboard!$B$6="Optimistic",Scenarios!E171,Scenarios!E257)) -> 0.54207701 | F32: =IF(Dashboard!$B$6="Base Case",Scenarios!F85,IF(Dashboard!$B$6="Optimistic",Scenarios!F171,Scenarios!F257)) -> 0.43558262 | G32: =IF(Dashboard!$B$6="Base Case",Scenarios!G85,IF(Dashboard!$B$6="Optimistic",Scenarios!G171,Scenarios!G257)) -> 0.35976772 | H32: =IF(Dashboard!$B$6="Base Case",Scenarios!H85,IF(Dashboard!$B$6="Optimistic",Scenarios!H171,Scenarios!H257)) -> 0.3029953
A33: ROE % | B33: =IF(Dashboard!$B$6="Base Case",Scenarios!B86,IF(Dashboard!$B$6="Optimistic",Scenarios!B172,Scenarios!B258)) -> 0.33794103 | C33: =IF(Dashboard!$B$6="Base Case",Scenarios!C86,IF(Dashboard!$B$6="Optimistic",Scenarios!C172,Scenarios!C258)) -> 0.34485914 | D33: =IF(Dashboard!$B$6="Base Case",Scenarios!D86,IF(Dashboard!$B$6="Optimistic",Scenarios!D172,Scenarios!D258)) -> 0.41585981 | E33: =IF(Dashboard!$B$6="Base Case",Scenarios!E86,IF(Dashboard!$B$6="Optimistic",Scenarios!E172,Scenarios!E258)) -> 0.39102003 | F33: =IF(Dashboard!$B$6="Base Case",Scenarios!F86,IF(Dashboard!$B$6="Optimistic",Scenarios!F172,Scenarios!F258)) -> 0.34580278 | G33: =IF(Dashboard!$B$6="Base Case",Scenarios!G86,IF(Dashboard!$B$6="Optimistic",Scenarios!G172,Scenarios!G258)) -> 0.30261158 | H33: =IF(Dashboard!$B$6="Base Case",Scenarios!H86,IF(Dashboard!$B$6="Optimistic",Scenarios!H172,Scenarios!H258)) -> 0.27193717
A34: ROIC % | B34: =IF(Dashboard!$B$6="Base Case",Scenarios!B87,IF(Dashboard!$B$6="Optimistic",Scenarios!B173,Scenarios!B259)) -> 0.24878084 | C34: =IF(Dashboard!$B$6="Base Case",Scenarios!C87,IF(Dashboard!$B$6="Optimistic",Scenarios!C173,Scenarios!C259)) -> 0.27245454 | D34: =IF(Dashboard!$B$6="Base Case",Scenarios!D87,IF(Dashboard!$B$6="Optimistic",Scenarios!D173,Scenarios!D259)) -> 0.45766787 | E34: =IF(Dashboard!$B$6="Base Case",Scenarios!E87,IF(Dashboard!$B$6="Optimistic",Scenarios!E173,Scenarios!E259)) -> 0.59869229 | F34: =IF(Dashboard!$B$6="Base Case",Scenarios!F87,IF(Dashboard!$B$6="Optimistic",Scenarios!F173,Scenarios!F259)) -> 0.63623372 | G34: =IF(Dashboard!$B$6="Base Case",Scenarios!G87,IF(Dashboard!$B$6="Optimistic",Scenarios!G173,Scenarios!G259)) -> 0.67337831 | H34: =IF(Dashboard!$B$6="Base Case",Scenarios!H87,IF(Dashboard!$B$6="Optimistic",Scenarios!H173,Scenarios!H259)) -> 0.71143182
A35: ROA % | B35: =IF(Dashboard!$B$6="Base Case",Scenarios!B88,IF(Dashboard!$B$6="Optimistic",Scenarios!B174,Scenarios!B260)) -> 0.11724202 | C35: =IF(Dashboard!$B$6="Base Case",Scenarios!C88,IF(Dashboard!$B$6="Optimistic",Scenarios!C174,Scenarios!C260)) -> 0.12936793 | D35: =IF(Dashboard!$B$6="Base Case",Scenarios!D88,IF(Dashboard!$B$6="Optimistic",Scenarios!D174,Scenarios!D260)) -> 0.16613 | E35: =IF(Dashboard!$B$6="Base Case",Scenarios!E88,IF(Dashboard!$B$6="Optimistic",Scenarios!E174,Scenarios!E260)) -> 0.16646884 | F35: =IF(Dashboard!$B$6="Base Case",Scenarios!F88,IF(Dashboard!$B$6="Optimistic",Scenarios!F174,Scenarios!F260)) -> 0.16427297 | G35: =IF(Dashboard!$B$6="Base Case",Scenarios!G88,IF(Dashboard!$B$6="Optimistic",Scenarios!G174,Scenarios!G260)) -> 0.15695416 | H35: =IF(Dashboard!$B$6="Base Case",Scenarios!H88,IF(Dashboard!$B$6="Optimistic",Scenarios!H174,Scenarios!H260)) -> 0.1515287
A38: ⚖️ SCENARIO COMPARISON — Terminal Year
A39: Metric | B39: Active Scenario
A40: Revenue | B40: =IF(Dashboard!$B$6="Base Case",Scenarios!H67,IF(Dashboard!$B$6="Optimistic",Scenarios!H153,Scenarios!H239)) -> 1344061
A41: EBITDA | B41: =IF(Dashboard!$B$6="Base Case",Scenarios!H71,IF(Dashboard!$B$6="Optimistic",Scenarios!H157,Scenarios!H243)) -> 309134.04
A42: Net Income | B42: =IF(Dashboard!$B$6="Base Case",Scenarios!H74,IF(Dashboard!$B$6="Optimistic",Scenarios!H160,Scenarios!H246)) -> 231471.1
A43: Free Cash Flow | B43: =IF(Dashboard!$B$6="Base Case",Scenarios!H78,IF(Dashboard!$B$6="Optimistic",Scenarios!H164,Scenarios!H250)) -> 238220.32
A44: Cash Balance | B44: =IF(Dashboard!$B$6="Base Case",Scenarios!H83,IF(Dashboard!$B$6="Optimistic",Scenarios!H169,Scenarios!H255)) -> 947161.42
A45: Total Equity | B45: =IF(Dashboard!$B$6="Base Case",Scenarios!H82,IF(Dashboard!$B$6="Optimistic",Scenarios!H168,Scenarios!H254)) -> 924106.73
A46: ROE | B46: =IF(Dashboard!$B$6="Base Case",Scenarios!H86,IF(Dashboard!$B$6="Optimistic",Scenarios!H172,Scenarios!H258)) -> 0.27193717
A47: ROIC | B47: =IF(Dashboard!$B$6="Base Case",Scenarios!H87,IF(Dashboard!$B$6="Optimistic",Scenarios!H173,Scenarios!H259)) -> 0.71143182
A48: Gross Margin | B48: =IF(Dashboard!$B$6="Base Case",Scenarios!H70,IF(Dashboard!$B$6="Optimistic",Scenarios!H156,Scenarios!H242)) -> 0.4
A50: ⚠ The scenario selector (B6) drives the entire model. Edit scenario values in the Scenarios sheet.

Sheet Company Info
A1: COMPANY INFORMATION & MODEL CONFIGURATION
A3: SECTION 1 — COMPANY IDENTIFICATION
A4: Company Name | B4: Demo Company Inc. | C4: ← Edit
A5: Legal Entity Type | B5: Société Anonyme (S.A.E.) | C5: ← Edit
A6: Industry / Sector | B6: Technology / Software | C6: ← Edit
A7: Founded Year | B7: 2010 | C7: ← Edit
A8: Commercial Register No. | B8: 12345-Cairo-2010 | C8: Auto
A9: Tax Identification No. | B9: 123-456-789 | C9: Auto
A10: Headquarters Address | B10: 5 El-Nile Street, Zamalek, Cairo, Egypt | C10: Auto
A12: SECTION 2 — FINANCIAL MODEL CONFIGURATION
A13: Reporting Currency | B13: Egyptian Pound (EGP) | C13: Auto
A14: Currency Symbol | B14: E£ | C14: Auto
A15: Fiscal Year End | B15: December 31 | C15: ← Edit
A16: Historical Period | B16: 2024 – 2025 (Actual) | C16: Auto
A17: Projection Period | B17: 2026E – 2030E (5 Years) | C17: Auto
A18: Model Version | B18: 3SM-v8 | Apr 2026 | C18: Auto
A19: Last Updated | B19: April 26, 2026 | C19: Auto
A21: SECTION 3 — EGYPT REGULATORY / TAX
A22: Corporate Income Tax Rate | B22: 0.225 | C22: Auto
A23: VAT Rate (Standard) | B23: 0.14 | C23: Auto
A24: Dividend Withholding Tax | B24: 0.1 | C24: Auto
A25: CBE Policy Rate (Discount) | B25: 0.195 | C25: Auto
A26: Risk-Free Rate (12M T-Bill) | B26: 0.235 | C26: Auto
A27: Financial Year Note | B27: July 1 – June 30 (Note: model uses Dec) | C27: Auto
A29: SECTION 4 — REPORT & PREPARER INFORMATION
A30: Prepared By | B30: Financial Modeling Team | C30: ← Edit
A31: Reviewed By | B31: CFO | C31: ← Edit
A32: Preparation Date | B32: April 26, 2026 | C32: Auto
A33: Purpose | B33: Internal Planning & Analysis | C33: ← Edit
A34: Confidentiality | B34: CONFIDENTIAL — Internal Use Only | C34: ← Edit
A35: Contact Email | B35: finance@democompany.com | C35: ← Edit
A37: Note: All financial rates are driven by the WOLF engine. To update rates, use "Refresh Rates" in the engine dashboard, then re-export.

Sheet Scenarios
A1: SCENARIO DATA — COMPLETE ENGINE VALUES
A2: This sheet stores the full engine-computed data for each scenario. All projection columns in Assumptions reference this sheet via IF formulas.
A4: ▎ BASE CASE · Moderate growth with stable margins
A5: Assumption / Computed Value | B5: 2024 | C5: 2025 | D5: 2026E | E5: 2027E | F5: 2028E | G5: 2029E | H5: 2030E
A6: ── Income Statement Drivers ──
A7: Revenue (Year 1 Historical) | B7: 850000 | C7: 0 | D7: 0 | E7: 0 | F7: 0 | G7: 0 | H7: 0
A8: Revenue Growth Rate | B8: 0 | C8: 0.11764706 | D8: 0.1 | E8: 0.08 | F8: 0.07 | G8: 0.06 | H8: 0.05
A9: COGS % of Revenue | B9: 0.6 | C9: 0.6 | D9: 0.6 | E9: 0.6 | F9: 0.6 | G9: 0.6 | H9: 0.6
A10: SG&A % of Revenue | B10: 0.15 | C10: 0.15 | D10: 0.15 | E10: 0.15 | F10: 0.15 | G10: 0.15 | H10: 0.15
A11: R&D % of Revenue | B11: 0.05 | C11: 0.05 | D11: 0 | E11: 0 | F11: 0 | G11: 0 | H11: 0
A12: Other OpEx % of Revenue | B12: 0.02 | C12: 0.02 | D12: 0.02 | E12: 0.02 | F12: 0.02 | G12: 0.02 | H12: 0.02
A13: Tax Rate | B13: 0.225 | C13: 0.225 | D13: 0.225 | E13: 0.225 | F13: 0.225 | G13: 0.225 | H13: 0.225
A14: Other Income / Expense | B14: 0 | C14: 0 | D14: 0 | E14: 0 | F14: 0 | G14: 0 | H14: 0
A15: Shares Outstanding | B15: 100000 | C15: 100000 | D15: 100000 | E15: 100000 | F15: 100000 | G15: 100000 | H15: 100000
A16: Stock-Based Comp Amount | B16: 0 | C16: 0 | D16: 0 | E16: 0 | F16: 0 | G16: 0 | H16: 0
A17: EPD Rate (Employee Profit Sharing) | B17: 0.1 | C17: 0.1 | D17: 0.1 | E17: 0.1 | F17: 0.1 | G17: 0.1 | H17: 0.1
A18: Issued (Paid-Up) Capital | B18: 10000 | C18: 10000 | D18: 10000 | E18: 10000 | F18: 10000 | G18: 10000 | H18: 10000
A19: ── Balance Sheet / WC Drivers ──
A20: DSO (Days) | B20: 45 | C20: 45 | D20: 45 | E20: 45 | F20: 45 | G20: 45 | H20: 45
A21: DIO (Days) | B21: 30 | C21: 30 | D21: 30 | E21: 30 | F21: 30 | G21: 30 | H21: 30
A22: DPO (Days) | B22: 40 | C22: 40 | D22: 40 | E22: 40 | F22: 40 | G22: 40 | H22: 40
A23: Prepaid % of Revenue | B23: 0.01 | C23: 0.01 | D23: 0.01 | E23: 0.01 | F23: 0.01 | G23: 0.01 | H23: 0.01
A24: Accrued Exp % of Revenue | B24: 0.03 | C24: 0.03 | D24: 0.03 | E24: 0.03 | F24: 0.03 | G24: 0.03 | H24: 0.03
A25: Deferred Rev % of Revenue | B25: 0.02 | C25: 0.02 | D25: 0.02 | E25: 0.02 | F25: 0.02 | G25: 0.02 | H25: 0.02
A26: ── CapEx & Depreciation ──
A27: CapEx % of Revenue | B27: 0 | C27: 0.047368 | D27: 0.05 | E27: 0.05 | F27: 0.05 | G27: 0.05 | H27: 0.05
A28: Depreciation Rate (% Gross PPE) | B28: 0.082352941 | C28: 0.083116883 | D28: 0.1 | E28: 0.1 | F28: 0.1 | G28: 0.1 | H28: 0.1
A29: Amortization Amount | B29: 5000 | C29: 5000 | D29: 5000 | E29: 5000 | F29: 5000 | G29: 5000 | H29: 5000
A30: ── Debt & Financing ──
A31: Interest Rate (on Debt) | B31: 0.22 | C31: 0.22 | D31: 0.22 | E31: 0.2 | F31: 0.18 | G31: 0.17 | H31: 0.16
A32: Interest Income Rate (on Cash) | B32: 0.19 | C32: 0.19 | D32: 0.19 | E32: 0.17 | F32: 0.15 | G32: 0.13 | H32: 0.12
A33: Short-Term Debt | B33: 50000 | C33: 50000 | D33: 50000 | E33: 50000 | F33: 50000 | G33: 50000 | H33: 50000
A34: LT Debt Issuance | B34: 0 | C34: 0 | D34: 0 | E34: 0 | F34: 0 | G34: 0 | H34: 0
A35: LT Debt Repayment | B35: 0 | C35: 20000 | D35: 0 | E35: 0 | F35: 0 | G35: 0 | H35: 0
A36: Current Portion LTD | B36: 20000 | C36: 20000 | D36: 20000 | E36: 20000 | F36: 20000 | G36: 20000 | H36: 20000
A37: Dividend Payout Ratio | B37: 0 | C37: 0.48300728 | D37: 0.3 | E37: 0.3 | F37: 0.3 | G37: 0.3 | H37: 0.3
A38: Share Repurchase Amount | B38: 0 | C38: 0 | D38: 0 | E38: 0 | F38: 0 | G38: 0 | H38: 0
A39: Equity Issuance | B39: 0 | C39: 10000 | D39: 0 | E39: 0 | F39: 0 | G39: 0 | H39: 0
A40: ── VAT Settings ──
A41: Enable VAT | B41: 1 | C41: 1 | D41: 1 | E41: 1 | F41: 1 | G41: 1 | H41: 1
A42: VAT Rate | B42: 0.14 | C42: 0.14 | D42: 0.14 | E42: 0.14 | F42: 0.14 | G42: 0.14 | H42: 0.14
A43: ── BS / Equity Direct Values ──
A44: Goodwill | B44: 100000 | C44: 100000 | D44: 100000 | E44: 100000 | F44: 100000 | G44: 100000 | H44: 100000
A45: Other Current Assets | B45: 10000 | C45: 10000 | D45: 10000 | E45: 10000 | F45: 10000 | G45: 10000 | H45: 10000
A46: Other Long-Term Assets | B46: 20000 | C46: 20000 | D46: 20000 | E46: 20000 | F46: 20000 | G46: 20000 | H46: 20000
A47: Other Current Liabilities | B47: 15000 | C47: 15000 | D47: 15000 | E47: 15000 | F47: 15000 | G47: 15000 | H47: 15000
A48: Deferred Tax Liabilities | B48: 30000 | C48: 30000 | D48: 30000 | E48: 30000 | F48: 30000 | G48: 30000 | H48: 30000
A49: Other LT Liabilities | B49: 25000 | C49: 25000 | D49: 25000 | E49: 25000 | F49: 25000 | G49: 25000 | H49: 25000
A50: Common Stock | B50: 10000 | C50: 10000 | D50: 10000 | E50: 10000 | F50: 10000 | G50: 10000 | H50: 10000
A51: APIC | B51: 210000 | C51: 220000 | D51: 220000 | E51: 220000 | F51: 220000 | G51: 220000 | H51: 220000
A52: Other Comprehensive Income | B52: 0 | C52: 0 | D52: 0 | E52: 0 | F52: 0 | G52: 0 | H52: 0
A53: ── Engine-Computed Values ──
A54: Interest Income (Computed) | B54: 2500 | C54: 3000 | D54: 58322.115 | E54: 80000.745 | F54: 88687.637 | G54: 94238.234 | H54: 104504.81
A55: Interest Expense (Computed) | B55: 14000 | C55: 13000 | D55: 61600 | E55: 56000 | F55: 50400 | G55: 47600 | H55: 44800
A56: Depreciation (Computed) | B56: 28000 | C56: 32000 | D56: 41112.5 | E56: 46546.5 | F56: 52387.005 | G56: 58606.155 | H56: 65166.453
A57: Gross PP&E (Computed) | B57: 340000 | C57: 385000 | D57: 437250 | E57: 493680 | F57: 554060.1 | G57: 618063.01 | H57: 685266.06
A58: Accum Depreciation (Computed) | B58: 128000 | C58: 160000 | D58: 201112.5 | E58: 247659 | F58: 300046.01 | G58: 358652.16 | H58: 423818.61
A59: Net PP&E (Computed) | B59: 212000 | C59: 225000 | D59: 236137.5 | E59: 246021 | F59: 254014.09 | G59: 259410.85 | H59: 261447.44
A60: Intangibles (Computed) | B60: 45000 | C60: 40000 | D60: 35000 | E60: 30000 | F60: 25000 | G60: 20000 | H60: 15000
A61: Long-Term Debt (Computed) | B61: 230000 | C61: 210000 | D61: 210000 | E61: 210000 | F61: 210000 | G61: 210000 | H61: 210000
A62: Retained Earnings (Computed) | B62: 28823 | C62: 78506 | D62: 168242.03 | E62: 281531.78 | F62: 407817.19 | G62: 543279.93 | H62: 689106.73
A63: Treasury Stock (Computed) | B63: 0 | C63: 0 | D63: 0 | E63: 0 | F63: 0 | G63: 0 | H63: 0
A64: APIC (Computed) | B64: 210000 | C64: 220000 | D64: 220000 | E64: 220000 | F64: 220000 | G64: 220000 | H64: 220000
A65: Dividends Paid (Computed) | B65: 0 | C65: -46417 | D65: -38458.299 | E65: -48552.747 | F65: -54122.322 | G65: -58055.46 | H65: -62497.198
A66: ── Dashboard Output Metrics ──
A67: Revenue | B67: 850000 | C67: 950000 | D67: ='_Calc_Base'!D4 -> 1045000 | E67: ='_Calc_Base'!E4 -> 1128600 | F67: ='_Calc_Base'!F4 -> 1207602 | G67: ='_Calc_Base'!G4 -> 1280058.1 | H67: ='_Calc_Base'!H4 -> 1344061
A68: Revenue Growth % | B68: 0 | C68: 0.11764706 | D68: =IF(C67=0,0,(Scenarios!D67-C67)/C67) -> 0.1 | E68: =IF(D67=0,0,(Scenarios!E67-D67)/D67) -> 0.08 | F68: =IF(E67=0,0,(Scenarios!F67-E67)/E67) -> 0.07 | G68: =IF(F67=0,0,(Scenarios!G67-F67)/F67) -> 0.06 | H68: =IF(G67=0,0,(Scenarios!H67-G67)/G67) -> 0.05
A69: Gross Profit | B69: 340000 | C69: 380000 | D69: ='_Calc_Base'!D7 -> 418000 | E69: ='_Calc_Base'!E7 -> 451440 | F69: ='_Calc_Base'!F7 -> 483040.8 | G69: ='_Calc_Base'!G7 -> 512023.25 | H69: ='_Calc_Base'!H7 -> 537624.41
A70: Gross Margin % | B70: 0.4 | C70: 0.4 | D70: =IF('_Calc_Base'!D4=0,0,'_Calc_Base'!D7/'_Calc_Base'!D4) -> 0.4 | E70: =IF('_Calc_Base'!E4=0,0,'_Calc_Base'!E7/'_Calc_Base'!E4) -> 0.4 | F70: =IF('_Calc_Base'!F4=0,0,'_Calc_Base'!F7/'_Calc_Base'!F4) -> 0.4 | G70: =IF('_Calc_Base'!G4=0,0,'_Calc_Base'!G7/'_Calc_Base'!G4) -> 0.4 | H70: =IF('_Calc_Base'!H4=0,0,'_Calc_Base'!H7/'_Calc_Base'!H4) -> 0.4
A71: EBITDA | B71: 153000 | C71: 171000 | D71: ='_Calc_Base'!D15+'_Calc_Base'!D10+'_Calc_Base'!D11 -> 240350 | E71: ='_Calc_Base'!E15+'_Calc_Base'!E10+'_Calc_Base'!E11 -> 259578 | F71: ='_Calc_Base'!F15+'_Calc_Base'!F10+'_Calc_Base'!F11 -> 277748.46 | G71: ='_Calc_Base'!G15+'_Calc_Base'!G10+'_Calc_Base'!G11 -> 294413.37 | H71: ='_Calc_Base'!H15+'_Calc_Base'!H10+'_Calc_Base'!H11 -> 309134.04
A72: EBIT | B72: 120000 | C72: 134000 | D72: ='_Calc_Base'!D15 -> 194237.5 | E72: ='_Calc_Base'!E15 -> 208031.5 | F72: ='_Calc_Base'!F15 -> 220361.46 | G72: ='_Calc_Base'!G15 -> 230807.21 | H72: ='_Calc_Base'!H15 -> 238967.58
A73: EBIT Margin % | B73: 0.14117647 | C73: 0.14105263 | D73: =IF('_Calc_Base'!D4=0,0,'_Calc_Base'!D15/'_Calc_Base'!D4) -> 0.18587321 | E73: =IF('_Calc_Base'!E4=0,0,'_Calc_Base'!E15/'_Calc_Base'!E4) -> 0.18432704 | F73: =IF('_Calc_Base'!F4=0,0,'_Calc_Base'!F15/'_Calc_Base'!F4) -> 0.18247854 | G73: =IF('_Calc_Base'!G4=0,0,'_Calc_Base'!G15/'_Calc_Base'!G4) -> 0.18030995 | H73: =IF('_Calc_Base'!H4=0,0,'_Calc_Base'!H15/'_Calc_Base'!H4) -> 0.17779519
A74: Net Income | B74: 84087.5 | C74: 96100 | D74: ='_Calc_Base'!D21 -> 147993.7 | E74: ='_Calc_Base'!E21 -> 179824.99 | F74: ='_Calc_Base'!F21 -> 200453.05 | G74: ='_Calc_Base'!G21 -> 215020.22 | H74: ='_Calc_Base'!H21 -> 231471.1
A75: Net Margin % | B75: 0.098926471 | C75: 0.10115789 | D75: =IF('_Calc_Base'!D4=0,0,'_Calc_Base'!D21/'_Calc_Base'!D4) -> 0.14162077 | E75: =IF('_Calc_Base'!E4=0,0,'_Calc_Base'!E21/'_Calc_Base'!E4) -> 0.15933456 | F75: =IF('_Calc_Base'!F4=0,0,'_Calc_Base'!F21/'_Calc_Base'!F4) -> 0.16599264 | G75: =IF('_Calc_Base'!G4=0,0,'_Calc_Base'!G21/'_Calc_Base'!G4) -> 0.16797692 | H75: =IF('_Calc_Base'!H4=0,0,'_Calc_Base'!H21/'_Calc_Base'!H4) -> 0.1722177
A76: EPS | B76: 0.840875 | C76: 0.961 | D76: ='_Calc_Base'!D23/Scenarios!D15 -> 1.3319433 | E76: ='_Calc_Base'!E23/Scenarios!E15 -> 1.6184249 | F76: ='_Calc_Base'!F23/Scenarios!F15 -> 1.8040774 | G76: ='_Calc_Base'!G23/Scenarios!G15 -> 1.935182 | H76: ='_Calc_Base'!H23/Scenarios!H15 -> 2.0832399
A77: Cash from Operations | B77: 0 | C77: 126417 | D77: ='_Calc_Base'!D93 -> 319424.67 | E77: ='_Calc_Base'!E93 -> 236316.49 | F77: ='_Calc_Base'!F93 -> 262513.07 | G77: ='_Calc_Base'!G93 -> 282912.21 | H77: ='_Calc_Base'!H93 -> 305423.37
A78: Free Cash Flow | B78: 0 | C78: 81417 | D78: ='_Calc_Base'!D111 -> 267174.67 | E78: ='_Calc_Base'!E111 -> 179886.49 | F78: ='_Calc_Base'!F111 -> 202132.97 | G78: ='_Calc_Base'!G111 -> 218909.3 | H78: ='_Calc_Base'!H111 -> 238220.32
A79: Ending Cash | B79: 0 | C79: 200000 | D79: ='_Calc_Base'!D110 -> 413917 | E79: ='_Calc_Base'!E110 -> 527268.24 | F79: ='_Calc_Base'!F110 -> 655233.58 | G79: ='_Calc_Base'!G110 -> 794585.4 | H79: ='_Calc_Base'!H110 -> 947161.42
A80: Total Assets | B80: 717213 | C80: 768472 | D80: ='_Calc_Base'!D51 -> 1013189.4 | E80: ='_Calc_Base'!E51 -> 1147274.9 | F80: ='_Calc_Base'!F51 -> 1293212.3 | G80: ='_Calc_Base'!G51 -> 1446698.8 | H80: ='_Calc_Base'!H51 -> 1608446.5
A81: Total Debt | B81: 300000 | C81: 280000 | D81: ='_Calc_Base'!D55+'_Calc_Base'!D62 -> 280000 | E81: ='_Calc_Base'!E55+'_Calc_Base'!E62 -> 280000 | F81: ='_Calc_Base'!F55+'_Calc_Base'!F62 -> 280000 | G81: ='_Calc_Base'!G55+'_Calc_Base'!G62 -> 280000 | H81: ='_Calc_Base'!H55+'_Calc_Base'!H62 -> 280000
A82: Total Equity | B82: 248823 | C82: 308506 | D82: ='_Calc_Base'!D74 -> 403242.03 | E82: ='_Calc_Base'!E74 -> 516531.78 | F82: ='_Calc_Base'!F74 -> 642817.19 | G82: ='_Calc_Base'!G74 -> 778279.93 | H82: ='_Calc_Base'!H74 -> 924106.73
A83: Cash Balance | B83: 175000 | C83: 200000 | D83: ='_Calc_Base'!D36 -> 413917 | E83: ='_Calc_Base'!E36 -> 527268.24 | F83: ='_Calc_Base'!F36 -> 655233.58 | G83: ='_Calc_Base'!G36 -> 794585.4 | H83: ='_Calc_Base'!H36 -> 947161.42
A84: Current Ratio | B84: 1.8551339 | C84: 1.966866 | D84: =IF('_Calc_Base'!D60=0,0,'_Calc_Base'!D42/'_Calc_Base'!D60) -> 1.8033242 | E84: =IF('_Calc_Base'!E60=0,0,'_Calc_Base'!E42/'_Calc_Base'!E60) -> 2.0540479 | F84: =IF('_Calc_Base'!F60=0,0,'_Calc_Base'!F42/'_Calc_Base'!F60) -> 2.3202115 | G84: =IF('_Calc_Base'!G60=0,0,'_Calc_Base'!G42/'_Calc_Base'!G60) -> 2.5960313 | H84: =IF('_Calc_Base'!H60=0,0,'_Calc_Base'!H42/'_Calc_Base'!H60) -> 2.8902554
A85: Debt / Equity | B85: 1.2056763 | C85: 0.90759985 | D85: =IF('_Calc_Base'!D74=0,0,('_Calc_Base'!D55+'_Calc_Base'!D62)/'_Calc_Base'!D74) -> 0.69437206 | E85: =IF('_Calc_Base'!E74=0,0,('_Calc_Base'!E55+'_Calc_Base'!E62)/'_Calc_Base'!E74) -> 0.54207701 | F85: =IF('_Calc_Base'!F74=0,0,('_Calc_Base'!F55+'_Calc_Base'!F62)/'_Calc_Base'!F74) -> 0.43558262 | G85: =IF('_Calc_Base'!G74=0,0,('_Calc_Base'!G55+'_Calc_Base'!G62)/'_Calc_Base'!G74) -> 0.35976772 | H85: =IF('_Calc_Base'!H74=0,0,('_Calc_Base'!H55+'_Calc_Base'!H62)/'_Calc_Base'!H74) -> 0.3029953
A86: ROE % | B86: 0.33794103 | C86: 0.34485914 | D86: =IF('_Calc_Base'!D74=0,0,'_Calc_Base'!D21/'_Calc_Base'!D74) -> 0.41585981 | E86: =IF('_Calc_Base'!E74=0,0,'_Calc_Base'!E21/'_Calc_Base'!E74) -> 0.39102003 | F86: =IF('_Calc_Base'!F74=0,0,'_Calc_Base'!F21/'_Calc_Base'!F74) -> 0.34580278 | G86: =IF('_Calc_Base'!G74=0,0,'_Calc_Base'!G21/'_Calc_Base'!G74) -> 0.30261158 | H86: =IF('_Calc_Base'!H74=0,0,'_Calc_Base'!H21/'_Calc_Base'!H74) -> 0.27193717
A87: ROIC % | B87: 0.24878084 | C87: 0.27245454 | D87: =IF(('_Calc_Base'!D74+'_Calc_Base'!D55+'_Calc_Base'!D62+'_Calc_Base'!D56-'_Calc_Base'!D36)=0,0,'_Calc_Base'!D33/('_Calc_Base'!D74+'_Calc_Base'!D55+'_Calc_Base'!D62+'_Calc_Base'!D56-'_Calc_Base'!D36)) -> 0.45766787 | E87: =IF(('_Calc_Base'!E74+'_Calc_Base'!E55+'_Calc_Base'!E62+'_Calc_Base'!E56-'_Calc_Base'!E36)=0,0,'_Calc_Base'!E33/('_Calc_Base'!E74+'_Calc_Base'!E55+'_Calc_Base'!E62+'_Calc_Base'!E56-'_Calc_Base'!E36)) -> 0.59869229 | F87: =IF(('_Calc_Base'!F74+'_Calc_Base'!F55+'_Calc_Base'!F62+'_Calc_Base'!F56-'_Calc_Base'!F36)=0,0,'_Calc_Base'!F33/('_Calc_Base'!F74+'_Calc_Base'!F55+'_Calc_Base'!F62+'_Calc_Base'!F56-'_Calc_Base'!F36)) -> 0.63623372 | G87: =IF(('_Calc_Base'!G74+'_Calc_Base'!G55+'_Calc_Base'!G62+'_Calc_Base'!G56-'_Calc_Base'!G36)=0,0,'_Calc_Base'!G33/('_Calc_Base'!G74+'_Calc_Base'!G55+'_Calc_Base'!G62+'_Calc_Base'!G56-'_Calc_Base'!G36)) -> 0.67337831 | H87: =IF(('_Calc_Base'!H74+'_Calc_Base'!H55+'_Calc_Base'!H62+'_Calc_Base'!H56-'_Calc_Base'!H36)=0,0,'_Calc_Base'!H33/('_Calc_Base'!H74+'_Calc_Base'!H55+'_Calc_Base'!H62+'_Calc_Base'!H56-'_Calc_Base'!H36)) -> 0.71143182
A88: ROA % | B88: 0.11724202 | C88: 0.12936793 | D88: =IF('_Calc_Base'!D51=0,0,'_Calc_Base'!D21/'_Calc_Base'!D51) -> 0.16613 | E88: =IF('_Calc_Base'!E51=0,0,'_Calc_Base'!E21/'_Calc_Base'!E51) -> 0.16646884 | F88: =IF('_Calc_Base'!F51=0,0,'_Calc_Base'!F21/'_Calc_Base'!F51) -> 0.16427297 | G88: =IF('_Calc_Base'!G51=0,0,'_Calc_Base'!G21/'_Calc_Base'!G51) -> 0.15695416 | H88: =IF('_Calc_Base'!H51=0,0,'_Calc_Base'!H21/'_Calc_Base'!H51) -> 0.1515287
A90: ▎ OPTIMISTIC · High growth with margin expansion
A91: Assumption / Computed Value | B91: 2024 | C91: 2025 | D91: 2026E | E91: 2027E | F91: 2028E | G91: 2029E | H91: 2030E
A92: ── Income Statement Drivers ──
A93: Revenue (Year 1 Historical) | B93: 850000 | C93: 0 | D93: 0 | E93: 0 | F93: 0 | G93: 0 | H93: 0
A94: Revenue Growth Rate | B94: 0 | C94: 0.11764706 | D94: 0.15 | E94: 0.12 | F94: 0.1 | G94: 0.09 | H94: 0.08
A95: COGS % of Revenue | B95: 0.6 | C95: 0.6 | D95: 0.55 | E95: 0.54 | F95: 0.53 | G95: 0.52 | H95: 0.51
A96: SG&A % of Revenue | B96: 0.15 | C96: 0.15 | D96: 0.13 | E96: 0.12 | F96: 0.12 | G96: 0.11 | H96: 0.11
A97: R&D % of Revenue | B97: 0.05 | C97: 0.05 | D97: 0 | E97: 0 | F97: 0 | G97: 0 | H97: 0
A98: Other OpEx % of Revenue | B98: 0.02 | C98: 0.02 | D98: 0.02 | E98: 0.02 | F98: 0.02 | G98: 0.02 | H98: 0.02
A99: Tax Rate | B99: 0.225 | C99: 0.225 | D99: 0.225 | E99: 0.225 | F99: 0.225 | G99: 0.225 | H99: 0.225
A100: Other Income / Expense | B100: 0 | C100: 0 | D100: 0 | E100: 0 | F100: 0 | G100: 0 | H100: 0
A101: Shares Outstanding | B101: 100000 | C101: 100000 | D101: 100000 | E101: 100000 | F101: 100000 | G101: 100000 | H101: 100000
A102: Stock-Based Comp Amount | B102: 0 | C102: 0 | D102: 0 | E102: 0 | F102: 0 | G102: 0 | H102: 0
...

Sheet Assumptions
A1: Assumption | B1: 2024 | C1: 2025 | D1: 2026E | E1: 2027E | F1: 2028E | G1: 2029E | H1: 2030E
A2: ── Income Statement Drivers ──
A3: Revenue (Year 1 Historical) | B3: 850000 | D3: =IF(Assumptions!$B$67="Base Case",Scenarios!D7,IF(Assumptions!$B$67="Optimistic",Scenarios!D93,Scenarios!D179)) -> 0 | E3: =IF(Assumptions!$B$67="Base Case",Scenarios!E7,IF(Assumptions!$B$67="Optimistic",Scenarios!E93,Scenarios!E179)) -> 0 | F3: =IF(Assumptions!$B$67="Base Case",Scenarios!F7,IF(Assumptions!$B$67="Optimistic",Scenarios!F93,Scenarios!F179)) -> 0 | G3: =IF(Assumptions!$B$67="Base Case",Scenarios!G7,IF(Assumptions!$B$67="Optimistic",Scenarios!G93,Scenarios!G179)) -> 0 | H3: =IF(Assumptions!$B$67="Base Case",Scenarios!H7,IF(Assumptions!$B$67="Optimistic",Scenarios!H93,Scenarios!H179)) -> 0
A4: Revenue Growth Rate | D4: =IF(Assumptions!$B$67="Base Case",Scenarios!D8,IF(Assumptions!$B$67="Optimistic",Scenarios!D94,Scenarios!D180)) -> 0.1 | E4: =IF(Assumptions!$B$67="Base Case",Scenarios!E8,IF(Assumptions!$B$67="Optimistic",Scenarios!E94,Scenarios!E180)) -> 0.08 | F4: =IF(Assumptions!$B$67="Base Case",Scenarios!F8,IF(Assumptions!$B$67="Optimistic",Scenarios!F94,Scenarios!F180)) -> 0.07 | G4: =IF(Assumptions!$B$67="Base Case",Scenarios!G8,IF(Assumptions!$B$67="Optimistic",Scenarios!G94,Scenarios!G180)) -> 0.06 | H4: =IF(Assumptions!$B$67="Base Case",Scenarios!H8,IF(Assumptions!$B$67="Optimistic",Scenarios!H94,Scenarios!H180)) -> 0.05
A5: COGS % of Revenue | D5: =IF(Assumptions!$B$67="Base Case",Scenarios!D9,IF(Assumptions!$B$67="Optimistic",Scenarios!D95,Scenarios!D181)) -> 0.6 | E5: =IF(Assumptions!$B$67="Base Case",Scenarios!E9,IF(Assumptions!$B$67="Optimistic",Scenarios!E95,Scenarios!E181)) -> 0.6 | F5: =IF(Assumptions!$B$67="Base Case",Scenarios!F9,IF(Assumptions!$B$67="Optimistic",Scenarios!F95,Scenarios!F181)) -> 0.6 | G5: =IF(Assumptions!$B$67="Base Case",Scenarios!G9,IF(Assumptions!$B$67="Optimistic",Scenarios!G95,Scenarios!G181)) -> 0.6 | H5: =IF(Assumptions!$B$67="Base Case",Scenarios!H9,IF(Assumptions!$B$67="Optimistic",Scenarios!H95,Scenarios!H181)) -> 0.6
A6: SG&A % of Revenue | D6: =IF(Assumptions!$B$67="Base Case",Scenarios!D10,IF(Assumptions!$B$67="Optimistic",Scenarios!D96,Scenarios!D182)) -> 0.15 | E6: =IF(Assumptions!$B$67="Base Case",Scenarios!E10,IF(Assumptions!$B$67="Optimistic",Scenarios!E96,Scenarios!E182)) -> 0.15 | F6: =IF(Assumptions!$B$67="Base Case",Scenarios!F10,IF(Assumptions!$B$67="Optimistic",Scenarios!F96,Scenarios!F182)) -> 0.15 | G6: =IF(Assumptions!$B$67="Base Case",Scenarios!G10,IF(Assumptions!$B$67="Optimistic",Scenarios!G96,Scenarios!G182)) -> 0.15 | H6: =IF(Assumptions!$B$67="Base Case",Scenarios!H10,IF(Assumptions!$B$67="Optimistic",Scenarios!H96,Scenarios!H182)) -> 0.15
A7: R&D % of Revenue | D7: =IF(Assumptions!$B$67="Base Case",Scenarios!D11,IF(Assumptions!$B$67="Optimistic",Scenarios!D97,Scenarios!D183)) -> 0 | E7: =IF(Assumptions!$B$67="Base Case",Scenarios!E11,IF(Assumptions!$B$67="Optimistic",Scenarios!E97,Scenarios!E183)) -> 0 | F7: =IF(Assumptions!$B$67="Base Case",Scenarios!F11,IF(Assumptions!$B$67="Optimistic",Scenarios!F97,Scenarios!F183)) -> 0 | G7: =IF(Assumptions!$B$67="Base Case",Scenarios!G11,IF(Assumptions!$B$67="Optimistic",Scenarios!G97,Scenarios!G183)) -> 0 | H7: =IF(Assumptions!$B$67="Base Case",Scenarios!H11,IF(Assumptions!$B$67="Optimistic",Scenarios!H97,Scenarios!H183)) -> 0
A8: Other OpEx % of Revenue | D8: =IF(Assumptions!$B$67="Base Case",Scenarios!D12,IF(Assumptions!$B$67="Optimistic",Scenarios!D98,Scenarios!D184)) -> 0.02 | E8: =IF(Assumptions!$B$67="Base Case",Scenarios!E12,IF(Assumptions!$B$67="Optimistic",Scenarios!E98,Scenarios!E184)) -> 0.02 | F8: =IF(Assumptions!$B$67="Base Case",Scenarios!F12,IF(Assumptions!$B$67="Optimistic",Scenarios!F98,Scenarios!F184)) -> 0.02 | G8: =IF(Assumptions!$B$67="Base Case",Scenarios!G12,IF(Assumptions!$B$67="Optimistic",Scenarios!G98,Scenarios!G184)) -> 0.02 | H8: =IF(Assumptions!$B$67="Base Case",Scenarios!H12,IF(Assumptions!$B$67="Optimistic",Scenarios!H98,Scenarios!H184)) -> 0.02
A9: Tax Rate | D9: =IF(Assumptions!$B$67="Base Case",Scenarios!D13,IF(Assumptions!$B$67="Optimistic",Scenarios!D99,Scenarios!D185)) -> 0.225 | E9: =IF(Assumptions!$B$67="Base Case",Scenarios!E13,IF(Assumptions!$B$67="Optimistic",Scenarios!E99,Scenarios!E185)) -> 0.225 | F9: =IF(Assumptions!$B$67="Base Case",Scenarios!F13,IF(Assumptions!$B$67="Optimistic",Scenarios!F99,Scenarios!F185)) -> 0.225 | G9: =IF(Assumptions!$B$67="Base Case",Scenarios!G13,IF(Assumptions!$B$67="Optimistic",Scenarios!G99,Scenarios!G185)) -> 0.225 | H9: =IF(Assumptions!$B$67="Base Case",Scenarios!H13,IF(Assumptions!$B$67="Optimistic",Scenarios!H99,Scenarios!H185)) -> 0.225
A10: VAT Enabled (1=Yes) | D10: =IF(Assumptions!$B$67="Base Case",Scenarios!D41,IF(Assumptions!$B$67="Optimistic",Scenarios!D127,Scenarios!D213)) -> 1 | E10: =IF(Assumptions!$B$67="Base Case",Scenarios!E41,IF(Assumptions!$B$67="Optimistic",Scenarios!E127,Scenarios!E213)) -> 1 | F10: =IF(Assumptions!$B$67="Base Case",Scenarios!F41,IF(Assumptions!$B$67="Optimistic",Scenarios!F127,Scenarios!F213)) -> 1 | G10: =IF(Assumptions!$B$67="Base Case",Scenarios!G41,IF(Assumptions!$B$67="Optimistic",Scenarios!G127,Scenarios!G213)) -> 1 | H10: =IF(Assumptions!$B$67="Base Case",Scenarios!H41,IF(Assumptions!$B$67="Optimistic",Scenarios!H127,Scenarios!H213)) -> 1
A11: VAT Rate | D11: =IF(Assumptions!$B$67="Base Case",Scenarios!D42,IF(Assumptions!$B$67="Optimistic",Scenarios!D128,Scenarios!D214)) -> 0.14 | E11: =IF(Assumptions!$B$67="Base Case",Scenarios!E42,IF(Assumptions!$B$67="Optimistic",Scenarios!E128,Scenarios!E214)) -> 0.14 | F11: =IF(Assumptions!$B$67="Base Case",Scenarios!F42,IF(Assumptions!$B$67="Optimistic",Scenarios!F128,Scenarios!F214)) -> 0.14 | G11: =IF(Assumptions!$B$67="Base Case",Scenarios!G42,IF(Assumptions!$B$67="Optimistic",Scenarios!G128,Scenarios!G214)) -> 0.14 | H11: =IF(Assumptions!$B$67="Base Case",Scenarios!H42,IF(Assumptions!$B$67="Optimistic",Scenarios!H128,Scenarios!H214)) -> 0.14
A12: Other Income / Expense | D12: =IF(Assumptions!$B$67="Base Case",Scenarios!D14,IF(Assumptions!$B$67="Optimistic",Scenarios!D100,Scenarios!D186)) -> 0 | E12: =IF(Assumptions!$B$67="Base Case",Scenarios!E14,IF(Assumptions!$B$67="Optimistic",Scenarios!E100,Scenarios!E186)) -> 0 | F12: =IF(Assumptions!$B$67="Base Case",Scenarios!F14,IF(Assumptions!$B$67="Optimistic",Scenarios!F100,Scenarios!F186)) -> 0 | G12: =IF(Assumptions!$B$67="Base Case",Scenarios!G14,IF(Assumptions!$B$67="Optimistic",Scenarios!G100,Scenarios!G186)) -> 0 | H12: =IF(Assumptions!$B$67="Base Case",Scenarios!H14,IF(Assumptions!$B$67="Optimistic",Scenarios!H100,Scenarios!H186)) -> 0
A13: Shares Outstanding | D13: =IF(Assumptions!$B$67="Base Case",Scenarios!D15,IF(Assumptions!$B$67="Optimistic",Scenarios!D101,Scenarios!D187)) -> 100000 | E13: =IF(Assumptions!$B$67="Base Case",Scenarios!E15,IF(Assumptions!$B$67="Optimistic",Scenarios!E101,Scenarios!E187)) -> 100000 | F13: =IF(Assumptions!$B$67="Base Case",Scenarios!F15,IF(Assumptions!$B$67="Optimistic",Scenarios!F101,Scenarios!F187)) -> 100000 | G13: =IF(Assumptions!$B$67="Base Case",Scenarios!G15,IF(Assumptions!$B$67="Optimistic",Scenarios!G101,Scenarios!G187)) -> 100000 | H13: =IF(Assumptions!$B$67="Base Case",Scenarios!H15,IF(Assumptions!$B$67="Optimistic",Scenarios!H101,Scenarios!H187)) -> 100000
A14: Stock-Based Comp Amount | D14: =IF(Assumptions!$B$67="Base Case",Scenarios!D16,IF(Assumptions!$B$67="Optimistic",Scenarios!D102,Scenarios!D188)) -> 0 | E14: =IF(Assumptions!$B$67="Base Case",Scenarios!E16,IF(Assumptions!$B$67="Optimistic",Scenarios!E102,Scenarios!E188)) -> 0 | F14: =IF(Assumptions!$B$67="Base Case",Scenarios!F16,IF(Assumptions!$B$67="Optimistic",Scenarios!F102,Scenarios!F188)) -> 0 | G14: =IF(Assumptions!$B$67="Base Case",Scenarios!G16,IF(Assumptions!$B$67="Optimistic",Scenarios!G102,Scenarios!G188)) -> 0 | H14: =IF(Assumptions!$B$67="Base Case",Scenarios!H16,IF(Assumptions!$B$67="Optimistic",Scenarios!H102,Scenarios!H188)) -> 0
A15: ── Balance Sheet / WC Drivers ──
A16: DSO (Days) | D16: =IF(Assumptions!$B$67="Base Case",Scenarios!D20,IF(Assumptions!$B$67="Optimistic",Scenarios!D106,Scenarios!D192)) -> 45 | E16: =IF(Assumptions!$B$67="Base Case",Scenarios!E20,IF(Assumptions!$B$67="Optimistic",Scenarios!E106,Scenarios!E192)) -> 45 | F16: =IF(Assumptions!$B$67="Base Case",Scenarios!F20,IF(Assumptions!$B$67="Optimistic",Scenarios!F106,Scenarios!F192)) -> 45 | G16: =IF(Assumptions!$B$67="Base Case",Scenarios!G20,IF(Assumptions!$B$67="Optimistic",Scenarios!G106,Scenarios!G192)) -> 45 | H16: =IF(Assumptions!$B$67="Base Case",Scenarios!H20,IF(Assumptions!$B$67="Optimistic",Scenarios!H106,Scenarios!H192)) -> 45
A17: DIO (Days) | D17: =IF(Assumptions!$B$67="Base Case",Scenarios!D21,IF(Assumptions!$B$67="Optimistic",Scenarios!D107,Scenarios!D193)) -> 30 | E17: =IF(Assumptions!$B$67="Base Case",Scenarios!E21,IF(Assumptions!$B$67="Optimistic",Scenarios!E107,Scenarios!E193)) -> 30 | F17: =IF(Assumptions!$B$67="Base Case",Scenarios!F21,IF(Assumptions!$B$67="Optimistic",Scenarios!F107,Scenarios!F193)) -> 30 | G17: =IF(Assumptions!$B$67="Base Case",Scenarios!G21,IF(Assumptions!$B$67="Optimistic",Scenarios!G107,Scenarios!G193)) -> 30 | H17: =IF(Assumptions!$B$67="Base Case",Scenarios!H21,IF(Assumptions!$B$67="Optimistic",Scenarios!H107,Scenarios!H193)) -> 30
A18: DPO (Days) | D18: =IF(Assumptions!$B$67="Base Case",Scenarios!D22,IF(Assumptions!$B$67="Optimistic",Scenarios!D108,Scenarios!D194)) -> 40 | E18: =IF(Assumptions!$B$67="Base Case",Scenarios!E22,IF(Assumptions!$B$67="Optimistic",Scenarios!E108,Scenarios!E194)) -> 40 | F18: =IF(Assumptions!$B$67="Base Case",Scenarios!F22,IF(Assumptions!$B$67="Optimistic",Scenarios!F108,Scenarios!F194)) -> 40 | G18: =IF(Assumptions!$B$67="Base Case",Scenarios!G22,IF(Assumptions!$B$67="Optimistic",Scenarios!G108,Scenarios!G194)) -> 40 | H18: =IF(Assumptions!$B$67="Base Case",Scenarios!H22,IF(Assumptions!$B$67="Optimistic",Scenarios!H108,Scenarios!H194)) -> 40
A19: Prepaid % of Revenue | D19: =IF(Assumptions!$B$67="Base Case",Scenarios!D23,IF(Assumptions!$B$67="Optimistic",Scenarios!D109,Scenarios!D195)) -> 0.01 | E19: =IF(Assumptions!$B$67="Base Case",Scenarios!E23,IF(Assumptions!$B$67="Optimistic",Scenarios!E109,Scenarios!E195)) -> 0.01 | F19: =IF(Assumptions!$B$67="Base Case",Scenarios!F23,IF(Assumptions!$B$67="Optimistic",Scenarios!F109,Scenarios!F195)) -> 0.01 | G19: =IF(Assumptions!$B$67="Base Case",Scenarios!G23,IF(Assumptions!$B$67="Optimistic",Scenarios!G109,Scenarios!G195)) -> 0.01 | H19: =IF(Assumptions!$B$67="Base Case",Scenarios!H23,IF(Assumptions!$B$67="Optimistic",Scenarios!H109,Scenarios!H195)) -> 0.01
A20: Accrued Exp % of Revenue | D20: =IF(Assumptions!$B$67="Base Case",Scenarios!D24,IF(Assumptions!$B$67="Optimistic",Scenarios!D110,Scenarios!D196)) -> 0.03 | E20: =IF(Assumptions!$B$67="Base Case",Scenarios!E24,IF(Assumptions!$B$67="Optimistic",Scenarios!E110,Scenarios!E196)) -> 0.03 | F20: =IF(Assumptions!$B$67="Base Case",Scenarios!F24,IF(Assumptions!$B$67="Optimistic",Scenarios!F110,Scenarios!F196)) -> 0.03 | G20: =IF(Assumptions!$B$67="Base Case",Scenarios!G24,IF(Assumptions!$B$67="Optimistic",Scenarios!G110,Scenarios!G196)) -> 0.03 | H20: =IF(Assumptions!$B$67="Base Case",Scenarios!H24,IF(Assumptions!$B$67="Optimistic",Scenarios!H110,Scenarios!H196)) -> 0.03
A21: Deferred Rev % of Revenue | D21: =IF(Assumptions!$B$67="Base Case",Scenarios!D25,IF(Assumptions!$B$67="Optimistic",Scenarios!D111,Scenarios!D197)) -> 0.02 | E21: =IF(Assumptions!$B$67="Base Case",Scenarios!E25,IF(Assumptions!$B$67="Optimistic",Scenarios!E111,Scenarios!E197)) -> 0.02 | F21: =IF(Assumptions!$B$67="Base Case",Scenarios!F25,IF(Assumptions!$B$67="Optimistic",Scenarios!F111,Scenarios!F197)) -> 0.02 | G21: =IF(Assumptions!$B$67="Base Case",Scenarios!G25,IF(Assumptions!$B$67="Optimistic",Scenarios!G111,Scenarios!G197)) -> 0.02 | H21: =IF(Assumptions!$B$67="Base Case",Scenarios!H25,IF(Assumptions!$B$67="Optimistic",Scenarios!H111,Scenarios!H197)) -> 0.02
A22: ── CapEx & Depreciation Drivers ──
A23: CapEx % of Revenue | D23: =IF(Assumptions!$B$67="Base Case",Scenarios!D27,IF(Assumptions!$B$67="Optimistic",Scenarios!D113,Scenarios!D199)) -> 0.05 | E23: =IF(Assumptions!$B$67="Base Case",Scenarios!E27,IF(Assumptions!$B$67="Optimistic",Scenarios!E113,Scenarios!E199)) -> 0.05 | F23: =IF(Assumptions!$B$67="Base Case",Scenarios!F27,IF(Assumptions!$B$67="Optimistic",Scenarios!F113,Scenarios!F199)) -> 0.05 | G23: =IF(Assumptions!$B$67="Base Case",Scenarios!G27,IF(Assumptions!$B$67="Optimistic",Scenarios!G113,Scenarios!G199)) -> 0.05 | H23: =IF(Assumptions!$B$67="Base Case",Scenarios!H27,IF(Assumptions!$B$67="Optimistic",Scenarios!H113,Scenarios!H199)) -> 0.05
A24: Depreciation Rate (% Gross PPE) | D24: =IF(Assumptions!$B$67="Base Case",Scenarios!D28,IF(Assumptions!$B$67="Optimistic",Scenarios!D114,Scenarios!D200)) -> 0.094025157 | E24: =IF(Assumptions!$B$67="Base Case",Scenarios!E28,IF(Assumptions!$B$67="Optimistic",Scenarios!E114,Scenarios!E200)) -> 0.094284759 | F24: =IF(Assumptions!$B$67="Base Case",Scenarios!F28,IF(Assumptions!$B$67="Optimistic",Scenarios!F114,Scenarios!F200)) -> 0.094551124 | G24: =IF(Assumptions!$B$67="Base Case",Scenarios!G28,IF(Assumptions!$B$67="Optimistic",Scenarios!G114,Scenarios!G200)) -> 0.094822299 | H24: =IF(Assumptions!$B$67="Base Case",Scenarios!H28,IF(Assumptions!$B$67="Optimistic",Scenarios!H114,Scenarios!H200)) -> 0.095096572
A25: Amortization Amount | D25: =IF(Assumptions!$B$67="Base Case",Scenarios!D29,IF(Assumptions!$B$67="Optimistic",Scenarios!D115,Scenarios!D201)) -> 5000 | E25: =IF(Assumptions!$B$67="Base Case",Scenarios!E29,IF(Assumptions!$B$67="Optimistic",Scenarios!E115,Scenarios!E201)) -> 5000 | F25: =IF(Assumptions!$B$67="Base Case",Scenarios!F29,IF(Assumptions!$B$67="Optimistic",Scenarios!F115,Scenarios!F201)) -> 5000 | G25: =IF(Assumptions!$B$67="Base Case",Scenarios!G29,IF(Assumptions!$B$67="Optimistic",Scenarios!G115,Scenarios!G201)) -> 5000 | H25: =IF(Assumptions!$B$67="Base Case",Scenarios!H29,IF(Assumptions!$B$67="Optimistic",Scenarios!H115,Scenarios!H201)) -> 5000
A26: ── Debt & Financing ──
A27: Interest Rate (on Debt) | D27: =IF(Assumptions!$B$67="Base Case",Scenarios!D31,IF(Assumptions!$B$67="Optimistic",Scenarios!D117,Scenarios!D203)) -> 0.22 | E27: =IF(Assumptions!$B$67="Base Case",Scenarios!E31,IF(Assumptions!$B$67="Optimistic",Scenarios!E117,Scenarios!E203)) -> 0.2 | F27: =IF(Assumptions!$B$67="Base Case",Scenarios!F31,IF(Assumptions!$B$67="Optimistic",Scenarios!F117,Scenarios!F203)) -> 0.18 | G27: =IF(Assumptions!$B$67="Base Case",Scenarios!G31,IF(Assumptions!$B$67="Optimistic",Scenarios!G117,Scenarios!G203)) -> 0.17 | H27: =IF(Assumptions!$B$67="Base Case",Scenarios!H31,IF(Assumptions!$B$67="Optimistic",Scenarios!H117,Scenarios!H203)) -> 0.16
A28: Interest Income Rate (on Cash) | D28: =IF(Assumptions!$B$67="Base Case",Scenarios!D32,IF(Assumptions!$B$67="Optimistic",Scenarios!D118,Scenarios!D204)) -> 0.19 | E28: =IF(Assumptions!$B$67="Base Case",Scenarios!E32,IF(Assumptions!$B$67="Optimistic",Scenarios!E118,Scenarios!E204)) -> 0.17 | F28: =IF(Assumptions!$B$67="Base Case",Scenarios!F32,IF(Assumptions!$B$67="Optimistic",Scenarios!F118,Scenarios!F204)) -> 0.15 | G28: =IF(Assumptions!$B$67="Base Case",Scenarios!G32,IF(Assumptions!$B$67="Optimistic",Scenarios!G118,Scenarios!G204)) -> 0.13 | H28: =IF(Assumptions!$B$67="Base Case",Scenarios!H32,IF(Assumptions!$B$67="Optimistic",Scenarios!H118,Scenarios!H204)) -> 0.12
A29: EPD Rate (Employee Profit Sharing) | D29: =IF(Assumptions!$B$67="Base Case",Scenarios!D17,IF(Assumptions!$B$67="Optimistic",Scenarios!D103,Scenarios!D189)) -> 0.1 | E29: =IF(Assumptions!$B$67="Base Case",Scenarios!E17,IF(Assumptions!$B$67="Optimistic",Scenarios!E103,Scenarios!E189)) -> 0.1 | F29: =IF(Assumptions!$B$67="Base Case",Scenarios!F17,IF(Assumptions!$B$67="Optimistic",Scenarios!F103,Scenarios!F189)) -> 0.1 | G29: =IF(Assumptions!$B$67="Base Case",Scenarios!G17,IF(Assumptions!$B$67="Optimistic",Scenarios!G103,Scenarios!G189)) -> 0.1 | H29: =IF(Assumptions!$B$67="Base Case",Scenarios!H17,IF(Assumptions!$B$67="Optimistic",Scenarios!H103,Scenarios!H189)) -> 0.1
A30: Short-Term Debt | D30: =IF(Assumptions!$B$67="Base Case",Scenarios!D33,IF(Assumptions!$B$67="Optimistic",Scenarios!D119,Scenarios!D205)) -> 50000 | E30: =IF(Assumptions!$B$67="Base Case",Scenarios!E33,IF(Assumptions!$B$67="Optimistic",Scenarios!E119,Scenarios!E205)) -> 50000 | F30: =IF(Assumptions!$B$67="Base Case",Scenarios!F33,IF(Assumptions!$B$67="Optimistic",Scenarios!F119,Scenarios!F205)) -> 50000 | G30: =IF(Assumptions!$B$67="Base Case",Scenarios!G33,IF(Assumptions!$B$67="Optimistic",Scenarios!G119,Scenarios!G205)) -> 50000 | H30: =IF(Assumptions!$B$67="Base Case",Scenarios!H33,IF(Assumptions!$B$67="Optimistic",Scenarios!H119,Scenarios!H205)) -> 50000
A31: LT Debt Issuance | D31: =IF(Assumptions!$B$67="Base Case",Scenarios!D34,IF(Assumptions!$B$67="Optimistic",Scenarios!D120,Scenarios!D206)) -> 0 | E31: =IF(Assumptions!$B$67="Base Case",Scenarios!E34,IF(Assumptions!$B$67="Optimistic",Scenarios!E120,Scenarios!E206)) -> 0 | F31: =IF(Assumptions!$B$67="Base Case",Scenarios!F34,IF(Assumptions!$B$67="Optimistic",Scenarios!F120,Scenarios!F206)) -> 0 | G31: =IF(Assumptions!$B$67="Base Case",Scenarios!G34,IF(Assumptions!$B$67="Optimistic",Scenarios!G120,Scenarios!G206)) -> 0 | H31: =IF(Assumptions!$B$67="Base Case",Scenarios!H34,IF(Assumptions!$B$67="Optimistic",Scenarios!H120,Scenarios!H206)) -> 0
A32: LT Debt Repayment | D32: =IF(Assumptions!$B$67="Base Case",Scenarios!D35,IF(Assumptions!$B$67="Optimistic",Scenarios!D121,Scenarios!D207)) -> 0 | E32: =IF(Assumptions!$B$67="Base Case",Scenarios!E35,IF(Assumptions!$B$67="Optimistic",Scenarios!E121,Scenarios!E207)) -> 0 | F32: =IF(Assumptions!$B$67="Base Case",Scenarios!F35,IF(Assumptions!$B$67="Optimistic",Scenarios!F121,Scenarios!F207)) -> 0 | G32: =IF(Assumptions!$B$67="Base Case",Scenarios!G35,IF(Assumptions!$B$67="Optimistic",Scenarios!G121,Scenarios!G207)) -> 0 | H32: =IF(Assumptions!$B$67="Base Case",Scenarios!H35,IF(Assumptions!$B$67="Optimistic",Scenarios!H121,Scenarios!H207)) -> 0
A33: Current Portion LTD | D33: =IF(Assumptions!$B$67="Base Case",Scenarios!D36,IF(Assumptions!$B$67="Optimistic",Scenarios!D122,Scenarios!D208)) -> 20000 | E33: =IF(Assumptions!$B$67="Base Case",Scenarios!E36,IF(Assumptions!$B$67="Optimistic",Scenarios!E122,Scenarios!E208)) -> 20000 | F33: =IF(Assumptions!$B$67="Base Case",Scenarios!F36,IF(Assumptions!$B$67="Optimistic",Scenarios!F122,Scenarios!F208)) -> 20000 | G33: =IF(Assumptions!$B$67="Base Case",Scenarios!G36,IF(Assumptions!$B$67="Optimistic",Scenarios!G122,Scenarios!G208)) -> 20000 | H33: =IF(Assumptions!$B$67="Base Case",Scenarios!H36,IF(Assumptions!$B$67="Optimistic",Scenarios!H122,Scenarios!H208)) -> 20000
A34: Dividend Payout Ratio | D34: =IF(Assumptions!$B$67="Base Case",Scenarios!D37,IF(Assumptions!$B$67="Optimistic",Scenarios!D123,Scenarios!D209)) -> 0.3 | E34: =IF(Assumptions!$B$67="Base Case",Scenarios!E37,IF(Assumptions!$B$67="Optimistic",Scenarios!E123,Scenarios!E209)) -> 0.3 | F34: =IF(Assumptions!$B$67="Base Case",Scenarios!F37,IF(Assumptions!$B$67="Optimistic",Scenarios!F123,Scenarios!F209)) -> 0.3 | G34: =IF(Assumptions!$B$67="Base Case",Scenarios!G37,IF(Assumptions!$B$67="Optimistic",Scenarios!G123,Scenarios!G209)) -> 0.3 | H34: =IF(Assumptions!$B$67="Base Case",Scenarios!H37,IF(Assumptions!$B$67="Optimistic",Scenarios!H123,Scenarios!H209)) -> 0.3
A35: Share Repurchase Amount | D35: =IF(Assumptions!$B$67="Base Case",Scenarios!D38,IF(Assumptions!$B$67="Optimistic",Scenarios!D124,Scenarios!D210)) -> 0 | E35: =IF(Assumptions!$B$67="Base Case",Scenarios!E38,IF(Assumptions!$B$67="Optimistic",Scenarios!E124,Scenarios!E210)) -> 0 | F35: =IF(Assumptions!$B$67="Base Case",Scenarios!F38,IF(Assumptions!$B$67="Optimistic",Scenarios!F124,Scenarios!F210)) -> 0 | G35: =IF(Assumptions!$B$67="Base Case",Scenarios!G38,IF(Assumptions!$B$67="Optimistic",Scenarios!G124,Scenarios!G210)) -> 0 | H35: =IF(Assumptions!$B$67="Base Case",Scenarios!H38,IF(Assumptions!$B$67="Optimistic",Scenarios!H124,Scenarios!H210)) -> 0
A36: Legal Reserve % | D36: 0.05 | E36: 0.05 | F36: 0.05 | G36: 0.05 | H36: 0.05
A37: Paid-Up Capital | D37: =IF(Assumptions!$B$67="Base Case",Scenarios!D18,IF(Assumptions!$B$67="Optimistic",Scenarios!D104,Scenarios!D190)) -> 10000 | E37: =IF(Assumptions!$B$67="Base Case",Scenarios!E18,IF(Assumptions!$B$67="Optimistic",Scenarios!E104,Scenarios!E190)) -> 10000 | F37: =IF(Assumptions!$B$67="Base Case",Scenarios!F18,IF(Assumptions!$B$67="Optimistic",Scenarios!F104,Scenarios!F190)) -> 10000 | G37: =IF(Assumptions!$B$67="Base Case",Scenarios!G18,IF(Assumptions!$B$67="Optimistic",Scenarios!G104,Scenarios!G190)) -> 10000 | H37: =IF(Assumptions!$B$67="Base Case",Scenarios!H18,IF(Assumptions!$B$67="Optimistic",Scenarios!H104,Scenarios!H190)) -> 10000
A38: Dividend WHT Rate | D38: 0.1 | E38: 0.1 | F38: 0.1 | G38: 0.1 | H38: 0.1
A39: Equity Issuance | D39: =IF(Assumptions!$B$67="Base Case",Scenarios!D39,IF(Assumptions!$B$67="Optimistic",Scenarios!D125,Scenarios!D211)) -> 0 | E39: =IF(Assumptions!$B$67="Base Case",Scenarios!E39,IF(Assumptions!$B$67="Optimistic",Scenarios!E125,Scenarios!E211)) -> 0 | F39: =IF(Assumptions!$B$67="Base Case",Scenarios!F39,IF(Assumptions!$B$67="Optimistic",Scenarios!F125,Scenarios!F211)) -> 0 | G39: =IF(Assumptions!$B$67="Base Case",Scenarios!G39,IF(Assumptions!$B$67="Optimistic",Scenarios!G125,Scenarios!G211)) -> 0 | H39: =IF(Assumptions!$B$67="Base Case",Scenarios!H39,IF(Assumptions!$B$67="Optimistic",Scenarios!H125,Scenarios!H211)) -> 0
A40: ── BS / Equity Direct Values ──
A41: Goodwill | B41: ='Historical Data'!B33 -> 100000 | C41: ='Historical Data'!C33 -> 100000 | D41: =IF(Assumptions!$B$67="Base Case",Scenarios!D44,IF(Assumptions!$B$67="Optimistic",Scenarios!D130,Scenarios!D216)) -> 100000 | E41: =IF(Assumptions!$B$67="Base Case",Scenarios!E44,IF(Assumptions!$B$67="Optimistic",Scenarios!E130,Scenarios!E216)) -> 100000 | F41: =IF(Assumptions!$B$67="Base Case",Scenarios!F44,IF(Assumptions!$B$67="Optimistic",Scenarios!F130,Scenarios!F216)) -> 100000 | G41: =IF(Assumptions!$B$67="Base Case",Scenarios!G44,IF(Assumptions!$B$67="Optimistic",Scenarios!G130,Scenarios!G216)) -> 100000 | H41: =IF(Assumptions!$B$67="Base Case",Scenarios!H44,IF(Assumptions!$B$67="Optimistic",Scenarios!H130,Scenarios!H216)) -> 100000
A42: Other Current Assets | B42: ='Historical Data'!B28 -> 10000 | C42: ='Historical Data'!C28 -> 10000 | D42: =IF(Assumptions!$B$67="Base Case",Scenarios!D45,IF(Assumptions!$B$67="Optimistic",Scenarios!D131,Scenarios!D217)) -> 10000 | E42: =IF(Assumptions!$B$67="Base Case",Scenarios!E45,IF(Assumptions!$B$67="Optimistic",Scenarios!E131,Scenarios!E217)) -> 10000 | F42: =IF(Assumptions!$B$67="Base Case",Scenarios!F45,IF(Assumptions!$B$67="Optimistic",Scenarios!F131,Scenarios!F217)) -> 10000 | G42: =IF(Assumptions!$B$67="Base Case",Scenarios!G45,IF(Assumptions!$B$67="Optimistic",Scenarios!G131,Scenarios!G217)) -> 10000 | H42: =IF(Assumptions!$B$67="Base Case",Scenarios!H45,IF(Assumptions!$B$67="Optimistic",Scenarios!H131,Scenarios!H217)) -> 10000
A43: Other Long-Term Assets | B43: ='Historical Data'!B34 -> 20000 | C43: ='Historical Data'!C34 -> 20000 | D43: =IF(Assumptions!$B$67="Base Case",Scenarios!D46,IF(Assumptions!$B$67="Optimistic",Scenarios!D132,Scenarios!D218)) -> 20000 | E43: =IF(Assumptions!$B$67="Base Case",Scenarios!E46,IF(Assumptions!$B$67="Optimistic",Scenarios!E132,Scenarios!E218)) -> 20000 | F43: =IF(Assumptions!$B$67="Base Case",Scenarios!F46,IF(Assumptions!$B$67="Optimistic",Scenarios!F132,Scenarios!F218)) -> 20000 | G43: =IF(Assumptions!$B$67="Base Case",Scenarios!G46,IF(Assumptions!$B$67="Optimistic",Scenarios!G132,Scenarios!G218)) -> 20000 | H43: =IF(Assumptions!$B$67="Base Case",Scenarios!H46,IF(Assumptions!$B$67="Optimistic",Scenarios!H132,Scenarios!H218)) -> 20000
A44: Other Current Liabilities | B44: ='Historical Data'!B41 -> 15000 | C44: ='Historical Data'!C41 -> 15000 | D44: =IF(Assumptions!$B$67="Base Case",Scenarios!D47,IF(Assumptions!$B$67="Optimistic",Scenarios!D133,Scenarios!D219)) -> 15000 | E44: =IF(Assumptions!$B$67="Base Case",Scenarios!E47,IF(Assumptions!$B$67="Optimistic",Scenarios!E133,Scenarios!E219)) -> 15000 | F44: =IF(Assumptions!$B$67="Base Case",Scenarios!F47,IF(Assumptions!$B$67="Optimistic",Scenarios!F133,Scenarios!F219)) -> 15000 | G44: =IF(Assumptions!$B$67="Base Case",Scenarios!G47,IF(Assumptions!$B$67="Optimistic",Scenarios!G133,Scenarios!G219)) -> 15000 | H44: =IF(Assumptions!$B$67="Base Case",Scenarios!H47,IF(Assumptions!$B$67="Optimistic",Scenarios!H133,Scenarios!H219)) -> 15000
A45: Deferred Tax Liabilities | B45: ='Historical Data'!B43 -> 30000 | C45: ='Historical Data'!C43 -> 30000 | D45: =IF(Assumptions!$B$67="Base Case",Scenarios!D48,IF(Assumptions!$B$67="Optimistic",Scenarios!D134,Scenarios!D220)) -> 30000 | E45: =IF(Assumptions!$B$67="Base Case",Scenarios!E48,IF(Assumptions!$B$67="Optimistic",Scenarios!E134,Scenarios!E220)) -> 30000 | F45: =IF(Assumptions!$B$67="Base Case",Scenarios!F48,IF(Assumptions!$B$67="Optimistic",Scenarios!F134,Scenarios!F220)) -> 30000 | G45: =IF(Assumptions!$B$67="Base Case",Scenarios!G48,IF(Assumptions!$B$67="Optimistic",Scenarios!G134,Scenarios!G220)) -> 30000 | H45: =IF(Assumptions!$B$67="Base Case",Scenarios!H48,IF(Assumptions!$B$67="Optimistic",Scenarios!H134,Scenarios!H220)) -> 30000
A46: Other LT Liabilities | B46: ='Historical Data'!B44 -> 25000 | C46: ='Historical Data'!C44 -> 25000 | D46: =IF(Assumptions!$B$67="Base Case",Scenarios!D49,IF(Assumptions!$B$67="Optimistic",Scenarios!D135,Scenarios!D221)) -> 25000 | E46: =IF(Assumptions!$B$67="Base Case",Scenarios!E49,IF(Assumptions!$B$67="Optimistic",Scenarios!E135,Scenarios!E221)) -> 25000 | F46: =IF(Assumptions!$B$67="Base Case",Scenarios!F49,IF(Assumptions!$B$67="Optimistic",Scenarios!F135,Scenarios!F221)) -> 25000 | G46: =IF(Assumptions!$B$67="Base Case",Scenarios!G49,IF(Assumptions!$B$67="Optimistic",Scenarios!G135,Scenarios!G221)) -> 25000 | H46: =IF(Assumptions!$B$67="Base Case",Scenarios!H49,IF(Assumptions!$B$67="Optimistic",Scenarios!H135,Scenarios!H221)) -> 25000
A47: Common Stock | B47: ='Historical Data'!B45 -> 10000 | C47: ='Historical Data'!C45 -> 10000 | D47: =IF(Assumptions!$B$67="Base Case",Scenarios!D50,IF(Assumptions!$B$67="Optimistic",Scenarios!D136,Scenarios!D222)) -> 10000 | E47: =IF(Assumptions!$B$67="Base Case",Scenarios!E50,IF(Assumptions!$B$67="Optimistic",Scenarios!E136,Scenarios!E222)) -> 10000 | F47: =IF(Assumptions!$B$67="Base Case",Scenarios!F50,IF(Assumptions!$B$67="Optimistic",Scenarios!F136,Scenarios!F222)) -> 10000 | G47: =IF(Assumptions!$B$67="Base Case",Scenarios!G50,IF(Assumptions!$B$67="Optimistic",Scenarios!G136,Scenarios!G222)) -> 10000 | H47: =IF(Assumptions!$B$67="Base Case",Scenarios!H50,IF(Assumptions!$B$67="Optimistic",Scenarios!H136,Scenarios!H222)) -> 10000
A48: APIC | B48: ='Historical Data'!B46 -> 210000 | C48: ='Historical Data'!C46 -> 220000 | D48: =IF(Assumptions!$B$67="Base Case",Scenarios!D51,IF(Assumptions!$B$67="Optimistic",Scenarios!D137,Scenarios!D223)) -> 220000 | E48: =IF(Assumptions!$B$67="Base Case",Scenarios!E51,IF(Assumptions!$B$67="Optimistic",Scenarios!E137,Scenarios!E223)) -> 220000 | F48: =IF(Assumptions!$B$67="Base Case",Scenarios!F51,IF(Assumptions!$B$67="Optimistic",Scenarios!F137,Scenarios!F223)) -> 220000 | G48: =IF(Assumptions!$B$67="Base Case",Scenarios!G51,IF(Assumptions!$B$67="Optimistic",Scenarios!G137,Scenarios!G223)) -> 220000 | H48: =IF(Assumptions!$B$67="Base Case",Scenarios!H51,IF(Assumptions!$B$67="Optimistic",Scenarios!H137,Scenarios!H223)) -> 220000
A49: Other Comprehensive Income | B49: ='Historical Data'!B50 -> 0 | C49: ='Historical Data'!C50 -> 0 | D49: =IF(Assumptions!$B$67="Base Case",Scenarios!D52,IF(Assumptions!$B$67="Optimistic",Scenarios!D138,Scenarios!D224)) -> 0 | E49: =IF(Assumptions!$B$67="Base Case",Scenarios!E52,IF(Assumptions!$B$67="Optimistic",Scenarios!E138,Scenarios!E224)) -> 0 | F49: =IF(Assumptions!$B$67="Base Case",Scenarios!F52,IF(Assumptions!$B$67="Optimistic",Scenarios!F138,Scenarios!F224)) -> 0 | G49: =IF(Assumptions!$B$67="Base Case",Scenarios!G52,IF(Assumptions!$B$67="Optimistic",Scenarios!G138,Scenarios!G224)) -> 0 | H49: =IF(Assumptions!$B$67="Base Case",Scenarios!H52,IF(Assumptions!$B$67="Optimistic",Scenarios!H138,Scenarios!H224)) -> 0
A50: ── Engine-Computed Values ──
A51: Interest Income (Computed) | B51: ='Historical Data'!B15 -> 2500 | C51: ='Historical Data'!C15 -> 3000 | D51: =IF(Assumptions!$B$67="Base Case",Scenarios!D54,IF(Assumptions!$B$67="Optimistic",Scenarios!D140,Scenarios!D226)) -> 58322.115 | E51: =IF(Assumptions!$B$67="Base Case",Scenarios!E54,IF(Assumptions!$B$67="Optimistic",Scenarios!E140,Scenarios!E226)) -> 80000.745 | F51: =IF(Assumptions!$B$67="Base Case",Scenarios!F54,IF(Assumptions!$B$67="Optimistic",Scenarios!F140,Scenarios!F226)) -> 88687.637 | G51: =IF(Assumptions!$B$67="Base Case",Scenarios!G54,IF(Assumptions!$B$67="Optimistic",Scenarios!G140,Scenarios!G226)) -> 94238.234 | H51: =IF(Assumptions!$B$67="Base Case",Scenarios!H54,IF(Assumptions!$B$67="Optimistic",Scenarios!H140,Scenarios!H226)) -> 104504.81
A52: Interest Expense (Computed) | B52: ='Historical Data'!B14 -> 14000 | C52: ='Historical Data'!C14 -> 13000 | D52: =IF(Assumptions!$B$67="Base Case",Scenarios!D55,IF(Assumptions!$B$67="Optimistic",Scenarios!D141,Scenarios!D227)) -> 61600 | E52: =IF(Assumptions!$B$67="Base Case",Scenarios!E55,IF(Assumptions!$B$67="Optimistic",Scenarios!E141,Scenarios!E227)) -> 56000 | F52: =IF(Assumptions!$B$67="Base Case",Scenarios!F55,IF(Assumptions!$B$67="Optimistic",Scenarios!F141,Scenarios!F227)) -> 50400 | G52: =IF(Assumptions!$B$67="Base Case",Scenarios!G55,IF(Assumptions!$B$67="Optimistic",Scenarios!G141,Scenarios!G227)) -> 47600 | H52: =IF(Assumptions!$B$67="Base Case",Scenarios!H55,IF(Assumptions!$B$67="Optimistic",Scenarios!H141,Scenarios!H227)) -> 44800
A53: Depreciation (Computed) | B53: ='Historical Data'!B9 -> 28000 | C53: ='Historical Data'!C9 -> 32000 | D53: =IF(Assumptions!$B$67="Base Case",Scenarios!D56,IF(Assumptions!$B$67="Optimistic",Scenarios!D142,Scenarios!D228)) -> 41112.5 | E53: =IF(Assumptions!$B$67="Base Case",Scenarios!E56,IF(Assumptions!$B$67="Optimistic",Scenarios!E142,Scenarios!E228)) -> 46546.5 | F53: =IF(Assumptions!$B$67="Base Case",Scenarios!F56,IF(Assumptions!$B$67="Optimistic",Scenarios!F142,Scenarios!F228)) -> 52387.005 | G53: =IF(Assumptions!$B$67="Base Case",Scenarios!G56,IF(Assumptions!$B$67="Optimistic",Scenarios!G142,Scenarios!G228)) -> 58606.155 | H53: =IF(Assumptions!$B$67="Base Case",Scenarios!H56,IF(Assumptions!$B$67="Optimistic",Scenarios!H142,Scenarios!H228)) -> 65166.453
A54: Gross PP&E (Computed) | B54: ='Historical Data'!B29 -> 340000 | C54: ='Historical Data'!C29 -> 385000 | D54: =IF(Assumptions!$B$67="Base Case",Scenarios!D57,IF(Assumptions!$B$67="Optimistic",Scenarios!D143,Scenarios!D229)) -> 437250 | E54: =IF(Assumptions!$B$67="Base Case",Scenarios!E57,IF(Assumptions!$B$67="Optimistic",Scenarios!E143,Scenarios!E229)) -> 493680 | F54: =IF(Assumptions!$B$67="Base Case",Scenarios!F57,IF(Assumptions!$B$67="Optimistic",Scenarios!F143,Scenarios!F229)) -> 554060.1 | G54: =IF(Assumptions!$B$67="Base Case",Scenarios!G57,IF(Assumptions!$B$67="Optimistic",Scenarios!G143,Scenarios!G229)) -> 618063.01 | H54: =IF(Assumptions!$B$67="Base Case",Scenarios!H57,IF(Assumptions!$B$67="Optimistic",Scenarios!H143,Scenarios!H229)) -> 685266.06
A55: Accum Depreciation (Computed) | B55: ='Historical Data'!B30 -> 128000 | C55: ='Historical Data'!C30 -> 160000 | D55: =IF(Assumptions!$B$67="Base Case",Scenarios!D58,IF(Assumptions!$B$67="Optimistic",Scenarios!D144,Scenarios!D230)) -> 201112.5 | E55: =IF(Assumptions!$B$67="Base Case",Scenarios!E58,IF(Assumptions!$B$67="Optimistic",Scenarios!E144,Scenarios!E230)) -> 247659 | F55: =IF(Assumptions!$B$67="Base Case",Scenarios!F58,IF(Assumptions!$B$67="Optimistic",Scenarios!F144,Scenarios!F230)) -> 300046.01 | G55: =IF(Assumptions!$B$67="Base Case",Scenarios!G58,IF(Assumptions!$B$67="Optimistic",Scenarios!G144,Scenarios!G230)) -> 358652.16 | H55: =IF(Assumptions!$B$67="Base Case",Scenarios!H58,IF(Assumptions!$B$67="Optimistic",Scenarios!H144,Scenarios!H230)) -> 423818.61
A56: Net PP&E (Computed) | B56: ='Historical Data'!B31 -> 212000 | C56: ='Historical Data'!C31 -> 225000 | D56: =IF(Assumptions!$B$67="Base Case",Scenarios!D59,IF(Assumptions!$B$67="Optimistic",Scenarios!D145,Scenarios!D231)) -> 236137.5 | E56: =IF(Assumptions!$B$67="Base Case",Scenarios!E59,IF(Assumptions!$B$67="Optimistic",Scenarios!E145,Scenarios!E231)) -> 246021 | F56: =IF(Assumptions!$B$67="Base Case",Scenarios!F59,IF(Assumptions!$B$67="Optimistic",Scenarios!F145,Scenarios!F231)) -> 254014.09 | G56: =IF(Assumptions!$B$67="Base Case",Scenarios!G59,IF(Assumptions!$B$67="Optimistic",Scenarios!G145,Scenarios!G231)) -> 259410.85 | H56: =IF(Assumptions!$B$67="Base Case",Scenarios!H59,IF(Assumptions!$B$67="Optimistic",Scenarios!H145,Scenarios!H231)) -> 261447.44
A57: Intangibles (Computed) | B57: ='Historical Data'!B32 -> 45000 | C57: ='Historical Data'!C32 -> 40000 | D57: =IF(Assumptions!$B$67="Base Case",Scenarios!D60,IF(Assumptions!$B$67="Optimistic",Scenarios!D146,Scenarios!D232)) -> 35000 | E57: =IF(Assumptions!$B$67="Base Case",Scenarios!E60,IF(Assumptions!$B$67="Optimistic",Scenarios!E146,Scenarios!E232)) -> 30000 | F57: =IF(Assumptions!$B$67="Base Case",Scenarios!F60,IF(Assumptions!$B$67="Optimistic",Scenarios!F146,Scenarios!F232)) -> 25000 | G57: =IF(Assumptions!$B$67="Base Case",Scenarios!G60,IF(Assumptions!$B$67="Optimistic",Scenarios!G146,Scenarios!G232)) -> 20000 | H57: =IF(Assumptions!$B$67="Base Case",Scenarios!H60,IF(Assumptions!$B$67="Optimistic",Scenarios!H146,Scenarios!H232)) -> 15000
A58: Long-Term Debt (Computed) | B58: ='Historical Data'!B42 -> 230000 | C58: ='Historical Data'!C42 -> 210000 | D58: =IF(Assumptions!$B$67="Base Case",Scenarios!D61,IF(Assumptions!$B$67="Optimistic",Scenarios!D147,Scenarios!D233)) -> 210000 | E58: =IF(Assumptions!$B$67="Base Case",Scenarios!E61,IF(Assumptions!$B$67="Optimistic",Scenarios!E147,Scenarios!E233)) -> 210000 | F58: =IF(Assumptions!$B$67="Base Case",Scenarios!F61,IF(Assumptions!$B$67="Optimistic",Scenarios!F147,Scenarios!F233)) -> 210000 | G58: =IF(Assumptions!$B$67="Base Case",Scenarios!G61,IF(Assumptions!$B$67="Optimistic",Scenarios!G147,Scenarios!G233)) -> 210000 | H58: =IF(Assumptions!$B$67="Base Case",Scenarios!H61,IF(Assumptions!$B$67="Optimistic",Scenarios!H147,Scenarios!H233)) -> 210000
A59: Retained Earnings (Computed) | B59: ='Historical Data'!B48 -> 28823 | C59: ='Historical Data'!C48 -> 78506 | D59: =IF(Assumptions!$B$67="Base Case",Scenarios!D62,IF(Assumptions!$B$67="Optimistic",Scenarios!D148,Scenarios!D234)) -> 168242.03 | E59: =IF(Assumptions!$B$67="Base Case",Scenarios!E62,IF(Assumptions!$B$67="Optimistic",Scenarios!E148,Scenarios!E234)) -> 281531.78 | F59: =IF(Assumptions!$B$67="Base Case",Scenarios!F62,IF(Assumptions!$B$67="Optimistic",Scenarios!F148,Scenarios!F234)) -> 407817.19 | G59: =IF(Assumptions!$B$67="Base Case",Scenarios!G62,IF(Assumptions!$B$67="Optimistic",Scenarios!G148,Scenarios!G234)) -> 543279.93 | H59: =IF(Assumptions!$B$67="Base Case",Scenarios!H62,IF(Assumptions!$B$67="Optimistic",Scenarios!H148,Scenarios!H234)) -> 689106.73
A60: Treasury Stock (Computed) | B60: ='Historical Data'!B49 -> 0 | C60: ='Historical Data'!C49 -> 0 | D60: =IF(Assumptions!$B$67="Base Case",Scenarios!D63,IF(Assumptions!$B$67="Optimistic",Scenarios!D149,Scenarios!D235)) -> 0 | E60: =IF(Assumptions!$B$67="Base Case",Scenarios!E63,IF(Assumptions!$B$67="Optimistic",Scenarios!E149,Scenarios!E235)) -> 0 | F60: =IF(Assumptions!$B$67="Base Case",Scenarios!F63,IF(Assumptions!$B$67="Optimistic",Scenarios!F149,Scenarios!F235)) -> 0 | G60: =IF(Assumptions!$B$67="Base Case",Scenarios!G63,IF(Assumptions!$B$67="Optimistic",Scenarios!G149,Scenarios!G235)) -> 0 | H60: =IF(Assumptions!$B$67="Base Case",Scenarios!H63,IF(Assumptions!$B$67="Optimistic",Scenarios!H149,Scenarios!H235)) -> 0
A61: APIC (Computed) | B61: ='Historical Data'!B46 -> 210000 | C61: ='Historical Data'!C46 -> 220000 | D61: =IF(Assumptions!$B$67="Base Case",Scenarios!D64,IF(Assumptions!$B$67="Optimistic",Scenarios!D150,Scenarios!D236)) -> 220000 | E61: =IF(Assumptions!$B$67="Base Case",Scenarios!E64,IF(Assumptions!$B$67="Optimistic",Scenarios!E150,Scenarios!E236)) -> 220000 | F61: =IF(Assumptions!$B$67="Base Case",Scenarios!F64,IF(Assumptions!$B$67="Optimistic",Scenarios!F150,Scenarios!F236)) -> 220000 | G61: =IF(Assumptions!$B$67="Base Case",Scenarios!G64,IF(Assumptions!$B$67="Optimistic",Scenarios!G150,Scenarios!G236)) -> 220000 | H61: =IF(Assumptions!$B$67="Base Case",Scenarios!H64,IF(Assumptions!$B$67="Optimistic",Scenarios!H150,Scenarios!H236)) -> 220000
A62: Legal Reserve (Computed) | B62: ='Historical Data'!B47 -> 0 | C62: ='Historical Data'!C47 -> 0 | D62: 5000 | E62: 5000 | F62: 5000 | G62: 5000 | H62: 5000
A63: EOS Provision (Computed) | B63: ='Historical Data'!B51 -> 0 | C63: ='Historical Data'!C51 -> 0 | D63: 0 | E63: 0 | F63: 0 | G63: 0 | H63: 0
A64: Dividends Paid (Computed) | B64: 0 | C64: ='Historical Data'!C18-('Historical Data'!C48-'Historical Data'!B48) -> -46417 | D64: =IF(Assumptions!$B$67="Base Case",Scenarios!D65,IF(Assumptions!$B$67="Optimistic",Scenarios!D151,Scenarios!D237)) -> -38458.299 | E64: =IF(Assumptions!$B$67="Base Case",Scenarios!E65,IF(Assumptions!$B$67="Optimistic",Scenarios!E151,Scenarios!E237)) -> -48552.747 | F64: =IF(Assumptions!$B$67="Base Case",Scenarios!F65,IF(Assumptions!$B$67="Optimistic",Scenarios!F151,Scenarios!F237)) -> -54122.322 | G64: =IF(Assumptions!$B$67="Base Case",Scenarios!G65,IF(Assumptions!$B$67="Optimistic",Scenarios!G151,Scenarios!G237)) -> -58055.46 | H64: =IF(Assumptions!$B$67="Base Case",Scenarios!H65,IF(Assumptions!$B$67="Optimistic",Scenarios!H151,Scenarios!H237)) -> -62497.198
A66: ── SCENARIO CONTROL ──
A67: Active Scenario | B67: =Dashboard!B6 -> Base Case
A68: ⚠ Change scenario via Dashboard!B6 dropdown only.

Sheet Income Statement
A1: Demo Company Inc. — Income Statement | B1: 2024 (A) | C1: 2025 (A) | D1: 2026E | E1: 2027E | F1: 2028E | G1: 2029E | H1: 2030E
A2: Revenue | B2: ='Historical Data'!B4 -> 850000 | C2: ='Historical Data'!C4 -> 950000 | D2: =C2*(1+Assumptions!D4) -> 1045000 | E2: =D2*(1+Assumptions!E4) -> 1128600 | F2: =E2*(1+Assumptions!F4) -> 1207602 | G2: =F2*(1+Assumptions!G4) -> 1280058.1 | H2: =G2*(1+Assumptions!H4) -> 1344061
A3: Revenue Growth % | B3: =0 -> 0 | C3: =IF('Historical Data'!B4=0,0,('Historical Data'!C4-'Historical Data'!B4)/'Historical Data'!B4) -> 0.11764706 | D3: =Assumptions!D4 -> 0.1 | E3: =Assumptions!E4 -> 0.08 | F3: =Assumptions!F4 -> 0.07 | G3: =Assumptions!G4 -> 0.06 | H3: =Assumptions!H4 -> 0.05
A4: Cost of Goods Sold | B4: =B2*IF('Historical Data'!B4=0,0,'Historical Data'!B5/'Historical Data'!B4) -> 510000 | C4: =C2*IF('Historical Data'!C4=0,0,'Historical Data'!C5/'Historical Data'!C4) -> 570000 | D4: =D2*Assumptions!D5 -> 627000 | E4: =E2*Assumptions!E5 -> 677160 | F4: =F2*Assumptions!F5 -> 724561.2 | G4: =G2*Assumptions!G5 -> 768034.87 | H4: =H2*Assumptions!H5 -> 806436.62
A5: Gross Profit | B5: =B2-B4 -> 340000 | C5: =C2-C4 -> 380000 | D5: =D2-D4 -> 418000 | E5: =E2-E4 -> 451440 | F5: =F2-F4 -> 483040.8 | G5: =G2-G4 -> 512023.25 | H5: =H2-H4 -> 537624.41
A6: Gross Margin | B6: =IF(B2=0,0,B5/B2) -> 0.4 | C6: =IF(C2=0,0,C5/C2) -> 0.4 | D6: =IF(D2=0,0,D5/D2) -> 0.4 | E6: =IF(E2=0,0,E5/E2) -> 0.4 | F6: =IF(F2=0,0,F5/F2) -> 0.4 | G6: =IF(G2=0,0,G5/G2) -> 0.4 | H6: =IF(H2=0,0,H5/H2) -> 0.4
A8: Operating Expenses
A9: SG&A | B9: =B2*IF('Historical Data'!B4=0,0,'Historical Data'!B7/'Historical Data'!B4) -> 127500 | C9: =C2*IF('Historical Data'!C4=0,0,'Historical Data'!C7/'Historical Data'!C4) -> 142500 | D9: =D2*Assumptions!D6 -> 156750 | E9: =E2*Assumptions!E6 -> 169290 | F9: =F2*Assumptions!F6 -> 181140.3 | G9: =G2*Assumptions!G6 -> 192008.72 | H9: =H2*Assumptions!H6 -> 201609.15
A10: R&D | B10: =B2*IF('Historical Data'!B4=0,0,'Historical Data'!B8/'Historical Data'!B4) -> 42500 | C10: =C2*IF('Historical Data'!C4=0,0,'Historical Data'!C8/'Historical Data'!C4) -> 47500 | D10: =D2*Assumptions!D7 -> 0 | E10: =E2*Assumptions!E7 -> 0 | F10: =F2*Assumptions!F7 -> 0 | G10: =G2*Assumptions!G7 -> 0 | H10: =H2*Assumptions!H7 -> 0
A11: Depreciation | B11: ='Historical Data'!B9 -> 28000 | C11: ='Historical Data'!C9 -> 32000 | D11: =(Assumptions!C54+'Income Statement'!D2*Assumptions!D23/2)*Assumptions!D24 -> 41112.5 | E11: =(Assumptions!D54+'Income Statement'!E2*Assumptions!E23/2)*Assumptions!E24 -> 46546.5 | F11: =(Assumptions!E54+'Income Statement'!F2*Assumptions!F23/2)*Assumptions!F24 -> 52387.005 | G11: =(Assumptions!F54+'Income Statement'!G2*Assumptions!G23/2)*Assumptions!G24 -> 58606.155 | H11: =(Assumptions!G54+'Income Statement'!H2*Assumptions!H23/2)*Assumptions!H24 -> 65166.453
A12: Amortization | B12: ='Historical Data'!B10 -> 5000 | C12: ='Historical Data'!C10 -> 5000 | D12: =Assumptions!D25 -> 5000 | E12: =Assumptions!E25 -> 5000 | F12: =Assumptions!F25 -> 5000 | G12: =Assumptions!G25 -> 5000 | H12: =Assumptions!H25 -> 5000
A13: Other OpEx | B13: =B2*IF('Historical Data'!B4=0,0,'Historical Data'!B11/'Historical Data'!B4) -> 17000 | C13: =C2*IF('Historical Data'!C4=0,0,'Historical Data'!C11/'Historical Data'!C4) -> 19000 | D13: =D2*Assumptions!D8 -> 20900 | E13: =E2*Assumptions!E8 -> 22572 | F13: =F2*Assumptions!F8 -> 24152.04 | G13: =G2*Assumptions!G8 -> 25601.162 | H13: =H2*Assumptions!H8 -> 26881.221
A14: Stock-Based Comp | B14: ='Historical Data'!B21 -> 0 | C14: ='Historical Data'!C21 -> 0 | D14: =Assumptions!D14 -> 0 | E14: =Assumptions!E14 -> 0 | F14: =Assumptions!F14 -> 0 | G14: =Assumptions!G14 -> 0 | H14: =Assumptions!H14 -> 0
A15: Total OpEx | B15: =B9+B10+B11+B12+B13+B14 -> 220000 | C15: =C9+C10+C11+C12+C13+C14 -> 246000 | D15: =D9+D10+D11+D12+D13+D14 -> 223762.5 | E15: =E9+E10+E11+E12+E13+E14 -> 243408.5 | F15: =F9+F10+F11+F12+F13+F14 -> 262679.35 | G15: =G9+G10+G11+G12+G13+G14 -> 281216.04 | H15: =H9+H10+H11+H12+H13+H14 -> 298656.83
A17: EBIT | B17: =B5-B15 -> 120000 | C17: =C5-C15 -> 134000 | D17: =D5-D15 -> 194237.5 | E17: =E5-E15 -> 208031.5 | F17: =F5-F15 -> 220361.46 | G17: =G5-G15 -> 230807.21 | H17: =H5-H15 -> 238967.58
A18: EBITDA | B18: =B17+B11+B12 -> 153000 | C18: =C17+C11+C12 -> 171000 | D18: =D17+D11+D12 -> 240350 | E18: =E17+E11+E12 -> 259578 | F18: =F17+F11+F12 -> 277748.46 | G18: =G17+G11+G12 -> 294413.37 | H18: =H17+H11+H12 -> 309134.04
A19: EBIT Margin | B19: =IF(B2=0,0,B17/B2) -> 0.14117647 | C19: =IF(C2=0,0,C17/C2) -> 0.14105263 | D19: =IF(D2=0,0,D17/D2) -> 0.18587321 | E19: =IF(E2=0,0,E17/E2) -> 0.18432704 | F19: =IF(F2=0,0,F17/F2) -> 0.18247854 | G19: =IF(G2=0,0,G17/G2) -> 0.18030995 | H19: =IF(H2=0,0,H17/H2) -> 0.17779519
A21: Interest Income | B21: ='Historical Data'!B15 -> 2500 | C21: ='Historical Data'!C15 -> 3000 | D21: =Assumptions!D51 -> 58322.115 | E21: =Assumptions!E51 -> 80000.745 | F21: =Assumptions!F51 -> 88687.637 | G21: =Assumptions!G51 -> 94238.234 | H21: =Assumptions!H51 -> 104504.81
A22: Interest Expense | B22: ='Historical Data'!B14 -> 14000 | C22: ='Historical Data'!C14 -> 13000 | D22: =Assumptions!D52 -> 61600 | E22: =Assumptions!E52 -> 56000 | F22: =Assumptions!F52 -> 50400 | G22: =Assumptions!G52 -> 47600 | H22: =Assumptions!H52 -> 44800
A23: Other Income/Expense | B23: ='Historical Data'!B19 -> 0 | C23: ='Historical Data'!C19 -> 0 | D23: =Assumptions!D12 -> 0 | E23: =Assumptions!E12 -> 0 | F23: =Assumptions!F12 -> 0 | G23: =Assumptions!G12 -> 0 | H23: =Assumptions!H12 -> 0
A24: EBT | B24: =B17+B21-B22+B23 -> 108500 | C24: =C17+C21-C22+C23 -> 124000 | D24: =D17+D21-D22+D23 -> 190959.61 | E24: =E17+E21-E22+E23 -> 232032.24 | F24: =F17+F21-F22+F23 -> 258649.09 | G24: =G17+G21-G22+G23 -> 277445.45 | H24: =H17+H21-H22+H23 -> 298672.39
A25: Tax Expense | B25: =MAX(0,B24*IF('Historical Data'!B16=0,0,'Historical Data'!B17/'Historical Data'!B16)) -> 24412.5 | C25: =MAX(0,C24*IF('Historical Data'!C16=0,0,'Historical Data'!C17/'Historical Data'!C16)) -> 27900 | D25: =MAX(0,D24*Assumptions!D9) -> 42965.913 | E25: =MAX(0,E24*Assumptions!E9) -> 52207.255 | F25: =MAX(0,F24*Assumptions!F9) -> 58196.046 | G25: =MAX(0,G24*Assumptions!G9) -> 62425.225 | H25: =MAX(0,H24*Assumptions!H9) -> 67201.288
A26: Tax Rate | B26: =IF('Historical Data'!B16=0,0,'Historical Data'!B17/'Historical Data'!B16) -> 0.225 | C26: =IF('Historical Data'!C16=0,0,'Historical Data'!C17/'Historical Data'!C16) -> 0.225 | D26: =Assumptions!D9 -> 0.225 | E26: =Assumptions!E9 -> 0.225 | F26: =Assumptions!F9 -> 0.225 | G26: =Assumptions!G9 -> 0.225 | H26: =Assumptions!H9 -> 0.225
A28: Net Income | B28: =B24-B25 -> 84087.5 | C28: =C24-C25 -> 96100 | D28: =D24-D25 -> 147993.7 | E28: =E24-E25 -> 179824.99 | F28: =F24-F25 -> 200453.05 | G28: =G24-G25 -> 215020.22 | H28: =H24-H25 -> 231471.1
A29: Employee Profit Sharing (EPD) | B29: =0 -> 0 | C29: =0 -> 0 | D29: =MAX(0,D28*Assumptions!D29) -> 14799.37 | E29: =MAX(0,E28*Assumptions!E29) -> 17982.499 | F29: =MAX(0,F28*Assumptions!F29) -> 20045.305 | G29: =MAX(0,G28*Assumptions!G29) -> 21502.022 | H29: =MAX(0,H28*Assumptions!H29) -> 23147.11
A30: Net Income After EPD | B30: =B28-B29 -> 84087.5 | C30: =C28-C29 -> 96100 | D30: =D28-D29 -> 133194.33 | E30: =E28-E29 -> 161842.49 | F30: =F28-F29 -> 180407.74 | G30: =G28-G29 -> 193518.2 | H30: =H28-H29 -> 208323.99
A31: Legal Reserve Addition (5% NI) | B31: ='Historical Data'!B47 -> 0 | C31: ='Historical Data'!C47-'Historical Data'!B47 -> 0 | D31: =Assumptions!D62-'Historical Data'!C47 -> 5000 | E31: =Assumptions!E62-Assumptions!D62 -> 0 | F31: =Assumptions!F62-Assumptions!E62 -> 0 | G31: =Assumptions!G62-Assumptions!F62 -> 0 | H31: =Assumptions!H62-Assumptions!G62 -> 0
A32: Cumulative Legal Reserve | B32: ='Historical Data'!B47 -> 0 | C32: ='Historical Data'!C47 -> 0 | D32: =Assumptions!D62 -> 5000 | E32: =Assumptions!E62 -> 5000 | F32: =Assumptions!F62 -> 5000 | G32: =Assumptions!G62 -> 5000 | H32: =Assumptions!H62 -> 5000
A33: Distributable Profit | B33: =B28-B29-B31 -> 84087.5 | C33: =C28-C29-C31 -> 96100 | D33: =D28-D29-D31 -> 128194.33 | E33: =E28-E29-E31 -> 161842.49 | F33: =F28-F29-F31 -> 180407.74 | G33: =G28-G29-G31 -> 193518.2 | H33: =H28-H29-H31 -> 208323.99
A34: Gross Dividends | B34: =0 -> 0 | C34: =0 -> 0 | D34: =MAX(0,D33*Assumptions!D34) -> 38458.299 | E34: =MAX(0,E33*Assumptions!E34) -> 48552.747 | F34: =MAX(0,F33*Assumptions!F34) -> 54122.322 | G34: =MAX(0,G33*Assumptions!G34) -> 58055.46 | H34: =MAX(0,H33*Assumptions!H34) -> 62497.198
A35: Dividend WHT (10%) | B35: =B34*Assumptions!B38 -> 0 | C35: =C34*Assumptions!C38 -> 0 | D35: =D34*Assumptions!D38 -> 3845.8299 | E35: =E34*Assumptions!E38 -> 4855.2747 | F35: =F34*Assumptions!F38 -> 5412.2322 | G35: =G34*Assumptions!G38 -> 5805.546 | H35: =H34*Assumptions!H38 -> 6249.7198
A36: Net Dividends | B36: =B34-B35 -> 0 | C36: =C34-C35 -> 0 | D36: =D34-D35 -> 34612.469 | E36: =E34-E35 -> 43697.473 | F36: =F34-F35 -> 48710.09 | G36: =G34-G35 -> 52249.914 | H36: =H34-H35 -> 56247.478
A37: Addition to Retained Earnings | B37: 84087.5 | C37: 49683 | D37: =D33-D34 -> 89736.032 | E37: =E33-E34 -> 113289.74 | F37: =F33-F34 -> 126285.42 | G37: =G33-G34 -> 135462.74 | H37: =H33-H34 -> 145826.8
A39: Net Margin | B39: =IF(B2=0,0,B28/B2) -> 0.098926471 | C39: =IF(C2=0,0,C28/C2) -> 0.10115789 | D39: =IF(D2=0,0,D28/D2) -> 0.14162077 | E39: =IF(E2=0,0,E28/E2) -> 0.15933456 | F39: =IF(F2=0,0,F28/F2) -> 0.16599264 | G39: =IF(G2=0,0,G28/G2) -> 0.16797692 | H39: =IF(H2=0,0,H28/H2) -> 0.1722177
A40: EPS | B40: =IF('Historical Data'!B20=0,0,B30/'Historical Data'!B20) -> 0.840875 | C40: =IF('Historical Data'!C20=0,0,C30/'Historical Data'!C20) -> 0.961 | D40: =IF(Assumptions!D13=0,0,D30/Assumptions!D13) -> 1.3319433 | E40: =IF(Assumptions!E13=0,0,E30/Assumptions!E13) -> 1.6184249 | F40: =IF(Assumptions!F13=0,0,F30/Assumptions!F13) -> 1.8040774 | G40: =IF(Assumptions!G13=0,0,G30/Assumptions!G13) -> 1.935182 | H40: =IF(Assumptions!H13=0,0,H30/Assumptions!H13) -> 2.0832399
A42: MEMO ITEMS
A43: NOPAT | B43: =B17*(1-IF('Historical Data'!B16=0,0,'Historical Data'!B17/'Historical Data'!B16)) -> 93000 | C43: =C17*(1-IF('Historical Data'!C16=0,0,'Historical Data'!C17/'Historical Data'!C16)) -> 103850 | D43: =D17*(1-Assumptions!D9) -> 150534.06 | E43: =E17*(1-Assumptions!E9) -> 161224.41 | F43: =F17*(1-Assumptions!F9) -> 170780.13 | G43: =G17*(1-Assumptions!G9) -> 178875.59 | H43: =H17*(1-Assumptions!H9) -> 185199.88
A44: FCFF | B44: 0 | C44: 0 | D44: =IF(Dashboard!$B$6="Base Case",'_Calc_Base'!D34,IF(Dashboard!$B$6="Optimistic",'_Calc_Opt'!D34,'_Calc_Con'!D34)) -> 134245.03 | E44: =IF(Dashboard!$B$6="Base Case",'_Calc_Base'!E34,IF(Dashboard!$B$6="Optimistic",'_Calc_Opt'!E34,'_Calc_Con'!E34)) -> 147408.31 | F44: =IF(Dashboard!$B$6="Base Case",'_Calc_Base'!F34,IF(Dashboard!$B$6="Optimistic",'_Calc_Opt'!F34,'_Calc_Con'!F34)) -> 159345.72 | G44: =IF(Dashboard!$B$6="Base Case",'_Calc_Base'!G34,IF(Dashboard!$B$6="Optimistic",'_Calc_Opt'!G34,'_Calc_Con'!G34)) -> 170736.95 | H44: =IF(Dashboard!$B$6="Base Case",'_Calc_Base'!H34,IF(Dashboard!$B$6="Optimistic",'_Calc_Opt'!H34,'_Calc_Con'!H34)) -> 181324.61
A45: Disallowed Interest (Thin-Cap) | B45: 0 | C45: 0 | D45: 0 | E45: 0 | F45: 0 | G45: 0 | H45: 0
A46: Adjusted Taxable Income | B46: 108500 | C46: 124000 | D46: 190959.61 | E46: 232032.24 | F46: 258649.09 | G46: 277445.45 | H46: 298672.39
A47: Stock-Based Compensation | B47: ='Historical Data'!B21 -> 0 | C47: ='Historical Data'!C21 -> 0 | D47: =Assumptions!D14 -> 0 | E47: =Assumptions!E14 -> 0 | F47: =Assumptions!F14 -> 0 | G47: =Assumptions!G14 -> 0 | H47: =Assumptions!H14 -> 0

Sheet Balance Sheet
A1: Demo Company Inc. — Balance Sheet | B1: 2024 (A) | C1: 2025 (A) | D1: 2026E | E1: 2027E | F1: 2028E | G1: 2029E | H1: 2030E
A2: ASSETS
A3: Cash & Equivalents | B3: =B46-B4-B5-B6-B7-B8-B17 -> 175000 | C3: =C46-C4-C5-C6-C7-C8-C17 -> 200000 | D3: ='Cash Flow Statement'!C43 -> 413917 | E3: ='Cash Flow Statement'!D43 -> 527268.24 | F3: ='Cash Flow Statement'!E43 -> 655233.58 | G3: ='Cash Flow Statement'!F43 -> 794585.4 | H3: ='Cash Flow Statement'!G43 -> 947161.42
A4: Accounts Receivable | B4: ='Income Statement'!B2*IF('Historical Data'!B4=0,0,'Historical Data'!B25/'Historical Data'!B4*365)/365 -> 104795 | C4: ='Income Statement'!C2*IF('Historical Data'!C4=0,0,'Historical Data'!C25/'Historical Data'!C4*365)/365 -> 117123 | D4: ='Income Statement'!D2*Assumptions!D16/365 -> 128835.62 | E4: ='Income Statement'!E2*Assumptions!E16/365 -> 139142.47 | F4: ='Income Statement'!F2*Assumptions!F16/365 -> 148882.44 | G4: ='Income Statement'!G2*Assumptions!G16/365 -> 157815.38 | H4: ='Income Statement'!H2*Assumptions!H16/365 -> 165706.15
A5: Inventory | B5: ='Income Statement'!B4*IF('Historical Data'!B5=0,0,'Historical Data'!B26/'Historical Data'!B5*365)/365 -> 41918 | C5: ='Income Statement'!C4*IF('Historical Data'!C5=0,0,'Historical Data'!C26/'Historical Data'!C5*365)/365 -> 46849 | D5: ='Income Statement'!D4*Assumptions!D17/365 -> 51534.247 | E5: ='Income Statement'!E4*Assumptions!E17/365 -> 55656.986 | F5: ='Income Statement'!F4*Assumptions!F17/365 -> 59552.975 | G5: ='Income Statement'!G4*Assumptions!G17/365 -> 63126.154 | H5: ='Income Statement'!H4*Assumptions!H17/365 -> 66282.462
A6: Prepaid Expenses | B6: ='Income Statement'!B2*IF('Historical Data'!B4=0,0,'Historical Data'!B27/'Historical Data'!B4) -> 8500 | C6: ='Income Statement'!C2*IF('Historical Data'!C4=0,0,'Historical Data'!C27/'Historical Data'!C4) -> 9500 | D6: ='Income Statement'!D2*Assumptions!D19 -> 10450 | E6: ='Income Statement'!E2*Assumptions!E19 -> 11286 | F6: ='Income Statement'!F2*Assumptions!F19 -> 12076.02 | G6: ='Income Statement'!G2*Assumptions!G19 -> 12800.581 | H6: ='Income Statement'!H2*Assumptions!H19 -> 13440.61
A7: Other Current Assets | B7: ='Historical Data'!B28 -> 10000 | C7: ='Historical Data'!C28 -> 10000 | D7: =Assumptions!D42 -> 10000 | E7: =Assumptions!E42 -> 10000 | F7: =Assumptions!F42 -> 10000 | G7: =Assumptions!G42 -> 10000 | H7: =Assumptions!H42 -> 10000
A8: VAT Receivable | B8: 0 | C8: 0 | D8: =IF(Assumptions!D10=0,0,ABS('Income Statement'!D2*Assumptions!D23)*Assumptions!D11) -> 7315 | E8: =IF(Assumptions!E10=0,0,ABS('Income Statement'!E2*Assumptions!E23)*Assumptions!E11) -> 7900.2 | F8: =IF(Assumptions!F10=0,0,ABS('Income Statement'!F2*Assumptions!F23)*Assumptions!F11) -> 8453.214 | G8: =IF(Assumptions!G10=0,0,ABS('Income Statement'!G2*Assumptions!G23)*Assumptions!G11) -> 8960.4068 | H8: =IF(Assumptions!H10=0,0,ABS('Income Statement'!H2*Assumptions!H23)*Assumptions!H11) -> 9408.4272
A9: Total Current Assets | B9: =SUM(B3:B8) -> 340213 | C9: =SUM(C3:C8) -> 383472 | D9: =SUM(D3:D8) -> 622051.86 | E9: =SUM(E3:E8) -> 751253.89 | F9: =SUM(F3:F8) -> 894198.23 | G9: =SUM(G3:G8) -> 1047287.9 | H9: =SUM(H3:H8) -> 1211999.1
A11: Gross PP&E | B11: ='Historical Data'!B29 -> 340000 | C11: ='Historical Data'!C29 -> 385000 | D11: =C11+'Income Statement'!D2*Assumptions!D23 -> 437250 | E11: =D11+'Income Statement'!E2*Assumptions!E23 -> 493680 | F11: =E11+'Income Statement'!F2*Assumptions!F23 -> 554060.1 | G11: =F11+'Income Statement'!G2*Assumptions!G23 -> 618063.01 | H11: =G11+'Income Statement'!H2*Assumptions!H23 -> 685266.06
A12: Accumulated Depreciation | B12: ='Historical Data'!B30 -> 128000 | C12: ='Historical Data'!C30 -> 160000 | D12: =C12+'Income Statement'!D11 -> 201112.5 | E12: =D12+'Income Statement'!E11 -> 247659 | F12: =E12+'Income Statement'!F11 -> 300046.01 | G12: =F12+'Income Statement'!G11 -> 358652.16 | H12: =G12+'Income Statement'!H11 -> 423818.61
A13: Net PP&E | B13: =B11-B12 -> 212000 | C13: =C11-C12 -> 225000 | D13: =D11-D12 -> 236137.5 | E13: =E11-E12 -> 246021 | F13: =F11-F12 -> 254014.09 | G13: =G11-G12 -> 259410.85 | H13: =H11-H12 -> 261447.44
A14: Intangibles | B14: ='Historical Data'!B32 -> 45000 | C14: ='Historical Data'!C32 -> 40000 | D14: =MAX(0,C14-'Income Statement'!D12) -> 35000 | E14: =MAX(0,D14-'Income Statement'!E12) -> 30000 | F14: =MAX(0,E14-'Income Statement'!F12) -> 25000 | G14: =MAX(0,F14-'Income Statement'!G12) -> 20000 | H14: =MAX(0,G14-'Income Statement'!H12) -> 15000
A15: Goodwill | B15: ='Historical Data'!B33 -> 100000 | C15: ='Historical Data'!C33 -> 100000 | D15: =Assumptions!D41 -> 100000 | E15: =Assumptions!E41 -> 100000 | F15: =Assumptions!F41 -> 100000 | G15: =Assumptions!G41 -> 100000 | H15: =Assumptions!H41 -> 100000
A16: Other Long-Term Assets | B16: ='Historical Data'!B34 -> 20000 | C16: ='Historical Data'!C34 -> 20000 | D16: =Assumptions!D43 -> 20000 | E16: =Assumptions!E43 -> 20000 | F16: =Assumptions!F43 -> 20000 | G16: =Assumptions!G43 -> 20000 | H16: =Assumptions!H43 -> 20000
A17: Total Non-Current Assets | B17: =B13+B14+B15+B16 -> 377000 | C17: =C13+C14+C15+C16 -> 385000 | D17: =D13+D14+D15+D16 -> 391137.5 | E17: =E13+E14+E15+E16 -> 396021 | F17: =F13+F14+F15+F16 -> 399014.09 | G17: =G13+G14+G15+G16 -> 399410.85 | H17: =H13+H14+H15+H16 -> 396447.44
A18: Total Assets | B18: =B9+B17 -> 717213 | C18: =C9+C17 -> 768472 | D18: =D9+D17 -> 1013189.4 | E18: =E9+E17 -> 1147274.9 | F18: =F9+F17 -> 1293212.3 | G18: =G9+G17 -> 1446698.8 | H18: =H9+H17 -> 1608446.5
A20: LIABILITIES
A21: Accounts Payable | B21: ='Income Statement'!B4*IF('Historical Data'!B5=0,0,'Historical Data'!B36/'Historical Data'!B5*365)/365 -> 55890 | C21: ='Income Statement'!C4*IF('Historical Data'!C5=0,0,'Historical Data'!C36/'Historical Data'!C5*365)/365 -> 62466 | D21: ='Income Statement'!D4*Assumptions!D18/365 -> 68712.329 | E21: ='Income Statement'!E4*Assumptions!E18/365 -> 74209.315 | F21: ='Income Statement'!F4*Assumptions!F18/365 -> 79403.967 | G21: ='Income Statement'!G4*Assumptions!G18/365 -> 84168.205 | H21: ='Income Statement'!H4*Assumptions!H18/365 -> 88376.615
A22: Accrued Expenses | B22: ='Income Statement'!B2*IF('Historical Data'!B4=0,0,'Historical Data'!B37/'Historical Data'!B4) -> 25500 | C22: ='Income Statement'!C2*IF('Historical Data'!C4=0,0,'Historical Data'!C37/'Historical Data'!C4) -> 28500 | D22: ='Income Statement'!D2*Assumptions!D20 -> 31350 | E22: ='Income Statement'!E2*Assumptions!E20 -> 33858 | F22: ='Income Statement'!F2*Assumptions!F20 -> 36228.06 | G22: ='Income Statement'!G2*Assumptions!G20 -> 38401.744 | H22: ='Income Statement'!H2*Assumptions!H20 -> 40321.831
A23: Short-Term Debt | B23: ='Historical Data'!B38 -> 50000 | C23: ='Historical Data'!C38 -> 50000 | D23: =Assumptions!D30 -> 50000 | E23: =Assumptions!E30 -> 50000 | F23: =Assumptions!F30 -> 50000 | G23: =Assumptions!G30 -> 50000 | H23: =Assumptions!H30 -> 50000
A24: Current Portion LTD | B24: ='Historical Data'!B39 -> 20000 | C24: ='Historical Data'!C39 -> 20000 | D24: =Assumptions!D33 -> 20000 | E24: =Assumptions!E33 -> 20000 | F24: =Assumptions!F33 -> 20000 | G24: =Assumptions!G33 -> 20000 | H24: =Assumptions!H33 -> 20000
A25: Deferred Revenue | B25: ='Income Statement'!B2*IF('Historical Data'!B4=0,0,'Historical Data'!B40/'Historical Data'!B4) -> 17000 | C25: ='Income Statement'!C2*IF('Historical Data'!C4=0,0,'Historical Data'!C40/'Historical Data'!C4) -> 19000 | D25: ='Income Statement'!D2*Assumptions!D21 -> 20900 | E25: ='Income Statement'!E2*Assumptions!E21 -> 22572 | F25: ='Income Statement'!F2*Assumptions!F21 -> 24152.04 | G25: ='Income Statement'!G2*Assumptions!G21 -> 25601.162 | H25: ='Income Statement'!H2*Assumptions!H21 -> 26881.221
A26: Other Current Liabilities | B26: ='Historical Data'!B41 -> 15000 | C26: ='Historical Data'!C41 -> 15000 | D26: =Assumptions!D44 -> 15000 | E26: =Assumptions!E44 -> 15000 | F26: =Assumptions!F44 -> 15000 | G26: =Assumptions!G44 -> 15000 | H26: =Assumptions!H44 -> 15000
A27: VAT Payable | B27: 0 | C27: 0 | D27: =IF(Assumptions!D10=0,0,MAX(0,'Income Statement'!D2*Assumptions!D11-ABS('Income Statement'!D2*Assumptions!D23)*Assumptions!D11)) -> 138985 | E27: =IF(Assumptions!E10=0,0,MAX(0,'Income Statement'!E2*Assumptions!E11-ABS('Income Statement'!E2*Assumptions!E23)*Assumptions!E11)) -> 150103.8 | F27: =IF(Assumptions!F10=0,0,MAX(0,'Income Statement'!F2*Assumptions!F11-ABS('Income Statement'!F2*Assumptions!F23)*Assumptions!F11)) -> 160611.07 | G27: =IF(Assumptions!G10=0,0,MAX(0,'Income Statement'!G2*Assumptions!G11-ABS('Income Statement'!G2*Assumptions!G23)*Assumptions!G11)) -> 170247.73 | H27: =IF(Assumptions!H10=0,0,MAX(0,'Income Statement'!H2*Assumptions!H11-ABS('Income Statement'!H2*Assumptions!H23)*Assumptions!H11)) -> 178760.12
A28: Total Current Liabilities | B28: =SUM(B21:B27) -> 183390 | C28: =SUM(C21:C27) -> 194966 | D28: =SUM(D21:D27) -> 344947.33 | E28: =SUM(E21:E27) -> 365743.12 | F28: =SUM(F21:F27) -> 385395.13 | G28: =SUM(G21:G27) -> 403418.84 | H28: =SUM(H21:H27) -> 419339.78
A30: Long-Term Debt | B30: ='Historical Data'!B42 -> 230000 | C30: ='Historical Data'!C42 -> 210000 | D30: =C30+Assumptions!D31-Assumptions!D32 -> 210000 | E30: =D30+Assumptions!E31-Assumptions!E32 -> 210000 | F30: =E30+Assumptions!F31-Assumptions!F32 -> 210000 | G30: =F30+Assumptions!G31-Assumptions!G32 -> 210000 | H30: =G30+Assumptions!H31-Assumptions!H32 -> 210000
A31: Deferred Tax Liabilities | B31: ='Historical Data'!B43 -> 30000 | C31: ='Historical Data'!C43 -> 30000 | D31: =Assumptions!D45 -> 30000 | E31: =Assumptions!E45 -> 30000 | F31: =Assumptions!F45 -> 30000 | G31: =Assumptions!G45 -> 30000 | H31: =Assumptions!H45 -> 30000
A32: End of Service Provision | B32: ='Historical Data'!B51 -> 0 | C32: ='Historical Data'!C51 -> 0 | D32: =Assumptions!D63 -> 0 | E32: =Assumptions!E63 -> 0 | F32: =Assumptions!F63 -> 0 | G32: =Assumptions!G63 -> 0 | H32: =Assumptions!H63 -> 0
A33: Other LT Liabilities | B33: ='Historical Data'!B44 -> 25000 | C33: ='Historical Data'!C44 -> 25000 | D33: =Assumptions!D46 -> 25000 | E33: =Assumptions!E46 -> 25000 | F33: =Assumptions!F46 -> 25000 | G33: =Assumptions!G46 -> 25000 | H33: =Assumptions!H46 -> 25000
A34: Total Non-Current Liabilities | B34: =SUM(B30:B33) -> 285000 | C34: =SUM(C30:C33) -> 265000 | D34: =SUM(D30:D33) -> 265000 | E34: =SUM(E30:E33) -> 265000 | F34: =SUM(F30:F33) -> 265000 | G34: =SUM(G30:G33) -> 265000 | H34: =SUM(H30:H33) -> 265000
A35: Total Liabilities | B35: =B28+B34 -> 468390 | C35: =C28+C34 -> 459966 | D35: =D28+D34 -> 609947.33 | E35: =E28+E34 -> 630743.12 | F35: =F28+F34 -> 650395.13 | G35: =G28+G34 -> 668418.84 | H35: =H28+H34 -> 684339.78
A37: EQUITY
A38: Common Stock | B38: ='Historical Data'!B45 -> 10000 | C38: ='Historical Data'!C45 -> 10000 | D38: =Assumptions!D47 -> 10000 | E38: =Assumptions!E47 -> 10000 | F38: =Assumptions!F47 -> 10000 | G38: =Assumptions!G47 -> 10000 | H38: =Assumptions!H47 -> 10000
A39: Additional Paid-in Capital | B39: ='Historical Data'!B46 -> 210000 | C39: ='Historical Data'!C46 -> 220000 | D39: =C39+Assumptions!D39+Assumptions!D14 -> 220000 | E39: =D39+Assumptions!E39+Assumptions!E14 -> 220000 | F39: =E39+Assumptions!F39+Assumptions!F14 -> 220000 | G39: =F39+Assumptions!G39+Assumptions!G14 -> 220000 | H39: =G39+Assumptions!H39+Assumptions!H14 -> 220000
A40: Legal Reserve | B40: ='Historical Data'!B47 -> 0 | C40: ='Historical Data'!C47 -> 0 | D40: =C40+'Income Statement'!D31 -> 5000 | E40: =D40+'Income Statement'!E31 -> 5000 | F40: =E40+'Income Statement'!F31 -> 5000 | G40: =F40+'Income Statement'!G31 -> 5000 | H40: =G40+'Income Statement'!H31 -> 5000
A41: Retained Earnings | B41: ='Historical Data'!B48 -> 28823 | C41: ='Historical Data'!C48 -> 78506 | D41: =C41+'Income Statement'!D37 -> 168242.03 | E41: =D41+'Income Statement'!E37 -> 281531.78 | F41: =E41+'Income Statement'!F37 -> 407817.19 | G41: =F41+'Income Statement'!G37 -> 543279.93 | H41: =G41+'Income Statement'!H37 -> 689106.73
A42: Treasury Stock | B42: ='Historical Data'!B49 -> 0 | C42: ='Historical Data'!C49 -> 0 | D42: =C42-Assumptions!D35 -> 0 | E42: =D42-Assumptions!E35 -> 0 | F42: =E42-Assumptions!F35 -> 0 | G42: =F42-Assumptions!G35 -> 0 | H42: =G42-Assumptions!H35 -> 0
A43: Other Comprehensive Income | B43: ='Historical Data'!B50 -> 0 | C43: ='Historical Data'!C50 -> 0 | D43: =Assumptions!D49 -> 0 | E43: =Assumptions!E49 -> 0 | F43: =Assumptions!F49 -> 0 | G43: =Assumptions!G49 -> 0 | H43: =Assumptions!H49 -> 0
A44: Total Equity | B44: =SUM(B38:B43) -> 248823 | C44: =SUM(C38:C43) -> 308506 | D44: =SUM(D38:D43) -> 403242.03 | E44: =SUM(E38:E43) -> 516531.78 | F44: =SUM(F38:F43) -> 642817.19 | G44: =SUM(G38:G43) -> 778279.93 | H44: =SUM(H38:H43) -> 924106.73
A46: Total Liabilities + Equity | B46: =B35+B44 -> 717213 | C46: =C35+C44 -> 768472 | D46: =D35+D44 -> 1013189.4 | E46: =E35+E44 -> 1147274.9 | F46: =F35+F44 -> 1293212.3 | G46: =G35+G44 -> 1446698.8 | H46: =H35+H44 -> 1608446.5
A47: Balance Check (A − L+E) | B47: =B18-B46 -> 0 | C47: =C18-C46 -> 0 | D47: =D18-D46 -> 0 | E47: =E18-E46 -> 0 | F47: =F18-F46 -> 0 | G47: =G18-G46 -> 0 | H47: =H18-H46 -> 0
A48: Balanced? | B48: =IF(ABS(B47)<1,"✓ Balanced","✗ Imbalanced") -> ✓ Balanced | C48: =IF(ABS(C47)<1,"✓ Balanced","✗ Imbalanced") -> ✓ Balanced | D48: =IF(ABS(D47)<1,"✓ Balanced","✗ Imbalanced") -> ✓ Balanced | E48: =IF(ABS(E47)<1,"✓ Balanced","✗ Imbalanced") -> ✓ Balanced | F48: =IF(ABS(F47)<1,"✓ Balanced","✗ Imbalanced") -> ✓ Balanced | G48: =IF(ABS(G47)<1,"✓ Balanced","✗ Imbalanced") -> ✓ Balanced | H48: =IF(ABS(H47)<1,"✓ Balanced","✗ Imbalanced") -> ✓ Balanced

Sheet Cash Flow Statement
A1: Demo Company Inc. — Cash Flow Statement | B1: 2025 (A) | C1: 2026E | D1: 2027E | E1: 2028E | F1: 2029E | G1: 2030E
A2: Operating Activities
A3: Net Income | B3: ='Income Statement'!C28 -> 96100 | C3: ='Income Statement'!D28 -> 147993.7 | D3: ='Income Statement'!E28 -> 179824.99 | E3: ='Income Statement'!F28 -> 200453.05 | F3: ='Income Statement'!G28 -> 215020.22 | G3: ='Income Statement'!H28 -> 231471.1
A4: Depreciation | B4: ='Income Statement'!C11 -> 32000 | C4: ='Income Statement'!D11 -> 41112.5 | D4: ='Income Statement'!E11 -> 46546.5 | E4: ='Income Statement'!F11 -> 52387.005 | F4: ='Income Statement'!G11 -> 58606.155 | G4: ='Income Statement'!H11 -> 65166.453
A5: Amortization | B5: ='Income Statement'!C12 -> 5000 | C5: ='Income Statement'!D12 -> 5000 | D5: ='Income Statement'!E12 -> 5000 | E5: ='Income Statement'!F12 -> 5000 | F5: ='Income Statement'!G12 -> 5000 | G5: ='Income Statement'!H12 -> 5000
A6: Stock-Based Compensation | B6: ='Income Statement'!C47 -> 0 | C6: ='Income Statement'!D47 -> 0 | D6: ='Income Statement'!E47 -> 0 | E6: ='Income Statement'!F47 -> 0 | F6: ='Income Statement'!G47 -> 0 | G6: ='Income Statement'!H47 -> 0
A7: Deferred Taxes | B7: ='Balance Sheet'!C31-'Balance Sheet'!B31 -> 0 | C7: ='Balance Sheet'!D31-'Balance Sheet'!C31 -> 0 | D7: ='Balance Sheet'!E31-'Balance Sheet'!D31 -> 0 | E7: ='Balance Sheet'!F31-'Balance Sheet'!E31 -> 0 | F7: ='Balance Sheet'!G31-'Balance Sheet'!F31 -> 0 | G7: ='Balance Sheet'!H31-'Balance Sheet'!G31 -> 0
A8: Δ Other LT Liabilities | B8: ='Balance Sheet'!C33-'Balance Sheet'!B33 -> 0 | C8: ='Balance Sheet'!D33-'Balance Sheet'!C33 -> 0 | D8: ='Balance Sheet'!E33-'Balance Sheet'!D33 -> 0 | E8: ='Balance Sheet'!F33-'Balance Sheet'!E33 -> 0 | F8: ='Balance Sheet'!G33-'Balance Sheet'!F33 -> 0 | G8: ='Balance Sheet'!H33-'Balance Sheet'!G33 -> 0
A9: Δ OCI (non-cash) | B9: ='Balance Sheet'!C43-'Balance Sheet'!B43 -> 0 | C9: ='Balance Sheet'!D43-'Balance Sheet'!C43 -> 0 | D9: ='Balance Sheet'!E43-'Balance Sheet'!D43 -> 0 | E9: ='Balance Sheet'!F43-'Balance Sheet'!E43 -> 0 | F9: ='Balance Sheet'!G43-'Balance Sheet'!F43 -> 0 | G9: ='Balance Sheet'!H43-'Balance Sheet'!G43 -> 0
A10: Δ End of Service Provision | B10: ='Historical Data'!C51-'Historical Data'!B51 -> 0 | C10: =Assumptions!D63-'Historical Data'!C51 -> 0 | D10: =Assumptions!E63-Assumptions!D63 -> 0 | E10: =Assumptions!F63-Assumptions!E63 -> 0 | F10: =Assumptions!G63-Assumptions!F63 -> 0 | G10: =Assumptions!H63-Assumptions!G63 -> 0
A11: Working Capital Changes
A12: Change in A/R | B12: =-('Balance Sheet'!C4-'Balance Sheet'!B4) -> -12328 | C12: =-('Balance Sheet'!D4-'Balance Sheet'!C4) -> -11712.616 | D12: =-('Balance Sheet'!E4-'Balance Sheet'!D4) -> -10306.849 | E12: =-('Balance Sheet'!F4-'Balance Sheet'!E4) -> -9739.9726 | F12: =-('Balance Sheet'!G4-'Balance Sheet'!F4) -> -8932.9463 | G12: =-('Balance Sheet'!H4-'Balance Sheet'!G4) -> -7890.7692
A13: Change in Inventory | B13: =-('Balance Sheet'!C5-'Balance Sheet'!B5) -> -4931 | C13: =-('Balance Sheet'!D5-'Balance Sheet'!C5) -> -4685.2466 | D13: =-('Balance Sheet'!E5-'Balance Sheet'!D5) -> -4122.7397 | E13: =-('Balance Sheet'!F5-'Balance Sheet'!E5) -> -3895.989 | F13: =-('Balance Sheet'!G5-'Balance Sheet'!F5) -> -3573.1785 | G13: =-('Balance Sheet'!H5-'Balance Sheet'!G5) -> -3156.3077
A14: Change in Prepaid | B14: =-('Balance Sheet'!C6-'Balance Sheet'!B6) -> -1000 | C14: =-('Balance Sheet'!D6-'Balance Sheet'!C6) -> -950 | D14: =-('Balance Sheet'!E6-'Balance Sheet'!D6) -> -836 | E14: =-('Balance Sheet'!F6-'Balance Sheet'!E6) -> -790.02 | F14: =-('Balance Sheet'!G6-'Balance Sheet'!F6) -> -724.5612 | G14: =-('Balance Sheet'!H6-'Balance Sheet'!G6) -> -640.02906
A15: Change in A/P | B15: ='Balance Sheet'!C21-'Balance Sheet'!B21 -> 6576 | C15: ='Balance Sheet'!D21-'Balance Sheet'!C21 -> 6246.3288 | D15: ='Balance Sheet'!E21-'Balance Sheet'!D21 -> 5496.9863 | E15: ='Balance Sheet'!F21-'Balance Sheet'!E21 -> 5194.6521 | F15: ='Balance Sheet'!G21-'Balance Sheet'!F21 -> 4764.238 | G15: ='Balance Sheet'!H21-'Balance Sheet'!G21 -> 4208.4103
A16: Change in Accrued Exp | B16: ='Balance Sheet'!C22-'Balance Sheet'!B22 -> 3000 | C16: ='Balance Sheet'!D22-'Balance Sheet'!C22 -> 2850 | D16: ='Balance Sheet'!E22-'Balance Sheet'!D22 -> 2508 | E16: ='Balance Sheet'!F22-'Balance Sheet'!E22 -> 2370.06 | F16: ='Balance Sheet'!G22-'Balance Sheet'!F22 -> 2173.6836 | G16: ='Balance Sheet'!H22-'Balance Sheet'!G22 -> 1920.0872
A17: Change in Deferred Rev | B17: ='Balance Sheet'!C25-'Balance Sheet'!B25 -> 2000 | C17: ='Balance Sheet'!D25-'Balance Sheet'!C25 -> 1900 | D17: ='Balance Sheet'!E25-'Balance Sheet'!D25 -> 1672 | E17: ='Balance Sheet'!F25-'Balance Sheet'!E25 -> 1580.04 | F17: ='Balance Sheet'!G25-'Balance Sheet'!F25 -> 1449.1224 | G17: ='Balance Sheet'!H25-'Balance Sheet'!G25 -> 1280.0581
A18: Change in VAT Receivable | B18: =-('Balance Sheet'!C8-'Balance Sheet'!B8) -> 0 | C18: =-('Balance Sheet'!D8-'Balance Sheet'!C8) -> -7315 | D18: =-('Balance Sheet'!E8-'Balance Sheet'!D8) -> -585.2 | E18: =-('Balance Sheet'!F8-'Balance Sheet'!E8) -> -553.014 | F18: =-('Balance Sheet'!G8-'Balance Sheet'!F8) -> -507.19284 | G18: =-('Balance Sheet'!H8-'Balance Sheet'!G8) -> -448.02034
A19: Change in VAT Payable | B19: ='Balance Sheet'!C27-'Balance Sheet'!B27 -> 0 | C19: ='Balance Sheet'!D27-'Balance Sheet'!C27 -> 138985 | D19: ='Balance Sheet'!E27-'Balance Sheet'!D27 -> 11118.8 | E19: ='Balance Sheet'!F27-'Balance Sheet'!E27 -> 10507.266 | F19: ='Balance Sheet'!G27-'Balance Sheet'!F27 -> 9636.664 | G19: ='Balance Sheet'!H27-'Balance Sheet'!G27 -> 8512.3865
A20: Total WC Change | B20: =SUM(B12:B19) -> -6683 | C20: =SUM(C12:C19) -> 125318.47 | D20: =SUM(D12:D19) -> 4944.9973 | E20: =SUM(E12:E19) -> 4673.0224 | F20: =SUM(F12:F19) -> 4285.8291 | G20: =SUM(G12:G19) -> 3785.8157
A21: Cash from Operations | B21: =B3+B4+B5+B6+B7+B8+B9+B10+B20 -> 126417 | C21: =C3+C4+C5+C6+C7+C8+C9+C10+C20 -> 319424.67 | D21: =D3+D4+D5+D6+D7+D8+D9+D10+D20 -> 236316.49 | E21: =E3+E4+E5+E6+E7+E8+E9+E10+E20 -> 262513.07 | F21: =F3+F4+F5+F6+F7+F8+F9+F10+F20 -> 282912.21 | G21: =G3+G4+G5+G6+G7+G8+G9+G10+G20 -> 305423.37
A23: Investing Activities
A24: Capital Expenditures | B24: =-ABS('Income Statement'!C2*IF('Historical Data'!C4=0,0,('Historical Data'!C29-'Historical Data'!B29)/'Historical Data'!C4)) -> -45000 | C24: =-ABS('Income Statement'!D2*Assumptions!D23) -> -52250 | D24: =-ABS('Income Statement'!E2*Assumptions!E23) -> -56430 | E24: =-ABS('Income Statement'!F2*Assumptions!F23) -> -60380.1 | F24: =-ABS('Income Statement'!G2*Assumptions!G23) -> -64002.906 | G24: =-ABS('Income Statement'!H2*Assumptions!H23) -> -67203.051
A25: Purchase of Intangibles | B25: =-(('Balance Sheet'!C14-'Balance Sheet'!B14)+'Income Statement'!C12) -> 0 | C25: =-(('Balance Sheet'!D14-'Balance Sheet'!C14)+'Income Statement'!D12) -> 0 | D25: =-(('Balance Sheet'!E14-'Balance Sheet'!D14)+'Income Statement'!E12) -> 0 | E25: =-(('Balance Sheet'!F14-'Balance Sheet'!E14)+'Income Statement'!F12) -> 0 | F25: =-(('Balance Sheet'!G14-'Balance Sheet'!F14)+'Income Statement'!G12) -> 0 | G25: =-(('Balance Sheet'!H14-'Balance Sheet'!G14)+'Income Statement'!H12) -> 0
A26: Δ Other LT Assets | B26: =-('Balance Sheet'!C16-'Balance Sheet'!B16) -> 0 | C26: =-('Balance Sheet'!D16-'Balance Sheet'!C16) -> 0 | D26: =-('Balance Sheet'!E16-'Balance Sheet'!D16) -> 0 | E26: =-('Balance Sheet'!F16-'Balance Sheet'!E16) -> 0 | F26: =-('Balance Sheet'!G16-'Balance Sheet'!F16) -> 0 | G26: =-('Balance Sheet'!H16-'Balance Sheet'!G16) -> 0
A27: Acquisitions | B27: =0 -> 0 | C27: =0 -> 0 | D27: =0 -> 0 | E27: =0 -> 0 | F27: =0 -> 0 | G27: =0 -> 0
A28: Asset Sales | B28: =0 -> 0 | C28: =0 -> 0 | D28: =0 -> 0 | E28: =0 -> 0 | F28: =0 -> 0 | G28: =0 -> 0
A29: Cash from Investing | B29: =B24+B25+B26+B27+B28 -> -45000 | C29: =C24+C25+C26+C27+C28 -> -52250 | D29: =D24+D25+D26+D27+D28 -> -56430 | E29: =E24+E25+E26+E27+E28 -> -60380.1 | F29: =F24+F25+F26+F27+F28 -> -64002.906 | G29: =G24+G25+G26+G27+G28 -> -67203.051
A31: Financing Activities
A32: Debt Issuance | B32: =Assumptions!C31 -> 0 | C32: =Assumptions!D31 -> 0 | D32: =Assumptions!E31 -> 0 | E32: =Assumptions!F31 -> 0 | F32: =Assumptions!G31 -> 0 | G32: =Assumptions!H31 -> 0
A33: Debt Repayment | B33: =-ABS(Assumptions!C32) -> -20000 | C33: =-ABS(Assumptions!D32) -> 0 | D33: =-ABS(Assumptions!E32) -> 0 | E33: =-ABS(Assumptions!F32) -> 0 | F33: =-ABS(Assumptions!G32) -> 0 | G33: =-ABS(Assumptions!H32) -> 0
A34: Dividends Paid | B34: =Assumptions!C64 -> -46417 | C34: =-MAX(0,'Income Statement'!D33*Assumptions!D34) -> -38458.299 | D34: =-MAX(0,'Income Statement'!E33*Assumptions!E34) -> -48552.747 | E34: =-MAX(0,'Income Statement'!F33*Assumptions!F34) -> -54122.322 | F34: =-MAX(0,'Income Statement'!G33*Assumptions!G34) -> -58055.46 | G34: =-MAX(0,'Income Statement'!H33*Assumptions!H34) -> -62497.198
A35: Employee Profit Sharing Paid | B35: =-'Income Statement'!C29 -> 0 | C35: =-'Income Statement'!D29 -> -14799.37 | D35: =-'Income Statement'!E29 -> -17982.499 | E35: =-'Income Statement'!F29 -> -20045.305 | F35: =-'Income Statement'!G29 -> -21502.022 | G35: =-'Income Statement'!H29 -> -23147.11
A36: └ Dividend WHT (memo, incl. above) | B36: =-'Income Statement'!C35 -> 0 | C36: =-'Income Statement'!D35 -> -3845.8299 | D36: =-'Income Statement'!E35 -> -4855.2747 | E36: =-'Income Statement'!F35 -> -5412.2322 | F36: =-'Income Statement'!G35 -> -5805.546 | G36: =-'Income Statement'!H35 -> -6249.7198
A37: Equity Issuance | B37: =('Historical Data'!C45-'Historical Data'!B45)+('Historical Data'!C46-'Historical Data'!B46) -> 10000 | C37: =Assumptions!D39 -> 0 | D37: =Assumptions!E39 -> 0 | E37: =Assumptions!F39 -> 0 | F37: =Assumptions!G39 -> 0 | G37: =Assumptions!H39 -> 0
A38: Share Repurchases | B38: =-ABS('Historical Data'!C49-'Historical Data'!B49) -> 0 | C38: =-ABS(Assumptions!D35) -> 0 | D38: =-ABS(Assumptions!E35) -> 0 | E38: =-ABS(Assumptions!F35) -> 0 | F38: =-ABS(Assumptions!G35) -> 0 | G38: =-ABS(Assumptions!H35) -> 0
A39: Cash from Financing | B39: =B32+B33+B34+B35+B37+B38 -> -56417 | C39: =C32+C33+C34+C35+C37+C38 -> -53257.669 | D39: =D32+D33+D34+D35+D37+D38 -> -66535.246 | E39: =E32+E33+E34+E35+E37+E38 -> -74167.627 | F39: =F32+F33+F34+F35+F37+F38 -> -79557.482 | G39: =G32+G33+G34+G35+G37+G38 -> -85644.308
A41: Net Change in Cash | B41: =B21+B29+B39 -> 25000 | C41: =C21+C29+C39 -> 213917 | D41: =D21+D29+D39 -> 113351.24 | E41: =E21+E29+E39 -> 127965.35 | F41: =F21+F29+F39 -> 139351.82 | G41: =G21+G29+G39 -> 152576.01
A42: Beginning Cash | B42: ='Balance Sheet'!B3 -> 175000 | C42: ='Balance Sheet'!C3 -> 200000 | D42: ='Balance Sheet'!D3 -> 413917 | E42: ='Balance Sheet'!E3 -> 527268.24 | F42: ='Balance Sheet'!F3 -> 655233.58 | G42: ='Balance Sheet'!G3 -> 794585.4
A43: Ending Cash | B43: =B42+B41 -> 200000 | C43: =C42+C41 -> 413917 | D43: =D42+D41 -> 527268.24 | E43: =E42+E41 -> 655233.58 | F43: =F42+F41 -> 794585.4 | G43: =G42+G41 -> 947161.42
A45: Free Cash Flow | B45: =B21+B24 -> 81417 | C45: =C21+C24 -> 267174.67 | D45: =D21+D24 -> 179886.49 | E45: =E21+E24 -> 202132.97 | F45: =F21+F24 -> 218909.3 | G45: =G21+G24 -> 238220.32
A47: Reconciliation Check | B47: =IF(ABS(B43-'Balance Sheet'!C3)<0.01,"✓ Reconciles","✗ Error") -> ✓ Reconciles | C47: =IF(ABS(C43-'Balance Sheet'!D3)<0.01,"✓ Reconciles","✗ Error") -> ✓ Reconciles | D47: =IF(ABS(D43-'Balance Sheet'!E3)<0.01,"✓ Reconciles","✗ Error") -> ✓ Reconciles | E47: =IF(ABS(E43-'Balance Sheet'!F3)<0.01,"✓ Reconciles","✗ Error") -> ✓ Reconciles | F47: =IF(ABS(F43-'Balance Sheet'!G3)<0.01,"✓ Reconciles","✗ Error") -> ✓ Reconciles | G47: =IF(ABS(G43-'Balance Sheet'!H3)<0.01,"✓ Reconciles","✗ Error") -> ✓ Reconciles

Sheet Ratios
A1: Financial Ratios | B1: 2024 (A) | C1: 2025 (A) | D1: 2026E | E1: 2027E | F1: 2028E | G1: 2029E | H1: 2030E
A2: ── Profitability ──
A3: Gross Margin | B3: =IF('Income Statement'!B2=0,0,'Income Statement'!B5/'Income Statement'!B2) -> 0.4 | C3: =IF('Income Statement'!C2=0,0,'Income Statement'!C5/'Income Statement'!C2) -> 0.4 | D3: =IF('Income Statement'!D2=0,0,'Income Statement'!D5/'Income Statement'!D2) -> 0.4 | E3: =IF('Income Statement'!E2=0,0,'Income Statement'!E5/'Income Statement'!E2) -> 0.4 | F3: =IF('Income Statement'!F2=0,0,'Income Statement'!F5/'Income Statement'!F2) -> 0.4 | G3: =IF('Income Statement'!G2=0,0,'Income Statement'!G5/'Income Statement'!G2) -> 0.4 | H3: =IF('Income Statement'!H2=0,0,'Income Statement'!H5/'Income Statement'!H2) -> 0.4
A4: EBITDA Margin | B4: =IF('Income Statement'!B2=0,0,'Income Statement'!B18/'Income Statement'!B2) -> 0.18 | C4: =IF('Income Statement'!C2=0,0,'Income Statement'!C18/'Income Statement'!C2) -> 0.18 | D4: =IF('Income Statement'!D2=0,0,'Income Statement'!D18/'Income Statement'!D2) -> 0.23 | E4: =IF('Income Statement'!E2=0,0,'Income Statement'!E18/'Income Statement'!E2) -> 0.23 | F4: =IF('Income Statement'!F2=0,0,'Income Statement'!F18/'Income Statement'!F2) -> 0.23 | G4: =IF('Income Statement'!G2=0,0,'Income Statement'!G18/'Income Statement'!G2) -> 0.23 | H4: =IF('Income Statement'!H2=0,0,'Income Statement'!H18/'Income Statement'!H2) -> 0.23
A5: EBIT Margin | B5: =IF('Income Statement'!B2=0,0,'Income Statement'!B17/'Income Statement'!B2) -> 0.14117647 | C5: =IF('Income Statement'!C2=0,0,'Income Statement'!C17/'Income Statement'!C2) -> 0.14105263 | D5: =IF('Income Statement'!D2=0,0,'Income Statement'!D17/'Income Statement'!D2) -> 0.18587321 | E5: =IF('Income Statement'!E2=0,0,'Income Statement'!E17/'Income Statement'!E2) -> 0.18432704 | F5: =IF('Income Statement'!F2=0,0,'Income Statement'!F17/'Income Statement'!F2) -> 0.18247854 | G5: =IF('Income Statement'!G2=0,0,'Income Statement'!G17/'Income Statement'!G2) -> 0.18030995 | H5: =IF('Income Statement'!H2=0,0,'Income Statement'!H17/'Income Statement'!H2) -> 0.17779519
A6: Net Margin | B6: =IF('Income Statement'!B2=0,0,'Income Statement'!B28/'Income Statement'!B2) -> 0.098926471 | C6: =IF('Income Statement'!C2=0,0,'Income Statement'!C28/'Income Statement'!C2) -> 0.10115789 | D6: =IF('Income Statement'!D2=0,0,'Income Statement'!D28/'Income Statement'!D2) -> 0.14162077 | E6: =IF('Income Statement'!E2=0,0,'Income Statement'!E28/'Income Statement'!E2) -> 0.15933456 | F6: =IF('Income Statement'!F2=0,0,'Income Statement'!F28/'Income Statement'!F2) -> 0.16599264 | G6: =IF('Income Statement'!G2=0,0,'Income Statement'!G28/'Income Statement'!G2) -> 0.16797692 | H6: =IF('Income Statement'!H2=0,0,'Income Statement'!H28/'Income Statement'!H2) -> 0.1722177
A7: ROA | B7: =IF('Balance Sheet'!B18=0,0,'Income Statement'!B28/'Balance Sheet'!B18) -> 0.11724202 | C7: =IF('Balance Sheet'!C18=0,0,'Income Statement'!C28/'Balance Sheet'!C18) -> 0.12936793 | D7: =IF('Balance Sheet'!D18=0,0,'Income Statement'!D28/'Balance Sheet'!D18) -> 0.16613 | E7: =IF('Balance Sheet'!E18=0,0,'Income Statement'!E28/'Balance Sheet'!E18) -> 0.16646884 | F7: =IF('Balance Sheet'!F18=0,0,'Income Statement'!F28/'Balance Sheet'!F18) -> 0.16427297 | G7: =IF('Balance Sheet'!G18=0,0,'Income Statement'!G28/'Balance Sheet'!G18) -> 0.15695416 | H7: =IF('Balance Sheet'!H18=0,0,'Income Statement'!H28/'Balance Sheet'!H18) -> 0.1515287
A8: ROE | B8: =IF('Balance Sheet'!B44=0,0,'Income Statement'!B28/'Balance Sheet'!B44) -> 0.33794103 | C8: =IF('Balance Sheet'!C44=0,0,'Income Statement'!C28/'Balance Sheet'!C44) -> 0.34485914 | D8: =IF('Balance Sheet'!D44=0,0,'Income Statement'!D28/'Balance Sheet'!D44) -> 0.41585981 | E8: =IF('Balance Sheet'!E44=0,0,'Income Statement'!E28/'Balance Sheet'!E44) -> 0.39102003 | F8: =IF('Balance Sheet'!F44=0,0,'Income Statement'!F28/'Balance Sheet'!F44) -> 0.34580278 | G8: =IF('Balance Sheet'!G44=0,0,'Income Statement'!G28/'Balance Sheet'!G44) -> 0.30261158 | H8: =IF('Balance Sheet'!H44=0,0,'Income Statement'!H28/'Balance Sheet'!H44) -> 0.27193717
A9: ROIC (Net IC) | B9: =IF(('Balance Sheet'!B44+'Balance Sheet'!B23+'Balance Sheet'!B30+'Balance Sheet'!B24-'Balance Sheet'!B3)=0,0,('Income Statement'!B17*(1-IF('Income Statement'!B24>0,'Income Statement'!B25/'Income Statement'!B24,0)))/('Balance Sheet'!B44+'Balance Sheet'!B23+'Balance Sheet'!B30+'Balance Sheet'!B24-'Balance Sheet'!B3)) -> 0.24878084 | C9: =IF(('Balance Sheet'!C44+'Balance Sheet'!C23+'Balance Sheet'!C30+'Balance Sheet'!C24-'Balance Sheet'!C3)=0,0,('Income Statement'!C17*(1-IF('Income Statement'!C24>0,'Income Statement'!C25/'Income Statement'!C24,0)))/('Balance Sheet'!C44+'Balance Sheet'!C23+'Balance Sheet'!C30+'Balance Sheet'!C24-'Balance Sheet'!C3)) -> 0.27245454 | D9: =IF(('Balance Sheet'!D44+'Balance Sheet'!D23+'Balance Sheet'!D30+'Balance Sheet'!D24-'Balance Sheet'!D3)=0,0,('Income Statement'!D17*(1-IF('Income Statement'!D24>0,'Income Statement'!D25/'Income Statement'!D24,0)))/('Balance Sheet'!D44+'Balance Sheet'!D23+'Balance Sheet'!D30+'Balance Sheet'!D24-'Balance Sheet'!D3)) -> 0.45766787 | E9: =IF(('Balance Sheet'!E44+'Balance Sheet'!E23+'Balance Sheet'!E30+'Balance Sheet'!E24-'Balance Sheet'!E3)=0,0,('Income Statement'!E17*(1-IF('Income Statement'!E24>0,'Income Statement'!E25/'Income Statement'!E24,0)))/('Balance Sheet'!E44+'Balance Sheet'!E23+'Balance Sheet'!E30+'Balance Sheet'!E24-'Balance Sheet'!E3)) -> 0.59869229 | F9: =IF(('Balance Sheet'!F44+'Balance Sheet'!F23+'Balance Sheet'!F30+'Balance Sheet'!F24-'Balance Sheet'!F3)=0,0,('Income Statement'!F17*(1-IF('Income Statement'!F24>0,'Income Statement'!F25/'Income Statement'!F24,0)))/('Balance Sheet'!F44+'Balance Sheet'!F23+'Balance Sheet'!F30+'Balance Sheet'!F24-'Balance Sheet'!F3)) -> 0.63623372 | G9: =IF(('Balance Sheet'!G44+'Balance Sheet'!G23+'Balance Sheet'!G30+'Balance Sheet'!G24-'Balance Sheet'!G3)=0,0,('Income Statement'!G17*(1-IF('Income Statement'!G24>0,'Income Statement'!G25/'Income Statement'!G24,0)))/('Balance Sheet'!G44+'Balance Sheet'!G23+'Balance Sheet'!G30+'Balance Sheet'!G24-'Balance Sheet'!G3)) -> 0.67337831 | H9: =IF(('Balance Sheet'!H44+'Balance Sheet'!H23+'Balance Sheet'!H30+'Balance Sheet'!H24-'Balance Sheet'!H3)=0,0,('Income Statement'!H17*(1-IF('Income Statement'!H24>0,'Income Statement'!H25/'Income Statement'!H24,0)))/('Balance Sheet'!H44+'Balance Sheet'!H23+'Balance Sheet'!H30+'Balance Sheet'!H24-'Balance Sheet'!H3)) -> 0.71143182
A10: ── Liquidity ──
A11: Current Ratio | B11: =IF('Balance Sheet'!B28=0,0,'Balance Sheet'!B9/'Balance Sheet'!B28) -> 1.8551339 | C11: =IF('Balance Sheet'!C28=0,0,'Balance Sheet'!C9/'Balance Sheet'!C28) -> 1.966866 | D11: =IF('Balance Sheet'!D28=0,0,'Balance Sheet'!D9/'Balance Sheet'!D28) -> 1.8033242 | E11: =IF('Balance Sheet'!E28=0,0,'Balance Sheet'!E9/'Balance Sheet'!E28) -> 2.0540479 | F11: =IF('Balance Sheet'!F28=0,0,'Balance Sheet'!F9/'Balance Sheet'!F28) -> 2.3202115 | G11: =IF('Balance Sheet'!G28=0,0,'Balance Sheet'!G9/'Balance Sheet'!G28) -> 2.5960313 | H11: =IF('Balance Sheet'!H28=0,0,'Balance Sheet'!H9/'Balance Sheet'!H28) -> 2.8902554
A12: Quick Ratio | B12: =IF('Balance Sheet'!B28=0,0,('Balance Sheet'!B9-'Balance Sheet'!B5)/'Balance Sheet'!B28) -> 1.6265609 | C12: =IF('Balance Sheet'!C28=0,0,('Balance Sheet'!C9-'Balance Sheet'!C5)/'Balance Sheet'!C28) -> 1.7265728 | D12: =IF('Balance Sheet'!D28=0,0,('Balance Sheet'!D9-'Balance Sheet'!D5)/'Balance Sheet'!D28) -> 1.6539267 | E12: =IF('Balance Sheet'!E28=0,0,('Balance Sheet'!E9-'Balance Sheet'!E5)/'Balance Sheet'!E28) -> 1.9018729 | F12: =IF('Balance Sheet'!F28=0,0,('Balance Sheet'!F9-'Balance Sheet'!F5)/'Balance Sheet'!F28) -> 2.1656871 | G12: =IF('Balance Sheet'!G28=0,0,('Balance Sheet'!G9-'Balance Sheet'!G5)/'Balance Sheet'!G28) -> 2.4395533 | H12: =IF('Balance Sheet'!H28=0,0,('Balance Sheet'!H9-'Balance Sheet'!H5)/'Balance Sheet'!H28) -> 2.7321915
A13: Cash Ratio | B13: =IF('Balance Sheet'!B28=0,0,'Balance Sheet'!B3/'Balance Sheet'!B28) -> 0.9542505 | C13: =IF('Balance Sheet'!C28=0,0,'Balance Sheet'!C3/'Balance Sheet'!C28) -> 1.0258199 | D13: =IF('Balance Sheet'!D28=0,0,'Balance Sheet'!D3/'Balance Sheet'!D28) -> 1.1999426 | E13: =IF('Balance Sheet'!E28=0,0,'Balance Sheet'!E3/'Balance Sheet'!E28) -> 1.4416354 | F13: =IF('Balance Sheet'!F28=0,0,'Balance Sheet'!F3/'Balance Sheet'!F28) -> 1.7001605 | G13: =IF('Balance Sheet'!G28=0,0,'Balance Sheet'!G3/'Balance Sheet'!G28) -> 1.9696289 | H13: =IF('Balance Sheet'!H28=0,0,'Balance Sheet'!H3/'Balance Sheet'!H28) -> 2.2586968
A14: Total Liabilities / Equity | B14: =IF('Balance Sheet'!B44=0,0,'Balance Sheet'!B35/'Balance Sheet'!B44) -> 1.2056763 | C14: =IF('Balance Sheet'!C44=0,0,'Balance Sheet'!C35/'Balance Sheet'!C44) -> 0.90759985 | D14: =IF('Balance Sheet'!D44=0,0,'Balance Sheet'!D35/'Balance Sheet'!D44) -> 0.69437206 | E14: =IF('Balance Sheet'!E44=0,0,'Balance Sheet'!E35/'Balance Sheet'!E44) -> 0.54207701 | F14: =IF('Balance Sheet'!F44=0,0,'Balance Sheet'!F35/'Balance Sheet'!F44) -> 0.43558262 | G14: =IF('Balance Sheet'!G44=0,0,'Balance Sheet'!G35/'Balance Sheet'!G44) -> 0.35976772 | H14: =IF('Balance Sheet'!H44=0,0,'Balance Sheet'!H35/'Balance Sheet'!H44) -> 0.3029953
A15: ── Efficiency ──
A16: Asset Turnover | B16: =IF('Balance Sheet'!B18=0,0,'Income Statement'!B2/'Balance Sheet'!B18) -> 1.185143 | C16: =IF('Balance Sheet'!C18=0,0,'Income Statement'!C2/'Balance Sheet'!C18) -> 1.2788714 | D16: =IF('Balance Sheet'!D18=0,0,'Income Statement'!D2/'Balance Sheet'!D18) -> 1.1730624 | E16: =IF('Balance Sheet'!E18=0,0,'Income Statement'!E2/'Balance Sheet'!E18) -> 1.0447754 | F16: =IF('Balance Sheet'!F18=0,0,'Income Statement'!F2/'Balance Sheet'!F18) -> 0.98964009 | G16: =IF('Balance Sheet'!G18=0,0,'Income Statement'!G2/'Balance Sheet'!G18) -> 0.93437931 | H16: =IF('Balance Sheet'!H18=0,0,'Income Statement'!H2/'Balance Sheet'!H18) -> 0.87986717
A17: Inventory Turnover (×) | B17: =IF('Balance Sheet'!B5=0,0,'Income Statement'!B4/'Balance Sheet'!B5) -> 12.166611 | C17: =IF(('Balance Sheet'!B5+'Balance Sheet'!C5)/2=0,0,'Income Statement'!C4/(('Balance Sheet'!B5+'Balance Sheet'!C5)/2)) -> 12.84261 | D17: =IF(('Balance Sheet'!C5+'Balance Sheet'!D5)/2=0,0,'Income Statement'!D4/(('Balance Sheet'!C5+'Balance Sheet'!D5)/2)) -> 12.746073 | E17: =IF(('Balance Sheet'!D5+'Balance Sheet'!E5)/2=0,0,'Income Statement'!E4/(('Balance Sheet'!D5+'Balance Sheet'!E5)/2)) -> 12.634615 | F17: =IF(('Balance Sheet'!E5+'Balance Sheet'!F5)/2=0,0,'Income Statement'!F4/(('Balance Sheet'!E5+'Balance Sheet'!F5)/2)) -> 12.5781 | G17: =IF(('Balance Sheet'!F5+'Balance Sheet'!G5)/2=0,0,'Income Statement'!G4/(('Balance Sheet'!F5+'Balance Sheet'!G5)/2)) -> 12.521036 | H17: =IF(('Balance Sheet'!G5+'Balance Sheet'!H5)/2=0,0,'Income Statement'!H4/(('Balance Sheet'!G5+'Balance Sheet'!H5)/2)) -> 12.463415
A18: Receivables Turnover (×) | B18: =IF('Balance Sheet'!B4=0,0,'Income Statement'!B2/'Balance Sheet'!B4) -> 8.111074 | C18: =IF(('Balance Sheet'!B4+'Balance Sheet'!C4)/2=0,0,'Income Statement'!C2/(('Balance Sheet'!B4+'Balance Sheet'!C4)/2)) -> 8.561721 | D18: =IF(('Balance Sheet'!C4+'Balance Sheet'!D4)/2=0,0,'Income Statement'!D2/(('Balance Sheet'!C4+'Balance Sheet'!D4)/2)) -> 8.4973644 | E18: =IF(('Balance Sheet'!D4+'Balance Sheet'!E4)/2=0,0,'Income Statement'!E2/(('Balance Sheet'!D4+'Balance Sheet'!E4)/2)) -> 8.4230769 | F18: =IF(('Balance Sheet'!E4+'Balance Sheet'!F4)/2=0,0,'Income Statement'!F2/(('Balance Sheet'!E4+'Balance Sheet'!F4)/2)) -> 8.3853999 | G18: =IF(('Balance Sheet'!F4+'Balance Sheet'!G4)/2=0,0,'Income Statement'!G2/(('Balance Sheet'!F4+'Balance Sheet'!G4)/2)) -> 8.3473571 | H18: =IF(('Balance Sheet'!G4+'Balance Sheet'!H4)/2=0,0,'Income Statement'!H2/(('Balance Sheet'!G4+'Balance Sheet'!H4)/2)) -> 8.3089431
A19: DSO (Days) | B19: =IF('Income Statement'!B2=0,0,'Balance Sheet'!B4/'Income Statement'!B2*365) -> 45.000206 | C19: =IF('Income Statement'!C2=0,0,'Balance Sheet'!C4/'Income Statement'!C2*365) -> 44.999889 | D19: =IF('Income Statement'!D2=0,0,'Balance Sheet'!D4/'Income Statement'!D2*365) -> 45 | E19: =IF('Income Statement'!E2=0,0,'Balance Sheet'!E4/'Income Statement'!E2*365) -> 45 | F19: =IF('Income Statement'!F2=0,0,'Balance Sheet'!F4/'Income Statement'!F2*365) -> 45 | G19: =IF('Income Statement'!G2=0,0,'Balance Sheet'!G4/'Income Statement'!G2*365) -> 45 | H19: =IF('Income Statement'!H2=0,0,'Balance Sheet'!H4/'Income Statement'!H2*365) -> 45
A20: DIO (Days) | B20: =IF('Income Statement'!B4=0,0,'Balance Sheet'!B5/'Income Statement'!B4*365) -> 30.000137 | C20: =IF('Income Statement'!C4=0,0,'Balance Sheet'!C5/'Income Statement'!C4*365) -> 29.999798 | D20: =IF('Income Statement'!D4=0,0,'Balance Sheet'!D5/'Income Statement'!D4*365) -> 30 | E20: =IF('Income Statement'!E4=0,0,'Balance Sheet'!E5/'Income Statement'!E4*365) -> 30 | F20: =IF('Income Statement'!F4=0,0,'Balance Sheet'!F5/'Income Statement'!F4*365) -> 30 | G20: =IF('Income Statement'!G4=0,0,'Balance Sheet'!G5/'Income Statement'!G4*365) -> 30 | H20: =IF('Income Statement'!H4=0,0,'Balance Sheet'!H5/'Income Statement'!H4*365) -> 30
A21: DPO (Days) | B21: =IF('Income Statement'!B4=0,0,'Balance Sheet'!B21/'Income Statement'!B4*365) -> 39.999706 | C21: =IF('Income Statement'!C4=0,0,'Balance Sheet'!C21/'Income Statement'!C4*365) -> 40.000158 | D21: =IF('Income Statement'!D4=0,0,'Balance Sheet'!D21/'Income Statement'!D4*365) -> 40 | E21: =IF('Income Statement'!E4=0,0,'Balance Sheet'!E21/'Income Statement'!E4*365) -> 40 | F21: =IF('Income Statement'!F4=0,0,'Balance Sheet'!F21/'Income Statement'!F4*365) -> 40 | G21: =IF('Income Statement'!G4=0,0,'Balance Sheet'!G21/'Income Statement'!G4*365) -> 40 | H21: =IF('Income Statement'!H4=0,0,'Balance Sheet'!H21/'Income Statement'!H4*365) -> 40
A22: Cash Conversion Cycle (Days) | B22: =B19+B20-B21 -> 35.000637 | C22: =C19+C20-C21 -> 34.99953 | D22: =D19+D20-D21 -> 35 | E22: =E19+E20-E21 -> 35 | F22: =F19+F20-F21 -> 35 | G22: =G19+G20-G21 -> 35 | H22: =H19+H20-H21 -> 35
A23: ── Leverage ──
A24: Total Debt / Equity (D/E) | B24: =IF('Balance Sheet'!B44=0,0,('Balance Sheet'!B23+'Balance Sheet'!B30+'Balance Sheet'!B24)/'Balance Sheet'!B44) -> 0 | C24: =IF('Balance Sheet'!C44=0,0,('Balance Sheet'!C23+'Balance Sheet'!C30+'Balance Sheet'!C24)/'Balance Sheet'!C44) -> 0 | D24: =IF('Balance Sheet'!D44=0,0,('Balance Sheet'!D23+'Balance Sheet'!D30+'Balance Sheet'!D24)/'Balance Sheet'!D44) -> 0 | E24: =IF('Balance Sheet'!E44=0,0,('Balance Sheet'!E23+'Balance Sheet'!E30+'Balance Sheet'!E24)/'Balance Sheet'!E44) -> 0 | F24: =IF('Balance Sheet'!F44=0,0,('Balance Sheet'!F23+'Balance Sheet'!F30+'Balance Sheet'!F24)/'Balance Sheet'!F44) -> 0 | G24: =IF('Balance Sheet'!G44=0,0,('Balance Sheet'!G23+'Balance Sheet'!G30+'Balance Sheet'!G24)/'Balance Sheet'!G44) -> 0 | H24: =IF('Balance Sheet'!H44=0,0,('Balance Sheet'!H23+'Balance Sheet'!H30+'Balance Sheet'!H24)/'Balance Sheet'!H44) -> 0
A25: Total Debt / Assets | B25: =IF('Balance Sheet'!B18=0,0,('Balance Sheet'!B23+'Balance Sheet'!B30+'Balance Sheet'!B24)/'Balance Sheet'!B18) -> 0.41828578 | C25: =IF('Balance Sheet'!C18=0,0,('Balance Sheet'!C23+'Balance Sheet'!C30+'Balance Sheet'!C24)/'Balance Sheet'!C18) -> 0.3643594 | D25: =IF('Balance Sheet'!D18=0,0,('Balance Sheet'!D23+'Balance Sheet'!D30+'Balance Sheet'!D24)/'Balance Sheet'!D18) -> 0.27635505 | E25: =IF('Balance Sheet'!E18=0,0,('Balance Sheet'!E23+'Balance Sheet'!E30+'Balance Sheet'!E24)/'Balance Sheet'!E18) -> 0.24405659 | F25: =IF('Balance Sheet'!F18=0,0,('Balance Sheet'!F23+'Balance Sheet'!F30+'Balance Sheet'!F24)/'Balance Sheet'!F18) -> 0.2165151 | G25: =IF('Balance Sheet'!G18=0,0,('Balance Sheet'!G23+'Balance Sheet'!G30+'Balance Sheet'!G24)/'Balance Sheet'!G18) -> 0.19354409 | H25: =IF('Balance Sheet'!H18=0,0,('Balance Sheet'!H23+'Balance Sheet'!H30+'Balance Sheet'!H24)/'Balance Sheet'!H18) -> 0.17408101
A26: Net Debt (EGP) | B26: =('Balance Sheet'!B23+'Balance Sheet'!B30+'Balance Sheet'!B24)-'Balance Sheet'!B3 -> 125000 | C26: =('Balance Sheet'!C23+'Balance Sheet'!C30+'Balance Sheet'!C24)-'Balance Sheet'!C3 -> 80000 | D26: =('Balance Sheet'!D23+'Balance Sheet'!D30+'Balance Sheet'!D24)-'Balance Sheet'!D3 -> -133917 | E26: =('Balance Sheet'!E23+'Balance Sheet'!E30+'Balance Sheet'!E24)-'Balance Sheet'!E3 -> -247268.24 | F26: =('Balance Sheet'!F23+'Balance Sheet'!F30+'Balance Sheet'!F24)-'Balance Sheet'!F3 -> -375233.58 | G26: =('Balance Sheet'!G23+'Balance Sheet'!G30+'Balance Sheet'!G24)-'Balance Sheet'!G3 -> -514585.4 | H26: =('Balance Sheet'!H23+'Balance Sheet'!H30+'Balance Sheet'!H24)-'Balance Sheet'!H3 -> -667161.42
A27: Net Debt / EBITDA (×) | B27: =IF('Income Statement'!B18=0,0,(('Balance Sheet'!B23+'Balance Sheet'!B30+'Balance Sheet'!B24)-'Balance Sheet'!B3)/'Income Statement'!B18) -> 0.81699346 | C27: =IF('Income Statement'!C18=0,0,(('Balance Sheet'!C23+'Balance Sheet'!C30+'Balance Sheet'!C24)-'Balance Sheet'!C3)/'Income Statement'!C18) -> 0.46783626 | D27: =IF('Income Statement'!D18=0,0,(('Balance Sheet'!D23+'Balance Sheet'!D30+'Balance Sheet'!D24)-'Balance Sheet'!D3)/'Income Statement'!D18) -> -0.55717494 | E27: =IF('Income Statement'!E18=0,0,(('Balance Sheet'!E23+'Balance Sheet'!E30+'Balance Sheet'!E24)-'Balance Sheet'!E3)/'Income Statement'!E18) -> -0.95257779 | F27: =IF('Income Statement'!F18=0,0,(('Balance Sheet'!F23+'Balance Sheet'!F30+'Balance Sheet'!F24)-'Balance Sheet'!F3)/'Income Statement'!F18) -> -1.3509835 | G27: =IF('Income Statement'!G18=0,0,(('Balance Sheet'!G23+'Balance Sheet'!G30+'Balance Sheet'!G24)-'Balance Sheet'!G3)/'Income Statement'!G18) -> -1.747833 | H27: =IF('Income Statement'!H18=0,0,(('Balance Sheet'!H23+'Balance Sheet'!H30+'Balance Sheet'!H24)-'Balance Sheet'!H3)/'Income Statement'!H18) -> -2.1581623
A28: Interest Coverage (×) | B28: =IF('Income Statement'!B22=0,0,'Income Statement'!B17/'Income Statement'!B22) -> 8.5714286 | C28: =IF('Income Statement'!C22=0,0,'Income Statement'!C17/'Income Statement'!C22) -> 10.307692 | D28: =IF('Income Statement'!D22=0,0,'Income Statement'!D17/'Income Statement'!D22) -> 3.1532062 | E28: =IF('Income Statement'!E22=0,0,'Income Statement'!E17/'Income Statement'!E22) -> 3.7148482 | F28: =IF('Income Statement'!F22=0,0,'Income Statement'!F17/'Income Statement'!F22) -> 4.3722511 | G28: =IF('Income Statement'!G22=0,0,'Income Statement'!G17/'Income Statement'!G22) -> 4.848891 | H28: =IF('Income Statement'!H22=0,0,'Income Statement'!H17/'Income Statement'!H22) -> 5.3340978
A29: ── Per Share ──
A30: EPS (After EPD) | B30: ='Income Statement'!B40 -> 0 | C30: ='Income Statement'!C40 -> 0 | D30: ='Income Statement'!D40 -> 0 | E30: ='Income Statement'!E40 -> 0 | F30: ='Income Statement'!F40 -> 0 | G30: ='Income Statement'!G40 -> 0 | H30: ='Income Statement'!H40 -> 0
A31: Book Value Per Share (BVPS) | B31: =IF('Historical Data'!B20=0,0,'Balance Sheet'!B44/'Historical Data'!B20) -> 0 | C31: =IF('Historical Data'!C20=0,0,'Balance Sheet'!C44/'Historical Data'!C20) -> 0 | D31: =IF(Assumptions!D13=0,0,'Balance Sheet'!D44/Assumptions!D13) -> 0 | E31: =IF(Assumptions!E13=0,0,'Balance Sheet'!E44/Assumptions!E13) -> 0 | F31: =IF(Assumptions!F13=0,0,'Balance Sheet'!F44/Assumptions!F13) -> 0 | G31: =IF(Assumptions!G13=0,0,'Balance Sheet'!G44/Assumptions!G13) -> 0 | H31: =IF(Assumptions!H13=0,0,'Balance Sheet'!H44/Assumptions!H13) -> 0
A32: Revenue Per Share | B32: =IF('Historical Data'!B20=0,0,'Income Statement'!B2/'Historical Data'!B20) -> 8.5 | C32: =IF('Historical Data'!C20=0,0,'Income Statement'!C2/'Historical Data'!C20) -> 9.5 | D32: =IF(Assumptions!D13=0,0,'Income Statement'!D2/Assumptions!D13) -> 10.45 | E32: =IF(Assumptions!E13=0,0,'Income Statement'!E2/Assumptions!E13) -> 11.286 | F32: =IF(Assumptions!F13=0,0,'Income Statement'!F2/Assumptions!F13) -> 12.07602 | G32: =IF(Assumptions!G13=0,0,'Income Statement'!G2/Assumptions!G13) -> 12.800581 | H32: =IF(Assumptions!H13=0,0,'Income Statement'!H2/Assumptions!H13) -> 13.44061
A33: FCFF Per Share | B33: =IF('Historical Data'!B20=0,0,'Income Statement'!B44/'Historical Data'!B20) -> 0 | C33: =IF('Historical Data'!C20=0,0,'Income Statement'!C44/'Historical Data'!C20) -> 0 | D33: =IF(Assumptions!D13=0,0,'Income Statement'!D44/Assumptions!D13) -> 0 | E33: =IF(Assumptions!E13=0,0,'Income Statement'!E44/Assumptions!E13) -> 0 | F33: =IF(Assumptions!F13=0,0,'Income Statement'!F44/Assumptions!F13) -> 0 | G33: =IF(Assumptions!G13=0,0,'Income Statement'!G44/Assumptions!G13) -> 0 | H33: =IF(Assumptions!H13=0,0,'Income Statement'!H44/Assumptions!H13) -> 0
A34: ── DuPont Decomposition ──
A35: Net Profit Margin | B35: =IF('Income Statement'!B2=0,0,'Income Statement'!B28/'Income Statement'!B2) -> 0.098926471 | C35: =IF('Income Statement'!C2=0,0,'Income Statement'!C28/'Income Statement'!C2) -> 0.10115789 | D35: =IF('Income Statement'!D2=0,0,'Income Statement'!D28/'Income Statement'!D2) -> 0.14162077 | E35: =IF('Income Statement'!E2=0,0,'Income Statement'!E28/'Income Statement'!E2) -> 0.15933456 | F35: =IF('Income Statement'!F2=0,0,'Income Statement'!F28/'Income Statement'!F2) -> 0.16599264 | G35: =IF('Income Statement'!G2=0,0,'Income Statement'!G28/'Income Statement'!G2) -> 0.16797692 | H35: =IF('Income Statement'!H2=0,0,'Income Statement'!H28/'Income Statement'!H2) -> 0.1722177
A36: Asset Turnover | B36: =IF('Balance Sheet'!B18=0,0,'Income Statement'!B2/'Balance Sheet'!B18) -> 1.185143 | C36: =IF('Balance Sheet'!C18=0,0,'Income Statement'!C2/'Balance Sheet'!C18) -> 1.2788714 | D36: =IF('Balance Sheet'!D18=0,0,'Income Statement'!D2/'Balance Sheet'!D18) -> 1.1730624 | E36: =IF('Balance Sheet'!E18=0,0,'Income Statement'!E2/'Balance Sheet'!E18) -> 1.0447754 | F36: =IF('Balance Sheet'!F18=0,0,'Income Statement'!F2/'Balance Sheet'!F18) -> 0.98964009 | G36: =IF('Balance Sheet'!G18=0,0,'Income Statement'!G2/'Balance Sheet'!G18) -> 0.93437931 | H36: =IF('Balance Sheet'!H18=0,0,'Income Statement'!H2/'Balance Sheet'!H18) -> 0.87986717
A37: Equity Multiplier | B37: =IF('Balance Sheet'!B44=0,0,'Balance Sheet'!B18/'Balance Sheet'!B44) -> 2.8824224 | C37: =IF('Balance Sheet'!C44=0,0,'Balance Sheet'!C18/'Balance Sheet'!C44) -> 2.4909467 | D37: =IF('Balance Sheet'!D44=0,0,'Balance Sheet'!D18/'Balance Sheet'!D44) -> 2.5126085 | E37: =IF('Balance Sheet'!E44=0,0,'Balance Sheet'!E18/'Balance Sheet'!E44) -> 2.2211119 | F37: =IF('Balance Sheet'!F44=0,0,'Balance Sheet'!F18/'Balance Sheet'!F44) -> 2.0117886 | G37: =IF('Balance Sheet'!G44=0,0,'Balance Sheet'!G18/'Balance Sheet'!G44) -> 1.8588412 | H37: =IF('Balance Sheet'!H44=0,0,'Balance Sheet'!H18/'Balance Sheet'!H44) -> 1.7405419
A38: DuPont ROE (3-Factor) | B38: =B35*B36*B37 -> 0 | C38: =C35*C36*C37 -> 0 | D38: =D35*D36*D37 -> 0 | E38: =E35*E36*E37 -> 0 | F38: =F35*F36*F37 -> 0 | G38: =G35*G36*G37 -> 0 | H38: =H35*H36*H37 -> 0
A39: Tax Burden (NI / EBT) | B39: =IF('Income Statement'!B24=0,0,'Income Statement'!B28/'Income Statement'!B24) -> 0.775 | C39: =IF('Income Statement'!C24=0,0,'Income Statement'!C28/'Income Statement'!C24) -> 0.775 | D39: =IF('Income Statement'!D24=0,0,'Income Statement'!D28/'Income Statement'!D24) -> 0.775 | E39: =IF('Income Statement'!E24=0,0,'Income Statement'!E28/'Income Statement'!E24) -> 0.775 | F39: =IF('Income Statement'!F24=0,0,'Income Statement'!F28/'Income Statement'!F24) -> 0.775 | G39: =IF('Income Statement'!G24=0,0,'Income Statement'!G28/'Income Statement'!G24) -> 0.775 | H39: =IF('Income Statement'!H24=0,0,'Income Statement'!H28/'Income Statement'!H24) -> 0.775
A40: Interest Burden (EBT / EBIT) | B40: =IF('Income Statement'!B17=0,0,'Income Statement'!B24/'Income Statement'!B17) -> 0.90416667 | C40: =IF('Income Statement'!C17=0,0,'Income Statement'!C24/'Income Statement'!C17) -> 0.92537313 | D40: =IF('Income Statement'!D17=0,0,'Income Statement'!D24/'Income Statement'!D17) -> 0.98312434 | E40: =IF('Income Statement'!E17=0,0,'Income Statement'!E24/'Income Statement'!E17) -> 1.1153707 | F40: =IF('Income Statement'!F17=0,0,'Income Statement'!F24/'Income Statement'!F17) -> 1.1737492 | G40: =IF('Income Statement'!G17=0,0,'Income Statement'!G24/'Income Statement'!G17) -> 1.2020658 | H40: =IF('Income Statement'!H17=0,0,'Income Statement'!H24/'Income Statement'!H17) -> 1.2498448
A41: Operating Margin | B41: =IF('Income Statement'!B2=0,0,'Income Statement'!B17/'Income Statement'!B2) -> 0 | C41: =IF('Income Statement'!C2=0,0,'Income Statement'!C17/'Income Statement'!C2) -> 0 | D41: =IF('Income Statement'!D2=0,0,'Income Statement'!D17/'Income Statement'!D2) -> 0 | E41: =IF('Income Statement'!E2=0,0,'Income Statement'!E17/'Income Statement'!E2) -> 0 | F41: =IF('Income Statement'!F2=0,0,'Income Statement'!F17/'Income Statement'!F2) -> 0 | G41: =IF('Income Statement'!G2=0,0,'Income Statement'!G17/'Income Statement'!G2) -> 0 | H41: =IF('Income Statement'!H2=0,0,'Income Statement'!H17/'Income Statement'!H2) -> 0
A42: DuPont ROE (5-Factor) | B42: =B39*B40*B41*B36*B37 -> 0 | C42: =C39*C40*C41*C36*C37 -> 0 | D42: =D39*D40*D41*D36*D37 -> 0 | E42: =E39*E40*E41*E36*E37 -> 0 | F42: =F39*F40*F41*F36*F37 -> 0 | G42: =G39*G40*G41*G36*G37 -> 0 | H42: =H39*H40*H41*H36*H37 -> 0
A43: ── Altman Z'-Score (Credit Risk) ──
A44: X1 = Working Capital / Total Assets | B44: =IF('Balance Sheet'!B18=0,0,('Balance Sheet'!B9-'Balance Sheet'!B28)/'Balance Sheet'!B18) -> 0 | C44: =IF('Balance Sheet'!C18=0,0,('Balance Sheet'!C9-'Balance Sheet'!C28)/'Balance Sheet'!C18) -> 0 | D44: =IF('Balance Sheet'!D18=0,0,('Balance Sheet'!D9-'Balance Sheet'!D28)/'Balance Sheet'!D18) -> 0 | E44: =IF('Balance Sheet'!E18=0,0,('Balance Sheet'!E9-'Balance Sheet'!E28)/'Balance Sheet'!E18) -> 0 | F44: =IF('Balance Sheet'!F18=0,0,('Balance Sheet'!F9-'Balance Sheet'!F28)/'Balance Sheet'!F18) -> 0 | G44: =IF('Balance Sheet'!G18=0,0,('Balance Sheet'!G9-'Balance Sheet'!G28)/'Balance Sheet'!G18) -> 0 | H44: =IF('Balance Sheet'!H18=0,0,('Balance Sheet'!H9-'Balance Sheet'!H28)/'Balance Sheet'!H18) -> 0
A45: X2 = Retained Earnings / Total Assets | B45: =IF('Balance Sheet'!B18=0,0,'Balance Sheet'!B41/'Balance Sheet'!B18) -> 0 | C45: =IF('Balance Sheet'!C18=0,0,'Balance Sheet'!C41/'Balance Sheet'!C18) -> 0 | D45: =IF('Balance Sheet'!D18=0,0,'Balance Sheet'!D41/'Balance Sheet'!D18) -> 0 | E45: =IF('Balance Sheet'!E18=0,0,'Balance Sheet'!E41/'Balance Sheet'!E18) -> 0 | F45: =IF('Balance Sheet'!F18=0,0,'Balance Sheet'!F41/'Balance Sheet'!F18) -> 0 | G45: =IF('Balance Sheet'!G18=0,0,'Balance Sheet'!G41/'Balance Sheet'!G18) -> 0 | H45: =IF('Balance Sheet'!H18=0,0,'Balance Sheet'!H41/'Balance Sheet'!H18) -> 0
A46: X3 = EBIT / Total Assets | B46: =IF('Balance Sheet'!B18=0,0,'Income Statement'!B17/'Balance Sheet'!B18) -> 0 | C46: =IF('Balance Sheet'!C18=0,0,'Income Statement'!C17/'Balance Sheet'!C18) -> 0 | D46: =IF('Balance Sheet'!D18=0,0,'Income Statement'!D17/'Balance Sheet'!D18) -> 0 | E46: =IF('Balance Sheet'!E18=0,0,'Income Statement'!E17/'Balance Sheet'!E18) -> 0 | F46: =IF('Balance Sheet'!F18=0,0,'Income Statement'!F17/'Balance Sheet'!F18) -> 0 | G46: =IF('Balance Sheet'!G18=0,0,'Income Statement'!G17/'Balance Sheet'!G18) -> 0 | H46: =IF('Balance Sheet'!H18=0,0,'Income Statement'!H17/'Balance Sheet'!H18) -> 0
A47: X4 = Book Equity / Total Financial Debt | B47: =IF(('Balance Sheet'!B23+'Balance Sheet'!B30+'Balance Sheet'!B24)=0,0,'Balance Sheet'!B44/('Balance Sheet'!B23+'Balance Sheet'!B30+'Balance Sheet'!B24)) -> 0 | C47: =IF(('Balance Sheet'!C23+'Balance Sheet'!C30+'Balance Sheet'!C24)=0,0,'Balance Sheet'!C44/('Balance Sheet'!C23+'Balance Sheet'!C30+'Balance Sheet'!C24)) -> 0 | D47: =IF(('Balance Sheet'!D23+'Balance Sheet'!D30+'Balance Sheet'!D24)=0,0,'Balance Sheet'!D44/('Balance Sheet'!D23+'Balance Sheet'!D30+'Balance Sheet'!D24)) -> 0 | E47: =IF(('Balance Sheet'!E23+'Balance Sheet'!E30+'Balance Sheet'!E24)=0,0,'Balance Sheet'!E44/('Balance Sheet'!E23+'Balance Sheet'!E30+'Balance Sheet'!E24)) -> 0 | F47: =IF(('Balance Sheet'!F23+'Balance Sheet'!F30+'Balance Sheet'!F24)=0,0,'Balance Sheet'!F44/('Balance Sheet'!F23+'Balance Sheet'!F30+'Balance Sheet'!F24)) -> 0 | G47: =IF(('Balance Sheet'!G23+'Balance Sheet'!G30+'Balance Sheet'!G24)=0,0,'Balance Sheet'!G44/('Balance Sheet'!G23+'Balance Sheet'!G30+'Balance Sheet'!G24)) -> 0 | H47: =IF(('Balance Sheet'!H23+'Balance Sheet'!H30+'Balance Sheet'!H24)=0,0,'Balance Sheet'!H44/('Balance Sheet'!H23+'Balance Sheet'!H30+'Balance Sheet'!H24)) -> 0
A48: Altman Z' Score (Emerging Markets) | B48: =6.56*B44+3.26*B45+6.72*B46+1.05*B47 -> 0 | C48: =6.56*C44+3.26*C45+6.72*C46+1.05*C47 -> 0 | D48: =6.56*D44+3.26*D45+6.72*D46+1.05*D47 -> 0 | E48: =6.56*E44+3.26*E45+6.72*E46+1.05*E47 -> 0 | F48: =6.56*F44+3.26*F45+6.72*F46+1.05*F47 -> 0 | G48: =6.56*G44+3.26*G45+6.72*G46+1.05*G47 -> 0 | H48: =6.56*H44+3.26*H45+6.72*H46+1.05*H47 -> 0
A49: Zone | B49: =IF(B48>=2.9,"✅ Safe",IF(B48>=1.23,"⚠️ Grey","❌ Distress")) -> 0 | C49: =IF(C48>=2.9,"✅ Safe",IF(C48>=1.23,"⚠️ Grey","❌ Distress")) -> 0 | D49: =IF(D48>=2.9,"✅ Safe",IF(D48>=1.23,"⚠️ Grey","❌ Distress")) -> 0 | E49: =IF(E48>=2.9,"✅ Safe",IF(E48>=1.23,"⚠️ Grey","❌ Distress")) -> 0 | F49: =IF(F48>=2.9,"✅ Safe",IF(F48>=1.23,"⚠️ Grey","❌ Distress")) -> 0 | G49: =IF(G48>=2.9,"✅ Safe",IF(G48>=1.23,"⚠️ Grey","❌ Distress")) -> 0 | H49: =IF(H48>=2.9,"✅ Safe",IF(H48>=1.23,"⚠️ Grey","❌ Distress")) -> 0
A50: ── Break-Even Analysis ──
A51: Fixed Costs (Total OpEx) | B51: ='Income Statement'!B15 -> 0 | C51: ='Income Statement'!C15 -> 0 | D51: ='Income Statement'!D15 -> 0 | E51: ='Income Statement'!E15 -> 0 | F51: ='Income Statement'!F15 -> 0 | G51: ='Income Statement'!G15 -> 0 | H51: ='Income Statement'!H15 -> 0
A52: Contribution Margin Ratio | B52: =IF('Income Statement'!B2=0,0,'Income Statement'!B5/'Income Statement'!B2) -> 0 | C52: =IF('Income Statement'!C2=0,0,'Income Statement'!C5/'Income Statement'!C2) -> 0 | D52: =IF('Income Statement'!D2=0,0,'Income Statement'!D5/'Income Statement'!D2) -> 0 | E52: =IF('Income Statement'!E2=0,0,'Income Statement'!E5/'Income Statement'!E2) -> 0 | F52: =IF('Income Statement'!F2=0,0,'Income Statement'!F5/'Income Statement'!F2) -> 0 | G52: =IF('Income Statement'!G2=0,0,'Income Statement'!G5/'Income Statement'!G2) -> 0 | H52: =IF('Income Statement'!H2=0,0,'Income Statement'!H5/'Income Statement'!H2) -> 0
A53: Break-Even Revenue (EGP) | B53: =IF(B52=0,0,B51/B52) -> 550000 | C53: =IF(C52=0,0,C51/C52) -> 615000 | D53: =IF(D52=0,0,D51/D52) -> 559406.25 | E53: =IF(E52=0,0,E51/E52) -> 608521.25 | F53: =IF(F52=0,0,F51/F52) -> 656698.36 | G53: =IF(G52=0,0,G51/G52) -> 703040.09 | H53: =IF(H52=0,0,H51/H52) -> 746642.07
A54: Margin of Safety % | B54: =IF('Income Statement'!B2=0,0,('Income Statement'!B2-B53)/'Income Statement'!B2) -> 0.35294118 | C54: =IF('Income Statement'!C2=0,0,('Income Statement'!C2-C53)/'Income Statement'!C2) -> 0.35263158 | D54: =IF('Income Statement'!D2=0,0,('Income Statement'!D2-D53)/'Income Statement'!D2) -> 0.46468301 | E54: =IF('Income Statement'!E2=0,0,('Income Statement'!E2-E53)/'Income Statement'!E2) -> 0.46081761 | F54: =IF('Income Statement'!F2=0,0,('Income Statement'!F2-F53)/'Income Statement'!F2) -> 0.45619636 | G54: =IF('Income Statement'!G2=0,0,('Income Statement'!G2-G53)/'Income Statement'!G2) -> 0.45077487 | H54: =IF('Income Statement'!H2=0,0,('Income Statement'!H2-H53)/'Income Statement'!H2) -> 0.44448797
A55: Margin of Safety (EGP) | B55: ='Income Statement'!B2-B53 -> 0 | C55: ='Income Statement'!C2-C53 -> 0 | D55: ='Income Statement'!D2-D53 -> 0 | E55: ='Income Statement'!E2-E53 -> 0 | F55: ='Income Statement'!F2-F53 -> 0 | G55: ='Income Statement'!G2-G53 -> 0 | H55: ='Income Statement'!H2-H53 -> 0
A56: Operating Leverage | B56: =IF('Income Statement'!B17=0,0,'Income Statement'!B5/'Income Statement'!B17) -> 2.8333333 | C56: =IF('Income Statement'!C17=0,0,'Income Statement'!C5/'Income Statement'!C17) -> 2.8358209 | D56: =IF('Income Statement'!D17=0,0,'Income Statement'!D5/'Income Statement'!D17) -> 2.1520046 | E56: =IF('Income Statement'!E17=0,0,'Income Statement'!E5/'Income Statement'!E17) -> 2.170056 | F56: =IF('Income Statement'!F17=0,0,'Income Statement'!F5/'Income Statement'!F17) -> 2.1920385 | G56: =IF('Income Statement'!G17=0,0,'Income Statement'!G5/'Income Statement'!G17) -> 2.2184023 | H56: =IF('Income Statement'!H17=0,0,'Income Statement'!H5/'Income Statement'!H17) -> 2.2497797

Sheet Working Capital
A1: Demo Company Inc. — Working Capital Schedule | B1: 2024 (A) | C1: 2025 (A) | D1: 2026E | E1: 2027E | F1: 2028E | G1: 2029E | H1: 2030E
A2: EFFICIENCY METRICS
A3: Days Sales Outstanding (DSO) | B3: =Assumptions!B16 -> 45.000206 | C3: =Assumptions!C16 -> 44.999889 | D3: =Assumptions!D16 -> 45 | E3: =Assumptions!E16 -> 45 | F3: =Assumptions!F16 -> 45 | G3: =Assumptions!G16 -> 45 | H3: =Assumptions!H16 -> 45
A4: Days Inventory Outstanding (DIO) | B4: =Assumptions!B17 -> 30.000137 | C4: =Assumptions!C17 -> 29.999798 | D4: =Assumptions!D17 -> 30 | E4: =Assumptions!E17 -> 30 | F4: =Assumptions!F17 -> 30 | G4: =Assumptions!G17 -> 30 | H4: =Assumptions!H17 -> 30
A5: Days Payables Outstanding (DPO) | B5: =Assumptions!B18 -> 39.999706 | C5: =Assumptions!C18 -> 40.000158 | D5: =Assumptions!D18 -> 40 | E5: =Assumptions!E18 -> 40 | F5: =Assumptions!F18 -> 40 | G5: =Assumptions!G18 -> 40 | H5: =Assumptions!H18 -> 40
A6: Cash Conversion Cycle (days) | B6: =B3+B4-B5 -> 35.000637 | C6: =C3+C4-C5 -> 34.99953 | D6: =D3+D4-D5 -> 35 | E6: =E3+E4-E5 -> 35 | F6: =F3+F4-F5 -> 35 | G6: =G3+G4-G5 -> 35 | H6: =H3+H4-H5 -> 35
A8: CURRENT ASSETS (excl. Cash)
A9: Accounts Receivable | B9: ='Balance Sheet'!B4 -> 104795 | C9: ='Balance Sheet'!C4 -> 117123 | D9: ='Balance Sheet'!D4 -> 128835.62 | E9: ='Balance Sheet'!E4 -> 139142.47 | F9: ='Balance Sheet'!F4 -> 148882.44 | G9: ='Balance Sheet'!G4 -> 157815.38 | H9: ='Balance Sheet'!H4 -> 165706.15
A10: Inventory | B10: ='Balance Sheet'!B5 -> 41918 | C10: ='Balance Sheet'!C5 -> 46849 | D10: ='Balance Sheet'!D5 -> 51534.247 | E10: ='Balance Sheet'!E5 -> 55656.986 | F10: ='Balance Sheet'!F5 -> 59552.975 | G10: ='Balance Sheet'!G5 -> 63126.154 | H10: ='Balance Sheet'!H5 -> 66282.462
A11: Prepaid Expenses | B11: ='Balance Sheet'!B6 -> 8500 | C11: ='Balance Sheet'!C6 -> 9500 | D11: ='Balance Sheet'!D6 -> 10450 | E11: ='Balance Sheet'!E6 -> 11286 | F11: ='Balance Sheet'!F6 -> 12076.02 | G11: ='Balance Sheet'!G6 -> 12800.581 | H11: ='Balance Sheet'!H6 -> 13440.61
A12: Other Current Assets | B12: ='Balance Sheet'!B7 -> 10000 | C12: ='Balance Sheet'!C7 -> 10000 | D12: ='Balance Sheet'!D7 -> 10000 | E12: ='Balance Sheet'!E7 -> 10000 | F12: ='Balance Sheet'!F7 -> 10000 | G12: ='Balance Sheet'!G7 -> 10000 | H12: ='Balance Sheet'!H7 -> 10000
A14: CURRENT LIABILITIES (excl. Debt)
A15: Accounts Payable | B15: ='Balance Sheet'!B21 -> 55890 | C15: ='Balance Sheet'!C21 -> 62466 | D15: ='Balance Sheet'!D21 -> 68712.329 | E15: ='Balance Sheet'!E21 -> 74209.315 | F15: ='Balance Sheet'!F21 -> 79403.967 | G15: ='Balance Sheet'!G21 -> 84168.205 | H15: ='Balance Sheet'!H21 -> 88376.615
A16: Accrued Expenses | B16: ='Balance Sheet'!B22 -> 25500 | C16: ='Balance Sheet'!C22 -> 28500 | D16: ='Balance Sheet'!D22 -> 31350 | E16: ='Balance Sheet'!E22 -> 33858 | F16: ='Balance Sheet'!F22 -> 36228.06 | G16: ='Balance Sheet'!G22 -> 38401.744 | H16: ='Balance Sheet'!H22 -> 40321.831
A17: Deferred Revenue | B17: ='Balance Sheet'!B25 -> 17000 | C17: ='Balance Sheet'!C25 -> 19000 | D17: ='Balance Sheet'!D25 -> 20900 | E17: ='Balance Sheet'!E25 -> 22572 | F17: ='Balance Sheet'!F25 -> 24152.04 | G17: ='Balance Sheet'!G25 -> 25601.162 | H17: ='Balance Sheet'!H25 -> 26881.221
A18: Other Current Liabilities | B18: ='Balance Sheet'!B26 -> 15000 | C18: ='Balance Sheet'!C26 -> 15000 | D18: ='Balance Sheet'!D26 -> 15000 | E18: ='Balance Sheet'!E26 -> 15000 | F18: ='Balance Sheet'!F26 -> 15000 | G18: ='Balance Sheet'!G26 -> 15000 | H18: ='Balance Sheet'!H26 -> 15000
A20: Net Working Capital | B20: =(B9+B10+B11+B12)-(B15+B16+B17+B18) -> 51823 | C20: =(C9+C10+C11+C12)-(C15+C16+C17+C18) -> 58506 | D20: =(D9+D10+D11+D12)-(D15+D16+D17+D18) -> 64857.534 | E20: =(E9+E10+E11+E12)-(E15+E16+E17+E18) -> 70446.137 | F20: =(F9+F10+F11+F12)-(F15+F16+F17+F18) -> 75727.367 | G20: =(G9+G10+G11+G12)-(G15+G16+G17+G18) -> 80571.009 | H20: =(H9+H10+H11+H12)-(H15+H16+H17+H18) -> 84849.559
A21: NWC Change | B21: =0 -> 0 | C21: =C20-B20 -> 6683 | D21: =D20-C20 -> 6351.5342 | E21: =E20-D20 -> 5588.6027 | F21: =F20-E20 -> 5281.2296 | G21: =G20-F20 -> 4843.642 | H21: =H20-G20 -> 4278.5504
A22: NWC % of Revenue | B22: =IF('Income Statement'!B2=0,0,B20/'Income Statement'!B2) -> 0.060968235 | C22: =IF('Income Statement'!C2=0,0,C20/'Income Statement'!C2) -> 0.061585263 | D22: =IF('Income Statement'!D2=0,0,D20/'Income Statement'!D2) -> 0.062064626 | E22: =IF('Income Statement'!E2=0,0,E20/'Income Statement'!E2) -> 0.062419047 | F22: =IF('Income Statement'!F2=0,0,F20/'Income Statement'!F2) -> 0.062708878 | G22: =IF('Income Statement'!G2=0,0,G20/'Income Statement'!G2) -> 0.062943242 | H22: =IF('Income Statement'!H2=0,0,H20/'Income Statement'!H2) -> 0.063129246

Sheet Depreciation Schedule
A1: Demo Company Inc. — PP&E Rollforward | B1: 2024 (A) | C1: 2025 (A) | D1: 2026E | E1: 2027E | F1: 2028E | G1: 2029E | H1: 2030E
A2: GROSS PP&E
A3: Beginning Gross PP&E | C3: ='Balance Sheet'!B11 -> 340000 | D3: ='Balance Sheet'!C11 -> 385000 | E3: ='Balance Sheet'!D11 -> 437250 | F3: ='Balance Sheet'!E11 -> 493680 | G3: ='Balance Sheet'!F11 -> 554060.1 | H3: ='Balance Sheet'!G11 -> 618063.01
A4: (+) Capital Expenditures | C4: =ABS('Income Statement'!C2*Assumptions!C23) -> 45000 | D4: =ABS('Income Statement'!D2*Assumptions!D23) -> 52250 | E4: =ABS('Income Statement'!E2*Assumptions!E23) -> 56430 | F4: =ABS('Income Statement'!F2*Assumptions!F23) -> 60380.1 | G4: =ABS('Income Statement'!G2*Assumptions!G23) -> 64002.906 | H4: =ABS('Income Statement'!H2*Assumptions!H23) -> 67203.051
A5: Ending Gross PP&E | B5: ='Balance Sheet'!B11 -> 340000 | C5: ='Balance Sheet'!C11 -> 385000 | D5: ='Balance Sheet'!D11 -> 437250 | E5: ='Balance Sheet'!E11 -> 493680 | F5: ='Balance Sheet'!F11 -> 554060.1 | G5: ='Balance Sheet'!G11 -> 618063.01 | H5: ='Balance Sheet'!H11 -> 685266.06
A7: ACCUMULATED DEPRECIATION
A8: Beginning Accum. Depreciation | C8: ='Balance Sheet'!B12 -> 128000 | D8: ='Balance Sheet'!C12 -> 160000 | E8: ='Balance Sheet'!D12 -> 201112.5 | F8: ='Balance Sheet'!E12 -> 247659 | G8: ='Balance Sheet'!F12 -> 300046.01 | H8: ='Balance Sheet'!G12 -> 358652.16
A9: (+) Depreciation Expense | B9: ='Income Statement'!B11 -> 28000 | C9: ='Income Statement'!C11 -> 32000 | D9: ='Income Statement'!D11 -> 41112.5 | E9: ='Income Statement'!E11 -> 46546.5 | F9: ='Income Statement'!F11 -> 52387.005 | G9: ='Income Statement'!G11 -> 58606.155 | H9: ='Income Statement'!H11 -> 65166.453
A10: Ending Accum. Depreciation | B10: ='Balance Sheet'!B12 -> 128000 | C10: ='Balance Sheet'!C12 -> 160000 | D10: ='Balance Sheet'!D12 -> 201112.5 | E10: ='Balance Sheet'!E12 -> 247659 | F10: ='Balance Sheet'!F12 -> 300046.01 | G10: ='Balance Sheet'!G12 -> 358652.16 | H10: ='Balance Sheet'!H12 -> 423818.61
A12: Net PP&E | B12: ='Balance Sheet'!B13 -> 212000 | C12: ='Balance Sheet'!C13 -> 225000 | D12: ='Balance Sheet'!D13 -> 236137.5 | E12: ='Balance Sheet'!E13 -> 246021 | F12: ='Balance Sheet'!F13 -> 254014.09 | G12: ='Balance Sheet'!G13 -> 259410.85 | H12: ='Balance Sheet'!H13 -> 261447.44
A14: KEY METRICS
A15: CapEx % of Revenue | C15: =IF('Income Statement'!C2=0,0,C4/'Income Statement'!C2) -> 0.047368421 | D15: =IF('Income Statement'!D2=0,0,D4/'Income Statement'!D2) -> 0.05 | E15: =IF('Income Statement'!E2=0,0,E4/'Income Statement'!E2) -> 0.05 | F15: =IF('Income Statement'!F2=0,0,F4/'Income Statement'!F2) -> 0.05 | G15: =IF('Income Statement'!G2=0,0,G4/'Income Statement'!G2) -> 0.05 | H15: =IF('Income Statement'!H2=0,0,H4/'Income Statement'!H2) -> 0.05
A16: Depreciation Rate (% Gross PP&E) | B16: =IF(B5=0,0,B9/B5) -> 0.082352941 | C16: =IF(C5=0,0,C9/C5) -> 0.083116883 | D16: =IF(D5=0,0,D9/D5) -> 0.094025157 | E16: =IF(E5=0,0,E9/E5) -> 0.094284759 | F16: =IF(F5=0,0,F9/F5) -> 0.094551124 | G16: =IF(G5=0,0,G9/G5) -> 0.094822299 | H16: =IF(H5=0,0,H9/H5) -> 0.095096572
A17: Implied Useful Life (yrs) | B17: =IF(B16=0,0,1/B16) -> 12.142857 | C17: =IF(C16=0,0,1/C16) -> 12.03125 | D17: =IF(D16=0,0,1/D16) -> 10.635452 | E17: =IF(E16=0,0,1/E16) -> 10.606168 | F17: =IF(F16=0,0,1/F16) -> 10.576289 | G17: =IF(G16=0,0,1/G16) -> 10.546043 | H17: =IF(H16=0,0,1/H16) -> 10.515626
A19: INTANGIBLES
A20: Amortization Expense | B20: ='Income Statement'!B12 -> 5000 | C20: ='Income Statement'!C12 -> 5000 | D20: ='Income Statement'!D12 -> 5000 | E20: ='Income Statement'!E12 -> 5000 | F20: ='Income Statement'!F12 -> 5000 | G20: ='Income Statement'!G12 -> 5000 | H20: ='Income Statement'!H12 -> 5000
A21: Net Intangibles | B21: ='Balance Sheet'!B14 -> 45000 | C21: ='Balance Sheet'!C14 -> 40000 | D21: ='Balance Sheet'!D14 -> 35000 | E21: ='Balance Sheet'!E14 -> 30000 | F21: ='Balance Sheet'!F14 -> 25000 | G21: ='Balance Sheet'!G14 -> 20000 | H21: ='Balance Sheet'!H14 -> 15000

Sheet Debt Schedule
A1: Demo Company Inc. — Debt Schedule | B1: 2024 (A) | C1: 2025 (A) | D1: 2026E | E1: 2027E | F1: 2028E | G1: 2029E | H1: 2030E
A2: LONG-TERM DEBT ROLLFORWARD
A3: Beginning Long-Term Debt | C3: ='Balance Sheet'!B30 -> 230000 | D3: ='Balance Sheet'!C30 -> 210000 | E3: ='Balance Sheet'!D30 -> 210000 | F3: ='Balance Sheet'!E30 -> 210000 | G3: ='Balance Sheet'!F30 -> 210000 | H3: ='Balance Sheet'!G30 -> 210000
A4: (+) New Issuance | C4: =Assumptions!C31 -> 0 | D4: =Assumptions!D31 -> 0 | E4: =Assumptions!E31 -> 0 | F4: =Assumptions!F31 -> 0 | G4: =Assumptions!G31 -> 0 | H4: =Assumptions!H31 -> 0
A5: (-) Repayments | C5: =-ABS(Assumptions!C32) -> -20000 | D5: =-ABS(Assumptions!D32) -> 0 | E5: =-ABS(Assumptions!E32) -> 0 | F5: =-ABS(Assumptions!F32) -> 0 | G5: =-ABS(Assumptions!G32) -> 0 | H5: =-ABS(Assumptions!H32) -> 0
A6: Ending Long-Term Debt | B6: ='Balance Sheet'!B30 -> 230000 | C6: ='Balance Sheet'!C30 -> 210000 | D6: ='Balance Sheet'!D30 -> 210000 | E6: ='Balance Sheet'!E30 -> 210000 | F6: ='Balance Sheet'!F30 -> 210000 | G6: ='Balance Sheet'!G30 -> 210000 | H6: ='Balance Sheet'!H30 -> 210000
A8: DEBT SUMMARY
A9: Short-Term Debt | B9: ='Balance Sheet'!B23 -> 50000 | C9: ='Balance Sheet'!C23 -> 50000 | D9: ='Balance Sheet'!D23 -> 50000 | E9: ='Balance Sheet'!E23 -> 50000 | F9: ='Balance Sheet'!F23 -> 50000 | G9: ='Balance Sheet'!G23 -> 50000 | H9: ='Balance Sheet'!H23 -> 50000
A10: Current Portion of LTD | B10: ='Balance Sheet'!B24 -> 20000 | C10: ='Balance Sheet'!C24 -> 20000 | D10: ='Balance Sheet'!D24 -> 20000 | E10: ='Balance Sheet'!E24 -> 20000 | F10: ='Balance Sheet'!F24 -> 20000 | G10: ='Balance Sheet'!G24 -> 20000 | H10: ='Balance Sheet'!H24 -> 20000
A11: Long-Term Debt | B11: ='Balance Sheet'!B30 -> 230000 | C11: ='Balance Sheet'!C30 -> 210000 | D11: ='Balance Sheet'!D30 -> 210000 | E11: ='Balance Sheet'!E30 -> 210000 | F11: ='Balance Sheet'!F30 -> 210000 | G11: ='Balance Sheet'!G30 -> 210000 | H11: ='Balance Sheet'!H30 -> 210000
A12: Total Debt | B12: =B9+B10+B11 -> 300000 | C12: =C9+C10+C11 -> 280000 | D12: =D9+D10+D11 -> 280000 | E12: =E9+E10+E11 -> 280000 | F12: =F9+F10+F11 -> 280000 | G12: =G9+G10+G11 -> 280000 | H12: =H9+H10+H11 -> 280000
A14: INTEREST ANALYSIS
A15: Beginning-of-Period Debt Balance | B15: =B12 -> 300000 | C15: =(C12+B12)/2 -> 290000 | D15: =(D12+C12)/2 -> 280000 | E15: =(E12+D12)/2 -> 280000 | F15: =(F12+E12)/2 -> 280000 | G15: =(G12+F12)/2 -> 280000 | H15: =(H12+G12)/2 -> 280000
A16: Interest Expense | B16: ='Income Statement'!B22 -> 14000 | C16: ='Income Statement'!C22 -> 13000 | D16: ='Income Statement'!D22 -> 61600 | E16: ='Income Statement'!E22 -> 56000 | F16: ='Income Statement'!F22 -> 50400 | G16: ='Income Statement'!G22 -> 47600 | H16: ='Income Statement'!H22 -> 44800
A17: Interest Income | B17: ='Income Statement'!B21 -> 2500 | C17: ='Income Statement'!C21 -> 3000 | D17: ='Income Statement'!D21 -> 58322.115 | E17: ='Income Statement'!E21 -> 80000.745 | F17: ='Income Statement'!F21 -> 88687.637 | G17: ='Income Statement'!G21 -> 94238.234 | H17: ='Income Statement'!H21 -> 104504.81
A18: Net Interest | B18: =B16-B17 -> 11500 | C18: =C16-C17 -> 10000 | D18: =D16-D17 -> 3277.8854 | E18: =E16-E17 -> -24000.745 | F18: =F16-F17 -> -38287.637 | G18: =G16-G17 -> -46638.234 | H18: =H16-H17 -> -59704.809
A20: LEVERAGE RATIOS
A21: Interest Coverage (EBIT / Int Exp) | B21: =IF(B16=0,0,'Income Statement'!B17/B16) -> 8.5714286 | C21: =IF(C16=0,0,'Income Statement'!C17/C16) -> 10.307692 | D21: =IF(D16=0,0,'Income Statement'!D17/D16) -> 3.1532062 | E21: =IF(E16=0,0,'Income Statement'!E17/E16) -> 3.7148482 | F21: =IF(F16=0,0,'Income Statement'!F17/F16) -> 4.3722511 | G21: =IF(G16=0,0,'Income Statement'!G17/G16) -> 4.848891 | H21: =IF(H16=0,0,'Income Statement'!H17/H16) -> 5.3340978
A22: Debt / Equity | B22: =IF('Balance Sheet'!B44=0,0,B12/'Balance Sheet'!B44) -> 1.2056763 | C22: =IF('Balance Sheet'!C44=0,0,C12/'Balance Sheet'!C44) -> 0.90759985 | D22: =IF('Balance Sheet'!D44=0,0,D12/'Balance Sheet'!D44) -> 0.69437206 | E22: =IF('Balance Sheet'!E44=0,0,E12/'Balance Sheet'!E44) -> 0.54207701 | F22: =IF('Balance Sheet'!F44=0,0,F12/'Balance Sheet'!F44) -> 0.43558262 | G22: =IF('Balance Sheet'!G44=0,0,G12/'Balance Sheet'!G44) -> 0.35976772 | H22: =IF('Balance Sheet'!H44=0,0,H12/'Balance Sheet'!H44) -> 0.3029953
A23: Debt / Total Assets | B23: =IF('Balance Sheet'!B18=0,0,B12/'Balance Sheet'!B18) -> 0.41828578 | C23: =IF('Balance Sheet'!C18=0,0,C12/'Balance Sheet'!C18) -> 0.3643594 | D23: =IF('Balance Sheet'!D18=0,0,D12/'Balance Sheet'!D18) -> 0.27635505 | E23: =IF('Balance Sheet'!E18=0,0,E12/'Balance Sheet'!E18) -> 0.24405659 | F23: =IF('Balance Sheet'!F18=0,0,F12/'Balance Sheet'!F18) -> 0.2165151 | G23: =IF('Balance Sheet'!G18=0,0,G12/'Balance Sheet'!G18) -> 0.19354409 | H23: =IF('Balance Sheet'!H18=0,0,H12/'Balance Sheet'!H18) -> 0.17408101
A24: Debt / EBITDA | B24: =IF('Income Statement'!B18=0,0,B12/'Income Statement'!B18) -> 1.9607843 | C24: =IF('Income Statement'!C18=0,0,C12/'Income Statement'!C18) -> 1.6374269 | D24: =IF('Income Statement'!D18=0,0,D12/'Income Statement'!D18) -> 1.1649678 | E24: =IF('Income Statement'!E18=0,0,E12/'Income Statement'!E18) -> 1.0786738 | F24: =IF('Income Statement'!F18=0,0,F12/'Income Statement'!F18) -> 1.0081064 | G24: =IF('Income Statement'!G18=0,0,G12/'Income Statement'!G18) -> 0.95104377 | H24: =IF('Income Statement'!H18=0,0,H12/'Income Statement'!H18) -> 0.90575597

Sheet DCF Valuation
A1: Demo Company Inc. — DCF Valuation
A3: ── WACC Calculation ──
A4: Risk-Free Rate (12M T-Bill) | B4: 0.235
A5: Equity Risk Premium | B5: 0.105
A6: Beta (β) | B6: 1
A7: Cost of Debt (pre-tax) | B7: 0.16
A8: Tax Rate | B8: 0.225
A9: Debt Weight | B9: 0.23253753
A10: Equity Weight | B10: 0.76746247
A11: Terminal Growth Rate | B11: 0.07
A12: Cost of Equity (CAPM) | B12: =B4+B6*B5 -> 0.34
A13: Cost of Debt (after-tax) | B13: =B7*(1-B8) -> 0.124
A14: WACC | B14: =B10*B12+B9*B13 -> 0.28977189
A16: ── FCF Projections ──
A17: Period | B17: 2026E | C17: 2027E | D17: 2028E | E17: 2029E | F17: 2030E
A18: FCFF (Unlevered Free Cash Flow) | B18: 134245.03 | C18: 147408.31 | D18: 159345.72 | E18: 170736.95 | F18: 181324.61
A19: Discount Factor | B19: =1/(1+B14)^1 -> 0.7753309 | C19: =1/(1+B14)^2 -> 0.601138 | D19: =1/(1+B14)^3 -> 0.46608086 | E19: =1/(1+B14)^4 -> 0.3613669 | F19: =1/(1+B14)^5 -> 0.28017892
A20: PV of FCF | B20: =B18*B19 -> 122040.93 | C20: =C18*C19 -> 121825.05 | D20: =D18*D19 -> 119718.8 | E20: =E18*E19 -> 116615.64 | F20: =F18*F19 -> 112588.32
A22: ── Valuation Summary ──
A23: Terminal Value | B23: =F18*(1+B11)/(B14-B11) -> 882812.31
A24: PV of Terminal Value | B24: =B23/(1+B14)^5 -> 247345.4
A25: Sum of PV(FCF) | B25: =SUM(B20:F20) -> 379467.06
A26: Enterprise Value | B26: =B24+B25 -> 626812.46
A27: Less: Net Debt | B27: =-667161.415001139 -> -667161.42
A28: Equity Value | B28: =B26-B27 -> 1293973.9
A29: Shares Outstanding | B29: =100000 -> 100000
A30: Implied Share Price | B30: =B28/B29 -> 12.939739
A32: ── Sensitivity: WACC × Terminal Growth ──
A33: Implied Share Price | B33: 0.05 | C33: 0.06 | D33: 0.07 | E33: 0.08 | F33: 0.09
A34: 0.26977189 | B34: 13.252046 | C34: 13.403344 | D34: 13.56979 | E34: 13.753777 | F34: 13.958233
A35: 0.27977189 | B35: 12.959256 | C35: 13.093118 | D35: 13.239742 | E35: 13.401046 | F35: 13.57935
A36: 0.28977189 | B36: 12.691045 | C36: 12.80998 | D36: 12.939739 | E36: 13.081869 | F36: 13.238228
A37: 0.29977189 | B37: 12.444457 | C37: 12.55054 | D37: 12.665857 | E37: 12.791668 | F37: 12.929474
A38: 0.30977189 | B38: 12.216988 | C38: 12.311947 | D38: 12.414828 | E38: 12.526663 | F38: 12.648676

Sheet Valuation Multiples
A1: Demo Company Inc. — Valuation Multiples
A3: ── Market Inputs ──
A4: Share Price | B4: 0
A5: Shares Outstanding | B5: 100000
A6: Market Cap | B6: 0
A7: Total Debt | B7: 280000
A8: Cash | B8: 947161.42
A9: Enterprise Value | B9: -667161.42
A11: ── Trading Multiples ──
A12: Multiple | B12: 2024 | C12: 2025 | D12: 2026E | E12: 2027E | F12: 2028E | G12: 2029E | H12: 2030E
A13: EV / Revenue | B13: -0.78489578 | C13: -0.70227517 | D13: -0.63843198 | E13: -0.59114072 | F13: -0.55246796 | G13: -0.52119619 | H13: -0.49637732
A14: EV / EBITDA | B14: -4.3605321 | C14: -3.9015287 | D14: -2.7757912 | E14: -2.570177 | F14: -2.4020346 | G14: -2.2660704 | H14: -2.1581623
A15: P / E | B15: 0 | C15: 0 | D15: 0 | E15: 0 | F15: 0 | G15: 0 | H15: 0
A16: P / Book | B16: 0 | C16: 0 | D16: 0 | E16: 0 | F16: 0 | G16: 0 | H16: 0
A17: FCF Yield | B17: 0 | C17: 0 | D17: 0 | E17: 0 | F17: 0 | G17: 0 | H17: 0
A18: Dividend Yield | B18: 0 | C18: 0 | D18: 0 | E18: 0 | F18: 0 | G18: 0 | H18: 0
A20: ── EGX 30 Benchmark Reference ──
A21: EGX 30 Avg P/E | B21: 8.0–15.0x
A22: EGX 30 Avg P/B | B22: 1.5–2.5x
A23: EGX 30 Avg Div Yield | B23: 2.0–4.0%
A24: Egyptian Market EV/EBITDA | B24: 6.0–10.0x

Sheet CBE Banking Metrics
A1: CBE Banking Metrics — Regulatory Compliance
A3: Metric | B3: Threshold | C3: 2024 | D3: 2025 | E3: 2026E | F3: 2027E | G3: 2028E | H3: 2029E | I3: 2030E
A4: Current Ratio | B4: ≥ 1.20x | C4: 1.8551339 | D4: 1.966866 | E4: 1.8033242 | F4: 2.0540479 | G4: 2.3202115 | H4: 2.5960313 | I4: 2.8902554
A5: Status | C5: =IF(C4>=1.2,"✓ PASS","✗ FAIL") -> ✓ PASS | D5: =IF(D4>=1.2,"✓ PASS","✗ FAIL") -> ✓ PASS | E5: =IF(E4>=1.2,"✓ PASS","✗ FAIL") -> ✓ PASS | F5: =IF(F4>=1.2,"✓ PASS","✗ FAIL") -> ✓ PASS | G5: =IF(G4>=1.2,"✓ PASS","✗ FAIL") -> ✓ PASS | H5: =IF(H4>=1.2,"✓ PASS","✗ FAIL") -> ✓ PASS | I5: =IF(I4>=1.2,"✓ PASS","✗ FAIL") -> ✓ PASS
A7: Debt-to-Equity | B7: ≤ 2.00x | C7: 1.2056763 | D7: 0.90759985 | E7: 0.69437206 | F7: 0.54207701 | G7: 0.43558262 | H7: 0.35976772 | I7: 0.3029953
A8: Status | C8: =IF(C7<=2,"✓ PASS","✗ FAIL") -> ✓ PASS | D8: =IF(D7<=2,"✓ PASS","✗ FAIL") -> ✓ PASS | E8: =IF(E7<=2,"✓ PASS","✗ FAIL") -> ✓ PASS | F8: =IF(F7<=2,"✓ PASS","✗ FAIL") -> ✓ PASS | G8: =IF(G7<=2,"✓ PASS","✗ FAIL") -> ✓ PASS | H8: =IF(H7<=2,"✓ PASS","✗ FAIL") -> ✓ PASS | I8: =IF(I7<=2,"✓ PASS","✗ FAIL") -> ✓ PASS
A10: Interest Coverage | B10: ≥ 2.00x | C10: 8.5714286 | D10: 10.307692 | E10: 3.1532062 | F10: 3.7148482 | G10: 4.3722511 | H10: 4.848891 | I10: 5.3340978
A11: Status | C11: =IF(C10>=2,"✓ PASS","✗ FAIL") -> ✓ PASS | D11: =IF(D10>=2,"✓ PASS","✗ FAIL") -> ✓ PASS | E11: =IF(E10>=2,"✓ PASS","✗ FAIL") -> ✓ PASS | F11: =IF(F10>=2,"✓ PASS","✗ FAIL") -> ✓ PASS | G11: =IF(G10>=2,"✓ PASS","✗ FAIL") -> ✓ PASS | H11: =IF(H10>=2,"✓ PASS","✗ FAIL") -> ✓ PASS | I11: =IF(I10>=2,"✓ PASS","✗ FAIL") -> ✓ PASS
A13: Net Debt / EBITDA | B13: ≤ 3.00x | C13: 0.81699346 | D13: 0.46783626 | E13: -0.55717494 | F13: -0.95257779 | G13: -1.3509835 | H13: -1.747833 | I13: -2.1581623
A14: Status | C14: =IF(C13<=3,"✓ PASS","✗ FAIL") -> ✓ PASS | D14: =IF(D13<=3,"✓ PASS","✗ FAIL") -> ✓ PASS | E14: =IF(E13<=3,"✓ PASS","✗ FAIL") -> ✓ PASS | F14: =IF(F13<=3,"✓ PASS","✗ FAIL") -> ✓ PASS | G14: =IF(G13<=3,"✓ PASS","✗ FAIL") -> ✓ PASS | H14: =IF(H13<=3,"✓ PASS","✗ FAIL") -> ✓ PASS | I14: =IF(I13<=3,"✓ PASS","✗ FAIL") -> ✓ PASS
A16: DSCR | B16: ≥ 1.25x | C16: 10.928571 | D16: 5.1818182 | E16: 3.9017857 | F16: 4.6353214 | G16: 5.5108821 | H16: 6.1851548 | I16: 6.9003133
A17: Status | C17: =IF(C16>=1.25,"✓ PASS","✗ FAIL") -> ✓ PASS | D17: =IF(D16>=1.25,"✓ PASS","✗ FAIL") -> ✓ PASS | E17: =IF(E16>=1.25,"✓ PASS","✗ FAIL") -> ✓ PASS | F17: =IF(F16>=1.25,"✓ PASS","✗ FAIL") -> ✓ PASS | G17: =IF(G16>=1.25,"✓ PASS","✗ FAIL") -> ✓ PASS | H17: =IF(H16>=1.25,"✓ PASS","✗ FAIL") -> ✓ PASS | I17: =IF(I16>=1.25,"✓ PASS","✗ FAIL") -> ✓ PASS
A20: ── Market Reference Rates ──
A21: CBE Discount Rate (Reference) | B21: 19.50% (MPC April 2, 2026)
A22: Commercial Lending Rate | B22: CBE + 2–3% spread
A23: Corporate Tax Rate (ETA) | B23: 22.5%
A24: Egyptian VAT Rate | B24: 14%
A26: Note: ETA e-invoicing compliance required for all B2B transactions.

Sheet VAT Schedule
A1: Demo Company Inc. — VAT Schedule
A2: VAT Rate: 14% (Egyptian standard — Law 67/2016)
A3: Item | B3: 2024 | C3: 2025 | D3: 2026E | E3: 2027E | F3: 2028E | G3: 2029E | H3: 2030E
A4: VAT Rate | B4: 0.14 | C4: 0.14 | D4: 0.14 | E4: 0.14 | F4: 0.14 | G4: 0.14 | H4: 0.14
A5: VAT on Revenue (Output) | B5: ='Income Statement'!B2*B4 -> 119000 | C5: ='Income Statement'!C2*C4 -> 133000 | D5: ='Income Statement'!D2*D4 -> 146300 | E5: ='Income Statement'!E2*E4 -> 158004 | F5: ='Income Statement'!F2*F4 -> 169064.28 | G5: ='Income Statement'!G2*G4 -> 179208.14 | H5: ='Income Statement'!H2*H4 -> 188168.54
A6: VAT on Purchases (Input) | B6: ='Income Statement'!B4*B4 -> 71400 | C6: ='Income Statement'!C4*C4 -> 79800 | D6: ='Income Statement'!D4*D4 -> 87780 | E6: ='Income Statement'!E4*E4 -> 94802.4 | F6: ='Income Statement'!F4*F4 -> 101438.57 | G6: ='Income Statement'!G4*G4 -> 107524.88 | H6: ='Income Statement'!H4*H4 -> 112901.13
A7: VAT on CapEx (Input) | B7: ='Income Statement'!B2*0*B4 -> 0 | C7: ='Income Statement'!C2*IF('Historical Data'!C4=0,0,('Historical Data'!C29-'Historical Data'!B29)/'Historical Data'!C4)*C4 -> 6300 | D7: ='Income Statement'!D2*Assumptions!D23*D4 -> 7315 | E7: ='Income Statement'!E2*Assumptions!E23*E4 -> 7900.2 | F7: ='Income Statement'!F2*Assumptions!F23*F4 -> 8453.214 | G7: ='Income Statement'!G2*Assumptions!G23*G4 -> 8960.4068 | H7: ='Income Statement'!H2*Assumptions!H23*H4 -> 9408.4272
A8: Total Input VAT | B8: =B6+B7 -> 71400 | C8: =C6+C7 -> 86100 | D8: =D6+D7 -> 95095 | E8: =E6+E7 -> 102702.6 | F8: =F6+F7 -> 109891.78 | G8: =G6+G7 -> 116485.29 | H8: =H6+H7 -> 122309.55
A10: Net VAT Payable | B10: =B5-B8 -> 47600 | C10: =C5-C8 -> 46900 | D10: =D5-D8 -> 51205 | E10: =E5-E8 -> 55301.4 | F10: =F5-F8 -> 59172.498 | G10: =G5-G8 -> 62722.848 | H10: =H5-H8 -> 65858.99
A12: ── BS Reconciliation ──
A13: BS: VAT Receivable | B13: ='Balance Sheet'!B8 -> 0 | C13: ='Balance Sheet'!C8 -> 0 | D13: ='Balance Sheet'!D8 -> 7315 | E13: ='Balance Sheet'!E8 -> 7900.2 | F13: ='Balance Sheet'!F8 -> 8453.214 | G13: ='Balance Sheet'!G8 -> 8960.4068 | H13: ='Balance Sheet'!H8 -> 9408.4272
A14: BS: VAT Payable | B14: ='Balance Sheet'!B27 -> 0 | C14: ='Balance Sheet'!C27 -> 0 | D14: ='Balance Sheet'!D27 -> 138985 | E14: ='Balance Sheet'!E27 -> 150103.8 | F14: ='Balance Sheet'!F27 -> 160611.07 | G14: ='Balance Sheet'!G27 -> 170247.73 | H14: ='Balance Sheet'!H27 -> 178760.12
A16: Note: ETA e-invoicing compliance required for all B2B transactions.

Sheet Historical Data
A1: Demo Company Inc. — Historical Data (2024–2025)
B2: 2024 | C2: 2025
A3: INCOME STATEMENT
A4: Revenue | B4: 850000 | C4: 950000
A5: COGS | B5: 510000 | C5: 570000
A6: Gross Profit | B6: 340000 | C6: 380000
A7: SG&A | B7: 127500 | C7: 142500
A8: R&D | B8: 42500 | C8: 47500
A9: Depreciation | B9: 28000 | C9: 32000
A10: Amortization | B10: 5000 | C10: 5000
A11: Other OpEx | B11: 17000 | C11: 19000
A12: Total OpEx | B12: 220000 | C12: 246000
A13: EBIT | B13: 120000 | C13: 134000
A14: Interest Expense | B14: 14000 | C14: 13000
A15: Interest Income | B15: 2500 | C15: 3000
... A21: Stock-Based Comp | B21: 0 | C21: 0
A23: BALANCE SHEET
A24: Cash & Equivalents | B24: 175000 | C24: 200000
A25: Accounts Receivable | B25: 104795 | C25: 117123
A26: Inventory | B26: 41918 | C26: 46849
A27: Prepaid Expenses | B27: 8500 | C27: 9500
A28: Other Current Assets | B28: 10000 | C28: 10000
A29: Gross PP&E | B29: 340000 | C29: 385000
A30: Accum. Depreciation | B30: 128000 | C30: 160000
A31: Net PP&E | B31: 212000 | C31: 225000
A32: Intangibles | B32: 45000 | C32: 40000
A33: Goodwill | B33: 100000 | C33: 100000
A34: Other LT Assets | B34: 20000 | C34: 20000
A35: Total Assets | B35: 717213 | C35: 768472
... A53: Total L+E | B53: 717213 | C53: 768472
A55: DERIVED ASSUMPTIONS (for reference)
A56: Gross Margin % | B56: =IF(B4=0,0,(B4-B5)/B4) -> 0 | C56: =IF(C4=0,0,(C4-C5)/C4) -> 0
A57: Effective Tax Rate % | B57: =IF(B16=0,0,B17/B16) -> 0 | C57: =IF(C16=0,0,C17/C16) -> 0
A58: DSO (Days) | B58: =IF(B4=0,0,ROUND(B25/B4*365,1)) -> 0 | C58: =IF(C4=0,0,ROUND(C25/C4*365,1)) -> 0
A59: DIO (Days) | B59: =IF(B5=0,0,ROUND(B26/B5*365,1)) -> 0 | C59: =IF(C5=0,0,ROUND(C26/C5*365,1)) -> 0
A60: DPO (Days) | B60: =IF(B5=0,0,ROUND(B36/B5*365,1)) -> 0 | C60: =IF(C5=0,0,ROUND(C36/C5*365,1)) -> 0

Sheet _Calc_Base
A1: _Calc_Base — Full 3-Statement Model | B1: 2024 | C1: 2025 | D1: 2026E | E1: 2027E | F1: 2028E | G1: 2029E | H1: 2030E
A2: ⚠ HOW TO RECALCULATE AFTER CHANGING ASSUMPTIONS: | 1. File → Options → Formulas → Enable iterative calculation (Max Iterations=1000, Max Change=0.001) | 2. Press Ctrl+Alt+F9 to force full recalculation | 3. Values shown by default are pre-calculated by the WOLF engine and are correct as-is.
A4: Revenue | B4: ='Income Statement'!B2 -> 850000 | C4: ='Income Statement'!C2 -> 950000 | D4: =C4*(1+Scenarios!D8) -> 1045000 | E4: =D4*(1+Scenarios!E8) -> 1128600 | F4: =E4*(1+Scenarios!F8) -> 1207602 | G4: =F4*(1+Scenarios!G8) -> 1280058.1 | H4: =G4*(1+Scenarios!H8) -> 1344061
A5: Revenue Growth % | B5: =0 -> 0 | C5: =(C4-B4)/B4 -> 0.11764706 | D5: =Scenarios!D8 -> 0.1 | E5: =Scenarios!E8 -> 0.08 | F5: =Scenarios!F8 -> 0.07 | G5: =Scenarios!G8 -> 0.06 | H5: =Scenarios!H8 -> 0.05
A6: COGS | B6: ='Income Statement'!B4 -> 510000 | C6: ='Income Statement'!C4 -> 570000 | D6: =D4*Scenarios!D9 -> 627000 | E6: =E4*Scenarios!E9 -> 677160 | F6: =F4*Scenarios!F9 -> 724561.2 | G6: =G4*Scenarios!G9 -> 768034.87 | H6: =H4*Scenarios!H9 -> 806436.62
A7: Gross Profit | B7: =B4-B6 -> 340000 | C7: =C4-C6 -> 380000 | D7: =D4-D6 -> 418000 | E7: =E4-E6 -> 451440 | F7: =F4-F6 -> 483040.8 | G7: =G4-G6 -> 512023.25 | H7: =H4-H6 -> 537624.41
A8: SG&A | B8: ='Income Statement'!B9 -> 127500 | C8: ='Income Statement'!C9 -> 142500 | D8: =D4*Scenarios!D10 -> 156750 | E8: =E4*Scenarios!E10 -> 169290 | F8: =F4*Scenarios!F10 -> 181140.3 | G8: =G4*Scenarios!G10 -> 192008.72 | H8: =H4*Scenarios!H10 -> 201609.15
A9: R&D | B9: ='Income Statement'!B10 -> 42500 | C9: ='Income Statement'!C10 -> 47500 | D9: =D4*Scenarios!D11 -> 0 | E9: =E4*Scenarios!E11 -> 0 | F9: =F4*Scenarios!F11 -> 0 | G9: =G4*Scenarios!G11 -> 0 | H9: =H4*Scenarios!H11 -> 0
A10: Depreciation | B10: ='Income Statement'!B11 -> 28000 | C10: ='Income Statement'!C11 -> 32000 | D10: =(C44+D4*Scenarios!D27/2)*Scenarios!D28 -> 41112.5 | E10: =(D44+E4*Scenarios!E27/2)*Scenarios!E28 -> 46546.5 | F10: =(E44+F4*Scenarios!F27/2)*Scenarios!F28 -> 52387.005 | G10: =(F44+G4*Scenarios!G27/2)*Scenarios!G28 -> 58606.155 | H10: =(G44+H4*Scenarios!H27/2)*Scenarios!H28 -> 65166.453
A11: Amortization | B11: ='Income Statement'!B12 -> 5000 | C11: ='Income Statement'!C12 -> 5000 | D11: =Scenarios!D29 -> 5000 | E11: =Scenarios!E29 -> 5000 | F11: =Scenarios!F29 -> 5000 | G11: =Scenarios!G29 -> 5000 | H11: =Scenarios!H29 -> 5000
A12: Other OpEx | B12: ='Income Statement'!B13 -> 17000 | C12: ='Income Statement'!C13 -> 19000 | D12: =D4*Scenarios!D12 -> 20900 | E12: =E4*Scenarios!E12 -> 22572 | F12: =F4*Scenarios!F12 -> 24152.04 | G12: =G4*Scenarios!G12 -> 25601.162 | H12: =H4*Scenarios!H12 -> 26881.221
A13: SBC | B13: ='Income Statement'!B14 -> 0 | C13: ='Income Statement'!C14 -> 0 | D13: =Scenarios!D16 -> 0 | E13: =Scenarios!E16 -> 0 | F13: =Scenarios!F16 -> 0 | G13: =Scenarios!G16 -> 0 | H13: =Scenarios!H16 -> 0
A14: Total OpEx | B14: =B8+B9+B10+B11+B12+B13 -> 220000 | C14: =C8+C9+C10+C11+C12+C13 -> 246000 | D14: =D8+D9+D10+D11+D12+D13 -> 223762.5 | E14: =E8+E9+E10+E11+E12+E13 -> 243408.5 | F14: =F8+F9+F10+F11+F12+F13 -> 262679.35 | G14: =G8+G9+G10+G11+G12+G13 -> 281216.04 | H14: =H8+H9+H10+H11+H12+H13 -> 298656.83
A15: EBIT | B15: =B7-B14 -> 120000 | C15: =C7-C14 -> 134000 | D15: =D7-D14 -> 194237.5 | E15: =E7-E14 -> 208031.5 | F15: =F7-F14 -> 220361.46 | G15: =G7-G14 -> 230807.21 | H15: =H7-H14 -> 238967.58
A16: Interest Income | B16: ='Income Statement'!B21 -> 2500 | C16: ='Income Statement'!C21 -> 3000 | D16: =C36*Scenarios!D32 -> 58322.115 | E16: =D36*Scenarios!E32 -> 80000.745 | F16: =E36*Scenarios!F32 -> 88687.637 | G16: =F36*Scenarios!G32 -> 94238.234 | H16: =G36*Scenarios!H32 -> 104504.81
A17: Interest Expense | B17: ='Income Statement'!B22 -> 14000 | C17: ='Income Statement'!C22 -> 13000 | D17: =(C55+C56+C62)*Scenarios!D31 -> 61600 | E17: =(D55+D56+D62)*Scenarios!E31 -> 56000 | F17: =(E55+E56+E62)*Scenarios!F31 -> 50400 | G17: =(F55+F56+F62)*Scenarios!G31 -> 47600 | H17: =(G55+G56+G62)*Scenarios!H31 -> 44800
A18: Other Income/Expense | B18: ='Income Statement'!B23 -> 0 | C18: ='Income Statement'!C23 -> 0 | D18: =Scenarios!D14 -> 0 | E18: =Scenarios!E14 -> 0 | F18: =Scenarios!F14 -> 0 | G18: =Scenarios!G14 -> 0 | H18: =Scenarios!H14 -> 0
A19: EBT | B19: =B15+B16-B17+B18 -> 108500 | C19: =C15+C16-C17+C18 -> 124000 | D19: =D15+D16-D17+D18 -> 190959.61 | E19: =E15+E16-E17+E18 -> 232032.24 | F19: =F15+F16-F17+F18 -> 258649.09 | G19: =G15+G16-G17+G18 -> 277445.45 | H19: =H15+H16-H17+H18 -> 298672.39
A20: Tax Expense | B20: ='Income Statement'!B25 -> 24412.5 | C20: ='Income Statement'!C25 -> 27900 | D20: =MAX(0,D19*Scenarios!D13) -> 42965.913 | E20: =MAX(0,E19*Scenarios!E13) -> 52207.255 | F20: =MAX(0,F19*Scenarios!F13) -> 58196.046 | G20: =MAX(0,G19*Scenarios!G13) -> 62425.225 | H20: =MAX(0,H19*Scenarios!H13) -> 67201.288
A21: Net Income | B21: =B19-B20 -> 84087.5 | C21: =C19-C20 -> 96100 | D21: =D19-D20 -> 147993.7 | E21: =E19-E20 -> 179824.99 | F21: =F19-F20 -> 200453.05 | G21: =G19-G20 -> 215020.22 | H21: =H19-H20 -> 231471.1
A22: Employee Profit Sharing (EPD) | B22: =0 -> 0 | C22: =0 -> 0 | D22: =MAX(0,D21*Scenarios!D17) -> 14799.37 | E22: =MAX(0,E21*Scenarios!E17) -> 17982.499 | F22: =MAX(0,F21*Scenarios!F17) -> 20045.305 | G22: =MAX(0,G21*Scenarios!G17) -> 21502.022 | H22: =MAX(0,H21*Scenarios!H17) -> 23147.11
A23: Net Income After EPD | B23: =B21-B22 -> 84087.5 | C23: =C21-C22 -> 96100 | D23: =D21-D22 -> 133194.33 | E23: =E21-E22 -> 161842.49 | F23: =F21-F22 -> 180407.74 | G23: =G21-G22 -> 193518.2 | H23: =H21-H22 -> 208323.99
A24: Legal Reserve Addition (5% NI, Law 159/1981) | B24: =0 -> 0 | C24: =0 -> 0 | D24: =IF(D21<=0,0,MIN(D21*0.05,MAX(0,Scenarios!D18*0.5-0))) -> 5000 | E24: =IF(E21<=0,0,MIN(E21*0.05,MAX(0,Scenarios!E18*0.5-D25))) -> 0 | F24: =IF(F21<=0,0,MIN(F21*0.05,MAX(0,Scenarios!F18*0.5-E25))) -> 0 | G24: =IF(G21<=0,0,MIN(G21*0.05,MAX(0,Scenarios!G18*0.5-F25))) -> 0 | H24: =IF(H21<=0,0,MIN(H21*0.05,MAX(0,Scenarios!H18*0.5-G25))) -> 0
A25: Cumulative Legal Reserve | B25: =0 -> 0 | C25: =0 -> 0 | D25: =D24 -> 5000 | E25: =D25+E24 -> 5000 | F25: =E25+F24 -> 5000 | G25: =F25+G24 -> 5000 | H25: =G25+H24 -> 5000
A26: Distributable Profit | B26: =B21-B22-B24 -> 84087.5 | C26: =C21-C22-C24 -> 96100 | D26: =D21-D22-D24 -> 128194.33 | E26: =E21-E22-E24 -> 161842.49 | F26: =F21-F22-F24 -> 180407.74 | G26: =G21-G22-G24 -> 193518.2 | H26: =H21-H22-H24 -> 208323.99
A27: Gross Dividends | B27: =0 -> 0 | C27: =0 -> 0 | D27: =MAX(0,D26*Scenarios!D37) -> 38458.299 | E27: =MAX(0,E26*Scenarios!E37) -> 48552.747 | F27: =MAX(0,F26*Scenarios!F37) -> 54122.322 | G27: =MAX(0,G26*Scenarios!G37) -> 58055.46 | H27: =MAX(0,H26*Scenarios!H37) -> 62497.198
A28: Dividend WHT (10%) | B28: =0 -> 0 | C28: =0 -> 0 | D28: =D27*0.10 -> 3845.8299 | E28: =E27*0.10 -> 4855.2747 | F28: =F27*0.10 -> 5412.2322 | G28: =G27*0.10 -> 5805.546 | H28: =H27*0.10 -> 6249.7198
A29: Net Dividends | B29: =0 -> 0 | C29: =0 -> 0 | D29: =D27-D28 -> 34612.469 | E29: =E27-E28 -> 43697.473 | F29: =F27-F28 -> 48710.09 | G29: =G27-G28 -> 52249.914 | H29: =H27-H28 -> 56247.478
A30: Addition to Retained Earnings | B30: =B26-B27 -> 84087.5 | C30: =C26-C27 -> 49683 | D30: =D26-D27 -> 89736.032 | E30: =E26-E27 -> 113289.74 | F30: =F26-F27 -> 126285.42 | G30: =G26-G27 -> 135462.74 | H30: =H26-H27 -> 145826.8
A32: EPS | B32: =IF(Scenarios!B15=0,0,B23/Scenarios!B15) -> 0.840875 | C32: =IF(Scenarios!C15=0,0,C23/Scenarios!C15) -> 0.961 | D32: =IF(Scenarios!D15=0,0,D23/Scenarios!D15) -> 1.3319433 | E32: =IF(Scenarios!E15=0,0,E23/Scenarios!E15) -> 1.6184249 | F32: =IF(Scenarios!F15=0,0,F23/Scenarios!F15) -> 1.8040774 | G32: =IF(Scenarios!G15=0,0,G23/Scenarios!G15) -> 1.935182 | H32: =IF(Scenarios!H15=0,0,H23/Scenarios!H15) -> 2.0832399
A33: NOPAT | B33: =B15*(1-Scenarios!B13) -> 93000 | C33: =C15*(1-Scenarios!C13) -> 103850 | D33: =D15*(1-Scenarios!D13) -> 150534.06 | E33: =E15*(1-Scenarios!E13) -> 161224.41 | F33: =F15*(1-Scenarios!F13) -> 170780.13 | G33: =G15*(1-Scenarios!G13) -> 178875.59 | H33: =H15*(1-Scenarios!H13) -> 185199.88
A34: FCFF | B34: =0 -> 0 | C34: =0 -> 0 | D34: =D33+D10+D11-(D4*Scenarios!D27)-(D37-C37)-(D38-C38)+(D53-C53) -> 0 | E34: =E33+E10+E11-(E4*Scenarios!E27)-(E37-D37)-(E38-D38)+(E53-D53) -> 0 | F34: =F33+F10+F11-(F4*Scenarios!F27)-(F37-E37)-(F38-E38)+(F53-E53) -> 0 | G34: =G33+G10+G11-(G4*Scenarios!G27)-(G37-F37)-(G38-F38)+(G53-F53) -> 0 | H34: =H33+H10+H11-(H4*Scenarios!H27)-(H37-G37)-(H38-G38)+(H53-G53) -> 0
A35: ── Balance Sheet ──
A36: Cash & Equivalents | B36: ='Balance Sheet'!B3 -> 175000 | C36: ='Balance Sheet'!C3 -> 200000 | D36: =D110 -> 413917 | E36: =E110 -> 527268.24 | F36: =F110 -> 655233.58 | G36: =G110 -> 794585.4 | H36: =H110 -> 947161.42
A37: Accounts Receivable | B37: ='Balance Sheet'!B4 -> 104795 | C37: ='Balance Sheet'!C4 -> 117123 | D37: =D4*Scenarios!D20/365 -> 128835.62 | E37: =E4*Scenarios!E20/365 -> 139142.47 | F37: =F4*Scenarios!F20/365 -> 148882.44 | G37: =G4*Scenarios!G20/365 -> 157815.38 | H37: =H4*Scenarios!H20/365 -> 165706.15
A38: Inventory | B38: ='Balance Sheet'!B5 -> 41918 | C38: ='Balance Sheet'!C5 -> 46849 | D38: =D6*Scenarios!D21/365 -> 51534.247 | E38: =E6*Scenarios!E21/365 -> 55656.986 | F38: =F6*Scenarios!F21/365 -> 59552.975 | G38: =G6*Scenarios!G21/365 -> 63126.154 | H38: =H6*Scenarios!H21/365 -> 66282.462
A39: Prepaid Expenses | B39: ='Balance Sheet'!B6 -> 8500 | C39: ='Balance Sheet'!C6 -> 9500 | D39: =D4*Scenarios!D23 -> 10450 | E39: =E4*Scenarios!E23 -> 11286 | F39: =F4*Scenarios!F23 -> 12076.02 | G39: =G4*Scenarios!G23 -> 12800.581 | H39: =H4*Scenarios!H23 -> 13440.61
B40: ='Balance Sheet'!B8 -> 0 | C40: ='Balance Sheet'!C8 -> 0 | D40: =IF(Scenarios!D41=0,0,ABS(D4*Scenarios!D27)*Scenarios!D42) -> 7315 | E40: =IF(Scenarios!E41=0,0,ABS(E4*Scenarios!E27)*Scenarios!E42) -> 7900.2 | F40: =IF(Scenarios!F41=0,0,ABS(F4*Scenarios!F27)*Scenarios!F42) -> 8453.214 | G40: =IF(Scenarios!G41=0,0,ABS(G4*Scenarios!G27)*Scenarios!G42) -> 8960.4068 | H40: =IF(Scenarios!H41=0,0,ABS(H4*Scenarios!H27)*Scenarios!H42) -> 9408.4272
A41: Other Current Assets | B41: ='Balance Sheet'!B7 -> 10000 | C41: ='Balance Sheet'!C7 -> 10000 | D41: =Scenarios!D45 -> 10000 | E41: =Scenarios!E45 -> 10000 | F41: =Scenarios!F45 -> 10000 | G41: =Scenarios!G45 -> 10000 | H41: =Scenarios!H45 -> 10000
A42: Total Current Assets | B42: =SUM(B36:B41) -> 340213 | C42: =SUM(C36:C41) -> 383472 | D42: =SUM(D36:D41) -> 622051.86 | E42: =SUM(E36:E41) -> 751253.89 | F42: =SUM(F36:F41) -> 894198.23 | G42: =SUM(G36:G41) -> 1047287.9 | H42: =SUM(H36:H41) -> 1211999.1
A44: Gross PP&E | B44: ='Balance Sheet'!B11 -> 340000 | C44: ='Balance Sheet'!C11 -> 385000 | D44: =C44+D4*Scenarios!D27 -> 437250 | E44: =D44+E4*Scenarios!E27 -> 493680 | F44: =E44+F4*Scenarios!F27 -> 554060.1 | G44: =F44+G4*Scenarios!G27 -> 618063.01 | H44: =G44+H4*Scenarios!H27 -> 685266.06
A45: Accumulated Depreciation | B45: ='Balance Sheet'!B12 -> 128000 | C45: ='Balance Sheet'!C12 -> 160000 | D45: =C45+D10 -> 201112.5 | E45: =D45+E10 -> 247659 | F45: =E45+F10 -> 300046.01 | G45: =F45+G10 -> 358652.16 | H45: =G45+H10 -> 423818.61
A46: Net PP&E | B46: =B44-B45 -> 212000 | C46: =C44-C45 -> 225000 | D46: =D44-D45 -> 236137.5 | E46: =E44-E45 -> 246021 | F46: =F44-F45 -> 254014.09 | G46: =G44-G45 -> 259410.85 | H46: =H44-H45 -> 261447.44
A47: Intangibles | B47: ='Balance Sheet'!B14 -> 45000 | C47: ='Balance Sheet'!C14 -> 40000 | D47: =MAX(0,C47-D11) -> 35000 | E47: =MAX(0,D47-E11) -> 30000 | F47: =MAX(0,E47-F11) -> 25000 | G47: =MAX(0,F47-G11) -> 20000 | H47: =MAX(0,G47-H11) -> 15000
A48: Goodwill | B48: ='Balance Sheet'!B15 -> 100000 | C48: ='Balance Sheet'!C15 -> 100000 | D48: =Scenarios!D44 -> 100000 | E48: =Scenarios!E44 -> 100000 | F48: =Scenarios!F44 -> 100000 | G48: =Scenarios!G44 -> 100000 | H48: =Scenarios!H44 -> 100000
A49: Other LT Assets | B49: ='Balance Sheet'!B16 -> 20000 | C49: ='Balance Sheet'!C16 -> 20000 | D49: =Scenarios!D46 -> 20000 | E49: =Scenarios!E46 -> 20000 | F49: =Scenarios!F46 -> 20000 | G49: =Scenarios!G46 -> 20000 | H49: =Scenarios!H46 -> 20000
A50: Total Non-Current Assets | B50: =B46+B47+B48+B49 -> 377000 | C50: =C46+C47+C48+C49 -> 385000 | D50: =D46+D47+D48+D49 -> 391137.5 | E50: =E46+E47+E48+E49 -> 396021 | F50: =F46+F47+F48+F49 -> 399014.09 | G50: =G46+G47+G48+G49 -> 399410.85 | H50: =H46+H47+H48+H49 -> 396447.44
A51: Total Assets | B51: =B42+B50 -> 717213 | C51: =C42+C50 -> 768472 | D51: =D42+D50 -> 1013189.4 | E51: =E42+E50 -> 1147274.9 | F51: =F42+F50 -> 1293212.3 | G51: =G42+G50 -> 1446698.8 | H51: =H42+H50 -> 1608446.5
A53: Accounts Payable | B53: ='Balance Sheet'!B21 -> 55890 | C53: ='Balance Sheet'!C21 -> 62466 | D53: =D6*Scenarios!D22/365 -> 68712.329 | E53: =E6*Scenarios!E22/365 -> 74209.315 | F53: =F6*Scenarios!F22/365 -> 79403.967 | G53: =G6*Scenarios!G22/365 -> 84168.205 | H53: =H6*Scenarios!H22/365 -> 88376.615
A54: Accrued Expenses | B54: ='Balance Sheet'!B22 -> 25500 | C54: ='Balance Sheet'!C22 -> 28500 | D54: =D4*Scenarios!D24 -> 31350 | E54: =E4*Scenarios!E24 -> 33858 | F54: =F4*Scenarios!F24 -> 36228.06 | G54: =G4*Scenarios!G24 -> 38401.744 | H54: =H4*Scenarios!H24 -> 40321.831
A55: Short-Term Debt | B55: ='Balance Sheet'!B23 -> 50000 | C55: ='Balance Sheet'!C23 -> 50000 | D55: =Scenarios!D33 -> 50000 | E55: =Scenarios!E33 -> 50000 | F55: =Scenarios!F33 -> 50000 | G55: =Scenarios!G33 -> 50000 | H55: =Scenarios!H33 -> 50000
A56: Current Portion LTD | B56: ='Balance Sheet'!B24 -> 20000 | C56: ='Balance Sheet'!C24 -> 20000 | D56: =Scenarios!D36 -> 20000 | E56: =Scenarios!E36 -> 20000 | F56: =Scenarios!F36 -> 20000 | G56: =Scenarios!G36 -> 20000 | H56: =Scenarios!H36 -> 20000
A57: Deferred Revenue | B57: ='Balance Sheet'!B25 -> 17000 | C57: ='Balance Sheet'!C25 -> 19000 | D57: =D4*Scenarios!D25 -> 20900 | E57: =E4*Scenarios!E25 -> 22572 | F57: =F4*Scenarios!F25 -> 24152.04 | G57: =G4*Scenarios!G25 -> 25601.162 | H57: =H4*Scenarios!H25 -> 26881.221
B58: ='Balance Sheet'!B27 -> 0 | C58: ='Balance Sheet'!C27 -> 0 | D58: =IF(Scenarios!D41=0,0,MAX(0,D4*Scenarios!D42-ABS(D4*Scenarios!D27)*Scenarios!D42)) -> 138985 | E58: =IF(Scenarios!E41=0,0,MAX(0,E4*Scenarios!E42-ABS(E4*Scenarios!E27)*Scenarios!E42)) -> 150103.8 | F58: =IF(Scenarios!F41=0,0,MAX(0,F4*Scenarios!F42-ABS(F4*Scenarios!F27)*Scenarios!F42)) -> 160611.07 | G58: =IF(Scenarios!G41=0,0,MAX(0,G4*Scenarios!G42-ABS(G4*Scenarios!G27)*Scenarios!G42)) -> 170247.73 | H58: =IF(Scenarios!H41=0,0,MAX(0,H4*Scenarios!H42-ABS(H4*Scenarios!H27)*Scenarios!H42)) -> 178760.12
A59: Other Current Liabilities | B59: ='Balance Sheet'!B26 -> 15000 | C59: ='Balance Sheet'!C26 -> 15000 | D59: =Scenarios!D47 -> 15000 | E59: =Scenarios!E47 -> 15000 | F59: =Scenarios!F47 -> 15000 | G59: =Scenarios!G47 -> 15000 | H59: =Scenarios!H47 -> 15000
A60: Total Current Liabilities | B60: =SUM(B53:B59) -> 183390 | C60: =SUM(C53:C59) -> 194966 | D60: =SUM(D53:D59) -> 344947.33 | E60: =SUM(E53:E59) -> 365743.12 | F60: =SUM(F53:F59) -> 385395.13 | G60: =SUM(G53:G59) -> 403418.84 | H60: =SUM(H53:H59) -> 419339.78
A62: Long-Term Debt | B62: ='Balance Sheet'!B30 -> 230000 | C62: ='Balance Sheet'!C30 -> 210000 | D62: =C62+Scenarios!D34-ABS(Scenarios!D35) -> 210000 | E62: =D62+Scenarios!E34-ABS(Scenarios!E35) -> 210000 | F62: =E62+Scenarios!F34-ABS(Scenarios!F35) -> 210000 | G62: =F62+Scenarios!G34-ABS(Scenarios!G35) -> 210000 | H62: =G62+Scenarios!H34-ABS(Scenarios!H35) -> 210000
A63: Deferred Tax Liabilities | B63: ='Balance Sheet'!B31 -> 30000 | C63: ='Balance Sheet'!C31 -> 30000 | D63: =Scenarios!D48 -> 30000 | E63: =Scenarios!E48 -> 30000 | F63: =Scenarios!F48 -> 30000 | G63: =Scenarios!G48 -> 30000 | H63: =Scenarios!H48 -> 30000
A64: Other LT Liabilities | B64: ='Balance Sheet'!B33 -> 25000 | C64: ='Balance Sheet'!C33 -> 25000 | D64: =Scenarios!D49 -> 25000 | E64: =Scenarios!E49 -> 25000 | F64: =Scenarios!F49 -> 25000 | G64: =Scenarios!G49 -> 25000 | H64: =Scenarios!H49 -> 25000
A65: Total Non-Current Liabilities | B65: =SUM(B62:B64) -> 285000 | C65: =SUM(C62:C64) -> 265000 | D65: =SUM(D62:D64) -> 265000 | E65: =SUM(E62:E64) -> 265000 | F65: =SUM(F62:F64) -> 265000 | G65: =SUM(G62:G64) -> 265000 | H65: =SUM(H62:H64) -> 265000
A66: Total Liabilities | B66: =B60+B65 -> 468390 | C66: =C60+C65 -> 459966 | D66: =D60+D65 -> 609947.33 | E66: =E60+E65 -> 630743.12 | F66: =F60+F65 -> 650395.13 | G66: =G60+G65 -> 668418.84 | H66: =H60+H65 -> 684339.78
A68: Common Stock | B68: ='Balance Sheet'!B38 -> 10000 | C68: ='Balance Sheet'!C38 -> 10000 | D68: =Scenarios!D50 -> 10000 | E68: =Scenarios!E50 -> 10000 | F68: =Scenarios!F50 -> 10000 | G68: =Scenarios!G50 -> 10000 | H68: =Scenarios!H50 -> 10000
A69: APIC | B69: ='Balance Sheet'!B39 -> 210000 | C69: ='Balance Sheet'!C39 -> 220000 | D69: =C69+D13+Scenarios!D39 -> 220000 | E69: =D69+E13+Scenarios!E39 -> 220000 | F69: =E69+F13+Scenarios!F39 -> 220000 | G69: =F69+G13+Scenarios!G39 -> 220000 | H69: =G69+H13+Scenarios!H39 -> 220000
A70: Legal Reserve (Equity) | B70: =B25 -> 0 | C70: =C25 -> 0 | D70: =D25 -> 5000 | E70: =E25 -> 5000 | F70: =F25 -> 5000 | G70: =G25 -> 5000 | H70: =H25 -> 5000
A71: Retained Earnings | B71: ='Balance Sheet'!B41 -> 28823 | C71: ='Balance Sheet'!C41 -> 78506 | D71: =C71+D30 -> 168242.03 | E71: =D71+E30 -> 281531.78 | F71: =E71+F30 -> 407817.19 | G71: =F71+G30 -> 543279.93 | H71: =G71+H30 -> 689106.73
A72: Treasury Stock | B72: ='Balance Sheet'!B42 -> 0 | C72: ='Balance Sheet'!C42 -> 0 | D72: =C72+D105 -> 0 | E72: =D72+E105 -> 0 | F72: =E72+F105 -> 0 | G72: =F72+G105 -> 0 | H72: =G72+H105 -> 0
A73: Other Comprehensive Income | B73: ='Balance Sheet'!B43 -> 0 | C73: ='Balance Sheet'!C43 -> 0 | D73: =Scenarios!D52 -> 0 | E73: =Scenarios!E52 -> 0 | F73: =Scenarios!F52 -> 0 | G73: =Scenarios!G52 -> 0 | H73: =Scenarios!H52 -> 0
A74: Total Equity | B74: =SUM(B68:B73) -> 248823 | C74: =SUM(C68:C73) -> 308506 | D74: =SUM(D68:D73) -> 403242.03 | E74: =SUM(E68:E73) -> 516531.78 | F74: =SUM(F68:F73) -> 642817.19 | G74: =SUM(G68:G73) -> 778279.93 | H74: =SUM(H68:H73) -> 924106.73
A76: ── Cash Flow ── | B76: =B66+B74 -> 717213 | C76: =C66+C74 -> 768472 | D76: =D66+D74 -> 1013189.4 | E76: =E66+E74 -> 1147274.9 | F76: =F66+F74 -> 1293212.3 | G76: =G66+G74 -> 1446698.8 | H76: =H66+H74 -> 1608446.5
A77: Balance Check (TA - TLE) | B77: =B51-B76 -> 0 | C77: =C51-C76 -> 0 | D77: =D51-D76 -> 0 | E77: =E51-E76 -> 0 | F77: =F51-F76 -> 0 | G77: =G51-G76 -> 0 | H77: =H51-H76 -> 0
A79: Net Income | C79: =C21 -> 96100 | D79: =D21 -> 147993.7 | E79: =E21 -> 179824.99 | F79: =F21 -> 200453.05 | G79: =G21 -> 215020.22 | H79: =H21 -> 231471.1
A80: + Depreciation | C80: =C10 -> 32000 | D80: =D10 -> 41112.5 | E80: =E10 -> 46546.5 | F80: =F10 -> 52387.005 | G80: =G10 -> 58606.155 | H80: =H10 -> 65166.453
A81: + Amortization | C81: =C11 -> 5000 | D81: =D11 -> 5000 | E81: =E11 -> 5000 | F81: =F11 -> 5000 | G81: =G11 -> 5000 | H81: =H11 -> 5000
A82: + SBC | C82: =C13 -> 0 | D82: =D13 -> 0 | E82: =E13 -> 0 | F82: =F13 -> 0 | G82: =G13 -> 0 | H82: =H13 -> 0
A83: Deferred Taxes | C83: =C63-B63 -> 0 | D83: =D63-C63 -> 0 | E83: =E63-D63 -> 0 | F83: =F63-E63 -> 0 | G83: =G63-F63 -> 0 | H83: =H63-G63 -> 0
A84: Δ A/R | C84: =-(C37-B37) -> -12328 | D84: =-(D37-C37) -> -11712.616 | E84: =-(E37-D37) -> -10306.849 | F84: =-(F37-E37) -> -9739.9726 | G84: =-(G37-F37) -> -8932.9463 | H84: =-(H37-G37) -> -7890.7692
A85: Δ Inventory | C85: =-(C38-B38) -> -4931 | D85: =-(D38-C38) -> -4685.2466 | E85: =-(E38-D38) -> -4122.7397 | F85: =-(F38-E38) -> -3895.989 | G85: =-(G38-F38) -> -3573.1785 | H85: =-(H38-G38) -> -3156.3077
A86: Δ Prepaid | C86: =-(C39-B39) -> -1000 | D86: =-(D39-C39) -> -950 | E86: =-(E39-D39) -> -836 | F86: =-(F39-E39) -> -790.02 | G86: =-(G39-F39) -> -724.5612 | H86: =-(H39-G39) -> -640.02906
A87: Δ A/P | C87: =C53-B53 -> 6576 | D87: =D53-C53 -> 6246.3288 | E87: =E53-D53 -> 5496.9863 | F87: =F53-E53 -> 5194.6521 | G87: =G53-F53 -> 4764.238 | H87: =H53-G53 -> 4208.4103
A88: Δ Accrued Exp | C88: =C54-B54 -> 3000 | D88: =D54-C54 -> 2850 | E88: =E54-D54 -> 2508 | F88: =F54-E54 -> 2370.06 | G88: =G54-F54 -> 2173.6836 | H88: =H54-G54 -> 1920.0872
A89: Δ Deferred Revenue | C89: =C57-B57 -> 2000 | D89: =D57-C57 -> 1900 | E89: =E57-D57 -> 1672 | F89: =F57-E57 -> 1580.04 | G89: =G57-F57 -> 1449.1224 | H89: =H57-G57 -> 1280.0581
C90: =-(C40-B40) -> 0 | D90: =-(D40-C40) -> -7315 | E90: =-(E40-D40) -> -585.2 | F90: =-(F40-E40) -> -553.014 | G90: =-(G40-F40) -> -507.19284 | H90: =-(H40-G40) -> -448.02034
C91: =C58-B58 -> 0 | D91: =D58-C58 -> 138985 | E91: =E58-D58 -> 11118.8 | F91: =F58-E58 -> 10507.266 | G91: =G58-F58 -> 9636.664 | H91: =H58-G58 -> 8512.3865
A92: Total WC Change | C92: =SUM(C84:C91) -> -6683 | D92: =SUM(D84:D91) -> 125318.47 | E92: =SUM(E84:E91) -> 4944.9973 | F92: =SUM(F84:F91) -> 4673.0224 | G92: =SUM(G84:G91) -> 4285.8291 | H92: =SUM(H84:H91) -> 3785.8157
A93: Cash from Operations | C93: =C79+C80+C81+C82+C83+C92 -> 126417 | D93: =D79+D80+D81+D82+D83+D92 -> 319424.67 | E93: =E79+E80+E81+E82+E83+E92 -> 236316.49 | F93: =F79+F80+F81+F82+F83+F92 -> 262513.07 | G93: =G79+G80+G81+G82+G83+G92 -> 282912.21 | H93: =H79+H80+H81+H82+H83+H92 -> 305423.37
A95: Capital Expenditures | C95: =-ABS(C4*Scenarios!C27) -> -45000 | D95: =-ABS(D4*Scenarios!D27) -> -52250 | E95: =-ABS(E4*Scenarios!E27) -> -56430 | F95: =-ABS(F4*Scenarios!F27) -> -60380.1 | G95: =-ABS(G4*Scenarios!G27) -> -64002.906 | H95: =-ABS(H4*Scenarios!H27) -> -67203.051
A96: Acquisitions | C96: =0 -> 0 | D96: =0 -> 0 | E96: =0 -> 0 | F96: =0 -> 0 | G96: =0 -> 0 | H96: =0 -> 0
A97: Asset Sales | C97: =0 -> 0 | D97: =0 -> 0 | E97: =0 -> 0 | F97: =0 -> 0 | G97: =0 -> 0 | H97: =0 -> 0
A98: Cash from Investing | C98: =C95+C96+C97 -> -45000 | D98: =D95+D96+D97 -> -52250 | E98: =E95+E96+E97 -> -56430 | F98: =F95+F96+F97 -> -60380.1 | G98: =G95+G96+G97 -> -64002.906 | H98: =H95+H96+H97 -> -67203.051
A100: Debt Issuance | C100: =Scenarios!C34 -> 0 | D100: =Scenarios!D34 -> 0 | E100: =Scenarios!E34 -> 0 | F100: =Scenarios!F34 -> 0 | G100: =Scenarios!G34 -> 0 | H100: =Scenarios!H34 -> 0
A101: Debt Repayment | C101: =-ABS(Scenarios!C35) -> -20000 | D101: =-ABS(Scenarios!D35) -> 0 | E101: =-ABS(Scenarios!E35) -> 0 | F101: =-ABS(Scenarios!F35) -> 0 | G101: =-ABS(Scenarios!G35) -> 0 | H101: =-ABS(Scenarios!H35) -> 0
A102: Dividends Paid | C102: =Scenarios!C65 -> -46417 | D102: =-MAX(0,D26*Scenarios!D37) -> -38458.299 | E102: =-MAX(0,E26*Scenarios!E37) -> -48552.747 | F102: =-MAX(0,F26*Scenarios!F37) -> -54122.322 | G102: =-MAX(0,G26*Scenarios!G37) -> -58055.46 | H102: =-MAX(0,H26*Scenarios!H37) -> -62497.198
A103: Employee Profit Sharing Paid | C103: =-C22 -> 0 | D103: =-D22 -> -14799.37 | E103: =-E22 -> -17982.499 | F103: =-F22 -> -20045.305 | G103: =-G22 -> -21502.022 | H103: =-H22 -> -23147.11
A104: Equity Issuance | C104: =Scenarios!C39 -> 10000 | D104: =Scenarios!D39 -> 0 | E104: =Scenarios!E39 -> 0 | F104: =Scenarios!F39 -> 0 | G104: =Scenarios!G39 -> 0 | H104: =Scenarios!H39 -> 0
A105: Share Repurchases | C105: =-ABS(Scenarios!C38) -> 0 | D105: =-ABS(Scenarios!D38) -> 0 | E105: =-ABS(Scenarios!E38) -> 0 | F105: =-ABS(Scenarios!F38) -> 0 | G105: =-ABS(Scenarios!G38) -> 0 | H105: =-ABS(Scenarios!H38) -> 0
A106: Cash from Financing | C106: =C100+C101+C102+C103+C104+C105 -> -56417 | D106: =D100+D101+D102+D103+D104+D105 -> -53257.669 | E106: =E100+E101+E102+E103+E104+E105 -> -66535.246 | F106: =F100+F101+F102+F103+F104+F105 -> -74167.627 | G106: =G100+G101+G102+G103+G104+G105 -> -79557.482 | H106: =H100+H101+H102+H103+H104+H105 -> -85644.308
A108: Net Change in Cash | C108: =C93+C98+C106 -> 25000 | D108: =D93+D98+D106 -> 213917 | E108: =E93+E98+E106 -> 113351.24 | F108: =F93+F98+F106 -> 127965.35 | G108: =G93+G98+G106 -> 139351.82 | H108: =H93+H98+H106 -> 152576.01
A109: Beginning Cash | C109: =B36 -> 175000 | D109: =C36 -> 200000 | E109: =D36 -> 413917 | F109: =E36 -> 527268.24 | G109: =F36 -> 655233.58 | H109: =G36 -> 794585.4
A110: Ending Cash | C110: =C109+C108 -> 200000 | D110: =D109+D108 -> 413917 | E110: =E109+E108 -> 527268.24 | F110: =F109+F108 -> 655233.58 | G110: =G109+G108 -> 794585.4 | H110: =H109+H108 -> 947161.42
A111: Free Cash Flow | C111: =C93+C95 -> 81417 | D111: =D93+D95 -> 267174.67 | E111: =E93+E95 -> 179886.49 | F111: =F93+F95 -> 202132.97 | G111: =G93+G95 -> 218909.3 | H111: =H93+H95 -> 238220.32

Sheet _Calc_Opt
A1: _Calc_Opt — Full 3-Statement Model | B1: 2024 | C1: 2025 | D1: 2026E | E1: 2027E | F1: 2028E | G1: 2029E | H1: 2030E
A2: ⚠ HOW TO RECALCULATE AFTER CHANGING ASSUMPTIONS: | 1. File → Options → Formulas → Enable iterative calculation (Max Iterations=1000, Max Change=0.001) | 2. Press Ctrl+Alt+F9 to force full recalculation | 3. Values shown by default are pre-calculated by the WOLF engine and are correct as-is.
A4: Revenue | B4: ='Income Statement'!B2 -> 850000 | C4: ='Income Statement'!C2 -> 950000 | D4: =C4*(1+Scenarios!D94) -> 1092500 | E4: =D4*(1+Scenarios!E94) -> 1223600 | F4: =E4*(1+Scenarios!F94) -> 1345960 | G4: =F4*(1+Scenarios!G94) -> 1467096.4 | H4: =G4*(1+Scenarios!H94) -> 1584464.1
A5: Revenue Growth % | B5: =0 -> 0 | C5: =(C4-B4)/B4 -> 0.11764706 | D5: =Scenarios!D94 -> 0.15 | E5: =Scenarios!E94 -> 0.12 | F5: =Scenarios!F94 -> 0.1 | G5: =Scenarios!G94 -> 0.09 | H5: =Scenarios!H94 -> 0.08
A6: COGS | B6: ='Income Statement'!B4 -> 510000 | C6: ='Income Statement'!C4 -> 570000 | D6: =D4*Scenarios!D95 -> 600875 | E6: =E4*Scenarios!E95 -> 660744 | F6: =F4*Scenarios!F95 -> 713358.8 | G6: =G4*Scenarios!G95 -> 762890.13 | H6: =H4*Scenarios!H95 -> 808076.7
A7: Gross Profit | B7: =B4-B6 -> 340000 | C7: =C4-C6 -> 380000 | D7: =D4-D6 -> 491625 | E7: =E4-E6 -> 562856 | F7: =F4-F6 -> 632601.2 | G7: =G4-G6 -> 704206.27 | H7: =H4-H6 -> 776387.41
A8: SG&A | B8: ='Income Statement'!B9 -> 127500 | C8: ='Income Statement'!C9 -> 142500 | D8: =D4*Scenarios!D96 -> 142025 | E8: =E4*Scenarios!E96 -> 146832 | F8: =F4*Scenarios!F96 -> 161515.2 | G8: =G4*Scenarios!G96 -> 161380.6 | H8: =H4*Scenarios!H96 -> 174291.05
A9: R&D | B9: ='Income Statement'!B10 -> 42500 | C9: ='Income Statement'!C10 -> 47500 | D9: =D4*Scenarios!D97 -> 0 | E9: =E4*Scenarios!E97 -> 0 | F9: =F4*Scenarios!F97 -> 0 | G9: =G4*Scenarios!G97 -> 0 | H9: =H4*Scenarios!H97 -> 0
A10: Depreciation | B10: ='Income Statement'!B11 -> 28000 | C10: ='Income Statement'!C11 -> 32000 | D10: =(C44+D4*Scenarios!D113/2)*Scenarios!D114 -> 41777.5 | E10: =(D44+E4*Scenarios!E113/2)*Scenarios!E114 -> 48725.8 | F10: =(E44+F4*Scenarios!F113/2)*Scenarios!F114 -> 56434.48 | G10: =(F44+G4*Scenarios!G113/2)*Scenarios!G114 -> 64873.649 | H10: =(G44+H4*Scenarios!H113/2)*Scenarios!H114 -> 74028.331
A11: Amortization | B11: ='Income Statement'!B12 -> 5000 | C11: ='Income Statement'!C12 -> 5000 | D11: =Scenarios!D115 -> 5000 | E11: =Scenarios!E115 -> 5000 | F11: =Scenarios!F115 -> 5000 | G11: =Scenarios!G115 -> 5000 | H11: =Scenarios!H115 -> 5000
A12: Other OpEx | B12: ='Income Statement'!B13 -> 17000 | C12: ='Income Statement'!C13 -> 19000 | D12: =D4*Scenarios!D98 -> 21850 | E12: =E4*Scenarios!E98 -> 24472 | F12: =F4*Scenarios!F98 -> 26919.2 | G12: =G4*Scenarios!G98 -> 29341.928 | H12: =H4*Scenarios!H98 -> 31689.282
A13: SBC | B13: ='Income Statement'!B14 -> 0 | C13: ='Income Statement'!C14 -> 0 | D13: =Scenarios!D102 -> 0 | E13: =Scenarios!E102 -> 0 | F13: =Scenarios!F102 -> 0 | G13: =Scenarios!G102 -> 0 | H13: =Scenarios!H102 -> 0
A14: Total OpEx | B14: =B8+B9+B10+B11+B12+B13 -> 220000 | C14: =C8+C9+C10+C11+C12+C13 -> 246000 | D14: =D8+D9+D10+D11+D12+D13 -> 210652.5 | E14: =E8+E9+E10+E11+E12+E13 -> 225029.8 | F14: =F8+F9+F10+F11+F12+F13 -> 249868.88 | G14: =G8+G9+G10+G11+G12+G13 -> 260596.18 | H14: =H8+H9+H10+H11+H12+H13 -> 285008.67
A15: EBIT | B15: =B7-B14 -> 120000 | C15: =C7-C14 -> 134000 | D15: =D7-D14 -> 280972.5 | E15: =E7-E14 -> 337826.2 | F15: =F7-F14 -> 382732.32 | G15: =G7-G14 -> 443610.09 | H15: =H7-H14 -> 491378.75
A16: Interest Income | B16: ='Income Statement'!B21 -> 2500 | C16: ='Income Statement'!C21 -> 3000 | D16: =C36*Scenarios!D118 -> 61108.254 | E16: =D36*Scenarios!E118 -> 89680.105 | F16: =E36*Scenarios!F118 -> 106880.88 | G16: =F36*Scenarios!G118 -> 121366.39 | H16: =G36*Scenarios!H118 -> 143138.17
A17: Interest Expense | B17: ='Income Statement'!B22 -> 14000 | C17: ='Income Statement'!C22 -> 13000 | D17: =(C55+C56+C62)*Scenarios!D117 -> 61600 | E17: =(D55+D56+D62)*Scenarios!E117 -> 56000 | F17: =(E55+E56+E62)*Scenarios!F117 -> 50400 | G17: =(F55+F56+F62)*Scenarios!G117 -> 47600 | H17: =(G55+G56+G62)*Scenarios!H117 -> 44800
