Workbook

Sheet Scenarios
A3: Base Case revenueBase | B3: 0.1 | C3: 0.1 | D3: 0.1 | E3: 0.1 | F3: 0.1 | G3: 0.1 | H3: 0.1 | I3: 0.1
A4: Base Case revenueBaseProjection | B4: 0.1 | C4: 0.1 | D4: 0.1 | E4: 0.1 | F4: 0.1 | G4: 0.1 | H4: 0.1 | I4: 0.1
A5: Base Case revenueGrowthRate | B5: 0.1 | C5: 0.1 | D5: 0.1 | E5: 0.1 | F5: 0.1 | G5: 0.1 | H5: 0.1 | I5: 0.1
A6: Base Case cogsPercent | B6: 0.1 | C6: 0.1 | D6: 0.1 | E6: 0.1 | F6: 0.1 | G6: 0.1 | H6: 0.1 | I6: 0.1
A7: Base Case sgaPercent | B7: 0.1 | C7: 0.1 | D7: 0.1 | E7: 0.1 | F7: 0.1 | G7: 0.1 | H7: 0.1 | I7: 0.1
A8: Base Case rdPercent | B8: 0.1 | C8: 0.1 | D8: 0.1 | E8: 0.1 | F8: 0.1 | G8: 0.1 | H8: 0.1 | I8: 0.1
A9: Base Case otherOpexPercent | B9: 0.1 | C9: 0.1 | D9: 0.1 | E9: 0.1 | F9: 0.1 | G9: 0.1 | H9: 0.1 | I9: 0.1
A10: Base Case taxRate | B10: 0.1 | C10: 0.1 | D10: 0.1 | E10: 0.1 | F10: 0.1 | G10: 0.1 | H10: 0.1 | I10: 0.1
A11: Base Case otherIncomeExpense | B11: 0.1 | C11: 0.1 | D11: 0.1 | E11: 0.1 | F11: 0.1 | G11: 0.1 | H11: 0.1 | I11: 0.1
A12: Base Case sharesOutstanding | B12: 0.1 | C12: 0.1 | D12: 0.1 | E12: 0.1 | F12: 0.1 | G12: 0.1 | H12: 0.1 | I12: 0.1
A13: Base Case stockBasedCompAmount | B13: 0.1 | C13: 0.1 | D13: 0.1 | E13: 0.1 | F13: 0.1 | G13: 0.1 | H13: 0.1 | I13: 0.1
A14: Base Case dso | B14: 0.1 | C14: 0.1 | D14: 0.1 | E14: 0.1 | F14: 0.1 | G14: 0.1 | H14: 0.1 | I14: 0.1
... A131: Conservative shareRepurchasesComputed | B131: 0.1 | C131: 0.1 | D131: 0.1 | E131: 0.1 | F131: 0.1 | G131: 0.1 | H131: 0.1 | I131: 0.1

Sheet Income Statement
B2: 100000 | C2: 200000 | D2: 300000
B3: 100000 | C3: 200000 | D3: 300000
B4: 100000 | C4: 200000 | D4: 300000
B5: 100000 | C5: 200000 | D5: 300000
B6: 100000 | C6: 200000 | D6: 300000
B7: 100000 | C7: 200000 | D7: 300000
B8: 100000 | C8: 200000 | D8: 300000
B9: 100000 | C9: 200000 | D9: 300000
B10: 100000 | C10: 200000 | D10: 300000
B11: 100000 | C11: 200000 | D11: 300000
B12: 100000 | C12: 200000 | D12: 300000
B13: 100000 | C13: 200000 | D13: 300000
... B19: 100000 | C19: 200000 | D19: 300000

Sheet Balance Sheet
B2: 50000 | C2: 100000 | D2: 150000
B3: 50000 | C3: 100000 | D3: 150000
B4: 50000 | C4: 100000 | D4: 150000
B5: 50000 | C5: 100000 | D5: 150000
B6: 50000 | C6: 100000 | D6: 150000
B7: 50000 | C7: 100000 | D7: 150000
B8: 50000 | C8: 100000 | D8: 150000
B9: 50000 | C9: 100000 | D9: 150000
B10: 50000 | C10: 100000 | D10: 150000
B11: 50000 | C11: 100000 | D11: 150000
B12: 50000 | C12: 100000 | D12: 150000
B13: 50000 | C13: 100000 | D13: 150000
... B33: 50000 | C33: 100000 | D33: 150000

Sheet _Calc_Base
A1: _Calc_Base — Full 3-Statement Model | B1: 2021A | C1: 2022A | D1: 2023A | E1: 2024E | F1: 2025E | G1: 2026E | H1: 2027E | I1: 2028E
A2: Revenue | B2: ='Income Statement'!B2 -> 0 | C2: ='Income Statement'!C2 -> 0 | D2: ='Income Statement'!D2 -> 0 | E2: =D2*(1+Scenarios!E5) -> 0 | F2: =E2*(1+Scenarios!F5) -> 0 | G2: =F2*(1+Scenarios!G5) -> 0 | H2: =G2*(1+Scenarios!H5) -> 0 | I2: =H2*(1+Scenarios!I5) -> 0
A3: Revenue Growth % | B3: =0 -> 0 | C3: =(C2-B2)/B2 -> 0 | D3: =(D2-C2)/C2 -> 0 | E3: =Scenarios!E5 -> 0 | F3: =Scenarios!F5 -> 0 | G3: =Scenarios!G5 -> 0 | H3: =Scenarios!H5 -> 0 | I3: =Scenarios!I5 -> 0
A4: COGS | B4: ='Income Statement'!B3 -> 0 | C4: ='Income Statement'!C3 -> 0 | D4: ='Income Statement'!D3 -> 0 | E4: =E2*Scenarios!E6 -> 0 | F4: =F2*Scenarios!F6 -> 0 | G4: =G2*Scenarios!G6 -> 0 | H4: =H2*Scenarios!H6 -> 0 | I4: =I2*Scenarios!I6 -> 0
A5: Gross Profit | B5: =B2-B4 -> 0 | C5: =C2-C4 -> 0 | D5: =D2-D4 -> 0 | E5: =E2-E4 -> 0 | F5: =F2-F4 -> 0 | G5: =G2-G4 -> 0 | H5: =H2-H4 -> 0 | I5: =I2-I4 -> 0
A6: SG&A | B6: ='Income Statement'!B5 -> 0 | C6: ='Income Statement'!C5 -> 0 | D6: ='Income Statement'!D5 -> 0 | E6: =E2*Scenarios!E7 -> 0 | F6: =F2*Scenarios!F7 -> 0 | G6: =G2*Scenarios!G7 -> 0 | H6: =H2*Scenarios!H7 -> 0 | I6: =I2*Scenarios!I7 -> 0
A7: R&D | B7: ='Income Statement'!B6 -> 0 | C7: ='Income Statement'!C6 -> 0 | D7: ='Income Statement'!D6 -> 0 | E7: =E2*Scenarios!E8 -> 0 | F7: =F2*Scenarios!F8 -> 0 | G7: =G2*Scenarios!G8 -> 0 | H7: =H2*Scenarios!H8 -> 0 | I7: =I2*Scenarios!I8 -> 0
A8: Depreciation | B8: ='Income Statement'!B16 -> 0 | C8: ='Income Statement'!C16 -> 0 | D8: ='Income Statement'!D16 -> 0 | E8: =(D28+E2*Scenarios!E20/2)*Scenarios!E21 -> 0 | F8: =(E28+F2*Scenarios!F20/2)*Scenarios!F21 -> 0 | G8: =(F28+G2*Scenarios!G20/2)*Scenarios!G21 -> 0 | H8: =(G28+H2*Scenarios!H20/2)*Scenarios!H21 -> 0 | I8: =(H28+I2*Scenarios!I20/2)*Scenarios!I21 -> 0
A9: Amortization | B9: ='Income Statement'!B17 -> 0 | C9: ='Income Statement'!C17 -> 0 | D9: ='Income Statement'!D17 -> 0 | E9: =Scenarios!E22 -> 0 | F9: =Scenarios!F22 -> 0 | G9: =Scenarios!G22 -> 0 | H9: =Scenarios!H22 -> 0 | I9: =Scenarios!I22 -> 0
A10: Other OpEx | B10: ='Income Statement'!B7 -> 0 | C10: ='Income Statement'!C7 -> 0 | D10: ='Income Statement'!D7 -> 0 | E10: =E2*Scenarios!E9 -> 0 | F10: =F2*Scenarios!F9 -> 0 | G10: =G2*Scenarios!G9 -> 0 | H10: =H2*Scenarios!H9 -> 0 | I10: =I2*Scenarios!I9 -> 0
A11: SBC | B11: ='Income Statement'!B18 -> 0 | C11: ='Income Statement'!C18 -> 0 | D11: ='Income Statement'!D18 -> 0 | E11: =Scenarios!E13 -> 0 | F11: =Scenarios!F13 -> 0 | G11: =Scenarios!G13 -> 0 | H11: =Scenarios!H13 -> 0 | I11: =Scenarios!I13 -> 0
A12: Total OpEx | B12: =B6+B7+B8+B9+B10+B11 -> 0 | C12: =C6+C7+C8+C9+C10+C11 -> 0 | D12: =D6+D7+D8+D9+D10+D11 -> 0 | E12: =E6+E7+E8+E9+E10+E11 -> 0 | F12: =F6+F7+F8+F9+F10+F11 -> 0 | G12: =G6+G7+G8+G9+G10+G11 -> 0 | H12: =H6+H7+H8+H9+H10+H11 -> 0 | I12: =I6+I7+I8+I9+I10+I11 -> 0
A13: EBIT | B13: =B5-B12 -> 0 | C13: =C5-C12 -> 0 | D13: =D5-D12 -> 0 | E13: =E5-E12 -> 0 | F13: =F5-F12 -> 0 | G13: =G5-G12 -> 0 | H13: =H5-H12 -> 0 | I13: =I5-I12 -> 0
A14: Interest Income | B14: ='Income Statement'!B10 -> 0 | C14: ='Income Statement'!C10 -> 0 | D14: ='Income Statement'!D10 -> 0 | E14: =D21*Scenarios!E24 -> 0 | F14: =E21*Scenarios!F24 -> 0 | G14: =F21*Scenarios!G24 -> 0 | H14: =G21*Scenarios!H24 -> 0 | I14: =H21*Scenarios!I24 -> 0
A15: Interest Expense | B15: ='Income Statement'!B11 -> 0 | C15: ='Income Statement'!C11 -> 0 | D15: ='Income Statement'!D11 -> 0 | E15: =(D45+E45)/2*Scenarios!E23 -> 0 | F15: =(E45+F45)/2*Scenarios!F23 -> 0 | G15: =(F45+G45)/2*Scenarios!G23 -> 0 | H15: =(G45+H45)/2*Scenarios!H23 -> 0 | I15: =(H45+I45)/2*Scenarios!I23 -> 0
A16: Other Income/Expense | B16: ='Income Statement'!B12 -> 0 | C16: ='Income Statement'!C12 -> 0 | D16: ='Income Statement'!D12 -> 0 | E16: =Scenarios!E11 -> 0 | F16: =Scenarios!F11 -> 0 | G16: =Scenarios!G11 -> 0 | H16: =Scenarios!H11 -> 0 | I16: =Scenarios!I11 -> 0
A17: EBT | B17: =B13+B14-B15+B16 -> 0 | C17: =C13+C14-C15+C16 -> 0 | D17: =D13+D14-D15+D16 -> 0 | E17: =E13+E14-E15+E16 -> 0 | F17: =F13+F14-F15+F16 -> 0 | G17: =G13+G14-G15+G16 -> 0 | H17: =H13+H14-H15+H16 -> 0 | I17: =I13+I14-I15+I16 -> 0
A18: Tax Expense | B18: ='Income Statement'!B14 -> 0 | C18: ='Income Statement'!C14 -> 0 | D18: ='Income Statement'!D14 -> 0 | E18: =MAX(0,E17*Scenarios!E10) -> 0 | F18: =MAX(0,F17*Scenarios!F10) -> 0 | G18: =MAX(0,G17*Scenarios!G10) -> 0 | H18: =MAX(0,H17*Scenarios!H10) -> 0 | I18: =MAX(0,I17*Scenarios!I10) -> 0
A19: Net Income | B19: =B17-B18 -> 0 | C19: =C17-C18 -> 0 | D19: =D17-D18 -> 0 | E19: =E17-E18 -> 0 | F19: =F17-F18 -> 0 | G19: =G17-G18 -> 0 | H19: =H17-H18 -> 0 | I19: =I17-I18 -> 0
A20: ── Balance Sheet ──
A21: Cash & Equivalents | B21: ='Balance Sheet'!B2 -> 0 | C21: ='Balance Sheet'!C2 -> 0 | D21: ='Balance Sheet'!D2 -> 0 | E21: =D21+E73+E78+E85 -> 0 | F21: =E21+F73+F78+F85 -> 0 | G21: =F21+G73+G78+G85 -> 0 | H21: =G21+H73+H78+H85 -> 0 | I21: =H21+I73+I78+I85 -> 0
A22: Accounts Receivable | B22: ='Balance Sheet'!B3 -> 0 | C22: ='Balance Sheet'!C3 -> 0 | D22: ='Balance Sheet'!D3 -> 0 | E22: =E2*Scenarios!E14/365 -> 0 | F22: =F2*Scenarios!F14/365 -> 0 | G22: =G2*Scenarios!G14/365 -> 0 | H22: =H2*Scenarios!H14/365 -> 0 | I22: =I2*Scenarios!I14/365 -> 0
A23: Inventory | B23: ='Balance Sheet'!B4 -> 0 | C23: ='Balance Sheet'!C4 -> 0 | D23: ='Balance Sheet'!D4 -> 0 | E23: =E4*Scenarios!E15/365 -> 0 | F23: =F4*Scenarios!F15/365 -> 0 | G23: =G4*Scenarios!G15/365 -> 0 | H23: =H4*Scenarios!H15/365 -> 0 | I23: =I4*Scenarios!I15/365 -> 0
A24: Prepaid Expenses | B24: ='Balance Sheet'!B5 -> 0 | C24: ='Balance Sheet'!C5 -> 0 | D24: ='Balance Sheet'!D5 -> 0 | E24: =E2*Scenarios!E17 -> 0 | F24: =F2*Scenarios!F17 -> 0 | G24: =G2*Scenarios!G17 -> 0 | H24: =H2*Scenarios!H17 -> 0 | I24: =I2*Scenarios!I17 -> 0
A25: Other Current Assets | B25: ='Balance Sheet'!B6 -> 0 | C25: ='Balance Sheet'!C6 -> 0 | D25: ='Balance Sheet'!D6 -> 0 | E25: =Scenarios!E33 -> 0 | F25: =Scenarios!F33 -> 0 | G25: =Scenarios!G33 -> 0 | H25: =Scenarios!H33 -> 0 | I25: =Scenarios!I33 -> 0
A26: Total Current Assets | B26: =SUM(B21:B25) -> 0 | C26: =SUM(C21:C25) -> 0 | D26: =SUM(D21:D25) -> 0 | E26: =SUM(E21:E25) -> 0 | F26: =SUM(F21:F25) -> 0 | G26: =SUM(G21:G25) -> 0 | H26: =SUM(H21:H25) -> 0 | I26: =SUM(I21:I25) -> 0
A28: Gross PP&E | B28: ='Balance Sheet'!B8 -> 0 | C28: ='Balance Sheet'!C8 -> 0 | D28: ='Balance Sheet'!D8 -> 0 | E28: =D28+E2*Scenarios!E20 -> 0 | F28: =E28+F2*Scenarios!F20 -> 0 | G28: =F28+G2*Scenarios!G20 -> 0 | H28: =G28+H2*Scenarios!H20 -> 0 | I28: =H28+I2*Scenarios!I20 -> 0
A29: Accumulated Depreciation | B29: ='Balance Sheet'!B9 -> 0 | C29: ='Balance Sheet'!C9 -> 0 | D29: ='Balance Sheet'!D9 -> 0 | E29: =D29+E8 -> 0 | F29: =E29+F8 -> 0 | G29: =F29+G8 -> 0 | H29: =G29+H8 -> 0 | I29: =H29+I8 -> 0
A30: Net PP&E | B30: =B28-B29 -> 0 | C30: =C28-C29 -> 0 | D30: =D28-D29 -> 0 | E30: =E28-E29 -> 0 | F30: =F28-F29 -> 0 | G30: =G28-G29 -> 0 | H30: =H28-H29 -> 0 | I30: =I28-I29 -> 0
A31: Intangibles | B31: ='Balance Sheet'!B11 -> 0 | C31: ='Balance Sheet'!C11 -> 0 | D31: ='Balance Sheet'!D11 -> 0 | E31: =MAX(0,D31-E9) -> 0 | F31: =MAX(0,E31-F9) -> 0 | G31: =MAX(0,F31-G9) -> 0 | H31: =MAX(0,G31-H9) -> 0 | I31: =MAX(0,H31-I9) -> 0
A32: Goodwill | B32: ='Balance Sheet'!B12 -> 0 | C32: ='Balance Sheet'!C12 -> 0 | D32: ='Balance Sheet'!D12 -> 0 | E32: =Scenarios!E32 -> 0 | F32: =Scenarios!F32 -> 0 | G32: =Scenarios!G32 -> 0 | H32: =Scenarios!H32 -> 0 | I32: =Scenarios!I32 -> 0
A33: Other LT Assets | B33: ='Balance Sheet'!B13 -> 0 | C33: ='Balance Sheet'!C13 -> 0 | D33: ='Balance Sheet'!D13 -> 0 | E33: =Scenarios!E34 -> 0 | F33: =Scenarios!F34 -> 0 | G33: =Scenarios!G34 -> 0 | H33: =Scenarios!H34 -> 0 | I33: =Scenarios!I34 -> 0
A34: Total Non-Current Assets | B34: =B30+B31+B32+B33 -> 0 | C34: =C30+C31+C32+C33 -> 0 | D34: =D30+D31+D32+D33 -> 0 | E34: =E30+E31+E32+E33 -> 0 | F34: =F30+F31+F32+F33 -> 0 | G34: =G30+G31+G32+G33 -> 0 | H34: =H30+H31+H32+H33 -> 0 | I34: =I30+I31+I32+I33 -> 0
A35: Total Assets | B35: =B26+B34 -> 0 | C35: =C26+C34 -> 0 | D35: =D26+D34 -> 0 | E35: =E26+E34 -> 0 | F35: =F26+F34 -> 0 | G35: =G26+G34 -> 0 | H35: =H26+H34 -> 0 | I35: =I26+I34 -> 0
A37: Accounts Payable | B37: ='Balance Sheet'!B15 -> 0 | C37: ='Balance Sheet'!C15 -> 0 | D37: ='Balance Sheet'!D15 -> 0 | E37: =E4*Scenarios!E16/365 -> 0 | F37: =F4*Scenarios!F16/365 -> 0 | G37: =G4*Scenarios!G16/365 -> 0 | H37: =H4*Scenarios!H16/365 -> 0 | I37: =I4*Scenarios!I16/365 -> 0
A38: Accrued Expenses | B38: ='Balance Sheet'!B16 -> 0 | C38: ='Balance Sheet'!C16 -> 0 | D38: ='Balance Sheet'!D16 -> 0 | E38: =E2*Scenarios!E18 -> 0 | F38: =F2*Scenarios!F18 -> 0 | G38: =G2*Scenarios!G18 -> 0 | H38: =H2*Scenarios!H18 -> 0 | I38: =I2*Scenarios!I18 -> 0
A39: Short-Term Debt | B39: ='Balance Sheet'!B18 -> 0 | C39: ='Balance Sheet'!C18 -> 0 | D39: ='Balance Sheet'!D18 -> 0 | E39: =Scenarios!E25 -> 0 | F39: =Scenarios!F25 -> 0 | G39: =Scenarios!G25 -> 0 | H39: =Scenarios!H25 -> 0 | I39: =Scenarios!I25 -> 0
A40: Current Portion LTD | B40: ='Balance Sheet'!B19 -> 0 | C40: ='Balance Sheet'!C19 -> 0 | D40: ='Balance Sheet'!D19 -> 0 | E40: =Scenarios!E28 -> 0 | F40: =Scenarios!F28 -> 0 | G40: =Scenarios!G28 -> 0 | H40: =Scenarios!H28 -> 0 | I40: =Scenarios!I28 -> 0
A41: Deferred Revenue | B41: ='Balance Sheet'!B17 -> 0 | C41: ='Balance Sheet'!C17 -> 0 | D41: ='Balance Sheet'!D17 -> 0 | E41: =E2*Scenarios!E19 -> 0 | F41: =F2*Scenarios!F19 -> 0 | G41: =G2*Scenarios!G19 -> 0 | H41: =H2*Scenarios!H19 -> 0 | I41: =I2*Scenarios!I19 -> 0
A42: Other Current Liabilities | B42: ='Balance Sheet'!B20 -> 0 | C42: ='Balance Sheet'!C20 -> 0 | D42: ='Balance Sheet'!D20 -> 0 | E42: =Scenarios!E35 -> 0 | F42: =Scenarios!F35 -> 0 | G42: =Scenarios!G35 -> 0 | H42: =Scenarios!H35 -> 0 | I42: =Scenarios!I35 -> 0
A43: Total Current Liabilities | B43: =SUM(B37:B42) -> 0 | C43: =SUM(C37:C42) -> 0 | D43: =SUM(D37:D42) -> 0 | E43: =SUM(E37:E42) -> 0 | F43: =SUM(F37:F42) -> 0 | G43: =SUM(G37:G42) -> 0 | H43: =SUM(H37:H42) -> 0 | I43: =SUM(I37:I42) -> 0
A45: Long-Term Debt | B45: ='Balance Sheet'!B22 -> 0 | C45: ='Balance Sheet'!C22 -> 0 | D45: ='Balance Sheet'!D22 -> 0 | E45: =D45+Scenarios!E26-Scenarios!E27 -> 0 | F45: =E45+Scenarios!F26-Scenarios!F27 -> 0 | G45: =F45+Scenarios!G26-Scenarios!G27 -> 0 | H45: =G45+Scenarios!H26-Scenarios!H27 -> 0 | I45: =H45+Scenarios!I26-Scenarios!I27 -> 0
A46: Deferred Tax Liabilities | B46: ='Balance Sheet'!B23 -> 0 | C46: ='Balance Sheet'!C23 -> 0 | D46: ='Balance Sheet'!D23 -> 0 | E46: =Scenarios!E36 -> 0 | F46: =Scenarios!F36 -> 0 | G46: =Scenarios!G36 -> 0 | H46: =Scenarios!H36 -> 0 | I46: =Scenarios!I36 -> 0
A47: Other LT Liabilities | B47: ='Balance Sheet'!B24 -> 0 | C47: ='Balance Sheet'!C24 -> 0 | D47: ='Balance Sheet'!D24 -> 0 | E47: =Scenarios!E37 -> 0 | F47: =Scenarios!F37 -> 0 | G47: =Scenarios!G37 -> 0 | H47: =Scenarios!H37 -> 0 | I47: =Scenarios!I37 -> 0
A48: Total Non-Current Liabilities | B48: =SUM(B45:B47) -> 0 | C48: =SUM(C45:C47) -> 0 | D48: =SUM(D45:D47) -> 0 | E48: =SUM(E45:E47) -> 0 | F48: =SUM(F45:F47) -> 0 | G48: =SUM(G45:G47) -> 0 | H48: =SUM(H45:H47) -> 0 | I48: =SUM(I45:I47) -> 0
A49: Total Liabilities | B49: =B43+B48 -> 0 | C49: =C43+C48 -> 0 | D49: =D43+D48 -> 0 | E49: =E43+E48 -> 0 | F49: =F43+F48 -> 0 | G49: =G43+G48 -> 0 | H49: =H43+H48 -> 0 | I49: =I43+I48 -> 0
A51: Common Stock | B51: ='Balance Sheet'!B26 -> 0 | C51: ='Balance Sheet'!C26 -> 0 | D51: ='Balance Sheet'!D26 -> 0 | E51: =Scenarios!E38 -> 0 | F51: =Scenarios!F38 -> 0 | G51: =Scenarios!G38 -> 0 | H51: =Scenarios!H38 -> 0 | I51: =Scenarios!I38 -> 0
A52: APIC | B52: ='Balance Sheet'!B27 -> 0 | C52: ='Balance Sheet'!C27 -> 0 | D52: ='Balance Sheet'!D27 -> 0 | E52: =D52+Scenarios!E31+Scenarios!E13 -> 0 | F52: =E52+Scenarios!F31+Scenarios!F13 -> 0 | G52: =F52+Scenarios!G31+Scenarios!G13 -> 0 | H52: =G52+Scenarios!H31+Scenarios!H13 -> 0 | I52: =H52+Scenarios!I31+Scenarios!I13 -> 0
A53: Retained Earnings | B53: ='Balance Sheet'!B28 -> 0 | C53: ='Balance Sheet'!C28 -> 0 | D53: ='Balance Sheet'!D28 -> 0 | E53: =D53+E19-MAX(0,E19*Scenarios!E29) -> 0 | F53: =E53+F19-MAX(0,F19*Scenarios!F29) -> 0 | G53: =F53+G19-MAX(0,G19*Scenarios!G29) -> 0 | H53: =G53+H19-MAX(0,H19*Scenarios!H29) -> 0 | I53: =H53+I19-MAX(0,I19*Scenarios!I29) -> 0
A54: Treasury Stock | B54: ='Balance Sheet'!B29 -> 0 | C54: ='Balance Sheet'!C29 -> 0 | D54: ='Balance Sheet'!D29 -> 0 | E54: =D54-Scenarios!E30 -> 0 | F54: =E54-Scenarios!F30 -> 0 | G54: =F54-Scenarios!G30 -> 0 | H54: =G54-Scenarios!H30 -> 0 | I54: =H54-Scenarios!I30 -> 0
A55: Other Comprehensive Income | B55: ='Balance Sheet'!B30 -> 0 | C55: ='Balance Sheet'!C30 -> 0 | D55: ='Balance Sheet'!D30 -> 0 | E55: =Scenarios!E40 -> 0 | F55: =Scenarios!F40 -> 0 | G55: =Scenarios!G40 -> 0 | H55: =Scenarios!H40 -> 0 | I55: =Scenarios!I40 -> 0
A56: Total Equity | B56: =SUM(B51:B55) -> 0 | C56: =SUM(C51:C55) -> 0 | D56: =SUM(D51:D55) -> 0 | E56: =SUM(E51:E55) -> 0 | F56: =SUM(F51:F55) -> 0 | G56: =SUM(G51:G55) -> 0 | H56: =SUM(H51:H55) -> 0 | I56: =SUM(I51:I55) -> 0
A58: Total Liabilities + Equity | B58: =B49+B56 -> 0 | C58: =C49+C56 -> 0 | D58: =D49+D56 -> 0 | E58: =E49+E56 -> 0 | F58: =F49+F56 -> 0 | G58: =G49+G56 -> 0 | H58: =H49+H56 -> 0 | I58: =I49+I56 -> 0
A59: Balance Check (TA - TLE) | B59: =B35-B58 -> 0 | C59: =C35-C58 -> 0 | D59: =D35-D58 -> 0 | E59: =E35-E58 -> 0 | F59: =F35-F58 -> 0 | G59: =G35-G58 -> 0 | H59: =H35-H58 -> 0 | I59: =I35-I58 -> 0
A60: ── Cash Flow ──
A61: Net Income | E61: =E19 -> 0 | F61: =F19 -> 0 | G61: =G19 -> 0 | H61: =H19 -> 0 | I61: =I19 -> 0
A62: + Depreciation | E62: =E8 -> 0 | F62: =F8 -> 0 | G62: =G8 -> 0 | H62: =H8 -> 0 | I62: =I8 -> 0
A63: + Amortization | E63: =E9 -> 0 | F63: =F9 -> 0 | G63: =G9 -> 0 | H63: =H9 -> 0 | I63: =I9 -> 0
A64: + SBC | E64: =E11 -> 0 | F64: =F11 -> 0 | G64: =G11 -> 0 | H64: =H11 -> 0 | I64: =I11 -> 0
A65: Deferred Taxes | E65: =E46-D46 -> 0 | F65: =F46-E46 -> 0 | G65: =G46-F46 -> 0 | H65: =H46-G46 -> 0 | I65: =I46-H46 -> 0
A66: Δ A/R | E66: =-(E22-D22) -> 0 | F66: =-(F22-E22) -> 0 | G66: =-(G22-F22) -> 0 | H66: =-(H22-G22) -> 0 | I66: =-(I22-H22) -> 0
A67: Δ Inventory | E67: =-(E23-D23) -> 0 | F67: =-(F23-E23) -> 0 | G67: =-(G23-F23) -> 0 | H67: =-(H23-G23) -> 0 | I67: =-(I23-H23) -> 0
A68: Δ Prepaid | E68: =-(E24-D24) -> 0 | F68: =-(F24-E24) -> 0 | G68: =-(G24-F24) -> 0 | H68: =-(H24-G24) -> 0 | I68: =-(I24-H24) -> 0
A69: Δ A/P | E69: =E37-D37 -> 0 | F69: =F37-E37 -> 0 | G69: =G37-F37 -> 0 | H69: =H37-G37 -> 0 | I69: =I37-H37 -> 0
A70: Δ Accrued Exp | E70: =E38-D38 -> 0 | F70: =F38-E38 -> 0 | G70: =G38-F38 -> 0 | H70: =H38-G38 -> 0 | I70: =I38-H38 -> 0
A71: Δ Deferred Revenue | E71: =E41-D41 -> 0 | F71: =F41-E41 -> 0 | G71: =G41-F41 -> 0 | H71: =H41-G41 -> 0 | I71: =I41-H41 -> 0
A72: Total WC Change | E72: =SUM(E66:E71) -> 0 | F72: =SUM(F66:F71) -> 0 | G72: =SUM(G66:G71) -> 0 | H72: =SUM(H66:H71) -> 0 | I72: =SUM(I66:I71) -> 0
A73: Cash from Operations | E73: =E61+E62+E63+E64+E65+E72 -> 0 | F73: =F61+F62+F63+F64+F65+F72 -> 0 | G73: =G61+G62+G63+G64+G65+G72 -> 0 | H73: =H61+H62+H63+H64+H65+H72 -> 0 | I73: =I61+I62+I63+I64+I65+I72 -> 0
A75: Capital Expenditures | E75: =-ABS(E2*Scenarios!E20) -> 0 | F75: =-ABS(F2*Scenarios!F20) -> 0 | G75: =-ABS(G2*Scenarios!G20) -> 0 | H75: =-ABS(H2*Scenarios!H20) -> 0 | I75: =-ABS(I2*Scenarios!I20) -> 0
A76: Acquisitions | E76: =0 -> 0 | F76: =0 -> 0 | G76: =0 -> 0 | H76: =0 -> 0 | I76: =0 -> 0
A77: Asset Sales | E77: =0 -> 0 | F77: =0 -> 0 | G77: =0 -> 0 | H77: =0 -> 0 | I77: =0 -> 0
A78: Cash from Investing | E78: =E75+E76+E77 -> 0 | F78: =F75+F76+F77 -> 0 | G78: =G75+G76+G77 -> 0 | H78: =H75+H76+H77 -> 0 | I78: =I75+I76+I77 -> 0
A80: Debt Issuance | E80: =Scenarios!E26 -> 0 | F80: =Scenarios!F26 -> 0 | G80: =Scenarios!G26 -> 0 | H80: =Scenarios!H26 -> 0 | I80: =Scenarios!I26 -> 0
A81: Debt Repayment | E81: =-ABS(Scenarios!E27) -> 0 | F81: =-ABS(Scenarios!F27) -> 0 | G81: =-ABS(Scenarios!G27) -> 0 | H81: =-ABS(Scenarios!H27) -> 0 | I81: =-ABS(Scenarios!I27) -> 0
A82: Dividends Paid | E82: =-MAX(0,E19*Scenarios!E29) -> 0 | F82: =-MAX(0,F19*Scenarios!F29) -> 0 | G82: =-MAX(0,G19*Scenarios!G29) -> 0 | H82: =-MAX(0,H19*Scenarios!H29) -> 0 | I82: =-MAX(0,I19*Scenarios!I29) -> 0
A83: Equity Issuance | E83: =Scenarios!E31 -> 0 | F83: =Scenarios!F31 -> 0 | G83: =Scenarios!G31 -> 0 | H83: =Scenarios!H31 -> 0 | I83: =Scenarios!I31 -> 0
A84: Share Repurchases | E84: =-ABS(Scenarios!E30) -> 0 | F84: =-ABS(Scenarios!F30) -> 0 | G84: =-ABS(Scenarios!G30) -> 0 | H84: =-ABS(Scenarios!H30) -> 0 | I84: =-ABS(Scenarios!I30) -> 0
A85: Cash from Financing | E85: =E80+E81+E82+E83+E84 -> 0 | F85: =F80+F81+F82+F83+F84 -> 0 | G85: =G80+G81+G82+G83+G84 -> 0 | H85: =H80+H81+H82+H83+H84 -> 0 | I85: =I80+I81+I82+I83+I84 -> 0
A87: Net Change in Cash | E87: =E73+E78+E85 -> 0 | F87: =F73+F78+F85 -> 0 | G87: =G73+G78+G85 -> 0 | H87: =H73+H78+H85 -> 0 | I87: =I73+I78+I85 -> 0
A88: Beginning Cash | E88: =D21 -> 0 | F88: =E21 -> 0 | G88: =F21 -> 0 | H88: =G21 -> 0 | I88: =H21 -> 0
A89: Ending Cash | E89: =E88+E87 -> 0 | F89: =F88+F87 -> 0 | G89: =G88+G87 -> 0 | H89: =H88+H87 -> 0 | I89: =I88+I87 -> 0
A90: Free Cash Flow | E90: =E73+E75 -> 0 | F90: =F73+F75 -> 0 | G90: =G73+G75 -> 0 | H90: =H73+H75 -> 0 | I90: =I73+I75 -> 0

Sheet _Calc_Opt
A1: _Calc_Opt — Full 3-Statement Model | B1: 2021A | C1: 2022A | D1: 2023A | E1: 2024E | F1: 2025E | G1: 2026E | H1: 2027E | I1: 2028E
A2: Revenue | B2: ='Income Statement'!B2 -> 0 | C2: ='Income Statement'!C2 -> 0 | D2: ='Income Statement'!D2 -> 0 | E2: =D2*(1+Scenarios!E48) -> 0 | F2: =E2*(1+Scenarios!F48) -> 0 | G2: =F2*(1+Scenarios!G48) -> 0 | H2: =G2*(1+Scenarios!H48) -> 0 | I2: =H2*(1+Scenarios!I48) -> 0
A3: Revenue Growth % | B3: =0 -> 0 | C3: =(C2-B2)/B2 -> 0 | D3: =(D2-C2)/C2 -> 0 | E3: =Scenarios!E48 -> 0 | F3: =Scenarios!F48 -> 0 | G3: =Scenarios!G48 -> 0 | H3: =Scenarios!H48 -> 0 | I3: =Scenarios!I48 -> 0
A4: COGS | B4: ='Income Statement'!B3 -> 0 | C4: ='Income Statement'!C3 -> 0 | D4: ='Income Statement'!D3 -> 0 | E4: =E2*Scenarios!E49 -> 0 | F4: =F2*Scenarios!F49 -> 0 | G4: =G2*Scenarios!G49 -> 0 | H4: =H2*Scenarios!H49 -> 0 | I4: =I2*Scenarios!I49 -> 0
A5: Gross Profit | B5: =B2-B4 -> 0 | C5: =C2-C4 -> 0 | D5: =D2-D4 -> 0 | E5: =E2-E4 -> 0 | F5: =F2-F4 -> 0 | G5: =G2-G4 -> 0 | H5: =H2-H4 -> 0 | I5: =I2-I4 -> 0
A6: SG&A | B6: ='Income Statement'!B5 -> 0 | C6: ='Income Statement'!C5 -> 0 | D6: ='Income Statement'!D5 -> 0 | E6: =E2*Scenarios!E50 -> 0 | F6: =F2*Scenarios!F50 -> 0 | G6: =G2*Scenarios!G50 -> 0 | H6: =H2*Scenarios!H50 -> 0 | I6: =I2*Scenarios!I50 -> 0
A7: R&D | B7: ='Income Statement'!B6 -> 0 | C7: ='Income Statement'!C6 -> 0 | D7: ='Income Statement'!D6 -> 0 | E7: =E2*Scenarios!E51 -> 0 | F7: =F2*Scenarios!F51 -> 0 | G7: =G2*Scenarios!G51 -> 0 | H7: =H2*Scenarios!H51 -> 0 | I7: =I2*Scenarios!I51 -> 0
A8: Depreciation | B8: ='Income Statement'!B16 -> 0 | C8: ='Income Statement'!C16 -> 0 | D8: ='Income Statement'!D16 -> 0 | E8: =(D28+E2*Scenarios!E63/2)*Scenarios!E64 -> 0 | F8: =(E28+F2*Scenarios!F63/2)*Scenarios!F64 -> 0 | G8: =(F28+G2*Scenarios!G63/2)*Scenarios!G64 -> 0 | H8: =(G28+H2*Scenarios!H63/2)*Scenarios!H64 -> 0 | I8: =(H28+I2*Scenarios!I63/2)*Scenarios!I64 -> 0
A9: Amortization | B9: ='Income Statement'!B17 -> 0 | C9: ='Income Statement'!C17 -> 0 | D9: ='Income Statement'!D17 -> 0 | E9: =Scenarios!E65 -> 0 | F9: =Scenarios!F65 -> 0 | G9: =Scenarios!G65 -> 0 | H9: =Scenarios!H65 -> 0 | I9: =Scenarios!I65 -> 0
A10: Other OpEx | B10: ='Income Statement'!B7 -> 0 | C10: ='Income Statement'!C7 -> 0 | D10: ='Income Statement'!D7 -> 0 | E10: =E2*Scenarios!E52 -> 0 | F10: =F2*Scenarios!F52 -> 0 | G10: =G2*Scenarios!G52 -> 0 | H10: =H2*Scenarios!H52 -> 0 | I10: =I2*Scenarios!I52 -> 0
A11: SBC | B11: ='Income Statement'!B18 -> 0 | C11: ='Income Statement'!C18 -> 0 | D11: ='Income Statement'!D18 -> 0 | E11: =Scenarios!E56 -> 0 | F11: =Scenarios!F56 -> 0 | G11: =Scenarios!G56 -> 0 | H11: =Scenarios!H56 -> 0 | I11: =Scenarios!I56 -> 0
A12: Total OpEx | B12: =B6+B7+B8+B9+B10+B11 -> 0 | C12: =C6+C7+C8+C9+C10+C11 -> 0 | D12: =D6+D7+D8+D9+D10+D11 -> 0 | E12: =E6+E7+E8+E9+E10+E11 -> 0 | F12: =F6+F7+F8+F9+F10+F11 -> 0 | G12: =G6+G7+G8+G9+G10+G11 -> 0 | H12: =H6+H7+H8+H9+H10+H11 -> 0 | I12: =I6+I7+I8+I9+I10+I11 -> 0
A13: EBIT | B13: =B5-B12 -> 0 | C13: =C5-C12 -> 0 | D13: =D5-D12 -> 0 | E13: =E5-E12 -> 0 | F13: =F5-F12 -> 0 | G13: =G5-G12 -> 0 | H13: =H5-H12 -> 0 | I13: =I5-I12 -> 0
A14: Interest Income | B14: ='Income Statement'!B10 -> 0 | C14: ='Income Statement'!C10 -> 0 | D14: ='Income Statement'!D10 -> 0 | E14: =D21*Scenarios!E67 -> 0 | F14: =E21*Scenarios!F67 -> 0 | G14: =F21*Scenarios!G67 -> 0 | H14: =G21*Scenarios!H67 -> 0 | I14: =H21*Scenarios!I67 -> 0
A15: Interest Expense | B15: ='Income Statement'!B11 -> 0 | C15: ='Income Statement'!C11 -> 0 | D15: ='Income Statement'!D11 -> 0 | E15: =(D45+E45)/2*Scenarios!E66 -> 0 | F15: =(E45+F45)/2*Scenarios!F66 -> 0 | G15: =(F45+G45)/2*Scenarios!G66 -> 0 | H15: =(G45+H45)/2*Scenarios!H66 -> 0 | I15: =(H45+I45)/2*Scenarios!I66 -> 0
A16: Other Income/Expense | B16: ='Income Statement'!B12 -> 0 | C16: ='Income Statement'!C12 -> 0 | D16: ='Income Statement'!D12 -> 0 | E16: =Scenarios!E54 -> 0 | F16: =Scenarios!F54 -> 0 | G16: =Scenarios!G54 -> 0 | H16: =Scenarios!H54 -> 0 | I16: =Scenarios!I54 -> 0
A17: EBT | B17: =B13+B14-B15+B16 -> 0 | C17: =C13+C14-C15+C16 -> 0 | D17: =D13+D14-D15+D16 -> 0 | E17: =E13+E14-E15+E16 -> 0 | F17: =F13+F14-F15+F16 -> 0 | G17: =G13+G14-G15+G16 -> 0 | H17: =H13+H14-H15+H16 -> 0 | I17: =I13+I14-I15+I16 -> 0
A18: Tax Expense | B18: ='Income Statement'!B14 -> 0 | C18: ='Income Statement'!C14 -> 0 | D18: ='Income Statement'!D14 -> 0 | E18: =MAX(0,E17*Scenarios!E53) -> 0 | F18: =MAX(0,F17*Scenarios!F53) -> 0 | G18: =MAX(0,G17*Scenarios!G53) -> 0 | H18: =MAX(0,H17*Scenarios!H53) -> 0 | I18: =MAX(0,I17*Scenarios!I53) -> 0
A19: Net Income | B19: =B17-B18 -> 0 | C19: =C17-C18 -> 0 | D19: =D17-D18 -> 0 | E19: =E17-E18 -> 0 | F19: =F17-F18 -> 0 | G19: =G17-G18 -> 0 | H19: =H17-H18 -> 0 | I19: =I17-I18 -> 0
A20: ── Balance Sheet ──
A21: Cash & Equivalents | B21: ='Balance Sheet'!B2 -> 0 | C21: ='Balance Sheet'!C2 -> 0 | D21: ='Balance Sheet'!D2 -> 0 | E21: =D21+E73+E78+E85 -> 0 | F21: =E21+F73+F78+F85 -> 0 | G21: =F21+G73+G78+G85 -> 0 | H21: =G21+H73+H78+H85 -> 0 | I21: =H21+I73+I78+I85 -> 0
A22: Accounts Receivable | B22: ='Balance Sheet'!B3 -> 0 | C22: ='Balance Sheet'!C3 -> 0 | D22: ='Balance Sheet'!D3 -> 0 | E22: =E2*Scenarios!E57/365 -> 0 | F22: =F2*Scenarios!F57/365 -> 0 | G22: =G2*Scenarios!G57/365 -> 0 | H22: =H2*Scenarios!H57/365 -> 0 | I22: =I2*Scenarios!I57/365 -> 0
A23: Inventory | B23: ='Balance Sheet'!B4 -> 0 | C23: ='Balance Sheet'!C4 -> 0 | D23: ='Balance Sheet'!D4 -> 0 | E23: =E4*Scenarios!E58/365 -> 0 | F23: =F4*Scenarios!F58/365 -> 0 | G23: =G4*Scenarios!G58/365 -> 0 | H23: =H4*Scenarios!H58/365 -> 0 | I23: =I4*Scenarios!I58/365 -> 0
A24: Prepaid Expenses | B24: ='Balance Sheet'!B5 -> 0 | C24: ='Balance Sheet'!C5 -> 0 | D24: ='Balance Sheet'!D5 -> 0 | E24: =E2*Scenarios!E60 -> 0 | F24: =F2*Scenarios!F60 -> 0 | G24: =G2*Scenarios!G60 -> 0 | H24: =H2*Scenarios!H60 -> 0 | I24: =I2*Scenarios!I60 -> 0
A25: Other Current Assets | B25: ='Balance Sheet'!B6 -> 0 | C25: ='Balance Sheet'!C6 -> 0 | D25: ='Balance Sheet'!D6 -> 0 | E25: =Scenarios!E76 -> 0 | F25: =Scenarios!F76 -> 0 | G25: =Scenarios!G76 -> 0 | H25: =Scenarios!H76 -> 0 | I25: =Scenarios!I76 -> 0
A26: Total Current Assets | B26: =SUM(B21:B25) -> 0 | C26: =SUM(C21:C25) -> 0 | D26: =SUM(D21:D25) -> 0 | E26: =SUM(E21:E25) -> 0 | F26: =SUM(F21:F25) -> 0 | G26: =SUM(G21:G25) -> 0 | H26: =SUM(H21:H25) -> 0 | I26: =SUM(I21:I25) -> 0
A28: Gross PP&E | B28: ='Balance Sheet'!B8 -> 0 | C28: ='Balance Sheet'!C8 -> 0 | D28: ='Balance Sheet'!D8 -> 0 | E28: =D28+E2*Scenarios!E63 -> 0 | F28: =E28+F2*Scenarios!F63 -> 0 | G28: =F28+G2*Scenarios!G63 -> 0 | H28: =G28+H2*Scenarios!H63 -> 0 | I28: =H28+I2*Scenarios!I63 -> 0
A29: Accumulated Depreciation | B29: ='Balance Sheet'!B9 -> 0 | C29: ='Balance Sheet'!C9 -> 0 | D29: ='Balance Sheet'!D9 -> 0 | E29: =D29+E8 -> 0 | F29: =E29+F8 -> 0 | G29: =F29+G8 -> 0 | H29: =G29+H8 -> 0 | I29: =H29+I8 -> 0
A30: Net PP&E | B30: =B28-B29 -> 0 | C30: =C28-C29 -> 0 | D30: =D28-D29 -> 0 | E30: =E28-E29 -> 0 | F30: =F28-F29 -> 0 | G30: =G28-G29 -> 0 | H30: =H28-H29 -> 0 | I30: =I28-I29 -> 0
A31: Intangibles | B31: ='Balance Sheet'!B11 -> 0 | C31: ='Balance Sheet'!C11 -> 0 | D31: ='Balance Sheet'!D11 -> 0 | E31: =MAX(0,D31-E9) -> 0 | F31: =MAX(0,E31-F9) -> 0 | G31: =MAX(0,F31-G9) -> 0 | H31: =MAX(0,G31-H9) -> 0 | I31: =MAX(0,H31-I9) -> 0
A32: Goodwill | B32: ='Balance Sheet'!B12 -> 0 | C32: ='Balance Sheet'!C12 -> 0 | D32: ='Balance Sheet'!D12 -> 0 | E32: =Scenarios!E75 -> 0 | F32: =Scenarios!F75 -> 0 | G32: =Scenarios!G75 -> 0 | H32: =Scenarios!H75 -> 0 | I32: =Scenarios!I75 -> 0
A33: Other LT Assets | B33: ='Balance Sheet'!B13 -> 0 | C33: ='Balance Sheet'!C13 -> 0 | D33: ='Balance Sheet'!D13 -> 0 | E33: =Scenarios!E77 -> 0 | F33: =Scenarios!F77 -> 0 | G33: =Scenarios!G77 -> 0 | H33: =Scenarios!H77 -> 0 | I33: =Scenarios!I77 -> 0
A34: Total Non-Current Assets | B34: =B30+B31+B32+B33 -> 0 | C34: =C30+C31+C32+C33 -> 0 | D34: =D30+D31+D32+D33 -> 0 | E34: =E30+E31+E32+E33 -> 0 | F34: =F30+F31+F32+F33 -> 0 | G34: =G30+G31+G32+G33 -> 0 | H34: =H30+H31+H32+H33 -> 0 | I34: =I30+I31+I32+I33 -> 0
A35: Total Assets | B35: =B26+B34 -> 0 | C35: =C26+C34 -> 0 | D35: =D26+D34 -> 0 | E35: =E26+E34 -> 0 | F35: =F26+F34 -> 0 | G35: =G26+G34 -> 0 | H35: =H26+H34 -> 0 | I35: =I26+I34 -> 0
A37: Accounts Payable | B37: ='Balance Sheet'!B15 -> 0 | C37: ='Balance Sheet'!C15 -> 0 | D37: ='Balance Sheet'!D15 -> 0 | E37: =E4*Scenarios!E59/365 -> 0 | F37: =F4*Scenarios!F59/365 -> 0 | G37: =G4*Scenarios!G59/365 -> 0 | H37: =H4*Scenarios!H59/365 -> 0 | I37: =I4*Scenarios!I59/365 -> 0
A38: Accrued Expenses | B38: ='Balance Sheet'!B16 -> 0 | C38: ='Balance Sheet'!C16 -> 0 | D38: ='Balance Sheet'!D16 -> 0 | E38: =E2*Scenarios!E61 -> 0 | F38: =F2*Scenarios!F61 -> 0 | G38: =G2*Scenarios!G61 -> 0 | H38: =H2*Scenarios!H61 -> 0 | I38: =I2*Scenarios!I61 -> 0
A39: Short-Term Debt | B39: ='Balance Sheet'!B18 -> 0 | C39: ='Balance Sheet'!C18 -> 0 | D39: ='Balance Sheet'!D18 -> 0 | E39: =Scenarios!E68 -> 0 | F39: =Scenarios!F68 -> 0 | G39: =Scenarios!G68 -> 0 | H39: =Scenarios!H68 -> 0 | I39: =Scenarios!I68 -> 0
A40: Current Portion LTD | B40: ='Balance Sheet'!B19 -> 0 | C40: ='Balance Sheet'!C19 -> 0 | D40: ='Balance Sheet'!D19 -> 0 | E40: =Scenarios!E71 -> 0 | F40: =Scenarios!F71 -> 0 | G40: =Scenarios!G71 -> 0 | H40: =Scenarios!H71 -> 0 | I40: =Scenarios!I71 -> 0
A41: Deferred Revenue | B41: ='Balance Sheet'!B17 -> 0 | C41: ='Balance Sheet'!C17 -> 0 | D41: ='Balance Sheet'!D17 -> 0 | E41: =E2*Scenarios!E62 -> 0 | F41: =F2*Scenarios!F62 -> 0 | G41: =G2*Scenarios!G62 -> 0 | H41: =H2*Scenarios!H62 -> 0 | I41: =I2*Scenarios!I62 -> 0
A42: Other Current Liabilities | B42: ='Balance Sheet'!B20 -> 0 | C42: ='Balance Sheet'!C20 -> 0 | D42: ='Balance Sheet'!D20 -> 0 | E42: =Scenarios!E78 -> 0 | F42: =Scenarios!F78 -> 0 | G42: =Scenarios!G78 -> 0 | H42: =Scenarios!H78 -> 0 | I42: =Scenarios!I78 -> 0
A43: Total Current Liabilities | B43: =SUM(B37:B42) -> 0 | C43: =SUM(C37:C42) -> 0 | D43: =SUM(D37:D42) -> 0 | E43: =SUM(E37:E42) -> 0 | F43: =SUM(F37:F42) -> 0 | G43: =SUM(G37:G42) -> 0 | H43: =SUM(H37:H42) -> 0 | I43: =SUM(I37:I42) -> 0
A45: Long-Term Debt | B45: ='Balance Sheet'!B22 -> 0 | C45: ='Balance Sheet'!C22 -> 0 | D45: ='Balance Sheet'!D22 -> 0 | E45: =D45+Scenarios!E69-Scenarios!E70 -> 0 | F45: =E45+Scenarios!F69-Scenarios!F70 -> 0 | G45: =F45+Scenarios!G69-Scenarios!G70 -> 0 | H45: =G45+Scenarios!H69-Scenarios!H70 -> 0 | I45: =H45+Scenarios!I69-Scenarios!I70 -> 0
A46: Deferred Tax Liabilities | B46: ='Balance Sheet'!B23 -> 0 | C46: ='Balance Sheet'!C23 -> 0 | D46: ='Balance Sheet'!D23 -> 0 | E46: =Scenarios!E79 -> 0 | F46: =Scenarios!F79 -> 0 | G46: =Scenarios!G79 -> 0 | H46: =Scenarios!H79 -> 0 | I46: =Scenarios!I79 -> 0
A47: Other LT Liabilities | B47: ='Balance Sheet'!B24 -> 0 | C47: ='Balance Sheet'!C24 -> 0 | D47: ='Balance Sheet'!D24 -> 0 | E47: =Scenarios!E80 -> 0 | F47: =Scenarios!F80 -> 0 | G47: =Scenarios!G80 -> 0 | H47: =Scenarios!H80 -> 0 | I47: =Scenarios!I80 -> 0
A48: Total Non-Current Liabilities | B48: =SUM(B45:B47) -> 0 | C48: =SUM(C45:C47) -> 0 | D48: =SUM(D45:D47) -> 0 | E48: =SUM(E45:E47) -> 0 | F48: =SUM(F45:F47) -> 0 | G48: =SUM(G45:G47) -> 0 | H48: =SUM(H45:H47) -> 0 | I48: =SUM(I45:I47) -> 0
A49: Total Liabilities | B49: =B43+B48 -> 0 | C49: =C43+C48 -> 0 | D49: =D43+D48 -> 0 | E49: =E43+E48 -> 0 | F49: =F43+F48 -> 0 | G49: =G43+G48 -> 0 | H49: =H43+H48 -> 0 | I49: =I43+I48 -> 0
A51: Common Stock | B51: ='Balance Sheet'!B26 -> 0 | C51: ='Balance Sheet'!C26 -> 0 | D51: ='Balance Sheet'!D26 -> 0 | E51: =Scenarios!E81 -> 0 | F51: =Scenarios!F81 -> 0 | G51: =Scenarios!G81 -> 0 | H51: =Scenarios!H81 -> 0 | I51: =Scenarios!I81 -> 0
A52: APIC | B52: ='Balance Sheet'!B27 -> 0 | C52: ='Balance Sheet'!C27 -> 0 | D52: ='Balance Sheet'!D27 -> 0 | E52: =D52+Scenarios!E74+Scenarios!E56 -> 0 | F52: =E52+Scenarios!F74+Scenarios!F56 -> 0 | G52: =F52+Scenarios!G74+Scenarios!G56 -> 0 | H52: =G52+Scenarios!H74+Scenarios!H56 -> 0 | I52: =H52+Scenarios!I74+Scenarios!I56 -> 0
A53: Retained Earnings | B53: ='Balance Sheet'!B28 -> 0 | C53: ='Balance Sheet'!C28 -> 0 | D53: ='Balance Sheet'!D28 -> 0 | E53: =D53+E19-MAX(0,E19*Scenarios!E72) -> 0 | F53: =E53+F19-MAX(0,F19*Scenarios!F72) -> 0 | G53: =F53+G19-MAX(0,G19*Scenarios!G72) -> 0 | H53: =G53+H19-MAX(0,H19*Scenarios!H72) -> 0 | I53: =H53+I19-MAX(0,I19*Scenarios!I72) -> 0
A54: Treasury Stock | B54: ='Balance Sheet'!B29 -> 0 | C54: ='Balance Sheet'!C29 -> 0 | D54: ='Balance Sheet'!D29 -> 0 | E54: =D54-Scenarios!E73 -> 0 | F54: =E54-Scenarios!F73 -> 0 | G54: =F54-Scenarios!G73 -> 0 | H54: =G54-Scenarios!H73 -> 0 | I54: =H54-Scenarios!I73 -> 0
A55: Other Comprehensive Income | B55: ='Balance Sheet'!B30 -> 0 | C55: ='Balance Sheet'!C30 -> 0 | D55: ='Balance Sheet'!D30 -> 0 | E55: =Scenarios!E83 -> 0 | F55: =Scenarios!F83 -> 0 | G55: =Scenarios!G83 -> 0 | H55: =Scenarios!H83 -> 0 | I55: =Scenarios!I83 -> 0
A56: Total Equity | B56: =SUM(B51:B55) -> 0 | C56: =SUM(C51:C55) -> 0 | D56: =SUM(D51:D55) -> 0 | E56: =SUM(E51:E55) -> 0 | F56: =SUM(F51:F55) -> 0 | G56: =SUM(G51:G55) -> 0 | H56: =SUM(H51:H55) -> 0 | I56: =SUM(I51:I55) -> 0
A58: Total Liabilities + Equity | B58: =B49+B56 -> 0 | C58: =C49+C56 -> 0 | D58: =D49+D56 -> 0 | E58: =E49+E56 -> 0 | F58: =F49+F56 -> 0 | G58: =G49+G56 -> 0 | H58: =H49+H56 -> 0 | I58: =I49+I56 -> 0
A59: Balance Check (TA - TLE) | B59: =B35-B58 -> 0 | C59: =C35-C58 -> 0 | D59: =D35-D58 -> 0 | E59: =E35-E58 -> 0 | F59: =F35-F58 -> 0 | G59: =G35-G58 -> 0 | H59: =H35-H58 -> 0 | I59: =I35-I58 -> 0
A60: ── Cash Flow ──
A61: Net Income | E61: =E19 -> 0 | F61: =F19 -> 0 | G61: =G19 -> 0 | H61: =H19 -> 0 | I61: =I19 -> 0
A62: + Depreciation | E62: =E8 -> 0 | F62: =F8 -> 0 | G62: =G8 -> 0 | H62: =H8 -> 0 | I62: =I8 -> 0
A63: + Amortization | E63: =E9 -> 0 | F63: =F9 -> 0 | G63: =G9 -> 0 | H63: =H9 -> 0 | I63: =I9 -> 0
A64: + SBC | E64: =E11 -> 0 | F64: =F11 -> 0 | G64: =G11 -> 0 | H64: =H11 -> 0 | I64: =I11 -> 0
A65: Deferred Taxes | E65: =E46-D46 -> 0 | F65: =F46-E46 -> 0 | G65: =G46-F46 -> 0 | H65: =H46-G46 -> 0 | I65: =I46-H46 -> 0
A66: Δ A/R | E66: =-(E22-D22) -> 0 | F66: =-(F22-E22) -> 0 | G66: =-(G22-F22) -> 0 | H66: =-(H22-G22) -> 0 | I66: =-(I22-H22) -> 0
A67: Δ Inventory | E67: =-(E23-D23) -> 0 | F67: =-(F23-E23) -> 0 | G67: =-(G23-F23) -> 0 | H67: =-(H23-G23) -> 0 | I67: =-(I23-H23) -> 0
A68: Δ Prepaid | E68: =-(E24-D24) -> 0 | F68: =-(F24-E24) -> 0 | G68: =-(G24-F24) -> 0 | H68: =-(H24-G24) -> 0 | I68: =-(I24-H24) -> 0
A69: Δ A/P | E69: =E37-D37 -> 0 | F69: =F37-E37 -> 0 | G69: =G37-F37 -> 0 | H69: =H37-G37 -> 0 | I69: =I37-H37 -> 0
A70: Δ Accrued Exp | E70: =E38-D38 -> 0 | F70: =F38-E38 -> 0 | G70: =G38-F38 -> 0 | H70: =H38-G38 -> 0 | I70: =I38-H38 -> 0
A71: Δ Deferred Revenue | E71: =E41-D41 -> 0 | F71: =F41-E41 -> 0 | G71: =G41-F41 -> 0 | H71: =H41-G41 -> 0 | I71: =I41-H41 -> 0
A72: Total WC Change | E72: =SUM(E66:E71) -> 0 | F72: =SUM(F66:F71) -> 0 | G72: =SUM(G66:G71) -> 0 | H72: =SUM(H66:H71) -> 0 | I72: =SUM(I66:I71) -> 0
A73: Cash from Operations | E73: =E61+E62+E63+E64+E65+E72 -> 0 | F73: =F61+F62+F63+F64+F65+F72 -> 0 | G73: =G61+G62+G63+G64+G65+G72 -> 0 | H73: =H61+H62+H63+H64+H65+H72 -> 0 | I73: =I61+I62+I63+I64+I65+I72 -> 0
A75: Capital Expenditures | E75: =-ABS(E2*Scenarios!E63) -> 0 | F75: =-ABS(F2*Scenarios!F63) -> 0 | G75: =-ABS(G2*Scenarios!G63) -> 0 | H75: =-ABS(H2*Scenarios!H63) -> 0 | I75: =-ABS(I2*Scenarios!I63) -> 0
A76: Acquisitions | E76: =0 -> 0 | F76: =0 -> 0 | G76: =0 -> 0 | H76: =0 -> 0 | I76: =0 -> 0
A77: Asset Sales | E77: =0 -> 0 | F77: =0 -> 0 | G77: =0 -> 0 | H77: =0 -> 0 | I77: =0 -> 0
A78: Cash from Investing | E78: =E75+E76+E77 -> 0 | F78: =F75+F76+F77 -> 0 | G78: =G75+G76+G77 -> 0 | H78: =H75+H76+H77 -> 0 | I78: =I75+I76+I77 -> 0
A80: Debt Issuance | E80: =Scenarios!E69 -> 0 | F80: =Scenarios!F69 -> 0 | G80: =Scenarios!G69 -> 0 | H80: =Scenarios!H69 -> 0 | I80: =Scenarios!I69 -> 0
A81: Debt Repayment | E81: =-ABS(Scenarios!E70) -> 0 | F81: =-ABS(Scenarios!F70) -> 0 | G81: =-ABS(Scenarios!G70) -> 0 | H81: =-ABS(Scenarios!H70) -> 0 | I81: =-ABS(Scenarios!I70) -> 0
A82: Dividends Paid | E82: =-MAX(0,E19*Scenarios!E72) -> 0 | F82: =-MAX(0,F19*Scenarios!F72) -> 0 | G82: =-MAX(0,G19*Scenarios!G72) -> 0 | H82: =-MAX(0,H19*Scenarios!H72) -> 0 | I82: =-MAX(0,I19*Scenarios!I72) -> 0
A83: Equity Issuance | E83: =Scenarios!E74 -> 0 | F83: =Scenarios!F74 -> 0 | G83: =Scenarios!G74 -> 0 | H83: =Scenarios!H74 -> 0 | I83: =Scenarios!I74 -> 0
A84: Share Repurchases | E84: =-ABS(Scenarios!E73) -> 0 | F84: =-ABS(Scenarios!F73) -> 0 | G84: =-ABS(Scenarios!G73) -> 0 | H84: =-ABS(Scenarios!H73) -> 0 | I84: =-ABS(Scenarios!I73) -> 0
A85: Cash from Financing | E85: =E80+E81+E82+E83+E84 -> 0 | F85: =F80+F81+F82+F83+F84 -> 0 | G85: =G80+G81+G82+G83+G84 -> 0 | H85: =H80+H81+H82+H83+H84 -> 0 | I85: =I80+I81+I82+I83+I84 -> 0
A87: Net Change in Cash | E87: =E73+E78+E85 -> 0 | F87: =F73+F78+F85 -> 0 | G87: =G73+G78+G85 -> 0 | H87: =H73+H78+H85 -> 0 | I87: =I73+I78+I85 -> 0
A88: Beginning Cash | E88: =D21 -> 0 | F88: =E21 -> 0 | G88: =F21 -> 0 | H88: =G21 -> 0 | I88: =H21 -> 0
A89: Ending Cash | E89: =E88+E87 -> 0 | F89: =F88+F87 -> 0 | G89: =G88+G87 -> 0 | H89: =H88+H87 -> 0 | I89: =I88+I87 -> 0
A90: Free Cash Flow | E90: =E73+E75 -> 0 | F90: =F73+F75 -> 0 | G90: =G73+G75 -> 0 | H90: =H73+H75 -> 0 | I90: =I73+I75 -> 0

Sheet _Calc_Con
A1: _Calc_Con — Full 3-Statement Model | B1: 2021A | C1: 2022A | D1: 2023A | E1: 2024E | F1: 2025E | G1: 2026E | H1: 2027E | I1: 2028E
A2: Revenue | B2: ='Income Statement'!B2 -> 0 | C2: ='Income Statement'!C2 -> 0 | D2: ='Income Statement'!D2 -> 0 | E2: =D2*(1+Scenarios!E91) -> 0 | F2: =E2*(1+Scenarios!F91) -> 0 | G2: =F2*(1+Scenarios!G91) -> 0 | H2: =G2*(1+Scenarios!H91) -> 0 | I2: =H2*(1+Scenarios!I91) -> 0
A3: Revenue Growth % | B3: =0 -> 0 | C3: =(C2-B2)/B2 -> 0 | D3: =(D2-C2)/C2 -> 0 | E3: =Scenarios!E91 -> 0 | F3: =Scenarios!F91 -> 0 | G3: =Scenarios!G91 -> 0 | H3: =Scenarios!H91 -> 0 | I3: =Scenarios!I91 -> 0
A4: COGS | B4: ='Income Statement'!B3 -> 0 | C4: ='Income Statement'!C3 -> 0 | D4: ='Income Statement'!D3 -> 0 | E4: =E2*Scenarios!E92 -> 0 | F4: =F2*Scenarios!F92 -> 0 | G4: =G2*Scenarios!G92 -> 0 | H4: =H2*Scenarios!H92 -> 0 | I4: =I2*Scenarios!I92 -> 0
A5: Gross Profit | B5: =B2-B4 -> 0 | C5: =C2-C4 -> 0 | D5: =D2-D4 -> 0 | E5: =E2-E4 -> 0 | F5: =F2-F4 -> 0 | G5: =G2-G4 -> 0 | H5: =H2-H4 -> 0 | I5: =I2-I4 -> 0
A6: SG&A | B6: ='Income Statement'!B5 -> 0 | C6: ='Income Statement'!C5 -> 0 | D6: ='Income Statement'!D5 -> 0 | E6: =E2*Scenarios!E93 -> 0 | F6: =F2*Scenarios!F93 -> 0 | G6: =G2*Scenarios!G93 -> 0 | H6: =H2*Scenarios!H93 -> 0 | I6: =I2*Scenarios!I93 -> 0
A7: R&D | B7: ='Income Statement'!B6 -> 0 | C7: ='Income Statement'!C6 -> 0 | D7: ='Income Statement'!D6 -> 0 | E7: =E2*Scenarios!E94 -> 0 | F7: =F2*Scenarios!F94 -> 0 | G7: =G2*Scenarios!G94 -> 0 | H7: =H2*Scenarios!H94 -> 0 | I7: =I2*Scenarios!I94 -> 0
A8: Depreciation | B8: ='Income Statement'!B16 -> 0 | C8: ='Income Statement'!C16 -> 0 | D8: ='Income Statement'!D16 -> 0 | E8: =(D28+E2*Scenarios!E106/2)*Scenarios!E107 -> 0 | F8: =(E28+F2*Scenarios!F106/2)*Scenarios!F107 -> 0 | G8: =(F28+G2*Scenarios!G106/2)*Scenarios!G107 -> 0 | H8: =(G28+H2*Scenarios!H106/2)*Scenarios!H107 -> 0 | I8: =(H28+I2*Scenarios!I106/2)*Scenarios!I107 -> 0
A9: Amortization | B9: ='Income Statement'!B17 -> 0 | C9: ='Income Statement'!C17 -> 0 | D9: ='Income Statement'!D17 -> 0 | E9: =Scenarios!E108 -> 0 | F9: =Scenarios!F108 -> 0 | G9: =Scenarios!G108 -> 0 | H9: =Scenarios!H108 -> 0 | I9: =Scenarios!I108 -> 0
A10: Other OpEx | B10: ='Income Statement'!B7 -> 0 | C10: ='Income Statement'!C7 -> 0 | D10: ='Income Statement'!D7 -> 0 | E10: =E2*Scenarios!E95 -> 0 | F10: =F2*Scenarios!F95 -> 0 | G10: =G2*Scenarios!G95 -> 0 | H10: =H2*Scenarios!H95 -> 0 | I10: =I2*Scenarios!I95 -> 0
A11: SBC | B11: ='Income Statement'!B18 -> 0 | C11: ='Income Statement'!C18 -> 0 | D11: ='Income Statement'!D18 -> 0 | E11: =Scenarios!E99 -> 0 | F11: =Scenarios!F99 -> 0 | G11: =Scenarios!G99 -> 0 | H11: =Scenarios!H99 -> 0 | I11: =Scenarios!I99 -> 0
A12: Total OpEx | B12: =B6+B7+B8+B9+B10+B11 -> 0 | C12: =C6+C7+C8+C9+C10+C11 -> 0 | D12: =D6+D7+D8+D9+D10+D11 -> 0 | E12: =E6+E7+E8+E9+E10+E11 -> 0 | F12: =F6+F7+F8+F9+F10+F11 -> 0 | G12: =G6+G7+G8+G9+G10+G11 -> 0 | H12: =H6+H7+H8+H9+H10+H11 -> 0 | I12: =I6+I7+I8+I9+I10+I11 -> 0
A13: EBIT | B13: =B5-B12 -> 0 | C13: =C5-C12 -> 0 | D13: =D5-D12 -> 0 | E13: =E5-E12 -> 0 | F13: =F5-F12 -> 0 | G13: =G5-G12 -> 0 | H13: =H5-H12 -> 0 | I13: =I5-I12 -> 0
A14: Interest Income | B14: ='Income Statement'!B10 -> 0 | C14: ='Income Statement'!C10 -> 0 | D14: ='Income Statement'!D10 -> 0 | E14: =D21*Scenarios!E110 -> 0 | F14: =E21*Scenarios!F110 -> 0 | G14: =F21*Scenarios!G110 -> 0 | H14: =G21*Scenarios!H110 -> 0 | I14: =H21*Scenarios!I110 -> 0
A15: Interest Expense | B15: ='Income Statement'!B11 -> 0 | C15: ='Income Statement'!C11 -> 0 | D15: ='Income Statement'!D11 -> 0 | E15: =(D45+E45)/2*Scenarios!E109 -> 0 | F15: =(E45+F45)/2*Scenarios!F109 -> 0 | G15: =(F45+G45)/2*Scenarios!G109 -> 0 | H15: =(G45+H45)/2*Scenarios!H109 -> 0 | I15: =(H45+I45)/2*Scenarios!I109 -> 0
A16: Other Income/Expense | B16: ='Income Statement'!B12 -> 0 | C16: ='Income Statement'!C12 -> 0 | D16: ='Income Statement'!D12 -> 0 | E16: =Scenarios!E97 -> 0 | F16: =Scenarios!F97 -> 0 | G16: =Scenarios!G97 -> 0 | H16: =Scenarios!H97 -> 0 | I16: =Scenarios!I97 -> 0
A17: EBT | B17: =B13+B14-B15+B16 -> 0 | C17: =C13+C14-C15+C16 -> 0 | D17: =D13+D14-D15+D16 -> 0 | E17: =E13+E14-E15+E16 -> 0 | F17: =F13+F14-F15+F16 -> 0 | G17: =G13+G14-G15+G16 -> 0 | H17: =H13+H14-H15+H16 -> 0 | I17: =I13+I14-I15+I16 -> 0
A18: Tax Expense | B18: ='Income Statement'!B14 -> 0 | C18: ='Income Statement'!C14 -> 0 | D18: ='Income Statement'!D14 -> 0 | E18: =MAX(0,E17*Scenarios!E96) -> 0 | F18: =MAX(0,F17*Scenarios!F96) -> 0 | G18: =MAX(0,G17*Scenarios!G96) -> 0 | H18: =MAX(0,H17*Scenarios!H96) -> 0 | I18: =MAX(0,I17*Scenarios!I96) -> 0
A19: Net Income | B19: =B17-B18 -> 0 | C19: =C17-C18 -> 0 | D19: =D17-D18 -> 0 | E19: =E17-E18 -> 0 | F19: =F17-F18 -> 0 | G19: =G17-G18 -> 0 | H19: =H17-H18 -> 0 | I19: =I17-I18 -> 0
A20: ── Balance Sheet ──
A21: Cash & Equivalents | B21: ='Balance Sheet'!B2 -> 0 | C21: ='Balance Sheet'!C2 -> 0 | D21: ='Balance Sheet'!D2 -> 0 | E21: =D21+E73+E78+E85 -> 0 | F21: =E21+F73+F78+F85 -> 0 | G21: =F21+G73+G78+G85 -> 0 | H21: =G21+H73+H78+H85 -> 0 | I21: =H21+I73+I78+I85 -> 0
A22: Accounts Receivable | B22: ='Balance Sheet'!B3 -> 0 | C22: ='Balance Sheet'!C3 -> 0 | D22: ='Balance Sheet'!D3 -> 0 | E22: =E2*Scenarios!E100/365 -> 0 | F22: =F2*Scenarios!F100/365 -> 0 | G22: =G2*Scenarios!G100/365 -> 0 | H22: =H2*Scenarios!H100/365 -> 0 | I22: =I2*Scenarios!I100/365 -> 0
A23: Inventory | B23: ='Balance Sheet'!B4 -> 0 | C23: ='Balance Sheet'!C4 -> 0 | D23: ='Balance Sheet'!D4 -> 0 | E23: =E4*Scenarios!E101/365 -> 0 | F23: =F4*Scenarios!F101/365 -> 0 | G23: =G4*Scenarios!G101/365 -> 0 | H23: =H4*Scenarios!H101/365 -> 0 | I23: =I4*Scenarios!I101/365 -> 0
A24: Prepaid Expenses | B24: ='Balance Sheet'!B5 -> 0 | C24: ='Balance Sheet'!C5 -> 0 | D24: ='Balance Sheet'!D5 -> 0 | E24: =E2*Scenarios!E103 -> 0 | F24: =F2*Scenarios!F103 -> 0 | G24: =G2*Scenarios!G103 -> 0 | H24: =H2*Scenarios!H103 -> 0 | I24: =I2*Scenarios!I103 -> 0
A25: Other Current Assets | B25: ='Balance Sheet'!B6 -> 0 | C25: ='Balance Sheet'!C6 -> 0 | D25: ='Balance Sheet'!D6 -> 0 | E25: =Scenarios!E119 -> 0 | F25: =Scenarios!F119 -> 0 | G25: =Scenarios!G119 -> 0 | H25: =Scenarios!H119 -> 0 | I25: =Scenarios!I119 -> 0
A26: Total Current Assets | B26: =SUM(B21:B25) -> 0 | C26: =SUM(C21:C25) -> 0 | D26: =SUM(D21:D25) -> 0 | E26: =SUM(E21:E25) -> 0 | F26: =SUM(F21:F25) -> 0 | G26: =SUM(G21:G25) -> 0 | H26: =SUM(H21:H25) -> 0 | I26: =SUM(I21:I25) -> 0
A28: Gross PP&E | B28: ='Balance Sheet'!B8 -> 0 | C28: ='Balance Sheet'!C8 -> 0 | D28: ='Balance Sheet'!D8 -> 0 | E28: =D28+E2*Scenarios!E106 -> 0 | F28: =E28+F2*Scenarios!F106 -> 0 | G28: =F28+G2*Scenarios!G106 -> 0 | H28: =G28+H2*Scenarios!H106 -> 0 | I28: =H28+I2*Scenarios!I106 -> 0
A29: Accumulated Depreciation | B29: ='Balance Sheet'!B9 -> 0 | C29: ='Balance Sheet'!C9 -> 0 | D29: ='Balance Sheet'!D9 -> 0 | E29: =D29+E8 -> 0 | F29: =E29+F8 -> 0 | G29: =F29+G8 -> 0 | H29: =G29+H8 -> 0 | I29: =H29+I8 -> 0
A30: Net PP&E | B30: =B28-B29 -> 0 | C30: =C28-C29 -> 0 | D30: =D28-D29 -> 0 | E30: =E28-E29 -> 0 | F30: =F28-F29 -> 0 | G30: =G28-G29 -> 0 | H30: =H28-H29 -> 0 | I30: =I28-I29 -> 0
A31: Intangibles | B31: ='Balance Sheet'!B11 -> 0 | C31: ='Balance Sheet'!C11 -> 0 | D31: ='Balance Sheet'!D11 -> 0 | E31: =MAX(0,D31-E9) -> 0 | F31: =MAX(0,E31-F9) -> 0 | G31: =MAX(0,F31-G9) -> 0 | H31: =MAX(0,G31-H9) -> 0 | I31: =MAX(0,H31-I9) -> 0
A32: Goodwill | B32: ='Balance Sheet'!B12 -> 0 | C32: ='Balance Sheet'!C12 -> 0 | D32: ='Balance Sheet'!D12 -> 0 | E32: =Scenarios!E118 -> 0 | F32: =Scenarios!F118 -> 0 | G32: =Scenarios!G118 -> 0 | H32: =Scenarios!H118 -> 0 | I32: =Scenarios!I118 -> 0
A33: Other LT Assets | B33: ='Balance Sheet'!B13 -> 0 | C33: ='Balance Sheet'!C13 -> 0 | D33: ='Balance Sheet'!D13 -> 0 | E33: =Scenarios!E120 -> 0 | F33: =Scenarios!F120 -> 0 | G33: =Scenarios!G120 -> 0 | H33: =Scenarios!H120 -> 0 | I33: =Scenarios!I120 -> 0
A34: Total Non-Current Assets | B34: =B30+B31+B32+B33 -> 0 | C34: =C30+C31+C32+C33 -> 0 | D34: =D30+D31+D32+D33 -> 0 | E34: =E30+E31+E32+E33 -> 0 | F34: =F30+F31+F32+F33 -> 0 | G34: =G30+G31+G32+G33 -> 0 | H34: =H30+H31+H32+H33 -> 0 | I34: =I30+I31+I32+I33 -> 0
A35: Total Assets | B35: =B26+B34 -> 0 | C35: =C26+C34 -> 0 | D35: =D26+D34 -> 0 | E35: =E26+E34 -> 0 | F35: =F26+F34 -> 0 | G35: =G26+G34 -> 0 | H35: =H26+H34 -> 0 | I35: =I26+I34 -> 0
A37: Accounts Payable | B37: ='Balance Sheet'!B15 -> 0 | C37: ='Balance Sheet'!C15 -> 0 | D37: ='Balance Sheet'!D15 -> 0 | E37: =E4*Scenarios!E102/365 -> 0 | F37: =F4*Scenarios!F102/365 -> 0 | G37: =G4*Scenarios!G102/365 -> 0 | H37: =H4*Scenarios!H102/365 -> 0 | I37: =I4*Scenarios!I102/365 -> 0
A38: Accrued Expenses | B38: ='Balance Sheet'!B16 -> 0 | C38: ='Balance Sheet'!C16 -> 0 | D38: ='Balance Sheet'!D16 -> 0 | E38: =E2*Scenarios!E104 -> 0 | F38: =F2*Scenarios!F104 -> 0 | G38: =G2*Scenarios!G104 -> 0 | H38: =H2*Scenarios!H104 -> 0 | I38: =I2*Scenarios!I104 -> 0
A39: Short-Term Debt | B39: ='Balance Sheet'!B18 -> 0 | C39: ='Balance Sheet'!C18 -> 0 | D39: ='Balance Sheet'!D18 -> 0 | E39: =Scenarios!E111 -> 0 | F39: =Scenarios!F111 -> 0 | G39: =Scenarios!G111 -> 0 | H39: =Scenarios!H111 -> 0 | I39: =Scenarios!I111 -> 0
A40: Current Portion LTD | B40: ='Balance Sheet'!B19 -> 0 | C40: ='Balance Sheet'!C19 -> 0 | D40: ='Balance Sheet'!D19 -> 0 | E40: =Scenarios!E114 -> 0 | F40: =Scenarios!F114 -> 0 | G40: =Scenarios!G114 -> 0 | H40: =Scenarios!H114 -> 0 | I40: =Scenarios!I114 -> 0
A41: Deferred Revenue | B41: ='Balance Sheet'!B17 -> 0 | C41: ='Balance Sheet'!C17 -> 0 | D41: ='Balance Sheet'!D17 -> 0 | E41: =E2*Scenarios!E105 -> 0 | F41: =F2*Scenarios!F105 -> 0 | G41: =G2*Scenarios!G105 -> 0 | H41: =H2*Scenarios!H105 -> 0 | I41: =I2*Scenarios!I105 -> 0
A42: Other Current Liabilities | B42: ='Balance Sheet'!B20 -> 0 | C42: ='Balance Sheet'!C20 -> 0 | D42: ='Balance Sheet'!D20 -> 0 | E42: =Scenarios!E121 -> 0 | F42: =Scenarios!F121 -> 0 | G42: =Scenarios!G121 -> 0 | H42: =Scenarios!H121 -> 0 | I42: =Scenarios!I121 -> 0
A43: Total Current Liabilities | B43: =SUM(B37:B42) -> 0 | C43: =SUM(C37:C42) -> 0 | D43: =SUM(D37:D42) -> 0 | E43: =SUM(E37:E42) -> 0 | F43: =SUM(F37:F42) -> 0 | G43: =SUM(G37:G42) -> 0 | H43: =SUM(H37:H42) -> 0 | I43: =SUM(I37:I42) -> 0
A45: Long-Term Debt | B45: ='Balance Sheet'!B22 -> 0 | C45: ='Balance Sheet'!C22 -> 0 | D45: ='Balance Sheet'!D22 -> 0 | E45: =D45+Scenarios!E112-Scenarios!E113 -> 0 | F45: =E45+Scenarios!F112-Scenarios!F113 -> 0 | G45: =F45+Scenarios!G112-Scenarios!G113 -> 0 | H45: =G45+Scenarios!H112-Scenarios!H113 -> 0 | I45: =H45+Scenarios!I112-Scenarios!I113 -> 0
A46: Deferred Tax Liabilities | B46: ='Balance Sheet'!B23 -> 0 | C46: ='Balance Sheet'!C23 -> 0 | D46: ='Balance Sheet'!D23 -> 0 | E46: =Scenarios!E122 -> 0 | F46: =Scenarios!F122 -> 0 | G46: =Scenarios!G122 -> 0 | H46: =Scenarios!H122 -> 0 | I46: =Scenarios!I122 -> 0
A47: Other LT Liabilities | B47: ='Balance Sheet'!B24 -> 0 | C47: ='Balance Sheet'!C24 -> 0 | D47: ='Balance Sheet'!D24 -> 0 | E47: =Scenarios!E123 -> 0 | F47: =Scenarios!F123 -> 0 | G47: =Scenarios!G123 -> 0 | H47: =Scenarios!H123 -> 0 | I47: =Scenarios!I123 -> 0
A48: Total Non-Current Liabilities | B48: =SUM(B45:B47) -> 0 | C48: =SUM(C45:C47) -> 0 | D48: =SUM(D45:D47) -> 0 | E48: =SUM(E45:E47) -> 0 | F48: =SUM(F45:F47) -> 0 | G48: =SUM(G45:G47) -> 0 | H48: =SUM(H45:H47) -> 0 | I48: =SUM(I45:I47) -> 0
A49: Total Liabilities | B49: =B43+B48 -> 0 | C49: =C43+C48 -> 0 | D49: =D43+D48 -> 0 | E49: =E43+E48 -> 0 | F49: =F43+F48 -> 0 | G49: =G43+G48 -> 0 | H49: =H43+H48 -> 0 | I49: =I43+I48 -> 0
A51: Common Stock | B51: ='Balance Sheet'!B26 -> 0 | C51: ='Balance Sheet'!C26 -> 0 | D51: ='Balance Sheet'!D26 -> 0 | E51: =Scenarios!E124 -> 0 | F51: =Scenarios!F124 -> 0 | G51: =Scenarios!G124 -> 0 | H51: =Scenarios!H124 -> 0 | I51: =Scenarios!I124 -> 0
A52: APIC | B52: ='Balance Sheet'!B27 -> 0 | C52: ='Balance Sheet'!C27 -> 0 | D52: ='Balance Sheet'!D27 -> 0 | E52: =D52+Scenarios!E117+Scenarios!E99 -> 0 | F52: =E52+Scenarios!F117+Scenarios!F99 -> 0 | G52: =F52+Scenarios!G117+Scenarios!G99 -> 0 | H52: =G52+Scenarios!H117+Scenarios!H99 -> 0 | I52: =H52+Scenarios!I117+Scenarios!I99 -> 0
A53: Retained Earnings | B53: ='Balance Sheet'!B28 -> 0 | C53: ='Balance Sheet'!C28 -> 0 | D53: ='Balance Sheet'!D28 -> 0 | E53: =D53+E19-MAX(0,E19*Scenarios!E115) -> 0 | F53: =E53+F19-MAX(0,F19*Scenarios!F115) -> 0 | G53: =F53+G19-MAX(0,G19*Scenarios!G115) -> 0 | H53: =G53+H19-MAX(0,H19*Scenarios!H115) -> 0 | I53: =H53+I19-MAX(0,I19*Scenarios!I115) -> 0
A54: Treasury Stock | B54: ='Balance Sheet'!B29 -> 0 | C54: ='Balance Sheet'!C29 -> 0 | D54: ='Balance Sheet'!D29 -> 0 | E54: =D54-Scenarios!E116 -> 0 | F54: =E54-Scenarios!F116 -> 0 | G54: =F54-Scenarios!G116 -> 0 | H54: =G54-Scenarios!H116 -> 0 | I54: =H54-Scenarios!I116 -> 0
A55: Other Comprehensive Income | B55: ='Balance Sheet'!B30 -> 0 | C55: ='Balance Sheet'!C30 -> 0 | D55: ='Balance Sheet'!D30 -> 0 | E55: =Scenarios!E126 -> 0 | F55: =Scenarios!F126 -> 0 | G55: =Scenarios!G126 -> 0 | H55: =Scenarios!H126 -> 0 | I55: =Scenarios!I126 -> 0
A56: Total Equity | B56: =SUM(B51:B55) -> 0 | C56: =SUM(C51:C55) -> 0 | D56: =SUM(D51:D55) -> 0 | E56: =SUM(E51:E55) -> 0 | F56: =SUM(F51:F55) -> 0 | G56: =SUM(G51:G55) -> 0 | H56: =SUM(H51:H55) -> 0 | I56: =SUM(I51:I55) -> 0
A58: Total Liabilities + Equity | B58: =B49+B56 -> 0 | C58: =C49+C56 -> 0 | D58: =D49+D56 -> 0 | E58: =E49+E56 -> 0 | F58: =F49+F56 -> 0 | G58: =G49+G56 -> 0 | H58: =H49+H56 -> 0 | I58: =I49+I56 -> 0
A59: Balance Check (TA - TLE) | B59: =B35-B58 -> 0 | C59: =C35-C58 -> 0 | D59: =D35-D58 -> 0 | E59: =E35-E58 -> 0 | F59: =F35-F58 -> 0 | G59: =G35-G58 -> 0 | H59: =H35-H58 -> 0 | I59: =I35-I58 -> 0
A60: ── Cash Flow ──
A61: Net Income | E61: =E19 -> 0 | F61: =F19 -> 0 | G61: =G19 -> 0 | H61: =H19 -> 0 | I61: =I19 -> 0
A62: + Depreciation | E62: =E8 -> 0 | F62: =F8 -> 0 | G62: =G8 -> 0 | H62: =H8 -> 0 | I62: =I8 -> 0
A63: + Amortization | E63: =E9 -> 0 | F63: =F9 -> 0 | G63: =G9 -> 0 | H63: =H9 -> 0 | I63: =I9 -> 0
A64: + SBC | E64: =E11 -> 0 | F64: =F11 -> 0 | G64: =G11 -> 0 | H64: =H11 -> 0 | I64: =I11 -> 0
A65: Deferred Taxes | E65: =E46-D46 -> 0 | F65: =F46-E46 -> 0 | G65: =G46-F46 -> 0 | H65: =H46-G46 -> 0 | I65: =I46-H46 -> 0
A66: Δ A/R | E66: =-(E22-D22) -> 0 | F66: =-(F22-E22) -> 0 | G66: =-(G22-F22) -> 0 | H66: =-(H22-G22) -> 0 | I66: =-(I22-H22) -> 0
A67: Δ Inventory | E67: =-(E23-D23) -> 0 | F67: =-(F23-E23) -> 0 | G67: =-(G23-F23) -> 0 | H67: =-(H23-G23) -> 0 | I67: =-(I23-H23) -> 0
A68: Δ Prepaid | E68: =-(E24-D24) -> 0 | F68: =-(F24-E24) -> 0 | G68: =-(G24-F24) -> 0 | H68: =-(H24-G24) -> 0 | I68: =-(I24-H24) -> 0
A69: Δ A/P | E69: =E37-D37 -> 0 | F69: =F37-E37 -> 0 | G69: =G37-F37 -> 0 | H69: =H37-G37 -> 0 | I69: =I37-H37 -> 0
A70: Δ Accrued Exp | E70: =E38-D38 -> 0 | F70: =F38-E38 -> 0 | G70: =G38-F38 -> 0 | H70: =H38-G38 -> 0 | I70: =I38-H38 -> 0
A71: Δ Deferred Revenue | E71: =E41-D41 -> 0 | F71: =F41-E41 -> 0 | G71: =G41-F41 -> 0 | H71: =H41-G41 -> 0 | I71: =I41-H41 -> 0
A72: Total WC Change | E72: =SUM(E66:E71) -> 0 | F72: =SUM(F66:F71) -> 0 | G72: =SUM(G66:G71) -> 0 | H72: =SUM(H66:H71) -> 0 | I72: =SUM(I66:I71) -> 0
A73: Cash from Operations | E73: =E61+E62+E63+E64+E65+E72 -> 0 | F73: =F61+F62+F63+F64+F65+F72 -> 0 | G73: =G61+G62+G63+G64+G65+G72 -> 0 | H73: =H61+H62+H63+H64+H65+H72 -> 0 | I73: =I61+I62+I63+I64+I65+I72 -> 0
A75: Capital Expenditures | E75: =-ABS(E2*Scenarios!E106) -> 0 | F75: =-ABS(F2*Scenarios!F106) -> 0 | G75: =-ABS(G2*Scenarios!G106) -> 0 | H75: =-ABS(H2*Scenarios!H106) -> 0 | I75: =-ABS(I2*Scenarios!I106) -> 0
A76: Acquisitions | E76: =0 -> 0 | F76: =0 -> 0 | G76: =0 -> 0 | H76: =0 -> 0 | I76: =0 -> 0
A77: Asset Sales | E77: =0 -> 0 | F77: =0 -> 0 | G77: =0 -> 0 | H77: =0 -> 0 | I77: =0 -> 0
A78: Cash from Investing | E78: =E75+E76+E77 -> 0 | F78: =F75+F76+F77 -> 0 | G78: =G75+G76+G77 -> 0 | H78: =H75+H76+H77 -> 0 | I78: =I75+I76+I77 -> 0
A80: Debt Issuance | E80: =Scenarios!E112 -> 0 | F80: =Scenarios!F112 -> 0 | G80: =Scenarios!G112 -> 0 | H80: =Scenarios!H112 -> 0 | I80: =Scenarios!I112 -> 0
A81: Debt Repayment | E81: =-ABS(Scenarios!E113) -> 0 | F81: =-ABS(Scenarios!F113) -> 0 | G81: =-ABS(Scenarios!G113) -> 0 | H81: =-ABS(Scenarios!H113) -> 0 | I81: =-ABS(Scenarios!I113) -> 0
A82: Dividends Paid | E82: =-MAX(0,E19*Scenarios!E115) -> 0 | F82: =-MAX(0,F19*Scenarios!F115) -> 0 | G82: =-MAX(0,G19*Scenarios!G115) -> 0 | H82: =-MAX(0,H19*Scenarios!H115) -> 0 | I82: =-MAX(0,I19*Scenarios!I115) -> 0
A83: Equity Issuance | E83: =Scenarios!E117 -> 0 | F83: =Scenarios!F117 -> 0 | G83: =Scenarios!G117 -> 0 | H83: =Scenarios!H117 -> 0 | I83: =Scenarios!I117 -> 0
A84: Share Repurchases | E84: =-ABS(Scenarios!E116) -> 0 | F84: =-ABS(Scenarios!F116) -> 0 | G84: =-ABS(Scenarios!G116) -> 0 | H84: =-ABS(Scenarios!H116) -> 0 | I84: =-ABS(Scenarios!I116) -> 0
A85: Cash from Financing | E85: =E80+E81+E82+E83+E84 -> 0 | F85: =F80+F81+F82+F83+F84 -> 0 | G85: =G80+G81+G82+G83+G84 -> 0 | H85: =H80+H81+H82+H83+H84 -> 0 | I85: =I80+I81+I82+I83+I84 -> 0
A87: Net Change in Cash | E87: =E73+E78+E85 -> 0 | F87: =F73+F78+F85 -> 0 | G87: =G73+G78+G85 -> 0 | H87: =H73+H78+H85 -> 0 | I87: =I73+I78+I85 -> 0
A88: Beginning Cash | E88: =D21 -> 0 | F88: =E21 -> 0 | G88: =F21 -> 0 | H88: =G21 -> 0 | I88: =H21 -> 0
A89: Ending Cash | E89: =E88+E87 -> 0 | F89: =F88+F87 -> 0 | G89: =G88+G87 -> 0 | H89: =H88+H87 -> 0 | I89: =I88+I87 -> 0
A90: Free Cash Flow | E90: =E73+E75 -> 0 | F90: =F73+F75 -> 0 | G90: =G73+G75 -> 0 | H90: =H73+H75 -> 0 | I90: =I73+I75 -> 0
