Workbook

Sheet Company Info
A1: COMPANY INFORMATION & MODEL CONFIGURATION
A3: SECTION 1 — COMPANY IDENTIFICATION
A4: Company Name | B4: TestCo | C4: ← Edit
A5: Legal Entity Type | B5: Société Anonyme (S.A.E.) | C5: ← Edit
A6: Industry / Sector | B6: Technology / Software | C6: ← Edit
A7: Founded Year | B7: 2010 | C7: ← Edit
A8: Commercial Register No. | B8: 12345-Cairo-2010 | C8: Auto
A9: Tax Identification No. | B9: 123-456-789 | C9: Auto
A10: Headquarters Address | B10: 5 El-Nile Street, Zamalek, Cairo, Egypt | C10: Auto
A12: SECTION 2 — FINANCIAL MODEL CONFIGURATION
A13: Reporting Currency | B13: Egyptian Pound (EGP) | C13: Auto
A14: Currency Symbol | B14: E£ | C14: Auto
A15: Fiscal Year End | B15: December 31 | C15: ← Edit
A16: Historical Period | B16: 2021 – 2023 (Actual) | C16: Auto
A17: Projection Period | B17: 2024E – 2028E (5 Years) | C17: Auto
A18: Revenue Projection Base (E£) | B18: 1000000 | C18: ← Edit
A19: Model Version | B19: v2.0 | Feb 2026 | C19: Auto
A20: Last Updated | B20: February 20, 2026 | C20: Auto
A22: SECTION 3 — EGYPT REGULATORY / TAX
A23: Corporate Income Tax Rate | B23: 0.225 | C23: ← Edit
A24: VAT Rate (Standard) | B24: 0.14 | C24: ← Edit
A25: Dividend Withholding Tax | B25: 0.1 | C25: ← Edit
A26: CBE Policy Rate (Reference) | B26: 0.2725 | C26: ← Edit
A27: Financial Year Note | B27: July 1 – June 30 (Note: model uses Dec) | C27: Auto
A29: SECTION 4 — REPORT & PREPARER INFORMATION
A30: Prepared By | B30: Financial Modeling Team | C30: ← Edit
A31: Reviewed By | B31: CFO | C31: ← Edit
A32: Preparation Date | B32: February 20, 2026 | C32: ← Edit
A33: Purpose | B33: Internal Planning & Analysis | C33: ← Edit
A34: Confidentiality | B34: CONFIDENTIAL — Internal Use Only | C34: ← Edit
A35: Contact Email | B35: finance@democompany.com | C35: ← Edit
A37: Note: Blue-text cells are editable inputs. Company Name (B4) flows to Dashboard and all sheet headers.

Sheet Scenarios
A1: SCENARIO DATA — COMPLETE ENGINE VALUES
A2: This sheet stores the full engine-computed data for each scenario. All projection columns in Assumptions reference this sheet via IF formulas.
A4: ▎ BASE CASE · Moderate growth with stable margins
A5: Assumption / Computed Value | B5: 2023 | C5: 2024 | D5: 2025E | E5: 2026E | F5: 2027E | G5: 2028E | H5: 2029E
A6: ── Income Statement Drivers ──
A7: Revenue Base (Historical) | B7: 850000 | C7: 0 | D7: 0 | E7: 0 | F7: 0 | G7: 0 | H7: 0
A8: Revenue Base (Projection) | B8: 1000000 | C8: 0 | D8: 0 | E8: 0 | F8: 0 | G8: 0 | H8: 0
A9: Revenue Growth Rate | B9: 0 | C9: 0.11764706 | D9: 0.1 | E9: 0.08 | F9: 0.07 | G9: 0.06 | H9: 0.05
A10: COGS % of Revenue | B10: 0.6 | C10: 0.6 | D10: 0.6 | E10: 0.6 | F10: 0.6 | G10: 0.6 | H10: 0.6
A11: SG&A % of Revenue | B11: 0.15 | C11: 0.15 | D11: 0.15 | E11: 0.15 | F11: 0.15 | G11: 0.15 | H11: 0.15
A12: R&D % of Revenue | B12: 0.05 | C12: 0.05 | D12: 0.05 | E12: 0.05 | F12: 0.05 | G12: 0.05 | H12: 0.05
A13: Other OpEx % of Revenue | B13: 0.02 | C13: 0.02 | D13: 0.02 | E13: 0.02 | F13: 0.02 | G13: 0.02 | H13: 0.02
A14: Tax Rate | B14: 0.25230415 | C14: 0.25201613 | D14: 0.25 | E14: 0.25 | F14: 0.25 | G14: 0.25 | H14: 0.25
A15: Other Income / Expense | B15: 0 | C15: 0 | D15: 0 | E15: 0 | F15: 0 | G15: 0 | H15: 0
A16: Shares Outstanding | B16: 100000 | C16: 100000 | D16: 100000 | E16: 100000 | F16: 100000 | G16: 100000 | H16: 100000
A17: Stock-Based Comp Amount | B17: 0 | C17: 0 | D17: 10000 | E17: 10000 | F17: 10000 | G17: 10000 | H17: 10000
A18: ── Balance Sheet / WC Drivers ──
A19: DSO (Days) | B19: 45.000206 | C19: 44.999889 | D19: 45 | E19: 45 | F19: 45 | G19: 45 | H19: 45
A20: DIO (Days) | B20: 30.000137 | C20: 29.999798 | D20: 30 | E20: 30 | F20: 30 | G20: 30 | H20: 30
A21: DPO (Days) | B21: 39.999706 | C21: 40.000158 | D21: 40 | E21: 40 | F21: 40 | G21: 40 | H21: 40
A22: Prepaid % of Revenue | B22: 0.01 | C22: 0.01 | D22: 0.01 | E22: 0.01 | F22: 0.01 | G22: 0.01 | H22: 0.01
A23: Accrued Exp % of Revenue | B23: 0.03 | C23: 0.03 | D23: 0.03 | E23: 0.03 | F23: 0.03 | G23: 0.03 | H23: 0.03
A24: Deferred Rev % of Revenue | B24: 0.02 | C24: 0.02 | D24: 0.02 | E24: 0.02 | F24: 0.02 | G24: 0.02 | H24: 0.02
A25: ── CapEx & Depreciation ──
A26: CapEx % of Revenue | B26: 0 | C26: 0.047368421 | D26: 0.05 | E26: 0.05 | F26: 0.05 | G26: 0.05 | H26: 0.05
A27: Depreciation Rate (% Gross PPE) | B27: 0.082352941 | C27: 0.083116883 | D27: 0.1 | E27: 0.1 | F27: 0.1 | G27: 0.1 | H27: 0.1
A28: Amortization Amount | B28: 5000 | C28: 5000 | D28: 5000 | E28: 5000 | F28: 5000 | G28: 5000 | H28: 5000
A29: ── Debt & Financing ──
A30: Interest Rate (on Debt) | B30: 0.05 | C30: 0.05 | D30: 0.05 | E30: 0.05 | F30: 0.05 | G30: 0.05 | H30: 0.05
A31: Interest Income Rate (on Cash) | B31: 0.02 | C31: 0.02 | D31: 0.02 | E31: 0.02 | F31: 0.02 | G31: 0.02 | H31: 0.02
A32: Short-Term Debt | B32: 50000 | C32: 50000 | D32: 50000 | E32: 50000 | F32: 50000 | G32: 50000 | H32: 50000
A33: LT Debt Issuance | B33: 0 | C33: 0 | D33: 0 | E33: 0 | F33: 0 | G33: 0 | H33: 0
A34: LT Debt Repayment | B34: 0 | C34: 20000 | D34: 20000 | E34: 20000 | F34: 20000 | G34: 20000 | H34: 20000
A35: Current Portion LTD | B35: 20000 | C35: 20000 | D35: 20000 | E35: 20000 | F35: 20000 | G35: 20000 | H35: 20000
A36: Dividend Payout Ratio | B36: 0 | C36: 0.46433423 | D36: 0.3 | E36: 0.3 | F36: 0.3 | G36: 0.3 | H36: 0.3
A37: Share Repurchase Amount | B37: 0 | C37: 0 | D37: 0 | E37: 0 | F37: 0 | G37: 0 | H37: 0
A38: Equity Issuance | B38: 0 | C38: 10000 | D38: 0 | E38: 0 | F38: 0 | G38: 0 | H38: 0
A39: ── BS / Equity Direct Values ──
A40: Goodwill | B40: 100000 | C40: 100000 | D40: 100000 | E40: 100000 | F40: 100000 | G40: 100000 | H40: 100000
A41: Other Current Assets | B41: 10000 | C41: 10000 | D41: 10000 | E41: 10000 | F41: 10000 | G41: 10000 | H41: 10000
A42: Other Long-Term Assets | B42: 20000 | C42: 20000 | D42: 20000 | E42: 20000 | F42: 20000 | G42: 20000 | H42: 20000
A43: Other Current Liabilities | B43: 15000 | C43: 15000 | D43: 15000 | E43: 15000 | F43: 15000 | G43: 15000 | H43: 15000
A44: Deferred Tax Liabilities | B44: 30000 | C44: 30000 | D44: 30000 | E44: 30000 | F44: 30000 | G44: 30000 | H44: 30000
A45: Other LT Liabilities | B45: 25000 | C45: 25000 | D45: 25000 | E45: 25000 | F45: 25000 | G45: 25000 | H45: 25000
A46: Common Stock | B46: 10000 | C46: 10000 | D46: 10000 | E46: 10000 | F46: 10000 | G46: 10000 | H46: 10000
A47: APIC | B47: 210000 | C47: 220000 | D47: 200000 | E47: 200000 | F47: 200000 | G47: 200000 | H47: 200000
A48: Other Comprehensive Income | B48: 0 | C48: 0 | D48: 0 | E48: 0 | F48: 0 | G48: 0 | H48: 0
A49: ── Engine-Computed Values ──
A50: Interest Income (Computed) | B50: 2500 | C50: 3000 | D50: 4420.376 | E50: 5341.8586 | F50: 6420.9591 | G50: 7654.8346 | H50: 9044.4367
A51: Interest Expense (Computed) | B51: 14000 | C51: 13000 | D51: 13500 | E51: 12500 | F51: 11500 | G51: 10500 | H51: 9500
A52: Depreciation (Computed) | B52: 28000 | C52: 32000 | D52: 41112.5 | E52: 46546.5 | F52: 52387.005 | G52: 58606.155 | H52: 65166.453
A53: Gross PP&E (Computed) | B53: 340000 | C53: 385000 | D53: 437250 | E53: 493680 | F53: 554060.1 | G53: 618063.01 | H53: 685266.06
A54: Accum Depreciation (Computed) | B54: 128000 | C54: 160000 | D54: 201112.5 | E54: 247659 | F54: 300046.01 | G54: 358652.16 | H54: 423818.61
A55: Net PP&E (Computed) | B55: 212000 | C55: 225000 | D55: 236137.5 | E55: 246021 | F55: 254014.09 | G55: 259410.85 | H55: 261447.44
A56: Intangibles (Computed) | B56: 45000 | C56: 40000 | D56: 35000 | E56: 30000 | F56: 25000 | G56: 20000 | H56: 15000
A57: Long-Term Debt (Computed) | B57: 230000 | C57: 210000 | D57: 190000 | E57: 170000 | F57: 150000 | G57: 130000 | H57: 110000
A58: Retained Earnings (Computed) | B58: 28823 | C58: 78506 | D58: 143032.63 | E58: 213615.4 | F58: 289689.11 | G58: 370517.66 | H58: 455204.87
A59: Treasury Stock (Computed) | B59: 0 | C59: 0 | D59: 0 | E59: 0 | F59: 0 | G59: 0 | H59: 0
A60: APIC (Computed) | B60: 210000 | C60: 220000 | D60: 230000 | E60: 240000 | F60: 250000 | G60: 260000 | H60: 270000
A61: Dividends Paid (Computed) | B61: 0 | C61: -43067 | D61: -27654.272 | E61: -30249.756 | F61: -32603.021 | G61: -34640.807 | H61: -36294.518
... A65: Asset Sales (Computed) | B65: 0 | C65: 0 | D65: 0 | E65: 0 | F65: 0 | G65: 0 | H65: 0
A67: ▎ OPTIMISTIC · High growth with margin expansion
A68: Assumption / Computed Value | B68: 2023 | C68: 2024 | D68: 2025E | E68: 2026E | F68: 2027E | G68: 2028E | H68: 2029E
A69: ── Income Statement Drivers ──
A70: Revenue Base (Historical) | B70: 850000 | C70: 0 | D70: 0 | E70: 0 | F70: 0 | G70: 0 | H70: 0
A71: Revenue Base (Projection) | B71: 1000000 | C71: 0 | D71: 0 | E71: 0 | F71: 0 | G71: 0 | H71: 0
A72: Revenue Growth Rate | B72: 0 | C72: 0.11764706 | D72: 0.15 | E72: 0.13 | F72: 0.12 | G72: 0.1 | H72: 0.08
A73: COGS % of Revenue | B73: 0.6 | C73: 0.6 | D73: 0.58 | E73: 0.57 | F73: 0.56 | G73: 0.55 | H73: 0.55
A74: SG&A % of Revenue | B74: 0.15 | C74: 0.15 | D74: 0.14 | E74: 0.13 | F74: 0.13 | G74: 0.12 | H74: 0.12
A75: R&D % of Revenue | B75: 0.05 | C75: 0.05 | D75: 0.05 | E75: 0.05 | F75: 0.05 | G75: 0.04 | H75: 0.04
A76: Other OpEx % of Revenue | B76: 0.02 | C76: 0.02 | D76: 0.02 | E76: 0.02 | F76: 0.02 | G76: 0.02 | H76: 0.02
A77: Tax Rate | B77: 0.25230415 | C77: 0.25201613 | D77: 0.25 | E77: 0.25 | F77: 0.25 | G77: 0.25 | H77: 0.25
A78: Other Income / Expense | B78: 0 | C78: 0 | D78: 0 | E78: 0 | F78: 0 | G78: 0 | H78: 0
A79: Shares Outstanding | B79: 100000 | C79: 100000 | D79: 100000 | E79: 100000 | F79: 100000 | G79: 100000 | H79: 100000
A80: Stock-Based Comp Amount | B80: 0 | C80: 0 | D80: 10000 | E80: 10000 | F80: 10000 | G80: 10000 | H80: 10000
A81: ── Balance Sheet / WC Drivers ──
A82: DSO (Days) | B82: 45.000206 | C82: 44.999889 | D82: 45 | E82: 45 | F82: 45 | G82: 45 | H82: 45
A83: DIO (Days) | B83: 30.000137 | C83: 29.999798 | D83: 30 | E83: 30 | F83: 30 | G83: 30 | H83: 30
A84: DPO (Days) | B84: 39.999706 | C84: 40.000158 | D84: 40 | E84: 40 | F84: 40 | G84: 40 | H84: 40
A85: Prepaid % of Revenue | B85: 0.01 | C85: 0.01 | D85: 0.01 | E85: 0.01 | F85: 0.01 | G85: 0.01 | H85: 0.01
A86: Accrued Exp % of Revenue | B86: 0.03 | C86: 0.03 | D86: 0.03 | E86: 0.03 | F86: 0.03 | G86: 0.03 | H86: 0.03
A87: Deferred Rev % of Revenue | B87: 0.02 | C87: 0.02 | D87: 0.02 | E87: 0.02 | F87: 0.02 | G87: 0.02 | H87: 0.02
A88: ── CapEx & Depreciation ──
A89: CapEx % of Revenue | B89: 0 | C89: 0.047368421 | D89: 0.06 | E89: 0.06 | F89: 0.05 | G89: 0.05 | H89: 0.05
A90: Depreciation Rate (% Gross PPE) | B90: 0.082352941 | C90: 0.083116883 | D90: 0.1 | E90: 0.1 | F90: 0.1 | G90: 0.1 | H90: 0.1
A91: Amortization Amount | B91: 5000 | C91: 5000 | D91: 5000 | E91: 5000 | F91: 5000 | G91: 5000 | H91: 5000
A92: ── Debt & Financing ──
A93: Interest Rate (on Debt) | B93: 0.05 | C93: 0.05 | D93: 0.05 | E93: 0.05 | F93: 0.05 | G93: 0.05 | H93: 0.05
A94: Interest Income Rate (on Cash) | B94: 0.02 | C94: 0.02 | D94: 0.02 | E94: 0.02 | F94: 0.02 | G94: 0.02 | H94: 0.02
A95: Short-Term Debt | B95: 50000 | C95: 50000 | D95: 50000 | E95: 50000 | F95: 50000 | G95: 50000 | H95: 50000
A96: LT Debt Issuance | B96: 0 | C96: 0 | D96: 0 | E96: 0 | F96: 0 | G96: 0 | H96: 0
A97: LT Debt Repayment | B97: 0 | C97: 20000 | D97: 20000 | E97: 20000 | F97: 20000 | G97: 20000 | H97: 20000
A98: Current Portion LTD | B98: 20000 | C98: 20000 | D98: 20000 | E98: 20000 | F98: 20000 | G98: 20000 | H98: 20000
A99: Dividend Payout Ratio | B99: 0 | C99: 0.46433423 | D99: 0.3 | E99: 0.3 | F99: 0.3 | G99: 0.3 | H99: 0.3
A100: Share Repurchase Amount | B100: 0 | C100: 0 | D100: 0 | E100: 0 | F100: 0 | G100: 0 | H100: 0
A101: Equity Issuance | B101: 0 | C101: 10000 | D101: 0 | E101: 0 | F101: 0 | G101: 0 | H101: 0
A102: ── BS / Equity Direct Values ──
A103: Goodwill | B103: 100000 | C103: 100000 | D103: 100000 | E103: 100000 | F103: 100000 | G103: 100000 | H103: 100000
A104: Other Current Assets | B104: 10000 | C104: 10000 | D104: 10000 | E104: 10000 | F104: 10000 | G104: 10000 | H104: 10000
A105: Other Long-Term Assets | B105: 20000 | C105: 20000 | D105: 20000 | E105: 20000 | F105: 20000 | G105: 20000 | H105: 20000
...

Sheet Assumptions
A1: Assumption | B1: 2023 | C1: 2024 | D1: 2025E | E1: 2026E | F1: 2027E | G1: 2028E | H1: 2029E
A2: ── Income Statement Drivers ──
A3: Revenue Base (Historical) | B3: 850000 | D3: =IF(Assumptions!$B$64="Base Case",Scenarios!D7,IF(Assumptions!$B$64="Optimistic",Scenarios!D70,Scenarios!D133)) -> 0 | E3: =IF(Assumptions!$B$64="Base Case",Scenarios!E7,IF(Assumptions!$B$64="Optimistic",Scenarios!E70,Scenarios!E133)) -> 0 | F3: =IF(Assumptions!$B$64="Base Case",Scenarios!F7,IF(Assumptions!$B$64="Optimistic",Scenarios!F70,Scenarios!F133)) -> 0 | G3: =IF(Assumptions!$B$64="Base Case",Scenarios!G7,IF(Assumptions!$B$64="Optimistic",Scenarios!G70,Scenarios!G133)) -> 0 | H3: =IF(Assumptions!$B$64="Base Case",Scenarios!H7,IF(Assumptions!$B$64="Optimistic",Scenarios!H70,Scenarios!H133)) -> 0
A4: Revenue Base (Projection) | B4: 1000000 | D4: =IF(Assumptions!$B$64="Base Case",Scenarios!D8,IF(Assumptions!$B$64="Optimistic",Scenarios!D71,Scenarios!D134)) -> 0 | E4: =IF(Assumptions!$B$64="Base Case",Scenarios!E8,IF(Assumptions!$B$64="Optimistic",Scenarios!E71,Scenarios!E134)) -> 0 | F4: =IF(Assumptions!$B$64="Base Case",Scenarios!F8,IF(Assumptions!$B$64="Optimistic",Scenarios!F71,Scenarios!F134)) -> 0 | G4: =IF(Assumptions!$B$64="Base Case",Scenarios!G8,IF(Assumptions!$B$64="Optimistic",Scenarios!G71,Scenarios!G134)) -> 0 | H4: =IF(Assumptions!$B$64="Base Case",Scenarios!H8,IF(Assumptions!$B$64="Optimistic",Scenarios!H71,Scenarios!H134)) -> 0
A5: Revenue Growth Rate | B5: 0 | C5: 0.11764706 | D5: =IF(Assumptions!$B$64="Base Case",Scenarios!D9,IF(Assumptions!$B$64="Optimistic",Scenarios!D72,Scenarios!D135)) -> 0.1 | E5: =IF(Assumptions!$B$64="Base Case",Scenarios!E9,IF(Assumptions!$B$64="Optimistic",Scenarios!E72,Scenarios!E135)) -> 0.08 | F5: =IF(Assumptions!$B$64="Base Case",Scenarios!F9,IF(Assumptions!$B$64="Optimistic",Scenarios!F72,Scenarios!F135)) -> 0.07 | G5: =IF(Assumptions!$B$64="Base Case",Scenarios!G9,IF(Assumptions!$B$64="Optimistic",Scenarios!G72,Scenarios!G135)) -> 0.06 | H5: =IF(Assumptions!$B$64="Base Case",Scenarios!H9,IF(Assumptions!$B$64="Optimistic",Scenarios!H72,Scenarios!H135)) -> 0.05
A6: COGS % of Revenue | B6: 0.6 | C6: 0.6 | D6: =IF(Assumptions!$B$64="Base Case",Scenarios!D10,IF(Assumptions!$B$64="Optimistic",Scenarios!D73,Scenarios!D136)) -> 0.6 | E6: =IF(Assumptions!$B$64="Base Case",Scenarios!E10,IF(Assumptions!$B$64="Optimistic",Scenarios!E73,Scenarios!E136)) -> 0.6 | F6: =IF(Assumptions!$B$64="Base Case",Scenarios!F10,IF(Assumptions!$B$64="Optimistic",Scenarios!F73,Scenarios!F136)) -> 0.6 | G6: =IF(Assumptions!$B$64="Base Case",Scenarios!G10,IF(Assumptions!$B$64="Optimistic",Scenarios!G73,Scenarios!G136)) -> 0.6 | H6: =IF(Assumptions!$B$64="Base Case",Scenarios!H10,IF(Assumptions!$B$64="Optimistic",Scenarios!H73,Scenarios!H136)) -> 0.6
A7: SG&A % of Revenue | B7: 0.15 | C7: 0.15 | D7: =IF(Assumptions!$B$64="Base Case",Scenarios!D11,IF(Assumptions!$B$64="Optimistic",Scenarios!D74,Scenarios!D137)) -> 0.15 | E7: =IF(Assumptions!$B$64="Base Case",Scenarios!E11,IF(Assumptions!$B$64="Optimistic",Scenarios!E74,Scenarios!E137)) -> 0.15 | F7: =IF(Assumptions!$B$64="Base Case",Scenarios!F11,IF(Assumptions!$B$64="Optimistic",Scenarios!F74,Scenarios!F137)) -> 0.15 | G7: =IF(Assumptions!$B$64="Base Case",Scenarios!G11,IF(Assumptions!$B$64="Optimistic",Scenarios!G74,Scenarios!G137)) -> 0.15 | H7: =IF(Assumptions!$B$64="Base Case",Scenarios!H11,IF(Assumptions!$B$64="Optimistic",Scenarios!H74,Scenarios!H137)) -> 0.15
A8: R&D % of Revenue | B8: 0.05 | C8: 0.05 | D8: =IF(Assumptions!$B$64="Base Case",Scenarios!D12,IF(Assumptions!$B$64="Optimistic",Scenarios!D75,Scenarios!D138)) -> 0.05 | E8: =IF(Assumptions!$B$64="Base Case",Scenarios!E12,IF(Assumptions!$B$64="Optimistic",Scenarios!E75,Scenarios!E138)) -> 0.05 | F8: =IF(Assumptions!$B$64="Base Case",Scenarios!F12,IF(Assumptions!$B$64="Optimistic",Scenarios!F75,Scenarios!F138)) -> 0.05 | G8: =IF(Assumptions!$B$64="Base Case",Scenarios!G12,IF(Assumptions!$B$64="Optimistic",Scenarios!G75,Scenarios!G138)) -> 0.05 | H8: =IF(Assumptions!$B$64="Base Case",Scenarios!H12,IF(Assumptions!$B$64="Optimistic",Scenarios!H75,Scenarios!H138)) -> 0.05
A9: Other OpEx % of Revenue | B9: 0.02 | C9: 0.02 | D9: =IF(Assumptions!$B$64="Base Case",Scenarios!D13,IF(Assumptions!$B$64="Optimistic",Scenarios!D76,Scenarios!D139)) -> 0.02 | E9: =IF(Assumptions!$B$64="Base Case",Scenarios!E13,IF(Assumptions!$B$64="Optimistic",Scenarios!E76,Scenarios!E139)) -> 0.02 | F9: =IF(Assumptions!$B$64="Base Case",Scenarios!F13,IF(Assumptions!$B$64="Optimistic",Scenarios!F76,Scenarios!F139)) -> 0.02 | G9: =IF(Assumptions!$B$64="Base Case",Scenarios!G13,IF(Assumptions!$B$64="Optimistic",Scenarios!G76,Scenarios!G139)) -> 0.02 | H9: =IF(Assumptions!$B$64="Base Case",Scenarios!H13,IF(Assumptions!$B$64="Optimistic",Scenarios!H76,Scenarios!H139)) -> 0.02
A10: Tax Rate | B10: 0.25230415 | C10: 0.25201613 | D10: =IF(Assumptions!$B$64="Base Case",Scenarios!D14,IF(Assumptions!$B$64="Optimistic",Scenarios!D77,Scenarios!D140)) -> 0.25 | E10: =IF(Assumptions!$B$64="Base Case",Scenarios!E14,IF(Assumptions!$B$64="Optimistic",Scenarios!E77,Scenarios!E140)) -> 0.25 | F10: =IF(Assumptions!$B$64="Base Case",Scenarios!F14,IF(Assumptions!$B$64="Optimistic",Scenarios!F77,Scenarios!F140)) -> 0.25 | G10: =IF(Assumptions!$B$64="Base Case",Scenarios!G14,IF(Assumptions!$B$64="Optimistic",Scenarios!G77,Scenarios!G140)) -> 0.25 | H10: =IF(Assumptions!$B$64="Base Case",Scenarios!H14,IF(Assumptions!$B$64="Optimistic",Scenarios!H77,Scenarios!H140)) -> 0.25
A11: Other Income / Expense | B11: 0 | C11: 0 | D11: =IF(Assumptions!$B$64="Base Case",Scenarios!D15,IF(Assumptions!$B$64="Optimistic",Scenarios!D78,Scenarios!D141)) -> 0 | E11: =IF(Assumptions!$B$64="Base Case",Scenarios!E15,IF(Assumptions!$B$64="Optimistic",Scenarios!E78,Scenarios!E141)) -> 0 | F11: =IF(Assumptions!$B$64="Base Case",Scenarios!F15,IF(Assumptions!$B$64="Optimistic",Scenarios!F78,Scenarios!F141)) -> 0 | G11: =IF(Assumptions!$B$64="Base Case",Scenarios!G15,IF(Assumptions!$B$64="Optimistic",Scenarios!G78,Scenarios!G141)) -> 0 | H11: =IF(Assumptions!$B$64="Base Case",Scenarios!H15,IF(Assumptions!$B$64="Optimistic",Scenarios!H78,Scenarios!H141)) -> 0
A12: Shares Outstanding | B12: 100000 | C12: 100000 | D12: =IF(Assumptions!$B$64="Base Case",Scenarios!D16,IF(Assumptions!$B$64="Optimistic",Scenarios!D79,Scenarios!D142)) -> 100000 | E12: =IF(Assumptions!$B$64="Base Case",Scenarios!E16,IF(Assumptions!$B$64="Optimistic",Scenarios!E79,Scenarios!E142)) -> 100000 | F12: =IF(Assumptions!$B$64="Base Case",Scenarios!F16,IF(Assumptions!$B$64="Optimistic",Scenarios!F79,Scenarios!F142)) -> 100000 | G12: =IF(Assumptions!$B$64="Base Case",Scenarios!G16,IF(Assumptions!$B$64="Optimistic",Scenarios!G79,Scenarios!G142)) -> 100000 | H12: =IF(Assumptions!$B$64="Base Case",Scenarios!H16,IF(Assumptions!$B$64="Optimistic",Scenarios!H79,Scenarios!H142)) -> 100000
A13: Stock-Based Comp Amount | B13: 0 | C13: 0 | D13: =IF(Assumptions!$B$64="Base Case",Scenarios!D17,IF(Assumptions!$B$64="Optimistic",Scenarios!D80,Scenarios!D143)) -> 10000 | E13: =IF(Assumptions!$B$64="Base Case",Scenarios!E17,IF(Assumptions!$B$64="Optimistic",Scenarios!E80,Scenarios!E143)) -> 10000 | F13: =IF(Assumptions!$B$64="Base Case",Scenarios!F17,IF(Assumptions!$B$64="Optimistic",Scenarios!F80,Scenarios!F143)) -> 10000 | G13: =IF(Assumptions!$B$64="Base Case",Scenarios!G17,IF(Assumptions!$B$64="Optimistic",Scenarios!G80,Scenarios!G143)) -> 10000 | H13: =IF(Assumptions!$B$64="Base Case",Scenarios!H17,IF(Assumptions!$B$64="Optimistic",Scenarios!H80,Scenarios!H143)) -> 10000
A14: ── Balance Sheet / WC Drivers ──
A15: DSO (Days) | B15: 45.000206 | C15: 44.999889 | D15: =IF(Assumptions!$B$64="Base Case",Scenarios!D19,IF(Assumptions!$B$64="Optimistic",Scenarios!D82,Scenarios!D145)) -> 45 | E15: =IF(Assumptions!$B$64="Base Case",Scenarios!E19,IF(Assumptions!$B$64="Optimistic",Scenarios!E82,Scenarios!E145)) -> 45 | F15: =IF(Assumptions!$B$64="Base Case",Scenarios!F19,IF(Assumptions!$B$64="Optimistic",Scenarios!F82,Scenarios!F145)) -> 45 | G15: =IF(Assumptions!$B$64="Base Case",Scenarios!G19,IF(Assumptions!$B$64="Optimistic",Scenarios!G82,Scenarios!G145)) -> 45 | H15: =IF(Assumptions!$B$64="Base Case",Scenarios!H19,IF(Assumptions!$B$64="Optimistic",Scenarios!H82,Scenarios!H145)) -> 45
A16: DIO (Days) | B16: 30.000137 | C16: 29.999798 | D16: =IF(Assumptions!$B$64="Base Case",Scenarios!D20,IF(Assumptions!$B$64="Optimistic",Scenarios!D83,Scenarios!D146)) -> 30 | E16: =IF(Assumptions!$B$64="Base Case",Scenarios!E20,IF(Assumptions!$B$64="Optimistic",Scenarios!E83,Scenarios!E146)) -> 30 | F16: =IF(Assumptions!$B$64="Base Case",Scenarios!F20,IF(Assumptions!$B$64="Optimistic",Scenarios!F83,Scenarios!F146)) -> 30 | G16: =IF(Assumptions!$B$64="Base Case",Scenarios!G20,IF(Assumptions!$B$64="Optimistic",Scenarios!G83,Scenarios!G146)) -> 30 | H16: =IF(Assumptions!$B$64="Base Case",Scenarios!H20,IF(Assumptions!$B$64="Optimistic",Scenarios!H83,Scenarios!H146)) -> 30
A17: DPO (Days) | B17: 39.999706 | C17: 40.000158 | D17: =IF(Assumptions!$B$64="Base Case",Scenarios!D21,IF(Assumptions!$B$64="Optimistic",Scenarios!D84,Scenarios!D147)) -> 40 | E17: =IF(Assumptions!$B$64="Base Case",Scenarios!E21,IF(Assumptions!$B$64="Optimistic",Scenarios!E84,Scenarios!E147)) -> 40 | F17: =IF(Assumptions!$B$64="Base Case",Scenarios!F21,IF(Assumptions!$B$64="Optimistic",Scenarios!F84,Scenarios!F147)) -> 40 | G17: =IF(Assumptions!$B$64="Base Case",Scenarios!G21,IF(Assumptions!$B$64="Optimistic",Scenarios!G84,Scenarios!G147)) -> 40 | H17: =IF(Assumptions!$B$64="Base Case",Scenarios!H21,IF(Assumptions!$B$64="Optimistic",Scenarios!H84,Scenarios!H147)) -> 40
A18: Prepaid % of Revenue | B18: 0.01 | C18: 0.01 | D18: =IF(Assumptions!$B$64="Base Case",Scenarios!D22,IF(Assumptions!$B$64="Optimistic",Scenarios!D85,Scenarios!D148)) -> 0.01 | E18: =IF(Assumptions!$B$64="Base Case",Scenarios!E22,IF(Assumptions!$B$64="Optimistic",Scenarios!E85,Scenarios!E148)) -> 0.01 | F18: =IF(Assumptions!$B$64="Base Case",Scenarios!F22,IF(Assumptions!$B$64="Optimistic",Scenarios!F85,Scenarios!F148)) -> 0.01 | G18: =IF(Assumptions!$B$64="Base Case",Scenarios!G22,IF(Assumptions!$B$64="Optimistic",Scenarios!G85,Scenarios!G148)) -> 0.01 | H18: =IF(Assumptions!$B$64="Base Case",Scenarios!H22,IF(Assumptions!$B$64="Optimistic",Scenarios!H85,Scenarios!H148)) -> 0.01
A19: Accrued Exp % of Revenue | B19: 0.03 | C19: 0.03 | D19: =IF(Assumptions!$B$64="Base Case",Scenarios!D23,IF(Assumptions!$B$64="Optimistic",Scenarios!D86,Scenarios!D149)) -> 0.03 | E19: =IF(Assumptions!$B$64="Base Case",Scenarios!E23,IF(Assumptions!$B$64="Optimistic",Scenarios!E86,Scenarios!E149)) -> 0.03 | F19: =IF(Assumptions!$B$64="Base Case",Scenarios!F23,IF(Assumptions!$B$64="Optimistic",Scenarios!F86,Scenarios!F149)) -> 0.03 | G19: =IF(Assumptions!$B$64="Base Case",Scenarios!G23,IF(Assumptions!$B$64="Optimistic",Scenarios!G86,Scenarios!G149)) -> 0.03 | H19: =IF(Assumptions!$B$64="Base Case",Scenarios!H23,IF(Assumptions!$B$64="Optimistic",Scenarios!H86,Scenarios!H149)) -> 0.03
A20: Deferred Rev % of Revenue | B20: 0.02 | C20: 0.02 | D20: =IF(Assumptions!$B$64="Base Case",Scenarios!D24,IF(Assumptions!$B$64="Optimistic",Scenarios!D87,Scenarios!D150)) -> 0.02 | E20: =IF(Assumptions!$B$64="Base Case",Scenarios!E24,IF(Assumptions!$B$64="Optimistic",Scenarios!E87,Scenarios!E150)) -> 0.02 | F20: =IF(Assumptions!$B$64="Base Case",Scenarios!F24,IF(Assumptions!$B$64="Optimistic",Scenarios!F87,Scenarios!F150)) -> 0.02 | G20: =IF(Assumptions!$B$64="Base Case",Scenarios!G24,IF(Assumptions!$B$64="Optimistic",Scenarios!G87,Scenarios!G150)) -> 0.02 | H20: =IF(Assumptions!$B$64="Base Case",Scenarios!H24,IF(Assumptions!$B$64="Optimistic",Scenarios!H87,Scenarios!H150)) -> 0.02
A21: ── CapEx & Depreciation Drivers ──
A22: CapEx % of Revenue | B22: 0 | C22: 0.047368421 | D22: =IF(Assumptions!$B$64="Base Case",Scenarios!D26,IF(Assumptions!$B$64="Optimistic",Scenarios!D89,Scenarios!D152)) -> 0.05 | E22: =IF(Assumptions!$B$64="Base Case",Scenarios!E26,IF(Assumptions!$B$64="Optimistic",Scenarios!E89,Scenarios!E152)) -> 0.05 | F22: =IF(Assumptions!$B$64="Base Case",Scenarios!F26,IF(Assumptions!$B$64="Optimistic",Scenarios!F89,Scenarios!F152)) -> 0.05 | G22: =IF(Assumptions!$B$64="Base Case",Scenarios!G26,IF(Assumptions!$B$64="Optimistic",Scenarios!G89,Scenarios!G152)) -> 0.05 | H22: =IF(Assumptions!$B$64="Base Case",Scenarios!H26,IF(Assumptions!$B$64="Optimistic",Scenarios!H89,Scenarios!H152)) -> 0.05
A23: Depreciation Rate (% Gross PPE) | B23: 0.082352941 | C23: 0.083116883 | D23: =IF(Assumptions!$B$64="Base Case",Scenarios!D27,IF(Assumptions!$B$64="Optimistic",Scenarios!D90,Scenarios!D153)) -> 0.1 | E23: =IF(Assumptions!$B$64="Base Case",Scenarios!E27,IF(Assumptions!$B$64="Optimistic",Scenarios!E90,Scenarios!E153)) -> 0.1 | F23: =IF(Assumptions!$B$64="Base Case",Scenarios!F27,IF(Assumptions!$B$64="Optimistic",Scenarios!F90,Scenarios!F153)) -> 0.1 | G23: =IF(Assumptions!$B$64="Base Case",Scenarios!G27,IF(Assumptions!$B$64="Optimistic",Scenarios!G90,Scenarios!G153)) -> 0.1 | H23: =IF(Assumptions!$B$64="Base Case",Scenarios!H27,IF(Assumptions!$B$64="Optimistic",Scenarios!H90,Scenarios!H153)) -> 0.1
A24: Amortization Amount | B24: 5000 | C24: 5000 | D24: =IF(Assumptions!$B$64="Base Case",Scenarios!D28,IF(Assumptions!$B$64="Optimistic",Scenarios!D91,Scenarios!D154)) -> 5000 | E24: =IF(Assumptions!$B$64="Base Case",Scenarios!E28,IF(Assumptions!$B$64="Optimistic",Scenarios!E91,Scenarios!E154)) -> 5000 | F24: =IF(Assumptions!$B$64="Base Case",Scenarios!F28,IF(Assumptions!$B$64="Optimistic",Scenarios!F91,Scenarios!F154)) -> 5000 | G24: =IF(Assumptions!$B$64="Base Case",Scenarios!G28,IF(Assumptions!$B$64="Optimistic",Scenarios!G91,Scenarios!G154)) -> 5000 | H24: =IF(Assumptions!$B$64="Base Case",Scenarios!H28,IF(Assumptions!$B$64="Optimistic",Scenarios!H91,Scenarios!H154)) -> 5000
A25: ── Debt & Financing ──
A26: Interest Rate (on Debt) | B26: 0.05 | C26: 0.05 | D26: =IF(Assumptions!$B$64="Base Case",Scenarios!D30,IF(Assumptions!$B$64="Optimistic",Scenarios!D93,Scenarios!D156)) -> 0.05 | E26: =IF(Assumptions!$B$64="Base Case",Scenarios!E30,IF(Assumptions!$B$64="Optimistic",Scenarios!E93,Scenarios!E156)) -> 0.05 | F26: =IF(Assumptions!$B$64="Base Case",Scenarios!F30,IF(Assumptions!$B$64="Optimistic",Scenarios!F93,Scenarios!F156)) -> 0.05 | G26: =IF(Assumptions!$B$64="Base Case",Scenarios!G30,IF(Assumptions!$B$64="Optimistic",Scenarios!G93,Scenarios!G156)) -> 0.05 | H26: =IF(Assumptions!$B$64="Base Case",Scenarios!H30,IF(Assumptions!$B$64="Optimistic",Scenarios!H93,Scenarios!H156)) -> 0.05
A27: Interest Income Rate (on Cash) | B27: 0.02 | C27: 0.02 | D27: =IF(Assumptions!$B$64="Base Case",Scenarios!D31,IF(Assumptions!$B$64="Optimistic",Scenarios!D94,Scenarios!D157)) -> 0.02 | E27: =IF(Assumptions!$B$64="Base Case",Scenarios!E31,IF(Assumptions!$B$64="Optimistic",Scenarios!E94,Scenarios!E157)) -> 0.02 | F27: =IF(Assumptions!$B$64="Base Case",Scenarios!F31,IF(Assumptions!$B$64="Optimistic",Scenarios!F94,Scenarios!F157)) -> 0.02 | G27: =IF(Assumptions!$B$64="Base Case",Scenarios!G31,IF(Assumptions!$B$64="Optimistic",Scenarios!G94,Scenarios!G157)) -> 0.02 | H27: =IF(Assumptions!$B$64="Base Case",Scenarios!H31,IF(Assumptions!$B$64="Optimistic",Scenarios!H94,Scenarios!H157)) -> 0.02
A28: Short-Term Debt | B28: 50000 | C28: 50000 | D28: =IF(Assumptions!$B$64="Base Case",Scenarios!D32,IF(Assumptions!$B$64="Optimistic",Scenarios!D95,Scenarios!D158)) -> 50000 | E28: =IF(Assumptions!$B$64="Base Case",Scenarios!E32,IF(Assumptions!$B$64="Optimistic",Scenarios!E95,Scenarios!E158)) -> 50000 | F28: =IF(Assumptions!$B$64="Base Case",Scenarios!F32,IF(Assumptions!$B$64="Optimistic",Scenarios!F95,Scenarios!F158)) -> 50000 | G28: =IF(Assumptions!$B$64="Base Case",Scenarios!G32,IF(Assumptions!$B$64="Optimistic",Scenarios!G95,Scenarios!G158)) -> 50000 | H28: =IF(Assumptions!$B$64="Base Case",Scenarios!H32,IF(Assumptions!$B$64="Optimistic",Scenarios!H95,Scenarios!H158)) -> 50000
A29: LT Debt Issuance | B29: 0 | C29: 0 | D29: =IF(Assumptions!$B$64="Base Case",Scenarios!D33,IF(Assumptions!$B$64="Optimistic",Scenarios!D96,Scenarios!D159)) -> 0 | E29: =IF(Assumptions!$B$64="Base Case",Scenarios!E33,IF(Assumptions!$B$64="Optimistic",Scenarios!E96,Scenarios!E159)) -> 0 | F29: =IF(Assumptions!$B$64="Base Case",Scenarios!F33,IF(Assumptions!$B$64="Optimistic",Scenarios!F96,Scenarios!F159)) -> 0 | G29: =IF(Assumptions!$B$64="Base Case",Scenarios!G33,IF(Assumptions!$B$64="Optimistic",Scenarios!G96,Scenarios!G159)) -> 0 | H29: =IF(Assumptions!$B$64="Base Case",Scenarios!H33,IF(Assumptions!$B$64="Optimistic",Scenarios!H96,Scenarios!H159)) -> 0
A30: LT Debt Repayment | B30: 0 | C30: 20000 | D30: =IF(Assumptions!$B$64="Base Case",Scenarios!D34,IF(Assumptions!$B$64="Optimistic",Scenarios!D97,Scenarios!D160)) -> 20000 | E30: =IF(Assumptions!$B$64="Base Case",Scenarios!E34,IF(Assumptions!$B$64="Optimistic",Scenarios!E97,Scenarios!E160)) -> 20000 | F30: =IF(Assumptions!$B$64="Base Case",Scenarios!F34,IF(Assumptions!$B$64="Optimistic",Scenarios!F97,Scenarios!F160)) -> 20000 | G30: =IF(Assumptions!$B$64="Base Case",Scenarios!G34,IF(Assumptions!$B$64="Optimistic",Scenarios!G97,Scenarios!G160)) -> 20000 | H30: =IF(Assumptions!$B$64="Base Case",Scenarios!H34,IF(Assumptions!$B$64="Optimistic",Scenarios!H97,Scenarios!H160)) -> 20000
A31: Current Portion LTD | B31: 20000 | C31: 20000 | D31: =IF(Assumptions!$B$64="Base Case",Scenarios!D35,IF(Assumptions!$B$64="Optimistic",Scenarios!D98,Scenarios!D161)) -> 20000 | E31: =IF(Assumptions!$B$64="Base Case",Scenarios!E35,IF(Assumptions!$B$64="Optimistic",Scenarios!E98,Scenarios!E161)) -> 20000 | F31: =IF(Assumptions!$B$64="Base Case",Scenarios!F35,IF(Assumptions!$B$64="Optimistic",Scenarios!F98,Scenarios!F161)) -> 20000 | G31: =IF(Assumptions!$B$64="Base Case",Scenarios!G35,IF(Assumptions!$B$64="Optimistic",Scenarios!G98,Scenarios!G161)) -> 20000 | H31: =IF(Assumptions!$B$64="Base Case",Scenarios!H35,IF(Assumptions!$B$64="Optimistic",Scenarios!H98,Scenarios!H161)) -> 20000
A32: Dividend Payout Ratio | B32: 0 | C32: 0.46433423 | D32: =IF(Assumptions!$B$64="Base Case",Scenarios!D36,IF(Assumptions!$B$64="Optimistic",Scenarios!D99,Scenarios!D162)) -> 0.3 | E32: =IF(Assumptions!$B$64="Base Case",Scenarios!E36,IF(Assumptions!$B$64="Optimistic",Scenarios!E99,Scenarios!E162)) -> 0.3 | F32: =IF(Assumptions!$B$64="Base Case",Scenarios!F36,IF(Assumptions!$B$64="Optimistic",Scenarios!F99,Scenarios!F162)) -> 0.3 | G32: =IF(Assumptions!$B$64="Base Case",Scenarios!G36,IF(Assumptions!$B$64="Optimistic",Scenarios!G99,Scenarios!G162)) -> 0.3 | H32: =IF(Assumptions!$B$64="Base Case",Scenarios!H36,IF(Assumptions!$B$64="Optimistic",Scenarios!H99,Scenarios!H162)) -> 0.3
A33: Share Repurchase Amount | B33: 0 | C33: 0 | D33: =IF(Assumptions!$B$64="Base Case",Scenarios!D37,IF(Assumptions!$B$64="Optimistic",Scenarios!D100,Scenarios!D163)) -> 0 | E33: =IF(Assumptions!$B$64="Base Case",Scenarios!E37,IF(Assumptions!$B$64="Optimistic",Scenarios!E100,Scenarios!E163)) -> 0 | F33: =IF(Assumptions!$B$64="Base Case",Scenarios!F37,IF(Assumptions!$B$64="Optimistic",Scenarios!F100,Scenarios!F163)) -> 0 | G33: =IF(Assumptions!$B$64="Base Case",Scenarios!G37,IF(Assumptions!$B$64="Optimistic",Scenarios!G100,Scenarios!G163)) -> 0 | H33: =IF(Assumptions!$B$64="Base Case",Scenarios!H37,IF(Assumptions!$B$64="Optimistic",Scenarios!H100,Scenarios!H163)) -> 0
A34: Equity Issuance | B34: 0 | C34: 10000 | D34: =IF(Assumptions!$B$64="Base Case",Scenarios!D38,IF(Assumptions!$B$64="Optimistic",Scenarios!D101,Scenarios!D164)) -> 0 | E34: =IF(Assumptions!$B$64="Base Case",Scenarios!E38,IF(Assumptions!$B$64="Optimistic",Scenarios!E101,Scenarios!E164)) -> 0 | F34: =IF(Assumptions!$B$64="Base Case",Scenarios!F38,IF(Assumptions!$B$64="Optimistic",Scenarios!F101,Scenarios!F164)) -> 0 | G34: =IF(Assumptions!$B$64="Base Case",Scenarios!G38,IF(Assumptions!$B$64="Optimistic",Scenarios!G101,Scenarios!G164)) -> 0 | H34: =IF(Assumptions!$B$64="Base Case",Scenarios!H38,IF(Assumptions!$B$64="Optimistic",Scenarios!H101,Scenarios!H164)) -> 0
A35: ── BS / Equity Direct Values ──
A36: Goodwill | B36: 100000 | C36: 100000 | D36: =IF(Assumptions!$B$64="Base Case",Scenarios!D40,IF(Assumptions!$B$64="Optimistic",Scenarios!D103,Scenarios!D166)) -> 100000 | E36: =IF(Assumptions!$B$64="Base Case",Scenarios!E40,IF(Assumptions!$B$64="Optimistic",Scenarios!E103,Scenarios!E166)) -> 100000 | F36: =IF(Assumptions!$B$64="Base Case",Scenarios!F40,IF(Assumptions!$B$64="Optimistic",Scenarios!F103,Scenarios!F166)) -> 100000 | G36: =IF(Assumptions!$B$64="Base Case",Scenarios!G40,IF(Assumptions!$B$64="Optimistic",Scenarios!G103,Scenarios!G166)) -> 100000 | H36: =IF(Assumptions!$B$64="Base Case",Scenarios!H40,IF(Assumptions!$B$64="Optimistic",Scenarios!H103,Scenarios!H166)) -> 100000
A37: Other Current Assets | B37: 10000 | C37: 10000 | D37: =IF(Assumptions!$B$64="Base Case",Scenarios!D41,IF(Assumptions!$B$64="Optimistic",Scenarios!D104,Scenarios!D167)) -> 10000 | E37: =IF(Assumptions!$B$64="Base Case",Scenarios!E41,IF(Assumptions!$B$64="Optimistic",Scenarios!E104,Scenarios!E167)) -> 10000 | F37: =IF(Assumptions!$B$64="Base Case",Scenarios!F41,IF(Assumptions!$B$64="Optimistic",Scenarios!F104,Scenarios!F167)) -> 10000 | G37: =IF(Assumptions!$B$64="Base Case",Scenarios!G41,IF(Assumptions!$B$64="Optimistic",Scenarios!G104,Scenarios!G167)) -> 10000 | H37: =IF(Assumptions!$B$64="Base Case",Scenarios!H41,IF(Assumptions!$B$64="Optimistic",Scenarios!H104,Scenarios!H167)) -> 10000
A38: Other Long-Term Assets | B38: 20000 | C38: 20000 | D38: =IF(Assumptions!$B$64="Base Case",Scenarios!D42,IF(Assumptions!$B$64="Optimistic",Scenarios!D105,Scenarios!D168)) -> 20000 | E38: =IF(Assumptions!$B$64="Base Case",Scenarios!E42,IF(Assumptions!$B$64="Optimistic",Scenarios!E105,Scenarios!E168)) -> 20000 | F38: =IF(Assumptions!$B$64="Base Case",Scenarios!F42,IF(Assumptions!$B$64="Optimistic",Scenarios!F105,Scenarios!F168)) -> 20000 | G38: =IF(Assumptions!$B$64="Base Case",Scenarios!G42,IF(Assumptions!$B$64="Optimistic",Scenarios!G105,Scenarios!G168)) -> 20000 | H38: =IF(Assumptions!$B$64="Base Case",Scenarios!H42,IF(Assumptions!$B$64="Optimistic",Scenarios!H105,Scenarios!H168)) -> 20000
A39: Other Current Liabilities | B39: 15000 | C39: 15000 | D39: =IF(Assumptions!$B$64="Base Case",Scenarios!D43,IF(Assumptions!$B$64="Optimistic",Scenarios!D106,Scenarios!D169)) -> 15000 | E39: =IF(Assumptions!$B$64="Base Case",Scenarios!E43,IF(Assumptions!$B$64="Optimistic",Scenarios!E106,Scenarios!E169)) -> 15000 | F39: =IF(Assumptions!$B$64="Base Case",Scenarios!F43,IF(Assumptions!$B$64="Optimistic",Scenarios!F106,Scenarios!F169)) -> 15000 | G39: =IF(Assumptions!$B$64="Base Case",Scenarios!G43,IF(Assumptions!$B$64="Optimistic",Scenarios!G106,Scenarios!G169)) -> 15000 | H39: =IF(Assumptions!$B$64="Base Case",Scenarios!H43,IF(Assumptions!$B$64="Optimistic",Scenarios!H106,Scenarios!H169)) -> 15000
A40: Deferred Tax Liabilities | B40: 30000 | C40: 30000 | D40: =IF(Assumptions!$B$64="Base Case",Scenarios!D44,IF(Assumptions!$B$64="Optimistic",Scenarios!D107,Scenarios!D170)) -> 30000 | E40: =IF(Assumptions!$B$64="Base Case",Scenarios!E44,IF(Assumptions!$B$64="Optimistic",Scenarios!E107,Scenarios!E170)) -> 30000 | F40: =IF(Assumptions!$B$64="Base Case",Scenarios!F44,IF(Assumptions!$B$64="Optimistic",Scenarios!F107,Scenarios!F170)) -> 30000 | G40: =IF(Assumptions!$B$64="Base Case",Scenarios!G44,IF(Assumptions!$B$64="Optimistic",Scenarios!G107,Scenarios!G170)) -> 30000 | H40: =IF(Assumptions!$B$64="Base Case",Scenarios!H44,IF(Assumptions!$B$64="Optimistic",Scenarios!H107,Scenarios!H170)) -> 30000
A41: Other LT Liabilities | B41: 25000 | C41: 25000 | D41: =IF(Assumptions!$B$64="Base Case",Scenarios!D45,IF(Assumptions!$B$64="Optimistic",Scenarios!D108,Scenarios!D171)) -> 25000 | E41: =IF(Assumptions!$B$64="Base Case",Scenarios!E45,IF(Assumptions!$B$64="Optimistic",Scenarios!E108,Scenarios!E171)) -> 25000 | F41: =IF(Assumptions!$B$64="Base Case",Scenarios!F45,IF(Assumptions!$B$64="Optimistic",Scenarios!F108,Scenarios!F171)) -> 25000 | G41: =IF(Assumptions!$B$64="Base Case",Scenarios!G45,IF(Assumptions!$B$64="Optimistic",Scenarios!G108,Scenarios!G171)) -> 25000 | H41: =IF(Assumptions!$B$64="Base Case",Scenarios!H45,IF(Assumptions!$B$64="Optimistic",Scenarios!H108,Scenarios!H171)) -> 25000
A42: Common Stock | B42: 10000 | C42: 10000 | D42: =IF(Assumptions!$B$64="Base Case",Scenarios!D46,IF(Assumptions!$B$64="Optimistic",Scenarios!D109,Scenarios!D172)) -> 10000 | E42: =IF(Assumptions!$B$64="Base Case",Scenarios!E46,IF(Assumptions!$B$64="Optimistic",Scenarios!E109,Scenarios!E172)) -> 10000 | F42: =IF(Assumptions!$B$64="Base Case",Scenarios!F46,IF(Assumptions!$B$64="Optimistic",Scenarios!F109,Scenarios!F172)) -> 10000 | G42: =IF(Assumptions!$B$64="Base Case",Scenarios!G46,IF(Assumptions!$B$64="Optimistic",Scenarios!G109,Scenarios!G172)) -> 10000 | H42: =IF(Assumptions!$B$64="Base Case",Scenarios!H46,IF(Assumptions!$B$64="Optimistic",Scenarios!H109,Scenarios!H172)) -> 10000
A43: APIC | B43: 210000 | C43: 220000 | D43: =IF(Assumptions!$B$64="Base Case",Scenarios!D47,IF(Assumptions!$B$64="Optimistic",Scenarios!D110,Scenarios!D173)) -> 200000 | E43: =IF(Assumptions!$B$64="Base Case",Scenarios!E47,IF(Assumptions!$B$64="Optimistic",Scenarios!E110,Scenarios!E173)) -> 200000 | F43: =IF(Assumptions!$B$64="Base Case",Scenarios!F47,IF(Assumptions!$B$64="Optimistic",Scenarios!F110,Scenarios!F173)) -> 200000 | G43: =IF(Assumptions!$B$64="Base Case",Scenarios!G47,IF(Assumptions!$B$64="Optimistic",Scenarios!G110,Scenarios!G173)) -> 200000 | H43: =IF(Assumptions!$B$64="Base Case",Scenarios!H47,IF(Assumptions!$B$64="Optimistic",Scenarios!H110,Scenarios!H173)) -> 200000
A44: Other Comprehensive Income | B44: 0 | C44: 0 | D44: =IF(Assumptions!$B$64="Base Case",Scenarios!D48,IF(Assumptions!$B$64="Optimistic",Scenarios!D111,Scenarios!D174)) -> 0 | E44: =IF(Assumptions!$B$64="Base Case",Scenarios!E48,IF(Assumptions!$B$64="Optimistic",Scenarios!E111,Scenarios!E174)) -> 0 | F44: =IF(Assumptions!$B$64="Base Case",Scenarios!F48,IF(Assumptions!$B$64="Optimistic",Scenarios!F111,Scenarios!F174)) -> 0 | G44: =IF(Assumptions!$B$64="Base Case",Scenarios!G48,IF(Assumptions!$B$64="Optimistic",Scenarios!G111,Scenarios!G174)) -> 0 | H44: =IF(Assumptions!$B$64="Base Case",Scenarios!H48,IF(Assumptions!$B$64="Optimistic",Scenarios!H111,Scenarios!H174)) -> 0
A45: ── Engine-Computed Values ──
A46: Interest Income (Computed) | B46: 2500 | C46: 3000 | D46: =IF(Assumptions!$B$64="Base Case",Scenarios!D50,IF(Assumptions!$B$64="Optimistic",Scenarios!D113,Scenarios!D176)) -> 4420.376 | E46: =IF(Assumptions!$B$64="Base Case",Scenarios!E50,IF(Assumptions!$B$64="Optimistic",Scenarios!E113,Scenarios!E176)) -> 5341.8586 | F46: =IF(Assumptions!$B$64="Base Case",Scenarios!F50,IF(Assumptions!$B$64="Optimistic",Scenarios!F113,Scenarios!F176)) -> 6420.9591 | G46: =IF(Assumptions!$B$64="Base Case",Scenarios!G50,IF(Assumptions!$B$64="Optimistic",Scenarios!G113,Scenarios!G176)) -> 7654.8346 | H46: =IF(Assumptions!$B$64="Base Case",Scenarios!H50,IF(Assumptions!$B$64="Optimistic",Scenarios!H113,Scenarios!H176)) -> 9044.4367
A47: Interest Expense (Computed) | B47: 14000 | C47: 13000 | D47: =IF(Assumptions!$B$64="Base Case",Scenarios!D51,IF(Assumptions!$B$64="Optimistic",Scenarios!D114,Scenarios!D177)) -> 13500 | E47: =IF(Assumptions!$B$64="Base Case",Scenarios!E51,IF(Assumptions!$B$64="Optimistic",Scenarios!E114,Scenarios!E177)) -> 12500 | F47: =IF(Assumptions!$B$64="Base Case",Scenarios!F51,IF(Assumptions!$B$64="Optimistic",Scenarios!F114,Scenarios!F177)) -> 11500 | G47: =IF(Assumptions!$B$64="Base Case",Scenarios!G51,IF(Assumptions!$B$64="Optimistic",Scenarios!G114,Scenarios!G177)) -> 10500 | H47: =IF(Assumptions!$B$64="Base Case",Scenarios!H51,IF(Assumptions!$B$64="Optimistic",Scenarios!H114,Scenarios!H177)) -> 9500
A48: Depreciation (Computed) | B48: 28000 | C48: 32000 | D48: =IF(Assumptions!$B$64="Base Case",Scenarios!D52,IF(Assumptions!$B$64="Optimistic",Scenarios!D115,Scenarios!D178)) -> 41112.5 | E48: =IF(Assumptions!$B$64="Base Case",Scenarios!E52,IF(Assumptions!$B$64="Optimistic",Scenarios!E115,Scenarios!E178)) -> 46546.5 | F48: =IF(Assumptions!$B$64="Base Case",Scenarios!F52,IF(Assumptions!$B$64="Optimistic",Scenarios!F115,Scenarios!F178)) -> 52387.005 | G48: =IF(Assumptions!$B$64="Base Case",Scenarios!G52,IF(Assumptions!$B$64="Optimistic",Scenarios!G115,Scenarios!G178)) -> 58606.155 | H48: =IF(Assumptions!$B$64="Base Case",Scenarios!H52,IF(Assumptions!$B$64="Optimistic",Scenarios!H115,Scenarios!H178)) -> 65166.453
A49: Gross PP&E (Computed) | B49: 340000 | C49: 385000 | D49: =IF(Assumptions!$B$64="Base Case",Scenarios!D53,IF(Assumptions!$B$64="Optimistic",Scenarios!D116,Scenarios!D179)) -> 437250 | E49: =IF(Assumptions!$B$64="Base Case",Scenarios!E53,IF(Assumptions!$B$64="Optimistic",Scenarios!E116,Scenarios!E179)) -> 493680 | F49: =IF(Assumptions!$B$64="Base Case",Scenarios!F53,IF(Assumptions!$B$64="Optimistic",Scenarios!F116,Scenarios!F179)) -> 554060.1 | G49: =IF(Assumptions!$B$64="Base Case",Scenarios!G53,IF(Assumptions!$B$64="Optimistic",Scenarios!G116,Scenarios!G179)) -> 618063.01 | H49: =IF(Assumptions!$B$64="Base Case",Scenarios!H53,IF(Assumptions!$B$64="Optimistic",Scenarios!H116,Scenarios!H179)) -> 685266.06
A50: Accum Depreciation (Computed) | B50: 128000 | C50: 160000 | D50: =IF(Assumptions!$B$64="Base Case",Scenarios!D54,IF(Assumptions!$B$64="Optimistic",Scenarios!D117,Scenarios!D180)) -> 201112.5 | E50: =IF(Assumptions!$B$64="Base Case",Scenarios!E54,IF(Assumptions!$B$64="Optimistic",Scenarios!E117,Scenarios!E180)) -> 247659 | F50: =IF(Assumptions!$B$64="Base Case",Scenarios!F54,IF(Assumptions!$B$64="Optimistic",Scenarios!F117,Scenarios!F180)) -> 300046.01 | G50: =IF(Assumptions!$B$64="Base Case",Scenarios!G54,IF(Assumptions!$B$64="Optimistic",Scenarios!G117,Scenarios!G180)) -> 358652.16 | H50: =IF(Assumptions!$B$64="Base Case",Scenarios!H54,IF(Assumptions!$B$64="Optimistic",Scenarios!H117,Scenarios!H180)) -> 423818.61
A51: Net PP&E (Computed) | B51: 212000 | C51: 225000 | D51: =IF(Assumptions!$B$64="Base Case",Scenarios!D55,IF(Assumptions!$B$64="Optimistic",Scenarios!D118,Scenarios!D181)) -> 236137.5 | E51: =IF(Assumptions!$B$64="Base Case",Scenarios!E55,IF(Assumptions!$B$64="Optimistic",Scenarios!E118,Scenarios!E181)) -> 246021 | F51: =IF(Assumptions!$B$64="Base Case",Scenarios!F55,IF(Assumptions!$B$64="Optimistic",Scenarios!F118,Scenarios!F181)) -> 254014.09 | G51: =IF(Assumptions!$B$64="Base Case",Scenarios!G55,IF(Assumptions!$B$64="Optimistic",Scenarios!G118,Scenarios!G181)) -> 259410.85 | H51: =IF(Assumptions!$B$64="Base Case",Scenarios!H55,IF(Assumptions!$B$64="Optimistic",Scenarios!H118,Scenarios!H181)) -> 261447.44
A52: Intangibles (Computed) | B52: 45000 | C52: 40000 | D52: =IF(Assumptions!$B$64="Base Case",Scenarios!D56,IF(Assumptions!$B$64="Optimistic",Scenarios!D119,Scenarios!D182)) -> 35000 | E52: =IF(Assumptions!$B$64="Base Case",Scenarios!E56,IF(Assumptions!$B$64="Optimistic",Scenarios!E119,Scenarios!E182)) -> 30000 | F52: =IF(Assumptions!$B$64="Base Case",Scenarios!F56,IF(Assumptions!$B$64="Optimistic",Scenarios!F119,Scenarios!F182)) -> 25000 | G52: =IF(Assumptions!$B$64="Base Case",Scenarios!G56,IF(Assumptions!$B$64="Optimistic",Scenarios!G119,Scenarios!G182)) -> 20000 | H52: =IF(Assumptions!$B$64="Base Case",Scenarios!H56,IF(Assumptions!$B$64="Optimistic",Scenarios!H119,Scenarios!H182)) -> 15000
A53: Long-Term Debt (Computed) | B53: 230000 | C53: 210000 | D53: =IF(Assumptions!$B$64="Base Case",Scenarios!D57,IF(Assumptions!$B$64="Optimistic",Scenarios!D120,Scenarios!D183)) -> 190000 | E53: =IF(Assumptions!$B$64="Base Case",Scenarios!E57,IF(Assumptions!$B$64="Optimistic",Scenarios!E120,Scenarios!E183)) -> 170000 | F53: =IF(Assumptions!$B$64="Base Case",Scenarios!F57,IF(Assumptions!$B$64="Optimistic",Scenarios!F120,Scenarios!F183)) -> 150000 | G53: =IF(Assumptions!$B$64="Base Case",Scenarios!G57,IF(Assumptions!$B$64="Optimistic",Scenarios!G120,Scenarios!G183)) -> 130000 | H53: =IF(Assumptions!$B$64="Base Case",Scenarios!H57,IF(Assumptions!$B$64="Optimistic",Scenarios!H120,Scenarios!H183)) -> 110000
A54: Retained Earnings (Computed) | B54: 28823 | C54: 78506 | D54: =IF(Assumptions!$B$64="Base Case",Scenarios!D58,IF(Assumptions!$B$64="Optimistic",Scenarios!D121,Scenarios!D184)) -> 143032.63 | E54: =IF(Assumptions!$B$64="Base Case",Scenarios!E58,IF(Assumptions!$B$64="Optimistic",Scenarios!E121,Scenarios!E184)) -> 213615.4 | F54: =IF(Assumptions!$B$64="Base Case",Scenarios!F58,IF(Assumptions!$B$64="Optimistic",Scenarios!F121,Scenarios!F184)) -> 289689.11 | G54: =IF(Assumptions!$B$64="Base Case",Scenarios!G58,IF(Assumptions!$B$64="Optimistic",Scenarios!G121,Scenarios!G184)) -> 370517.66 | H54: =IF(Assumptions!$B$64="Base Case",Scenarios!H58,IF(Assumptions!$B$64="Optimistic",Scenarios!H121,Scenarios!H184)) -> 455204.87
A55: Treasury Stock (Computed) | B55: 0 | C55: 0 | D55: =IF(Assumptions!$B$64="Base Case",Scenarios!D59,IF(Assumptions!$B$64="Optimistic",Scenarios!D122,Scenarios!D185)) -> 0 | E55: =IF(Assumptions!$B$64="Base Case",Scenarios!E59,IF(Assumptions!$B$64="Optimistic",Scenarios!E122,Scenarios!E185)) -> 0 | F55: =IF(Assumptions!$B$64="Base Case",Scenarios!F59,IF(Assumptions!$B$64="Optimistic",Scenarios!F122,Scenarios!F185)) -> 0 | G55: =IF(Assumptions!$B$64="Base Case",Scenarios!G59,IF(Assumptions!$B$64="Optimistic",Scenarios!G122,Scenarios!G185)) -> 0 | H55: =IF(Assumptions!$B$64="Base Case",Scenarios!H59,IF(Assumptions!$B$64="Optimistic",Scenarios!H122,Scenarios!H185)) -> 0
A56: APIC (Computed) | B56: 210000 | C56: 220000 | D56: =IF(Assumptions!$B$64="Base Case",Scenarios!D60,IF(Assumptions!$B$64="Optimistic",Scenarios!D123,Scenarios!D186)) -> 230000 | E56: =IF(Assumptions!$B$64="Base Case",Scenarios!E60,IF(Assumptions!$B$64="Optimistic",Scenarios!E123,Scenarios!E186)) -> 240000 | F56: =IF(Assumptions!$B$64="Base Case",Scenarios!F60,IF(Assumptions!$B$64="Optimistic",Scenarios!F123,Scenarios!F186)) -> 250000 | G56: =IF(Assumptions!$B$64="Base Case",Scenarios!G60,IF(Assumptions!$B$64="Optimistic",Scenarios!G123,Scenarios!G186)) -> 260000 | H56: =IF(Assumptions!$B$64="Base Case",Scenarios!H60,IF(Assumptions!$B$64="Optimistic",Scenarios!H123,Scenarios!H186)) -> 270000
A57: Dividends Paid (Computed) | B57: 0 | C57: -43067 | D57: =IF(Assumptions!$B$64="Base Case",Scenarios!D61,IF(Assumptions!$B$64="Optimistic",Scenarios!D124,Scenarios!D187)) -> -27654.272 | E57: =IF(Assumptions!$B$64="Base Case",Scenarios!E61,IF(Assumptions!$B$64="Optimistic",Scenarios!E124,Scenarios!E187)) -> -30249.756 | F57: =IF(Assumptions!$B$64="Base Case",Scenarios!F61,IF(Assumptions!$B$64="Optimistic",Scenarios!F124,Scenarios!F187)) -> -32603.021 | G57: =IF(Assumptions!$B$64="Base Case",Scenarios!G61,IF(Assumptions!$B$64="Optimistic",Scenarios!G124,Scenarios!G187)) -> -34640.807 | H57: =IF(Assumptions!$B$64="Base Case",Scenarios!H61,IF(Assumptions!$B$64="Optimistic",Scenarios!H124,Scenarios!H187)) -> -36294.518
... A61: Asset Sales (Computed) | B61: 0 | C61: 0 | D61: =IF(Assumptions!$B$64="Base Case",Scenarios!D65,IF(Assumptions!$B$64="Optimistic",Scenarios!D128,Scenarios!D191)) -> 0 | E61: =IF(Assumptions!$B$64="Base Case",Scenarios!E65,IF(Assumptions!$B$64="Optimistic",Scenarios!E128,Scenarios!E191)) -> 0 | F61: =IF(Assumptions!$B$64="Base Case",Scenarios!F65,IF(Assumptions!$B$64="Optimistic",Scenarios!F128,Scenarios!F191)) -> 0 | G61: =IF(Assumptions!$B$64="Base Case",Scenarios!G65,IF(Assumptions!$B$64="Optimistic",Scenarios!G128,Scenarios!G191)) -> 0 | H61: =IF(Assumptions!$B$64="Base Case",Scenarios!H65,IF(Assumptions!$B$64="Optimistic",Scenarios!H128,Scenarios!H191)) -> 0
A63: ── SCENARIO CONTROL ──
A64: Active Scenario | B64: =Dashboard!B6 -> Base Case
