Workbook

Sheet Dashboard
A1: WOLF
A2: FINANCIAL MODEL DASHBOARD · E£ (Egyptian Pound) · CONFIDENTIAL
A4: 📊 SCENARIO CONTROL
A5: Active Scenario | B5: Select Scenario →
A6: ▼ Scenario Selector | B6: Base Case | E6: =IF(B6="Base Case","Central planning — stable market | Revenue 10%→5% | COGS 60%",IF(B6="Optimistic","Bull case — strong execution | Revenue 15%→8% | COGS 55%","Bear case — headwinds | Revenue 5%→2% | COGS 63%")) -> Central planning — stable market | Revenue 10%→5% | COGS 60%
A8: 📈 KEY METRICS — ACTIVE SCENARIO
B9: 2021 | C9: 2022 | D9: 2023 | E9: 2024E | F9: 2025E | G9: 2026E | H9: 2027E | I9: 2028E
A10: 📗 INCOME STATEMENT
A11: Revenue (E£) | B11: =IF(Dashboard!$B$6="Base Case",Scenarios!B67,IF(Dashboard!$B$6="Optimistic",Scenarios!B152,Scenarios!B237)) -> 750000 | C11: =IF(Dashboard!$B$6="Base Case",Scenarios!C67,IF(Dashboard!$B$6="Optimistic",Scenarios!C152,Scenarios!C237)) -> 850000 | D11: =IF(Dashboard!$B$6="Base Case",Scenarios!D67,IF(Dashboard!$B$6="Optimistic",Scenarios!D152,Scenarios!D237)) -> 950000 | E11: =IF(Dashboard!$B$6="Base Case",Scenarios!E67,IF(Dashboard!$B$6="Optimistic",Scenarios!E152,Scenarios!E237)) -> 1045000 | F11: =IF(Dashboard!$B$6="Base Case",Scenarios!F67,IF(Dashboard!$B$6="Optimistic",Scenarios!F152,Scenarios!F237)) -> 1128600 | G11: =IF(Dashboard!$B$6="Base Case",Scenarios!G67,IF(Dashboard!$B$6="Optimistic",Scenarios!G152,Scenarios!G237)) -> 1207602 | H11: =IF(Dashboard!$B$6="Base Case",Scenarios!H67,IF(Dashboard!$B$6="Optimistic",Scenarios!H152,Scenarios!H237)) -> 1280058.1 | I11: =IF(Dashboard!$B$6="Base Case",Scenarios!I67,IF(Dashboard!$B$6="Optimistic",Scenarios!I152,Scenarios!I237)) -> 1344061
A12: Revenue Growth % | B12: =IF(Dashboard!$B$6="Base Case",Scenarios!B68,IF(Dashboard!$B$6="Optimistic",Scenarios!B153,Scenarios!B238)) -> 0 | C12: =IF(Dashboard!$B$6="Base Case",Scenarios!C68,IF(Dashboard!$B$6="Optimistic",Scenarios!C153,Scenarios!C238)) -> 0.13333333 | D12: =IF(Dashboard!$B$6="Base Case",Scenarios!D68,IF(Dashboard!$B$6="Optimistic",Scenarios!D153,Scenarios!D238)) -> 0.11764706 | E12: =IF(Dashboard!$B$6="Base Case",Scenarios!E68,IF(Dashboard!$B$6="Optimistic",Scenarios!E153,Scenarios!E238)) -> 0.1 | F12: =IF(Dashboard!$B$6="Base Case",Scenarios!F68,IF(Dashboard!$B$6="Optimistic",Scenarios!F153,Scenarios!F238)) -> 0.08 | G12: =IF(Dashboard!$B$6="Base Case",Scenarios!G68,IF(Dashboard!$B$6="Optimistic",Scenarios!G153,Scenarios!G238)) -> 0.07 | H12: =IF(Dashboard!$B$6="Base Case",Scenarios!H68,IF(Dashboard!$B$6="Optimistic",Scenarios!H153,Scenarios!H238)) -> 0.06 | I12: =IF(Dashboard!$B$6="Base Case",Scenarios!I68,IF(Dashboard!$B$6="Optimistic",Scenarios!I153,Scenarios!I238)) -> 0.05
A13: Gross Profit (E£) | B13: =IF(Dashboard!$B$6="Base Case",Scenarios!B69,IF(Dashboard!$B$6="Optimistic",Scenarios!B154,Scenarios!B239)) -> 300000 | C13: =IF(Dashboard!$B$6="Base Case",Scenarios!C69,IF(Dashboard!$B$6="Optimistic",Scenarios!C154,Scenarios!C239)) -> 340000 | D13: =IF(Dashboard!$B$6="Base Case",Scenarios!D69,IF(Dashboard!$B$6="Optimistic",Scenarios!D154,Scenarios!D239)) -> 380000 | E13: =IF(Dashboard!$B$6="Base Case",Scenarios!E69,IF(Dashboard!$B$6="Optimistic",Scenarios!E154,Scenarios!E239)) -> 418000 | F13: =IF(Dashboard!$B$6="Base Case",Scenarios!F69,IF(Dashboard!$B$6="Optimistic",Scenarios!F154,Scenarios!F239)) -> 451440 | G13: =IF(Dashboard!$B$6="Base Case",Scenarios!G69,IF(Dashboard!$B$6="Optimistic",Scenarios!G154,Scenarios!G239)) -> 483040.8 | H13: =IF(Dashboard!$B$6="Base Case",Scenarios!H69,IF(Dashboard!$B$6="Optimistic",Scenarios!H154,Scenarios!H239)) -> 512023.25 | I13: =IF(Dashboard!$B$6="Base Case",Scenarios!I69,IF(Dashboard!$B$6="Optimistic",Scenarios!I154,Scenarios!I239)) -> 537624.41
A14: Gross Margin % | B14: =IF(Dashboard!$B$6="Base Case",Scenarios!B70,IF(Dashboard!$B$6="Optimistic",Scenarios!B155,Scenarios!B240)) -> 0.4 | C14: =IF(Dashboard!$B$6="Base Case",Scenarios!C70,IF(Dashboard!$B$6="Optimistic",Scenarios!C155,Scenarios!C240)) -> 0.4 | D14: =IF(Dashboard!$B$6="Base Case",Scenarios!D70,IF(Dashboard!$B$6="Optimistic",Scenarios!D155,Scenarios!D240)) -> 0.4 | E14: =IF(Dashboard!$B$6="Base Case",Scenarios!E70,IF(Dashboard!$B$6="Optimistic",Scenarios!E155,Scenarios!E240)) -> 0.4 | F14: =IF(Dashboard!$B$6="Base Case",Scenarios!F70,IF(Dashboard!$B$6="Optimistic",Scenarios!F155,Scenarios!F240)) -> 0.4 | G14: =IF(Dashboard!$B$6="Base Case",Scenarios!G70,IF(Dashboard!$B$6="Optimistic",Scenarios!G155,Scenarios!G240)) -> 0.4 | H14: =IF(Dashboard!$B$6="Base Case",Scenarios!H70,IF(Dashboard!$B$6="Optimistic",Scenarios!H155,Scenarios!H240)) -> 0.4 | I14: =IF(Dashboard!$B$6="Base Case",Scenarios!I70,IF(Dashboard!$B$6="Optimistic",Scenarios!I155,Scenarios!I240)) -> 0.4
A15: EBITDA (E£) | B15: =IF(Dashboard!$B$6="Base Case",Scenarios!B71,IF(Dashboard!$B$6="Optimistic",Scenarios!B156,Scenarios!B241)) -> 135000 | C15: =IF(Dashboard!$B$6="Base Case",Scenarios!C71,IF(Dashboard!$B$6="Optimistic",Scenarios!C156,Scenarios!C241)) -> 153000 | D15: =IF(Dashboard!$B$6="Base Case",Scenarios!D71,IF(Dashboard!$B$6="Optimistic",Scenarios!D156,Scenarios!D241)) -> 171000 | E15: =IF(Dashboard!$B$6="Base Case",Scenarios!E71,IF(Dashboard!$B$6="Optimistic",Scenarios!E156,Scenarios!E241)) -> 178100 | F15: =IF(Dashboard!$B$6="Base Case",Scenarios!F71,IF(Dashboard!$B$6="Optimistic",Scenarios!F156,Scenarios!F241)) -> 193148 | G15: =IF(Dashboard!$B$6="Base Case",Scenarios!G71,IF(Dashboard!$B$6="Optimistic",Scenarios!G156,Scenarios!G241)) -> 207368.36 | H15: =IF(Dashboard!$B$6="Base Case",Scenarios!H71,IF(Dashboard!$B$6="Optimistic",Scenarios!H156,Scenarios!H241)) -> 220410.46 | I15: =IF(Dashboard!$B$6="Base Case",Scenarios!I71,IF(Dashboard!$B$6="Optimistic",Scenarios!I156,Scenarios!I241)) -> 231930.98
A16: EBIT (E£) | B16: =IF(Dashboard!$B$6="Base Case",Scenarios!B72,IF(Dashboard!$B$6="Optimistic",Scenarios!B157,Scenarios!B242)) -> 105000 | C16: =IF(Dashboard!$B$6="Base Case",Scenarios!C72,IF(Dashboard!$B$6="Optimistic",Scenarios!C157,Scenarios!C242)) -> 120000 | D16: =IF(Dashboard!$B$6="Base Case",Scenarios!D72,IF(Dashboard!$B$6="Optimistic",Scenarios!D157,Scenarios!D242)) -> 134000 | E16: =IF(Dashboard!$B$6="Base Case",Scenarios!E72,IF(Dashboard!$B$6="Optimistic",Scenarios!E157,Scenarios!E242)) -> 131987.5 | F16: =IF(Dashboard!$B$6="Base Case",Scenarios!F72,IF(Dashboard!$B$6="Optimistic",Scenarios!F157,Scenarios!F242)) -> 141601.5 | G16: =IF(Dashboard!$B$6="Base Case",Scenarios!G72,IF(Dashboard!$B$6="Optimistic",Scenarios!G157,Scenarios!G242)) -> 149981.36 | H16: =IF(Dashboard!$B$6="Base Case",Scenarios!H72,IF(Dashboard!$B$6="Optimistic",Scenarios!H157,Scenarios!H242)) -> 156804.31 | I16: =IF(Dashboard!$B$6="Base Case",Scenarios!I72,IF(Dashboard!$B$6="Optimistic",Scenarios!I157,Scenarios!I242)) -> 161764.53
A17: EBIT Margin % | B17: =IF(Dashboard!$B$6="Base Case",Scenarios!B73,IF(Dashboard!$B$6="Optimistic",Scenarios!B158,Scenarios!B243)) -> 0.14 | C17: =IF(Dashboard!$B$6="Base Case",Scenarios!C73,IF(Dashboard!$B$6="Optimistic",Scenarios!C158,Scenarios!C243)) -> 0.14117647 | D17: =IF(Dashboard!$B$6="Base Case",Scenarios!D73,IF(Dashboard!$B$6="Optimistic",Scenarios!D158,Scenarios!D243)) -> 0.14105263 | E17: =IF(Dashboard!$B$6="Base Case",Scenarios!E73,IF(Dashboard!$B$6="Optimistic",Scenarios!E158,Scenarios!E243)) -> 0.12630383 | F17: =IF(Dashboard!$B$6="Base Case",Scenarios!F73,IF(Dashboard!$B$6="Optimistic",Scenarios!F158,Scenarios!F243)) -> 0.12546651 | G17: =IF(Dashboard!$B$6="Base Case",Scenarios!G73,IF(Dashboard!$B$6="Optimistic",Scenarios!G158,Scenarios!G243)) -> 0.12419767 | H17: =IF(Dashboard!$B$6="Base Case",Scenarios!H73,IF(Dashboard!$B$6="Optimistic",Scenarios!H158,Scenarios!H243)) -> 0.1224978 | I17: =IF(Dashboard!$B$6="Base Case",Scenarios!I73,IF(Dashboard!$B$6="Optimistic",Scenarios!I158,Scenarios!I243)) -> 0.12035505
A18: Net Income (E£) | B18: =IF(Dashboard!$B$6="Base Case",Scenarios!B74,IF(Dashboard!$B$6="Optimistic",Scenarios!B159,Scenarios!B244)) -> 68875 | C18: =IF(Dashboard!$B$6="Base Case",Scenarios!C74,IF(Dashboard!$B$6="Optimistic",Scenarios!C159,Scenarios!C244)) -> 81125 | D18: =IF(Dashboard!$B$6="Base Case",Scenarios!D74,IF(Dashboard!$B$6="Optimistic",Scenarios!D159,Scenarios!D244)) -> 92750 | E18: =IF(Dashboard!$B$6="Base Case",Scenarios!E74,IF(Dashboard!$B$6="Optimistic",Scenarios!E159,Scenarios!E244)) -> 63836.015 | F18: =IF(Dashboard!$B$6="Base Case",Scenarios!F74,IF(Dashboard!$B$6="Optimistic",Scenarios!F159,Scenarios!F244)) -> 75076.661 | G18: =IF(Dashboard!$B$6="Base Case",Scenarios!G74,IF(Dashboard!$B$6="Optimistic",Scenarios!G159,Scenarios!G244)) -> 85553.403 | H18: =IF(Dashboard!$B$6="Base Case",Scenarios!H74,IF(Dashboard!$B$6="Optimistic",Scenarios!H159,Scenarios!H244)) -> 95010.855 | I18: =IF(Dashboard!$B$6="Base Case",Scenarios!I74,IF(Dashboard!$B$6="Optimistic",Scenarios!I159,Scenarios!I244)) -> 103208.62
A19: Net Margin % | B19: =IF(Dashboard!$B$6="Base Case",Scenarios!B75,IF(Dashboard!$B$6="Optimistic",Scenarios!B160,Scenarios!B245)) -> 0.091833333 | C19: =IF(Dashboard!$B$6="Base Case",Scenarios!C75,IF(Dashboard!$B$6="Optimistic",Scenarios!C160,Scenarios!C245)) -> 0.095441176 | D19: =IF(Dashboard!$B$6="Base Case",Scenarios!D75,IF(Dashboard!$B$6="Optimistic",Scenarios!D160,Scenarios!D245)) -> 0.097631579 | E19: =IF(Dashboard!$B$6="Base Case",Scenarios!E75,IF(Dashboard!$B$6="Optimistic",Scenarios!E160,Scenarios!E245)) -> 0.061087096 | F19: =IF(Dashboard!$B$6="Base Case",Scenarios!F75,IF(Dashboard!$B$6="Optimistic",Scenarios!F160,Scenarios!F245)) -> 0.066521939 | G19: =IF(Dashboard!$B$6="Base Case",Scenarios!G75,IF(Dashboard!$B$6="Optimistic",Scenarios!G160,Scenarios!G245)) -> 0.070845695 | H19: =IF(Dashboard!$B$6="Base Case",Scenarios!H75,IF(Dashboard!$B$6="Optimistic",Scenarios!H160,Scenarios!H245)) -> 0.07422386 | I19: =IF(Dashboard!$B$6="Base Case",Scenarios!I75,IF(Dashboard!$B$6="Optimistic",Scenarios!I160,Scenarios!I245)) -> 0.076788638
A20: EPS (E£) | B20: =IF(Dashboard!$B$6="Base Case",Scenarios!B76,IF(Dashboard!$B$6="Optimistic",Scenarios!B161,Scenarios!B246)) -> 0.68875 | C20: =IF(Dashboard!$B$6="Base Case",Scenarios!C76,IF(Dashboard!$B$6="Optimistic",Scenarios!C161,Scenarios!C246)) -> 0.81125 | D20: =IF(Dashboard!$B$6="Base Case",Scenarios!D76,IF(Dashboard!$B$6="Optimistic",Scenarios!D161,Scenarios!D246)) -> 0.9275 | E20: =IF(Dashboard!$B$6="Base Case",Scenarios!E76,IF(Dashboard!$B$6="Optimistic",Scenarios!E161,Scenarios!E246)) -> 0.63836015 | F20: =IF(Dashboard!$B$6="Base Case",Scenarios!F76,IF(Dashboard!$B$6="Optimistic",Scenarios!F161,Scenarios!F246)) -> 0.75076661 | G20: =IF(Dashboard!$B$6="Base Case",Scenarios!G76,IF(Dashboard!$B$6="Optimistic",Scenarios!G161,Scenarios!G246)) -> 0.85553403 | H20: =IF(Dashboard!$B$6="Base Case",Scenarios!H76,IF(Dashboard!$B$6="Optimistic",Scenarios!H161,Scenarios!H246)) -> 0.95010855 | I20: =IF(Dashboard!$B$6="Base Case",Scenarios!I76,IF(Dashboard!$B$6="Optimistic",Scenarios!I161,Scenarios!I246)) -> 1.0320862
A21: 💵 CASH FLOW
A22: CFO (E£) | B22: — | C22: =IF(Dashboard!$B$6="Base Case",Scenarios!C77,IF(Dashboard!$B$6="Optimistic",Scenarios!C162,Scenarios!C247)) -> 107439 | D22: =IF(Dashboard!$B$6="Base Case",Scenarios!D77,IF(Dashboard!$B$6="Optimistic",Scenarios!D162,Scenarios!D247)) -> 123067 | E22: =IF(Dashboard!$B$6="Base Case",Scenarios!E77,IF(Dashboard!$B$6="Optimistic",Scenarios!E162,Scenarios!E247)) -> 113596.98 | F22: =IF(Dashboard!$B$6="Base Case",Scenarios!F77,IF(Dashboard!$B$6="Optimistic",Scenarios!F162,Scenarios!F247)) -> 131034.56 | G22: =IF(Dashboard!$B$6="Base Case",Scenarios!G77,IF(Dashboard!$B$6="Optimistic",Scenarios!G162,Scenarios!G247)) -> 147659.18 | H22: =IF(Dashboard!$B$6="Base Case",Scenarios!H77,IF(Dashboard!$B$6="Optimistic",Scenarios!H162,Scenarios!H247)) -> 163773.37 | I22: =IF(Dashboard!$B$6="Base Case",Scenarios!I77,IF(Dashboard!$B$6="Optimistic",Scenarios!I162,Scenarios!I247)) -> 179096.52
A23: Free Cash Flow (E£) | B23: — | C23: =IF(Dashboard!$B$6="Base Case",Scenarios!C78,IF(Dashboard!$B$6="Optimistic",Scenarios!C163,Scenarios!C248)) -> 67439 | D23: =IF(Dashboard!$B$6="Base Case",Scenarios!D78,IF(Dashboard!$B$6="Optimistic",Scenarios!D163,Scenarios!D248)) -> 78067 | E23: =IF(Dashboard!$B$6="Base Case",Scenarios!E78,IF(Dashboard!$B$6="Optimistic",Scenarios!E163,Scenarios!E248)) -> 61346.981 | F23: =IF(Dashboard!$B$6="Base Case",Scenarios!F78,IF(Dashboard!$B$6="Optimistic",Scenarios!F163,Scenarios!F248)) -> 74604.558 | G23: =IF(Dashboard!$B$6="Base Case",Scenarios!G78,IF(Dashboard!$B$6="Optimistic",Scenarios!G163,Scenarios!G248)) -> 87279.078 | H23: =IF(Dashboard!$B$6="Base Case",Scenarios!H78,IF(Dashboard!$B$6="Optimistic",Scenarios!H163,Scenarios!H248)) -> 99770.462 | I23: =IF(Dashboard!$B$6="Base Case",Scenarios!I78,IF(Dashboard!$B$6="Optimistic",Scenarios!I163,Scenarios!I248)) -> 111893.47
A24: Ending Cash (E£) | B24: — | C24: =IF(Dashboard!$B$6="Base Case",Scenarios!C79,IF(Dashboard!$B$6="Optimistic",Scenarios!C164,Scenarios!C249)) -> 175000 | D24: =IF(Dashboard!$B$6="Base Case",Scenarios!D79,IF(Dashboard!$B$6="Optimistic",Scenarios!D164,Scenarios!D249)) -> 200000 | E24: =IF(Dashboard!$B$6="Base Case",Scenarios!E79,IF(Dashboard!$B$6="Optimistic",Scenarios!E164,Scenarios!E249)) -> 238155.18 | F24: =IF(Dashboard!$B$6="Base Case",Scenarios!F79,IF(Dashboard!$B$6="Optimistic",Scenarios!F164,Scenarios!F249)) -> 289005.91 | G24: =IF(Dashboard!$B$6="Base Case",Scenarios!G79,IF(Dashboard!$B$6="Optimistic",Scenarios!G164,Scenarios!G249)) -> 352007.31 | H24: =IF(Dashboard!$B$6="Base Case",Scenarios!H79,IF(Dashboard!$B$6="Optimistic",Scenarios!H164,Scenarios!H249)) -> 427027.23 | I24: =IF(Dashboard!$B$6="Base Case",Scenarios!I79,IF(Dashboard!$B$6="Optimistic",Scenarios!I164,Scenarios!I249)) -> 513760.27
A25: 🏦 BALANCE SHEET
A26: Total Assets (E£) | B26: =IF(Dashboard!$B$6="Base Case",Scenarios!B80,IF(Dashboard!$B$6="Optimistic",Scenarios!B165,Scenarios!B250)) -> 666952 | C26: =IF(Dashboard!$B$6="Base Case",Scenarios!C80,IF(Dashboard!$B$6="Optimistic",Scenarios!C165,Scenarios!C250)) -> 717213 | D26: =IF(Dashboard!$B$6="Base Case",Scenarios!D80,IF(Dashboard!$B$6="Optimistic",Scenarios!D165,Scenarios!D250)) -> 768472 | E26: =IF(Dashboard!$B$6="Base Case",Scenarios!E80,IF(Dashboard!$B$6="Optimistic",Scenarios!E165,Scenarios!E250)) -> 830112.54 | F26: =IF(Dashboard!$B$6="Base Case",Scenarios!F80,IF(Dashboard!$B$6="Optimistic",Scenarios!F165,Scenarios!F250)) -> 901112.36 | G26: =IF(Dashboard!$B$6="Base Case",Scenarios!G80,IF(Dashboard!$B$6="Optimistic",Scenarios!G165,Scenarios!G250)) -> 981532.84 | H26: =IF(Dashboard!$B$6="Base Case",Scenarios!H80,IF(Dashboard!$B$6="Optimistic",Scenarios!H165,Scenarios!H250)) -> 1070180.2 | I26: =IF(Dashboard!$B$6="Base Case",Scenarios!I80,IF(Dashboard!$B$6="Optimistic",Scenarios!I165,Scenarios!I250)) -> 1165636.9
A27: Total Debt (E£) | B27: =IF(Dashboard!$B$6="Base Case",Scenarios!B81,IF(Dashboard!$B$6="Optimistic",Scenarios!B166,Scenarios!B251)) -> 320000 | C27: =IF(Dashboard!$B$6="Base Case",Scenarios!C81,IF(Dashboard!$B$6="Optimistic",Scenarios!C166,Scenarios!C251)) -> 300000 | D27: =IF(Dashboard!$B$6="Base Case",Scenarios!D81,IF(Dashboard!$B$6="Optimistic",Scenarios!D166,Scenarios!D251)) -> 280000 | E27: =IF(Dashboard!$B$6="Base Case",Scenarios!E81,IF(Dashboard!$B$6="Optimistic",Scenarios!E166,Scenarios!E251)) -> 260000 | F27: =IF(Dashboard!$B$6="Base Case",Scenarios!F81,IF(Dashboard!$B$6="Optimistic",Scenarios!F166,Scenarios!F251)) -> 240000 | G27: =IF(Dashboard!$B$6="Base Case",Scenarios!G81,IF(Dashboard!$B$6="Optimistic",Scenarios!G166,Scenarios!G251)) -> 220000 | H27: =IF(Dashboard!$B$6="Base Case",Scenarios!H81,IF(Dashboard!$B$6="Optimistic",Scenarios!H166,Scenarios!H251)) -> 200000 | I27: =IF(Dashboard!$B$6="Base Case",Scenarios!I81,IF(Dashboard!$B$6="Optimistic",Scenarios!I166,Scenarios!I251)) -> 180000
A28: Total Equity (E£) | B28: =IF(Dashboard!$B$6="Base Case",Scenarios!B82,IF(Dashboard!$B$6="Optimistic",Scenarios!B167,Scenarios!B252)) -> 190137 | C28: =IF(Dashboard!$B$6="Base Case",Scenarios!C82,IF(Dashboard!$B$6="Optimistic",Scenarios!C167,Scenarios!C252)) -> 248823 | D28: =IF(Dashboard!$B$6="Base Case",Scenarios!D82,IF(Dashboard!$B$6="Optimistic",Scenarios!D167,Scenarios!D252)) -> 308506 | E28: =IF(Dashboard!$B$6="Base Case",Scenarios!E82,IF(Dashboard!$B$6="Optimistic",Scenarios!E167,Scenarios!E252)) -> 379150.21 | F28: =IF(Dashboard!$B$6="Base Case",Scenarios!F82,IF(Dashboard!$B$6="Optimistic",Scenarios!F167,Scenarios!F252)) -> 460473.04 | G28: =IF(Dashboard!$B$6="Base Case",Scenarios!G82,IF(Dashboard!$B$6="Optimistic",Scenarios!G167,Scenarios!G252)) -> 551748.77 | H28: =IF(Dashboard!$B$6="Base Case",Scenarios!H82,IF(Dashboard!$B$6="Optimistic",Scenarios!H167,Scenarios!H252)) -> 652009.09 | I28: =IF(Dashboard!$B$6="Base Case",Scenarios!I82,IF(Dashboard!$B$6="Optimistic",Scenarios!I167,Scenarios!I252)) -> 760057.27
A29: Cash (E£) | B29: =IF(Dashboard!$B$6="Base Case",Scenarios!B83,IF(Dashboard!$B$6="Optimistic",Scenarios!B168,Scenarios!B253)) -> 150000 | C29: =IF(Dashboard!$B$6="Base Case",Scenarios!C83,IF(Dashboard!$B$6="Optimistic",Scenarios!C168,Scenarios!C253)) -> 175000 | D29: =IF(Dashboard!$B$6="Base Case",Scenarios!D83,IF(Dashboard!$B$6="Optimistic",Scenarios!D168,Scenarios!D253)) -> 200000 | E29: =IF(Dashboard!$B$6="Base Case",Scenarios!E83,IF(Dashboard!$B$6="Optimistic",Scenarios!E168,Scenarios!E253)) -> 238155.18 | F29: =IF(Dashboard!$B$6="Base Case",Scenarios!F83,IF(Dashboard!$B$6="Optimistic",Scenarios!F168,Scenarios!F253)) -> 289005.91 | G29: =IF(Dashboard!$B$6="Base Case",Scenarios!G83,IF(Dashboard!$B$6="Optimistic",Scenarios!G168,Scenarios!G253)) -> 352007.31 | H29: =IF(Dashboard!$B$6="Base Case",Scenarios!H83,IF(Dashboard!$B$6="Optimistic",Scenarios!H168,Scenarios!H253)) -> 427027.23 | I29: =IF(Dashboard!$B$6="Base Case",Scenarios!I83,IF(Dashboard!$B$6="Optimistic",Scenarios!I168,Scenarios!I253)) -> 513760.27
A30: 📊 KEY RATIOS
A31: Current Ratio | B31: =IF(Dashboard!$B$6="Base Case",Scenarios!B84,IF(Dashboard!$B$6="Optimistic",Scenarios!B169,Scenarios!B254)) -> 1.7283241 | C31: =IF(Dashboard!$B$6="Base Case",Scenarios!C84,IF(Dashboard!$B$6="Optimistic",Scenarios!C169,Scenarios!C254)) -> 1.8551339 | D31: =IF(Dashboard!$B$6="Base Case",Scenarios!D84,IF(Dashboard!$B$6="Optimistic",Scenarios!D169,Scenarios!D254)) -> 1.966866 | E31: =IF(Dashboard!$B$6="Base Case",Scenarios!E84,IF(Dashboard!$B$6="Optimistic",Scenarios!E169,Scenarios!E254)) -> 2.1313366 | F31: =IF(Dashboard!$B$6="Base Case",Scenarios!F84,IF(Dashboard!$B$6="Optimistic",Scenarios!F169,Scenarios!F254)) -> 2.3422972 | G31: =IF(Dashboard!$B$6="Base Case",Scenarios!G84,IF(Dashboard!$B$6="Optimistic",Scenarios!G169,Scenarios!G254)) -> 2.5914592 | H31: =IF(Dashboard!$B$6="Base Case",Scenarios!H84,IF(Dashboard!$B$6="Optimistic",Scenarios!H169,Scenarios!H254)) -> 2.8767258 | I31: =IF(Dashboard!$B$6="Base Case",Scenarios!I84,IF(Dashboard!$B$6="Optimistic",Scenarios!I169,Scenarios!I254)) -> 3.197234
A32: Debt / Equity | B32: =IF(Dashboard!$B$6="Base Case",Scenarios!B85,IF(Dashboard!$B$6="Optimistic",Scenarios!B170,Scenarios!B255)) -> 1.682997 | C32: =IF(Dashboard!$B$6="Base Case",Scenarios!C85,IF(Dashboard!$B$6="Optimistic",Scenarios!C170,Scenarios!C255)) -> 1.2056763 | D32: =IF(Dashboard!$B$6="Base Case",Scenarios!D85,IF(Dashboard!$B$6="Optimistic",Scenarios!D170,Scenarios!D255)) -> 0.90759985 | E32: =IF(Dashboard!$B$6="Base Case",Scenarios!E85,IF(Dashboard!$B$6="Optimistic",Scenarios!E170,Scenarios!E255)) -> 0.68574404 | F32: =IF(Dashboard!$B$6="Base Case",Scenarios!F85,IF(Dashboard!$B$6="Optimistic",Scenarios!F170,Scenarios!F255)) -> 0.52120315 | G32: =IF(Dashboard!$B$6="Base Case",Scenarios!G85,IF(Dashboard!$B$6="Optimistic",Scenarios!G170,Scenarios!G255)) -> 0.39873219 | H32: =IF(Dashboard!$B$6="Base Case",Scenarios!H85,IF(Dashboard!$B$6="Optimistic",Scenarios!H170,Scenarios!H255)) -> 0.30674419 | I32: =IF(Dashboard!$B$6="Base Case",Scenarios!I85,IF(Dashboard!$B$6="Optimistic",Scenarios!I170,Scenarios!I255)) -> 0.23682426
A33: ROE % | B33: =IF(Dashboard!$B$6="Base Case",Scenarios!B86,IF(Dashboard!$B$6="Optimistic",Scenarios!B171,Scenarios!B256)) -> 0.36223881 | C33: =IF(Dashboard!$B$6="Base Case",Scenarios!C86,IF(Dashboard!$B$6="Optimistic",Scenarios!C171,Scenarios!C256)) -> 0.36962366 | D33: =IF(Dashboard!$B$6="Base Case",Scenarios!D86,IF(Dashboard!$B$6="Optimistic",Scenarios!D171,Scenarios!D256)) -> 0.33283752 | E33: =IF(Dashboard!$B$6="Base Case",Scenarios!E86,IF(Dashboard!$B$6="Optimistic",Scenarios!E171,Scenarios!E256)) -> 0.18566258 | F33: =IF(Dashboard!$B$6="Base Case",Scenarios!F86,IF(Dashboard!$B$6="Optimistic",Scenarios!F171,Scenarios!F256)) -> 0.17883416 | G33: =IF(Dashboard!$B$6="Base Case",Scenarios!G86,IF(Dashboard!$B$6="Optimistic",Scenarios!G171,Scenarios!G256)) -> 0.16904082 | H33: =IF(Dashboard!$B$6="Base Case",Scenarios!H86,IF(Dashboard!$B$6="Optimistic",Scenarios!H171,Scenarios!H256)) -> 0.15785709 | I33: =IF(Dashboard!$B$6="Base Case",Scenarios!I86,IF(Dashboard!$B$6="Optimistic",Scenarios!I171,Scenarios!I256)) -> 0.14618097
A34: ROA % | B34: =IF(Dashboard!$B$6="Base Case",Scenarios!B87,IF(Dashboard!$B$6="Optimistic",Scenarios!B172,Scenarios!B257)) -> 0.1032683 | C34: =IF(Dashboard!$B$6="Base Case",Scenarios!C87,IF(Dashboard!$B$6="Optimistic",Scenarios!C172,Scenarios!C257)) -> 0.11721868 | D34: =IF(Dashboard!$B$6="Base Case",Scenarios!D87,IF(Dashboard!$B$6="Optimistic",Scenarios!D172,Scenarios!D257)) -> 0.12485823 | E34: =IF(Dashboard!$B$6="Base Case",Scenarios!E87,IF(Dashboard!$B$6="Optimistic",Scenarios!E172,Scenarios!E257)) -> 0.079865673 | F34: =IF(Dashboard!$B$6="Base Case",Scenarios!F87,IF(Dashboard!$B$6="Optimistic",Scenarios!F172,Scenarios!F257)) -> 0.086732418 | G34: =IF(Dashboard!$B$6="Base Case",Scenarios!G87,IF(Dashboard!$B$6="Optimistic",Scenarios!G172,Scenarios!G257)) -> 0.090886379 | H34: =IF(Dashboard!$B$6="Base Case",Scenarios!H87,IF(Dashboard!$B$6="Optimistic",Scenarios!H172,Scenarios!H257)) -> 0.092616124 | I34: =IF(Dashboard!$B$6="Base Case",Scenarios!I87,IF(Dashboard!$B$6="Optimistic",Scenarios!I172,Scenarios!I257)) -> 0.092322948
A37: ⚖️ SCENARIO COMPARISON — Terminal Year
A38: Metric | B38: Active Scenario
A39: Revenue | B39: =IF(Dashboard!$B$6="Base Case",Scenarios!I67,IF(Dashboard!$B$6="Optimistic",Scenarios!I152,Scenarios!I237)) -> 1344061
A40: EBITDA | B40: =IF(Dashboard!$B$6="Base Case",Scenarios!I71,IF(Dashboard!$B$6="Optimistic",Scenarios!I156,Scenarios!I241)) -> 231930.98
A41: Net Income | B41: =IF(Dashboard!$B$6="Base Case",Scenarios!I74,IF(Dashboard!$B$6="Optimistic",Scenarios!I159,Scenarios!I244)) -> 103208.62
A42: Free Cash Flow | B42: =IF(Dashboard!$B$6="Base Case",Scenarios!I78,IF(Dashboard!$B$6="Optimistic",Scenarios!I163,Scenarios!I248)) -> 111893.47
A43: Cash Balance | B43: =IF(Dashboard!$B$6="Base Case",Scenarios!I83,IF(Dashboard!$B$6="Optimistic",Scenarios!I168,Scenarios!I253)) -> 513760.27
A44: Total Equity | B44: =IF(Dashboard!$B$6="Base Case",Scenarios!I82,IF(Dashboard!$B$6="Optimistic",Scenarios!I167,Scenarios!I252)) -> 760057.27
A45: ROE | B45: =IF(Dashboard!$B$6="Base Case",Scenarios!I86,IF(Dashboard!$B$6="Optimistic",Scenarios!I171,Scenarios!I256)) -> 0.14618097
A46: Gross Margin | B46: =IF(Dashboard!$B$6="Base Case",Scenarios!I70,IF(Dashboard!$B$6="Optimistic",Scenarios!I155,Scenarios!I240)) -> 0.4
A48: ⚠ The scenario selector (B6) drives the entire model. Edit scenario values in the Scenarios sheet.

Sheet Company Info
A1: COMPANY INFORMATION & MODEL CONFIGURATION
A3: SECTION 1 — COMPANY IDENTIFICATION
A4: Company Name | B4: WOLF | C4: ← Edit
A5: Legal Entity Type | B5: Société Anonyme (S.A.E.) | C5: ← Edit
A6: Industry / Sector | B6: Technology / Software | C6: ← Edit
A7: Founded Year | B7: 2010 | C7: ← Edit
A8: Commercial Register No. | B8: 12345-Cairo-2010 | C8: Auto
A9: Tax Identification No. | B9: 123-456-789 | C9: Auto
A10: Headquarters Address | B10: 5 El-Nile Street, Zamalek, Cairo, Egypt | C10: Auto
A12: SECTION 2 — FINANCIAL MODEL CONFIGURATION
A13: Reporting Currency | B13: Egyptian Pound (EGP) | C13: Auto
A14: Currency Symbol | B14: E£ | C14: Auto
A15: Fiscal Year End | B15: December 31 | C15: ← Edit
A16: Historical Period | B16: 2021 – 2023 (Actual) | C16: Auto
A17: Projection Period | B17: 2024E – 2028E (5 Years) | C17: Auto
A18: Revenue Projection Base (E£) | B18: 1000000 | C18: ← Edit
A19: Model Version | B19: v2.0 | Feb 2026 | C19: Auto
A20: Last Updated | B20: February 20, 2026 | C20: Auto
A22: SECTION 3 — EGYPT REGULATORY / TAX
A23: Corporate Income Tax Rate | B23: 0.225 | C23: ← Edit
A24: VAT Rate (Standard) | B24: 0.14 | C24: ← Edit
A25: Dividend Withholding Tax | B25: 0.1 | C25: ← Edit
A26: CBE Policy Rate (Reference) | B26: 0.2725 | C26: ← Edit
A27: Financial Year Note | B27: July 1 – June 30 (Note: model uses Dec) | C27: Auto
A29: SECTION 4 — REPORT & PREPARER INFORMATION
A30: Prepared By | B30: Financial Modeling Team | C30: ← Edit
A31: Reviewed By | B31: CFO | C31: ← Edit
A32: Preparation Date | B32: February 20, 2026 | C32: ← Edit
A33: Purpose | B33: Internal Planning & Analysis | C33: ← Edit
A34: Confidentiality | B34: CONFIDENTIAL — Internal Use Only | C34: ← Edit
A35: Contact Email | B35: finance@democompany.com | C35: ← Edit
A37: Note: Blue-text cells are editable inputs. Company Name (B4) flows to Dashboard and all sheet headers.

Sheet Scenarios
A1: SCENARIO DATA — COMPLETE ENGINE VALUES
A2: This sheet stores the full engine-computed data for each scenario. All projection columns in Assumptions reference this sheet via IF formulas.
A4: ▎ BASE CASE · Moderate growth with stable margins
A5: Assumption / Computed Value | B5: 2021 | C5: 2022 | D5: 2023 | E5: 2024E | F5: 2025E | G5: 2026E | H5: 2027E | I5: 2028E
A6: ── Income Statement Drivers ──
A7: Revenue Base (Historical) | B7: 750000 | C7: 0 | D7: 0 | E7: 0 | F7: 0 | G7: 0 | H7: 0 | I7: 0
A8: Revenue Base (Projection) | B8: 1000000 | C8: 0 | D8: 0 | E8: 0 | F8: 0 | G8: 0 | H8: 0 | I8: 0
A9: Revenue Growth Rate | B9: 0 | C9: 0.13333333 | D9: 0.11764706 | E9: 0.1 | F9: 0.08 | G9: 0.07 | H9: 0.06 | I9: 0.05
A10: COGS % of Revenue | B10: 0.6 | C10: 0.6 | D10: 0.6 | E10: 0.6 | F10: 0.6 | G10: 0.6 | H10: 0.6 | I10: 0.6
A11: SG&A % of Revenue | B11: 0.15 | C11: 0.15 | D11: 0.15 | E11: 0.15 | F11: 0.15 | G11: 0.15 | H11: 0.15 | I11: 0.15
A12: R&D % of Revenue | B12: 0.05 | C12: 0.05 | D12: 0.05 | E12: 0.05 | F12: 0.05 | G12: 0.05 | H12: 0.05 | I12: 0.05
A13: Other OpEx % of Revenue | B13: 0.02 | C13: 0.02 | D13: 0.02 | E13: 0.02 | F13: 0.02 | G13: 0.02 | H13: 0.02 | I13: 0.02
A14: Tax Rate | B14: 0.2513587 | C14: 0.25230415 | D14: 0.25201613 | E14: 0.225 | F14: 0.225 | G14: 0.225 | H14: 0.225 | I14: 0.225
A15: Other Income / Expense | B15: 0 | C15: 0 | D15: 0 | E15: 0 | F15: 0 | G15: 0 | H15: 0 | I15: 0
A16: Shares Outstanding | B16: 100000 | C16: 100000 | D16: 100000 | E16: 100000 | F16: 100000 | G16: 100000 | H16: 100000 | I16: 100000
A17: Stock-Based Comp Amount | B17: 0 | C17: 0 | D17: 0 | E17: 10000 | F17: 10000 | G17: 10000 | H17: 10000 | I17: 10000
A18: ── Balance Sheet / WC Drivers ──
A19: DSO (Days) | B19: 45.00012 | C19: 45.000206 | D19: 44.999889 | E19: 45 | F19: 45 | G19: 45 | H19: 45 | I19: 45
A20: DIO (Days) | B20: 29.999756 | C20: 30.000137 | D20: 29.999798 | E20: 30 | F20: 30 | G20: 30 | H20: 30 | I20: 30
A21: DPO (Days) | B21: 39.999944 | C21: 39.999706 | D21: 40.000158 | E21: 40 | F21: 40 | G21: 40 | H21: 40 | I21: 40
A22: Prepaid % of Revenue | B22: 0.01 | C22: 0.01 | D22: 0.01 | E22: 0.01 | F22: 0.01 | G22: 0.01 | H22: 0.01 | I22: 0.01
A23: Accrued Exp % of Revenue | B23: 0.03 | C23: 0.03 | D23: 0.03 | E23: 0.03 | F23: 0.03 | G23: 0.03 | H23: 0.03 | I23: 0.03
A24: Deferred Rev % of Revenue | B24: 0.02 | C24: 0.02 | D24: 0.02 | E24: 0.02 | F24: 0.02 | G24: 0.02 | H24: 0.02 | I24: 0.02
A25: ── CapEx & Depreciation ──
A26: CapEx % of Revenue | B26: 0 | C26: 0.047058824 | D26: 0.047368421 | E26: 0.05 | F26: 0.05 | G26: 0.05 | H26: 0.05 | I26: 0.05
A27: Depreciation Rate (% Gross PPE) | B27: 0.083333333 | C27: 0.082352941 | D27: 0.083116883 | E27: 0.094025157 | F27: 0.094284759 | G27: 0.094551124 | H27: 0.094822299 | I27: 0.095096572
A28: Amortization Amount | B28: 5000 | C28: 5000 | D28: 5000 | E28: 5000 | F28: 5000 | G28: 5000 | H28: 5000 | I28: 5000
A29: ── Debt & Financing ──
A30: Interest Rate (on Debt) | B30: 0.2 | C30: 0.2 | D30: 0.2 | E30: 0.2 | F30: 0.2 | G30: 0.2 | H30: 0.2 | I30: 0.2
A31: Interest Income Rate (on Cash) | B31: 0.02 | C31: 0.02 | D31: 0.02 | E31: 0.02 | F31: 0.02 | G31: 0.02 | H31: 0.02 | I31: 0.02
A32: Short-Term Debt | B32: 50000 | C32: 50000 | D32: 50000 | E32: 50000 | F32: 50000 | G32: 50000 | H32: 50000 | I32: 50000
A33: LT Debt Issuance | B33: 0 | C33: 0 | D33: 0 | E33: 0 | F33: 0 | G33: 0 | H33: 0 | I33: 0
A34: LT Debt Repayment | B34: 0 | C34: 20000 | D34: 20000 | E34: 20000 | F34: 20000 | G34: 20000 | H34: 20000 | I34: 20000
A35: Current Portion LTD | B35: 20000 | C35: 20000 | D35: 20000 | E35: 20000 | F35: 20000 | G35: 20000 | H35: 20000 | I35: 20000
A36: Dividend Payout Ratio | B36: 0 | C36: 0.39986441 | D36: 0.46433423 | E36: 0.05 | F36: 0.05 | G36: 0.05 | H36: 0.05 | I36: 0.05
A37: Share Repurchase Amount | B37: 0 | C37: 0 | D37: 0 | E37: 0 | F37: 0 | G37: 0 | H37: 0 | I37: 0
A38: Equity Issuance | B38: 0 | C38: 10000 | D38: 10000 | E38: 0 | F38: 0 | G38: 0 | H38: 0 | I38: 0
A39: ── BS / Equity Direct Values ──
A40: Goodwill | B40: 100000 | C40: 100000 | D40: 100000 | E40: 100000 | F40: 100000 | G40: 100000 | H40: 100000 | I40: 100000
A41: Other Current Assets | B41: 10000 | C41: 10000 | D41: 10000 | E41: 10000 | F41: 10000 | G41: 10000 | H41: 10000 | I41: 10000
A42: Other Long-Term Assets | B42: 20000 | C42: 20000 | D42: 20000 | E42: 20000 | F42: 20000 | G42: 20000 | H42: 20000 | I42: 20000
A43: Other Current Liabilities | B43: 15000 | C43: 15000 | D43: 15000 | E43: 15000 | F43: 15000 | G43: 15000 | H43: 15000 | I43: 15000
A44: Deferred Tax Liabilities | B44: 30000 | C44: 30000 | D44: 30000 | E44: 30000 | F44: 30000 | G44: 30000 | H44: 30000 | I44: 30000
A45: Other LT Liabilities | B45: 25000 | C45: 25000 | D45: 25000 | E45: 25000 | F45: 25000 | G45: 25000 | H45: 25000 | I45: 25000
A46: Common Stock | B46: 10000 | C46: 10000 | D46: 10000 | E46: 10000 | F46: 10000 | G46: 10000 | H46: 10000 | I46: 10000
A47: APIC | B47: 200000 | C47: 210000 | D47: 220000 | E47: 230000 | F47: 240000 | G47: 250000 | H47: 260000 | I47: 270000
A48: Other Comprehensive Income | B48: 0 | C48: 0 | D48: 0 | E48: 0 | F48: 0 | G48: 0 | H48: 0 | I48: 0
A49: ── Engine-Computed Values ──
A50: Interest Income (Computed) | B50: 2000 | C50: 2500 | D50: 3000 | E50: ='_Calc_Base'!E14 -> 4381.5518 | F50: ='_Calc_Base'!F14 -> 5271.6108 | G50: ='_Calc_Base'!G14 -> 6410.1322 | H50: ='_Calc_Base'!H14 -> 7790.3454 | I50: ='_Calc_Base'!I14 -> 9407.875
A51: Interest Expense (Computed) | B51: 15000 | C51: 14000 | D51: 13000 | E51: ='_Calc_Base'!E15 -> 54000 | F51: ='_Calc_Base'!F15 -> 50000 | G51: ='_Calc_Base'!G15 -> 46000 | H51: ='_Calc_Base'!H15 -> 42000 | I51: ='_Calc_Base'!I15 -> 38000
A52: Depreciation (Computed) | B52: 25000 | C52: 28000 | D52: 32000 | E52: ='_Calc_Base'!E8 -> 41112.5 | F52: ='_Calc_Base'!F8 -> 46546.5 | G52: ='_Calc_Base'!G8 -> 52387.005 | H52: ='_Calc_Base'!H8 -> 58606.155 | I52: ='_Calc_Base'!I8 -> 65166.453
A53: Gross PP&E (Computed) | B53: 300000 | C53: 340000 | D53: 385000 | E53: ='_Calc_Base'!E28 -> 437250 | F53: ='_Calc_Base'!F28 -> 493680 | G53: ='_Calc_Base'!G28 -> 554060.1 | H53: ='_Calc_Base'!H28 -> 618063.01 | I53: ='_Calc_Base'!I28 -> 685266.06
A54: Accum Depreciation (Computed) | B54: 100000 | C54: 128000 | D54: 160000 | E54: ='_Calc_Base'!E29 -> 201112.5 | F54: ='_Calc_Base'!F29 -> 247659 | G54: ='_Calc_Base'!G29 -> 300046.01 | H54: ='_Calc_Base'!H29 -> 358652.16 | I54: ='_Calc_Base'!I29 -> 423818.61
A55: Net PP&E (Computed) | B55: 200000 | C55: 212000 | D55: 225000 | E55: ='_Calc_Base'!E30 -> 236137.5 | F55: ='_Calc_Base'!F30 -> 246021 | G55: ='_Calc_Base'!G30 -> 254014.09 | H55: ='_Calc_Base'!H30 -> 259410.85 | I55: ='_Calc_Base'!I30 -> 261447.44
A56: Intangibles (Computed) | B56: 50000 | C56: 45000 | D56: 40000 | E56: ='_Calc_Base'!E31 -> 35000 | F56: ='_Calc_Base'!F31 -> 30000 | G56: ='_Calc_Base'!G31 -> 25000 | H56: ='_Calc_Base'!H31 -> 20000 | I56: ='_Calc_Base'!I31 -> 15000
A57: Long-Term Debt (Computed) | B57: 250000 | C57: 230000 | D57: 210000 | E57: ='_Calc_Base'!E45 -> 190000 | F57: ='_Calc_Base'!F45 -> 170000 | G57: ='_Calc_Base'!G45 -> 150000 | H57: ='_Calc_Base'!H45 -> 130000 | I57: ='_Calc_Base'!I45 -> 110000
A58: Retained Earnings (Computed) | B58: -19863 | C58: 28823 | D58: 78506 | E58: ='_Calc_Base'!E53 -> 139150.21 | F58: ='_Calc_Base'!F53 -> 210473.04 | G58: ='_Calc_Base'!G53 -> 291748.77 | H58: ='_Calc_Base'!H53 -> 382009.09 | I58: ='_Calc_Base'!I53 -> 480057.27
A59: Treasury Stock (Computed) | B59: 0 | C59: 0 | D59: 0 | E59: ='_Calc_Base'!E54 -> 0 | F59: ='_Calc_Base'!F54 -> 0 | G59: ='_Calc_Base'!G54 -> 0 | H59: ='_Calc_Base'!H54 -> 0 | I59: ='_Calc_Base'!I54 -> 0
A60: APIC (Computed) | B60: 200000 | C60: 210000 | D60: 220000 | E60: ='_Calc_Base'!E52 -> 230000 | F60: ='_Calc_Base'!F52 -> 240000 | G60: ='_Calc_Base'!G52 -> 250000 | H60: ='_Calc_Base'!H52 -> 260000 | I60: ='_Calc_Base'!I52 -> 270000
A61: Dividends Paid (Computed) | B61: 0 | C61: -32439 | D61: -43067 | E61: ='_Calc_Base'!E82 -> -3191.8008 | F61: ='_Calc_Base'!F82 -> -3753.833 | G61: ='_Calc_Base'!G82 -> -4277.6701 | H61: ='_Calc_Base'!H82 -> -4750.5428 | I61: ='_Calc_Base'!I82 -> -5160.4308
A62: Equity Issuance (Computed) | B62: 0 | C62: 10000 | D62: 10000 | E62: ='_Calc_Base'!E83 -> 0 | F62: ='_Calc_Base'!F83 -> 0 | G62: ='_Calc_Base'!G83 -> 0 | H62: ='_Calc_Base'!H83 -> 0 | I62: ='_Calc_Base'!I83 -> 0
A63: Share Repurchases (Computed) | B63: 0 | C63: 0 | D63: 0 | E63: ='_Calc_Base'!E84 -> 0 | F63: ='_Calc_Base'!F84 -> 0 | G63: ='_Calc_Base'!G84 -> 0 | H63: ='_Calc_Base'!H84 -> 0 | I63: ='_Calc_Base'!I84 -> 0
A64: Acquisitions (Computed) | B64: 0 | C64: 0 | D64: 0 | E64: ='_Calc_Base'!E76 -> 0 | F64: ='_Calc_Base'!F76 -> 0 | G64: ='_Calc_Base'!G76 -> 0 | H64: ='_Calc_Base'!H76 -> 0 | I64: ='_Calc_Base'!I76 -> 0
A65: Asset Sales (Computed) | B65: 0 | C65: 0 | D65: 0 | E65: ='_Calc_Base'!E77 -> 0 | F65: ='_Calc_Base'!F77 -> 0 | G65: ='_Calc_Base'!G77 -> 0 | H65: ='_Calc_Base'!H77 -> 0 | I65: ='_Calc_Base'!I77 -> 0
A66: ── Dashboard Output Metrics ──
A67: Revenue | B67: 750000 | C67: 850000 | D67: 950000 | E67: ='_Calc_Base'!E2 -> 1045000 | F67: ='_Calc_Base'!F2 -> 1128600 | G67: ='_Calc_Base'!G2 -> 1207602 | H67: ='_Calc_Base'!H2 -> 1280058.1 | I67: ='_Calc_Base'!I2 -> 1344061
A68: Revenue Growth % | B68: 0 | C68: 0.13333333 | D68: 0.11764706 | E68: =IF(D67=0,0,(Scenarios!E67-D67)/D67) -> 0.1 | F68: =IF(E67=0,0,(Scenarios!F67-E67)/E67) -> 0.08 | G68: =IF(F67=0,0,(Scenarios!G67-F67)/F67) -> 0.07 | H68: =IF(G67=0,0,(Scenarios!H67-G67)/G67) -> 0.06 | I68: =IF(H67=0,0,(Scenarios!I67-H67)/H67) -> 0.05
A69: Gross Profit | B69: 300000 | C69: 340000 | D69: 380000 | E69: ='_Calc_Base'!E5 -> 418000 | F69: ='_Calc_Base'!F5 -> 451440 | G69: ='_Calc_Base'!G5 -> 483040.8 | H69: ='_Calc_Base'!H5 -> 512023.25 | I69: ='_Calc_Base'!I5 -> 537624.41
A70: Gross Margin % | B70: 0.4 | C70: 0.4 | D70: 0.4 | E70: =IF('_Calc_Base'!E2=0,0,'_Calc_Base'!E5/'_Calc_Base'!E2) -> 0.4 | F70: =IF('_Calc_Base'!F2=0,0,'_Calc_Base'!F5/'_Calc_Base'!F2) -> 0.4 | G70: =IF('_Calc_Base'!G2=0,0,'_Calc_Base'!G5/'_Calc_Base'!G2) -> 0.4 | H70: =IF('_Calc_Base'!H2=0,0,'_Calc_Base'!H5/'_Calc_Base'!H2) -> 0.4 | I70: =IF('_Calc_Base'!I2=0,0,'_Calc_Base'!I5/'_Calc_Base'!I2) -> 0.4
A71: EBITDA | B71: 135000 | C71: 153000 | D71: 171000 | E71: ='_Calc_Base'!E13+'_Calc_Base'!E8+'_Calc_Base'!E9 -> 178100 | F71: ='_Calc_Base'!F13+'_Calc_Base'!F8+'_Calc_Base'!F9 -> 193148 | G71: ='_Calc_Base'!G13+'_Calc_Base'!G8+'_Calc_Base'!G9 -> 207368.36 | H71: ='_Calc_Base'!H13+'_Calc_Base'!H8+'_Calc_Base'!H9 -> 220410.46 | I71: ='_Calc_Base'!I13+'_Calc_Base'!I8+'_Calc_Base'!I9 -> 231930.98
A72: EBIT | B72: 105000 | C72: 120000 | D72: 134000 | E72: ='_Calc_Base'!E13 -> 131987.5 | F72: ='_Calc_Base'!F13 -> 141601.5 | G72: ='_Calc_Base'!G13 -> 149981.36 | H72: ='_Calc_Base'!H13 -> 156804.31 | I72: ='_Calc_Base'!I13 -> 161764.53
A73: EBIT Margin % | B73: 0.14 | C73: 0.14117647 | D73: 0.14105263 | E73: =IF('_Calc_Base'!E2=0,0,'_Calc_Base'!E13/'_Calc_Base'!E2) -> 0.12630383 | F73: =IF('_Calc_Base'!F2=0,0,'_Calc_Base'!F13/'_Calc_Base'!F2) -> 0.12546651 | G73: =IF('_Calc_Base'!G2=0,0,'_Calc_Base'!G13/'_Calc_Base'!G2) -> 0.12419767 | H73: =IF('_Calc_Base'!H2=0,0,'_Calc_Base'!H13/'_Calc_Base'!H2) -> 0.1224978 | I73: =IF('_Calc_Base'!I2=0,0,'_Calc_Base'!I13/'_Calc_Base'!I2) -> 0.12035505
A74: Net Income | B74: 68875 | C74: 81125 | D74: 92750 | E74: ='_Calc_Base'!E19 -> 63836.015 | F74: ='_Calc_Base'!F19 -> 75076.661 | G74: ='_Calc_Base'!G19 -> 85553.403 | H74: ='_Calc_Base'!H19 -> 95010.855 | I74: ='_Calc_Base'!I19 -> 103208.62
A75: Net Margin % | B75: 0.091833333 | C75: 0.095441176 | D75: 0.097631579 | E75: =IF('_Calc_Base'!E2=0,0,'_Calc_Base'!E19/'_Calc_Base'!E2) -> 0.061087096 | F75: =IF('_Calc_Base'!F2=0,0,'_Calc_Base'!F19/'_Calc_Base'!F2) -> 0.066521939 | G75: =IF('_Calc_Base'!G2=0,0,'_Calc_Base'!G19/'_Calc_Base'!G2) -> 0.070845695 | H75: =IF('_Calc_Base'!H2=0,0,'_Calc_Base'!H19/'_Calc_Base'!H2) -> 0.07422386 | I75: =IF('_Calc_Base'!I2=0,0,'_Calc_Base'!I19/'_Calc_Base'!I2) -> 0.076788638
A76: EPS | B76: 0.68875 | C76: 0.81125 | D76: 0.9275 | E76: ='_Calc_Base'!E19/Scenarios!E16 -> 0.63836015 | F76: ='_Calc_Base'!F19/Scenarios!F16 -> 0.75076661 | G76: ='_Calc_Base'!G19/Scenarios!G16 -> 0.85553403 | H76: ='_Calc_Base'!H19/Scenarios!H16 -> 0.95010855 | I76: ='_Calc_Base'!I19/Scenarios!I16 -> 1.0320862
A77: Cash from Operations | B77: 0 | C77: 107439 | D77: 123067 | E77: ='_Calc_Base'!E73 -> 113596.98 | F77: ='_Calc_Base'!F73 -> 131034.56 | G77: ='_Calc_Base'!G73 -> 147659.18 | H77: ='_Calc_Base'!H73 -> 163773.37 | I77: ='_Calc_Base'!I73 -> 179096.52
A78: Free Cash Flow | B78: 0 | C78: 67439 | D78: 78067 | E78: ='_Calc_Base'!E90 -> 61346.981 | F78: ='_Calc_Base'!F90 -> 74604.558 | G78: ='_Calc_Base'!G90 -> 87279.078 | H78: ='_Calc_Base'!H90 -> 99770.462 | I78: ='_Calc_Base'!I90 -> 111893.47
A79: Ending Cash | B79: 0 | C79: 175000 | D79: 200000 | E79: ='_Calc_Base'!E89 -> 238155.18 | F79: ='_Calc_Base'!F89 -> 289005.91 | G79: ='_Calc_Base'!G89 -> 352007.31 | H79: ='_Calc_Base'!H89 -> 427027.23 | I79: ='_Calc_Base'!I89 -> 513760.27
A80: Total Assets | B80: 666952 | C80: 717213 | D80: 768472 | E80: ='_Calc_Base'!E35 -> 830112.54 | F80: ='_Calc_Base'!F35 -> 901112.36 | G80: ='_Calc_Base'!G35 -> 981532.84 | H80: ='_Calc_Base'!H35 -> 1070180.2 | I80: ='_Calc_Base'!I35 -> 1165636.9
A81: Total Debt | B81: 320000 | C81: 300000 | D81: 280000 | E81: ='_Calc_Base'!E39+'_Calc_Base'!E45 -> 260000 | F81: ='_Calc_Base'!F39+'_Calc_Base'!F45 -> 240000 | G81: ='_Calc_Base'!G39+'_Calc_Base'!G45 -> 220000 | H81: ='_Calc_Base'!H39+'_Calc_Base'!H45 -> 200000 | I81: ='_Calc_Base'!I39+'_Calc_Base'!I45 -> 180000
A82: Total Equity | B82: 190137 | C82: 248823 | D82: 308506 | E82: ='_Calc_Base'!E56 -> 379150.21 | F82: ='_Calc_Base'!F56 -> 460473.04 | G82: ='_Calc_Base'!G56 -> 551748.77 | H82: ='_Calc_Base'!H56 -> 652009.09 | I82: ='_Calc_Base'!I56 -> 760057.27
A83: Cash Balance | B83: 150000 | C83: 175000 | D83: 200000 | E83: ='_Calc_Base'!E21 -> 238155.18 | F83: ='_Calc_Base'!F21 -> 289005.91 | G83: ='_Calc_Base'!G21 -> 352007.31 | H83: ='_Calc_Base'!H21 -> 427027.23 | I83: ='_Calc_Base'!I21 -> 513760.27
A84: Current Ratio | B84: 1.7283241 | C84: 1.8551339 | D84: 1.966866 | E84: =IF('_Calc_Base'!E43=0,0,'_Calc_Base'!E26/'_Calc_Base'!E43) -> 2.1313366 | F84: =IF('_Calc_Base'!F43=0,0,'_Calc_Base'!F26/'_Calc_Base'!F43) -> 2.3422972 | G84: =IF('_Calc_Base'!G43=0,0,'_Calc_Base'!G26/'_Calc_Base'!G43) -> 2.5914592 | H84: =IF('_Calc_Base'!H43=0,0,'_Calc_Base'!H26/'_Calc_Base'!H43) -> 2.8767258 | I84: =IF('_Calc_Base'!I43=0,0,'_Calc_Base'!I26/'_Calc_Base'!I43) -> 3.197234
A85: Debt / Equity | B85: 1.682997 | C85: 1.2056763 | D85: 0.90759985 | E85: =IF('_Calc_Base'!E56=0,0,('_Calc_Base'!E39+'_Calc_Base'!E45)/'_Calc_Base'!E56) -> 0.68574404 | F85: =IF('_Calc_Base'!F56=0,0,('_Calc_Base'!F39+'_Calc_Base'!F45)/'_Calc_Base'!F56) -> 0.52120315 | G85: =IF('_Calc_Base'!G56=0,0,('_Calc_Base'!G39+'_Calc_Base'!G45)/'_Calc_Base'!G56) -> 0.39873219 | H85: =IF('_Calc_Base'!H56=0,0,('_Calc_Base'!H39+'_Calc_Base'!H45)/'_Calc_Base'!H56) -> 0.30674419 | I85: =IF('_Calc_Base'!I56=0,0,('_Calc_Base'!I39+'_Calc_Base'!I45)/'_Calc_Base'!I56) -> 0.23682426
A86: ROE % | B86: 0.36223881 | C86: 0.36962366 | D86: 0.33283752 | E86: =IF('_Calc_Base'!E56=0,0,'_Calc_Base'!E19/'_Calc_Base'!E56) -> 0.18566258 | F86: =IF('_Calc_Base'!F56=0,0,'_Calc_Base'!F19/'_Calc_Base'!F56) -> 0.17883416 | G86: =IF('_Calc_Base'!G56=0,0,'_Calc_Base'!G19/'_Calc_Base'!G56) -> 0.16904082 | H86: =IF('_Calc_Base'!H56=0,0,'_Calc_Base'!H19/'_Calc_Base'!H56) -> 0.15785709 | I86: =IF('_Calc_Base'!I56=0,0,'_Calc_Base'!I19/'_Calc_Base'!I56) -> 0.14618097
A87: ROA % | B87: 0.1032683 | C87: 0.11721868 | D87: 0.12485823 | E87: =IF('_Calc_Base'!E35=0,0,'_Calc_Base'!E19/'_Calc_Base'!E35) -> 0.079865673 | F87: =IF('_Calc_Base'!F35=0,0,'_Calc_Base'!F19/'_Calc_Base'!F35) -> 0.086732418 | G87: =IF('_Calc_Base'!G35=0,0,'_Calc_Base'!G19/'_Calc_Base'!G35) -> 0.090886379 | H87: =IF('_Calc_Base'!H35=0,0,'_Calc_Base'!H19/'_Calc_Base'!H35) -> 0.092616124 | I87: =IF('_Calc_Base'!I35=0,0,'_Calc_Base'!I19/'_Calc_Base'!I35) -> 0.092322948
A89: ▎ OPTIMISTIC · High growth with margin expansion
A90: Assumption / Computed Value | B90: 2021 | C90: 2022 | D90: 2023 | E90: 2024E | F90: 2025E | G90: 2026E | H90: 2027E | I90: 2028E
A91: ── Income Statement Drivers ──
A92: Revenue Base (Historical) | B92: 750000 | C92: 0 | D92: 0 | E92: 0 | F92: 0 | G92: 0 | H92: 0 | I92: 0
A93: Revenue Base (Projection) | B93: 1000000 | C93: 0 | D93: 0 | E93: 0 | F93: 0 | G93: 0 | H93: 0 | I93: 0
A94: Revenue Growth Rate | B94: 0 | C94: 0.13333333 | D94: 0.11764706 | E94: 0.15 | F94: 0.12 | G94: 0.1 | H94: 0.09 | I94: 0.08
A95: COGS % of Revenue | B95: 0.6 | C95: 0.6 | D95: 0.6 | E95: 0.55 | F95: 0.54 | G95: 0.53 | H95: 0.52 | I95: 0.51
A96: SG&A % of Revenue | B96: 0.15 | C96: 0.15 | D96: 0.15 | E96: 0.13 | F96: 0.12 | G96: 0.12 | H96: 0.11 | I96: 0.11
A97: R&D % of Revenue | B97: 0.05 | C97: 0.05 | D97: 0.05 | E97: 0.05 | F97: 0.05 | G97: 0.05 | H97: 0.05 | I97: 0.05
A98: Other OpEx % of Revenue | B98: 0.02 | C98: 0.02 | D98: 0.02 | E98: 0.02 | F98: 0.02 | G98: 0.02 | H98: 0.02 | I98: 0.02
A99: Tax Rate | B99: 0.2513587 | C99: 0.25230415 | D99: 0.25201613 | E99: 0.225 | F99: 0.225 | G99: 0.225 | H99: 0.225 | I99: 0.225
A100: Other Income / Expense | B100: 0 | C100: 0 | D100: 0 | E100: 0 | F100: 0 | G100: 0 | H100: 0 | I100: 0
A101: Shares Outstanding | B101: 100000 | C101: 100000 | D101: 100000 | E101: 100000 | F101: 100000 | G101: 100000 | H101: 100000 | I101: 100000
A102: Stock-Based Comp Amount | B102: 0 | C102: 0 | D102: 0 | E102: 10000 | F102: 10000 | G102: 10000 | H102: 10000 | I102: 10000
...

Sheet Assumptions
A1: Assumption | B1: 2021 | C1: 2022 | D1: 2023 | E1: 2024E | F1: 2025E | G1: 2026E | H1: 2027E | I1: 2028E
A2: ── Income Statement Drivers ──
A3: Revenue Base (Historical) | B3: 750000 | E3: =IF(Assumptions!$B$64="Base Case",Scenarios!E7,IF(Assumptions!$B$64="Optimistic",Scenarios!E92,Scenarios!E177)) -> 0 | F3: =IF(Assumptions!$B$64="Base Case",Scenarios!F7,IF(Assumptions!$B$64="Optimistic",Scenarios!F92,Scenarios!F177)) -> 0 | G3: =IF(Assumptions!$B$64="Base Case",Scenarios!G7,IF(Assumptions!$B$64="Optimistic",Scenarios!G92,Scenarios!G177)) -> 0 | H3: =IF(Assumptions!$B$64="Base Case",Scenarios!H7,IF(Assumptions!$B$64="Optimistic",Scenarios!H92,Scenarios!H177)) -> 0 | I3: =IF(Assumptions!$B$64="Base Case",Scenarios!I7,IF(Assumptions!$B$64="Optimistic",Scenarios!I92,Scenarios!I177)) -> 0
A4: Revenue Base (Projection) | B4: 1000000 | E4: =IF(Assumptions!$B$64="Base Case",Scenarios!E8,IF(Assumptions!$B$64="Optimistic",Scenarios!E93,Scenarios!E178)) -> 0 | F4: =IF(Assumptions!$B$64="Base Case",Scenarios!F8,IF(Assumptions!$B$64="Optimistic",Scenarios!F93,Scenarios!F178)) -> 0 | G4: =IF(Assumptions!$B$64="Base Case",Scenarios!G8,IF(Assumptions!$B$64="Optimistic",Scenarios!G93,Scenarios!G178)) -> 0 | H4: =IF(Assumptions!$B$64="Base Case",Scenarios!H8,IF(Assumptions!$B$64="Optimistic",Scenarios!H93,Scenarios!H178)) -> 0 | I4: =IF(Assumptions!$B$64="Base Case",Scenarios!I8,IF(Assumptions!$B$64="Optimistic",Scenarios!I93,Scenarios!I178)) -> 0
A5: Revenue Growth Rate | B5: 0 | C5: 0.13333333 | D5: 0.11764706 | E5: =IF(Assumptions!$B$64="Base Case",Scenarios!E9,IF(Assumptions!$B$64="Optimistic",Scenarios!E94,Scenarios!E179)) -> 0.1 | F5: =IF(Assumptions!$B$64="Base Case",Scenarios!F9,IF(Assumptions!$B$64="Optimistic",Scenarios!F94,Scenarios!F179)) -> 0.08 | G5: =IF(Assumptions!$B$64="Base Case",Scenarios!G9,IF(Assumptions!$B$64="Optimistic",Scenarios!G94,Scenarios!G179)) -> 0.07 | H5: =IF(Assumptions!$B$64="Base Case",Scenarios!H9,IF(Assumptions!$B$64="Optimistic",Scenarios!H94,Scenarios!H179)) -> 0.06 | I5: =IF(Assumptions!$B$64="Base Case",Scenarios!I9,IF(Assumptions!$B$64="Optimistic",Scenarios!I94,Scenarios!I179)) -> 0.05
A6: COGS % of Revenue | B6: 0.6 | C6: 0.6 | D6: 0.6 | E6: =IF(Assumptions!$B$64="Base Case",Scenarios!E10,IF(Assumptions!$B$64="Optimistic",Scenarios!E95,Scenarios!E180)) -> 0.6 | F6: =IF(Assumptions!$B$64="Base Case",Scenarios!F10,IF(Assumptions!$B$64="Optimistic",Scenarios!F95,Scenarios!F180)) -> 0.6 | G6: =IF(Assumptions!$B$64="Base Case",Scenarios!G10,IF(Assumptions!$B$64="Optimistic",Scenarios!G95,Scenarios!G180)) -> 0.6 | H6: =IF(Assumptions!$B$64="Base Case",Scenarios!H10,IF(Assumptions!$B$64="Optimistic",Scenarios!H95,Scenarios!H180)) -> 0.6 | I6: =IF(Assumptions!$B$64="Base Case",Scenarios!I10,IF(Assumptions!$B$64="Optimistic",Scenarios!I95,Scenarios!I180)) -> 0.6
A7: SG&A % of Revenue | B7: 0.15 | C7: 0.15 | D7: 0.15 | E7: =IF(Assumptions!$B$64="Base Case",Scenarios!E11,IF(Assumptions!$B$64="Optimistic",Scenarios!E96,Scenarios!E181)) -> 0.15 | F7: =IF(Assumptions!$B$64="Base Case",Scenarios!F11,IF(Assumptions!$B$64="Optimistic",Scenarios!F96,Scenarios!F181)) -> 0.15 | G7: =IF(Assumptions!$B$64="Base Case",Scenarios!G11,IF(Assumptions!$B$64="Optimistic",Scenarios!G96,Scenarios!G181)) -> 0.15 | H7: =IF(Assumptions!$B$64="Base Case",Scenarios!H11,IF(Assumptions!$B$64="Optimistic",Scenarios!H96,Scenarios!H181)) -> 0.15 | I7: =IF(Assumptions!$B$64="Base Case",Scenarios!I11,IF(Assumptions!$B$64="Optimistic",Scenarios!I96,Scenarios!I181)) -> 0.15
A8: R&D % of Revenue | B8: 0.05 | C8: 0.05 | D8: 0.05 | E8: =IF(Assumptions!$B$64="Base Case",Scenarios!E12,IF(Assumptions!$B$64="Optimistic",Scenarios!E97,Scenarios!E182)) -> 0.05 | F8: =IF(Assumptions!$B$64="Base Case",Scenarios!F12,IF(Assumptions!$B$64="Optimistic",Scenarios!F97,Scenarios!F182)) -> 0.05 | G8: =IF(Assumptions!$B$64="Base Case",Scenarios!G12,IF(Assumptions!$B$64="Optimistic",Scenarios!G97,Scenarios!G182)) -> 0.05 | H8: =IF(Assumptions!$B$64="Base Case",Scenarios!H12,IF(Assumptions!$B$64="Optimistic",Scenarios!H97,Scenarios!H182)) -> 0.05 | I8: =IF(Assumptions!$B$64="Base Case",Scenarios!I12,IF(Assumptions!$B$64="Optimistic",Scenarios!I97,Scenarios!I182)) -> 0.05
A9: Other OpEx % of Revenue | B9: 0.02 | C9: 0.02 | D9: 0.02 | E9: =IF(Assumptions!$B$64="Base Case",Scenarios!E13,IF(Assumptions!$B$64="Optimistic",Scenarios!E98,Scenarios!E183)) -> 0.02 | F9: =IF(Assumptions!$B$64="Base Case",Scenarios!F13,IF(Assumptions!$B$64="Optimistic",Scenarios!F98,Scenarios!F183)) -> 0.02 | G9: =IF(Assumptions!$B$64="Base Case",Scenarios!G13,IF(Assumptions!$B$64="Optimistic",Scenarios!G98,Scenarios!G183)) -> 0.02 | H9: =IF(Assumptions!$B$64="Base Case",Scenarios!H13,IF(Assumptions!$B$64="Optimistic",Scenarios!H98,Scenarios!H183)) -> 0.02 | I9: =IF(Assumptions!$B$64="Base Case",Scenarios!I13,IF(Assumptions!$B$64="Optimistic",Scenarios!I98,Scenarios!I183)) -> 0.02
A10: Tax Rate | B10: 0.2513587 | C10: 0.25230415 | D10: 0.25201613 | E10: =IF(Assumptions!$B$64="Base Case",Scenarios!E14,IF(Assumptions!$B$64="Optimistic",Scenarios!E99,Scenarios!E184)) -> 0.225 | F10: =IF(Assumptions!$B$64="Base Case",Scenarios!F14,IF(Assumptions!$B$64="Optimistic",Scenarios!F99,Scenarios!F184)) -> 0.225 | G10: =IF(Assumptions!$B$64="Base Case",Scenarios!G14,IF(Assumptions!$B$64="Optimistic",Scenarios!G99,Scenarios!G184)) -> 0.225 | H10: =IF(Assumptions!$B$64="Base Case",Scenarios!H14,IF(Assumptions!$B$64="Optimistic",Scenarios!H99,Scenarios!H184)) -> 0.225 | I10: =IF(Assumptions!$B$64="Base Case",Scenarios!I14,IF(Assumptions!$B$64="Optimistic",Scenarios!I99,Scenarios!I184)) -> 0.225
A11: Other Income / Expense | B11: 0 | C11: 0 | D11: 0 | E11: =IF(Assumptions!$B$64="Base Case",Scenarios!E15,IF(Assumptions!$B$64="Optimistic",Scenarios!E100,Scenarios!E185)) -> 0 | F11: =IF(Assumptions!$B$64="Base Case",Scenarios!F15,IF(Assumptions!$B$64="Optimistic",Scenarios!F100,Scenarios!F185)) -> 0 | G11: =IF(Assumptions!$B$64="Base Case",Scenarios!G15,IF(Assumptions!$B$64="Optimistic",Scenarios!G100,Scenarios!G185)) -> 0 | H11: =IF(Assumptions!$B$64="Base Case",Scenarios!H15,IF(Assumptions!$B$64="Optimistic",Scenarios!H100,Scenarios!H185)) -> 0 | I11: =IF(Assumptions!$B$64="Base Case",Scenarios!I15,IF(Assumptions!$B$64="Optimistic",Scenarios!I100,Scenarios!I185)) -> 0
A12: Shares Outstanding | B12: 100000 | C12: 100000 | D12: 100000 | E12: =IF(Assumptions!$B$64="Base Case",Scenarios!E16,IF(Assumptions!$B$64="Optimistic",Scenarios!E101,Scenarios!E186)) -> 100000 | F12: =IF(Assumptions!$B$64="Base Case",Scenarios!F16,IF(Assumptions!$B$64="Optimistic",Scenarios!F101,Scenarios!F186)) -> 100000 | G12: =IF(Assumptions!$B$64="Base Case",Scenarios!G16,IF(Assumptions!$B$64="Optimistic",Scenarios!G101,Scenarios!G186)) -> 100000 | H12: =IF(Assumptions!$B$64="Base Case",Scenarios!H16,IF(Assumptions!$B$64="Optimistic",Scenarios!H101,Scenarios!H186)) -> 100000 | I12: =IF(Assumptions!$B$64="Base Case",Scenarios!I16,IF(Assumptions!$B$64="Optimistic",Scenarios!I101,Scenarios!I186)) -> 100000
A13: Stock-Based Comp Amount | B13: 0 | C13: 0 | D13: 0 | E13: =IF(Assumptions!$B$64="Base Case",Scenarios!E17,IF(Assumptions!$B$64="Optimistic",Scenarios!E102,Scenarios!E187)) -> 10000 | F13: =IF(Assumptions!$B$64="Base Case",Scenarios!F17,IF(Assumptions!$B$64="Optimistic",Scenarios!F102,Scenarios!F187)) -> 10000 | G13: =IF(Assumptions!$B$64="Base Case",Scenarios!G17,IF(Assumptions!$B$64="Optimistic",Scenarios!G102,Scenarios!G187)) -> 10000 | H13: =IF(Assumptions!$B$64="Base Case",Scenarios!H17,IF(Assumptions!$B$64="Optimistic",Scenarios!H102,Scenarios!H187)) -> 10000 | I13: =IF(Assumptions!$B$64="Base Case",Scenarios!I17,IF(Assumptions!$B$64="Optimistic",Scenarios!I102,Scenarios!I187)) -> 10000
A14: ── Balance Sheet / WC Drivers ──
A15: DSO (Days) | B15: 45.00012 | C15: 45.000206 | D15: 44.999889 | E15: =IF(Assumptions!$B$64="Base Case",Scenarios!E19,IF(Assumptions!$B$64="Optimistic",Scenarios!E104,Scenarios!E189)) -> 45 | F15: =IF(Assumptions!$B$64="Base Case",Scenarios!F19,IF(Assumptions!$B$64="Optimistic",Scenarios!F104,Scenarios!F189)) -> 45 | G15: =IF(Assumptions!$B$64="Base Case",Scenarios!G19,IF(Assumptions!$B$64="Optimistic",Scenarios!G104,Scenarios!G189)) -> 45 | H15: =IF(Assumptions!$B$64="Base Case",Scenarios!H19,IF(Assumptions!$B$64="Optimistic",Scenarios!H104,Scenarios!H189)) -> 45 | I15: =IF(Assumptions!$B$64="Base Case",Scenarios!I19,IF(Assumptions!$B$64="Optimistic",Scenarios!I104,Scenarios!I189)) -> 45
A16: DIO (Days) | B16: 29.999756 | C16: 30.000137 | D16: 29.999798 | E16: =IF(Assumptions!$B$64="Base Case",Scenarios!E20,IF(Assumptions!$B$64="Optimistic",Scenarios!E105,Scenarios!E190)) -> 30 | F16: =IF(Assumptions!$B$64="Base Case",Scenarios!F20,IF(Assumptions!$B$64="Optimistic",Scenarios!F105,Scenarios!F190)) -> 30 | G16: =IF(Assumptions!$B$64="Base Case",Scenarios!G20,IF(Assumptions!$B$64="Optimistic",Scenarios!G105,Scenarios!G190)) -> 30 | H16: =IF(Assumptions!$B$64="Base Case",Scenarios!H20,IF(Assumptions!$B$64="Optimistic",Scenarios!H105,Scenarios!H190)) -> 30 | I16: =IF(Assumptions!$B$64="Base Case",Scenarios!I20,IF(Assumptions!$B$64="Optimistic",Scenarios!I105,Scenarios!I190)) -> 30
A17: DPO (Days) | B17: 39.999944 | C17: 39.999706 | D17: 40.000158 | E17: =IF(Assumptions!$B$64="Base Case",Scenarios!E21,IF(Assumptions!$B$64="Optimistic",Scenarios!E106,Scenarios!E191)) -> 40 | F17: =IF(Assumptions!$B$64="Base Case",Scenarios!F21,IF(Assumptions!$B$64="Optimistic",Scenarios!F106,Scenarios!F191)) -> 40 | G17: =IF(Assumptions!$B$64="Base Case",Scenarios!G21,IF(Assumptions!$B$64="Optimistic",Scenarios!G106,Scenarios!G191)) -> 40 | H17: =IF(Assumptions!$B$64="Base Case",Scenarios!H21,IF(Assumptions!$B$64="Optimistic",Scenarios!H106,Scenarios!H191)) -> 40 | I17: =IF(Assumptions!$B$64="Base Case",Scenarios!I21,IF(Assumptions!$B$64="Optimistic",Scenarios!I106,Scenarios!I191)) -> 40
A18: Prepaid % of Revenue | B18: 0.01 | C18: 0.01 | D18: 0.01 | E18: =IF(Assumptions!$B$64="Base Case",Scenarios!E22,IF(Assumptions!$B$64="Optimistic",Scenarios!E107,Scenarios!E192)) -> 0.01 | F18: =IF(Assumptions!$B$64="Base Case",Scenarios!F22,IF(Assumptions!$B$64="Optimistic",Scenarios!F107,Scenarios!F192)) -> 0.01 | G18: =IF(Assumptions!$B$64="Base Case",Scenarios!G22,IF(Assumptions!$B$64="Optimistic",Scenarios!G107,Scenarios!G192)) -> 0.01 | H18: =IF(Assumptions!$B$64="Base Case",Scenarios!H22,IF(Assumptions!$B$64="Optimistic",Scenarios!H107,Scenarios!H192)) -> 0.01 | I18: =IF(Assumptions!$B$64="Base Case",Scenarios!I22,IF(Assumptions!$B$64="Optimistic",Scenarios!I107,Scenarios!I192)) -> 0.01
A19: Accrued Exp % of Revenue | B19: 0.03 | C19: 0.03 | D19: 0.03 | E19: =IF(Assumptions!$B$64="Base Case",Scenarios!E23,IF(Assumptions!$B$64="Optimistic",Scenarios!E108,Scenarios!E193)) -> 0.03 | F19: =IF(Assumptions!$B$64="Base Case",Scenarios!F23,IF(Assumptions!$B$64="Optimistic",Scenarios!F108,Scenarios!F193)) -> 0.03 | G19: =IF(Assumptions!$B$64="Base Case",Scenarios!G23,IF(Assumptions!$B$64="Optimistic",Scenarios!G108,Scenarios!G193)) -> 0.03 | H19: =IF(Assumptions!$B$64="Base Case",Scenarios!H23,IF(Assumptions!$B$64="Optimistic",Scenarios!H108,Scenarios!H193)) -> 0.03 | I19: =IF(Assumptions!$B$64="Base Case",Scenarios!I23,IF(Assumptions!$B$64="Optimistic",Scenarios!I108,Scenarios!I193)) -> 0.03
A20: Deferred Rev % of Revenue | B20: 0.02 | C20: 0.02 | D20: 0.02 | E20: =IF(Assumptions!$B$64="Base Case",Scenarios!E24,IF(Assumptions!$B$64="Optimistic",Scenarios!E109,Scenarios!E194)) -> 0.02 | F20: =IF(Assumptions!$B$64="Base Case",Scenarios!F24,IF(Assumptions!$B$64="Optimistic",Scenarios!F109,Scenarios!F194)) -> 0.02 | G20: =IF(Assumptions!$B$64="Base Case",Scenarios!G24,IF(Assumptions!$B$64="Optimistic",Scenarios!G109,Scenarios!G194)) -> 0.02 | H20: =IF(Assumptions!$B$64="Base Case",Scenarios!H24,IF(Assumptions!$B$64="Optimistic",Scenarios!H109,Scenarios!H194)) -> 0.02 | I20: =IF(Assumptions!$B$64="Base Case",Scenarios!I24,IF(Assumptions!$B$64="Optimistic",Scenarios!I109,Scenarios!I194)) -> 0.02
A21: ── CapEx & Depreciation Drivers ──
A22: CapEx % of Revenue | B22: 0 | C22: 0.047058824 | D22: 0.047368421 | E22: =IF(Assumptions!$B$64="Base Case",Scenarios!E26,IF(Assumptions!$B$64="Optimistic",Scenarios!E111,Scenarios!E196)) -> 0.05 | F22: =IF(Assumptions!$B$64="Base Case",Scenarios!F26,IF(Assumptions!$B$64="Optimistic",Scenarios!F111,Scenarios!F196)) -> 0.05 | G22: =IF(Assumptions!$B$64="Base Case",Scenarios!G26,IF(Assumptions!$B$64="Optimistic",Scenarios!G111,Scenarios!G196)) -> 0.05 | H22: =IF(Assumptions!$B$64="Base Case",Scenarios!H26,IF(Assumptions!$B$64="Optimistic",Scenarios!H111,Scenarios!H196)) -> 0.05 | I22: =IF(Assumptions!$B$64="Base Case",Scenarios!I26,IF(Assumptions!$B$64="Optimistic",Scenarios!I111,Scenarios!I196)) -> 0.05
A23: Depreciation Rate (% Gross PPE) | B23: 0.083333333 | C23: 0.082352941 | D23: 0.083116883 | E23: =IF(Assumptions!$B$64="Base Case",Scenarios!E27,IF(Assumptions!$B$64="Optimistic",Scenarios!E112,Scenarios!E197)) -> 0.094025157 | F23: =IF(Assumptions!$B$64="Base Case",Scenarios!F27,IF(Assumptions!$B$64="Optimistic",Scenarios!F112,Scenarios!F197)) -> 0.094284759 | G23: =IF(Assumptions!$B$64="Base Case",Scenarios!G27,IF(Assumptions!$B$64="Optimistic",Scenarios!G112,Scenarios!G197)) -> 0.094551124 | H23: =IF(Assumptions!$B$64="Base Case",Scenarios!H27,IF(Assumptions!$B$64="Optimistic",Scenarios!H112,Scenarios!H197)) -> 0.094822299 | I23: =IF(Assumptions!$B$64="Base Case",Scenarios!I27,IF(Assumptions!$B$64="Optimistic",Scenarios!I112,Scenarios!I197)) -> 0.095096572
A24: Amortization Amount | B24: 5000 | C24: 5000 | D24: 5000 | E24: =IF(Assumptions!$B$64="Base Case",Scenarios!E28,IF(Assumptions!$B$64="Optimistic",Scenarios!E113,Scenarios!E198)) -> 5000 | F24: =IF(Assumptions!$B$64="Base Case",Scenarios!F28,IF(Assumptions!$B$64="Optimistic",Scenarios!F113,Scenarios!F198)) -> 5000 | G24: =IF(Assumptions!$B$64="Base Case",Scenarios!G28,IF(Assumptions!$B$64="Optimistic",Scenarios!G113,Scenarios!G198)) -> 5000 | H24: =IF(Assumptions!$B$64="Base Case",Scenarios!H28,IF(Assumptions!$B$64="Optimistic",Scenarios!H113,Scenarios!H198)) -> 5000 | I24: =IF(Assumptions!$B$64="Base Case",Scenarios!I28,IF(Assumptions!$B$64="Optimistic",Scenarios!I113,Scenarios!I198)) -> 5000
A25: ── Debt & Financing ──
A26: Interest Rate (on Debt) | B26: 0.2 | C26: 0.2 | D26: 0.2 | E26: =IF(Assumptions!$B$64="Base Case",Scenarios!E30,IF(Assumptions!$B$64="Optimistic",Scenarios!E115,Scenarios!E200)) -> 0.2 | F26: =IF(Assumptions!$B$64="Base Case",Scenarios!F30,IF(Assumptions!$B$64="Optimistic",Scenarios!F115,Scenarios!F200)) -> 0.2 | G26: =IF(Assumptions!$B$64="Base Case",Scenarios!G30,IF(Assumptions!$B$64="Optimistic",Scenarios!G115,Scenarios!G200)) -> 0.2 | H26: =IF(Assumptions!$B$64="Base Case",Scenarios!H30,IF(Assumptions!$B$64="Optimistic",Scenarios!H115,Scenarios!H200)) -> 0.2 | I26: =IF(Assumptions!$B$64="Base Case",Scenarios!I30,IF(Assumptions!$B$64="Optimistic",Scenarios!I115,Scenarios!I200)) -> 0.2
A27: Interest Income Rate (on Cash) | B27: 0.02 | C27: 0.02 | D27: 0.02 | E27: =IF(Assumptions!$B$64="Base Case",Scenarios!E31,IF(Assumptions!$B$64="Optimistic",Scenarios!E116,Scenarios!E201)) -> 0.02 | F27: =IF(Assumptions!$B$64="Base Case",Scenarios!F31,IF(Assumptions!$B$64="Optimistic",Scenarios!F116,Scenarios!F201)) -> 0.02 | G27: =IF(Assumptions!$B$64="Base Case",Scenarios!G31,IF(Assumptions!$B$64="Optimistic",Scenarios!G116,Scenarios!G201)) -> 0.02 | H27: =IF(Assumptions!$B$64="Base Case",Scenarios!H31,IF(Assumptions!$B$64="Optimistic",Scenarios!H116,Scenarios!H201)) -> 0.02 | I27: =IF(Assumptions!$B$64="Base Case",Scenarios!I31,IF(Assumptions!$B$64="Optimistic",Scenarios!I116,Scenarios!I201)) -> 0.02
A28: Short-Term Debt | B28: 50000 | C28: 50000 | D28: 50000 | E28: =IF(Assumptions!$B$64="Base Case",Scenarios!E32,IF(Assumptions!$B$64="Optimistic",Scenarios!E117,Scenarios!E202)) -> 50000 | F28: =IF(Assumptions!$B$64="Base Case",Scenarios!F32,IF(Assumptions!$B$64="Optimistic",Scenarios!F117,Scenarios!F202)) -> 50000 | G28: =IF(Assumptions!$B$64="Base Case",Scenarios!G32,IF(Assumptions!$B$64="Optimistic",Scenarios!G117,Scenarios!G202)) -> 50000 | H28: =IF(Assumptions!$B$64="Base Case",Scenarios!H32,IF(Assumptions!$B$64="Optimistic",Scenarios!H117,Scenarios!H202)) -> 50000 | I28: =IF(Assumptions!$B$64="Base Case",Scenarios!I32,IF(Assumptions!$B$64="Optimistic",Scenarios!I117,Scenarios!I202)) -> 50000
A29: LT Debt Issuance | B29: 0 | C29: 0 | D29: 0 | E29: =IF(Assumptions!$B$64="Base Case",Scenarios!E33,IF(Assumptions!$B$64="Optimistic",Scenarios!E118,Scenarios!E203)) -> 0 | F29: =IF(Assumptions!$B$64="Base Case",Scenarios!F33,IF(Assumptions!$B$64="Optimistic",Scenarios!F118,Scenarios!F203)) -> 0 | G29: =IF(Assumptions!$B$64="Base Case",Scenarios!G33,IF(Assumptions!$B$64="Optimistic",Scenarios!G118,Scenarios!G203)) -> 0 | H29: =IF(Assumptions!$B$64="Base Case",Scenarios!H33,IF(Assumptions!$B$64="Optimistic",Scenarios!H118,Scenarios!H203)) -> 0 | I29: =IF(Assumptions!$B$64="Base Case",Scenarios!I33,IF(Assumptions!$B$64="Optimistic",Scenarios!I118,Scenarios!I203)) -> 0
A30: LT Debt Repayment | B30: 0 | C30: 20000 | D30: 20000 | E30: =IF(Assumptions!$B$64="Base Case",Scenarios!E34,IF(Assumptions!$B$64="Optimistic",Scenarios!E119,Scenarios!E204)) -> 20000 | F30: =IF(Assumptions!$B$64="Base Case",Scenarios!F34,IF(Assumptions!$B$64="Optimistic",Scenarios!F119,Scenarios!F204)) -> 20000 | G30: =IF(Assumptions!$B$64="Base Case",Scenarios!G34,IF(Assumptions!$B$64="Optimistic",Scenarios!G119,Scenarios!G204)) -> 20000 | H30: =IF(Assumptions!$B$64="Base Case",Scenarios!H34,IF(Assumptions!$B$64="Optimistic",Scenarios!H119,Scenarios!H204)) -> 20000 | I30: =IF(Assumptions!$B$64="Base Case",Scenarios!I34,IF(Assumptions!$B$64="Optimistic",Scenarios!I119,Scenarios!I204)) -> 20000
A31: Current Portion LTD | B31: 20000 | C31: 20000 | D31: 20000 | E31: =IF(Assumptions!$B$64="Base Case",Scenarios!E35,IF(Assumptions!$B$64="Optimistic",Scenarios!E120,Scenarios!E205)) -> 20000 | F31: =IF(Assumptions!$B$64="Base Case",Scenarios!F35,IF(Assumptions!$B$64="Optimistic",Scenarios!F120,Scenarios!F205)) -> 20000 | G31: =IF(Assumptions!$B$64="Base Case",Scenarios!G35,IF(Assumptions!$B$64="Optimistic",Scenarios!G120,Scenarios!G205)) -> 20000 | H31: =IF(Assumptions!$B$64="Base Case",Scenarios!H35,IF(Assumptions!$B$64="Optimistic",Scenarios!H120,Scenarios!H205)) -> 20000 | I31: =IF(Assumptions!$B$64="Base Case",Scenarios!I35,IF(Assumptions!$B$64="Optimistic",Scenarios!I120,Scenarios!I205)) -> 20000
A32: Dividend Payout Ratio | B32: 0 | C32: 0.39986441 | D32: 0.46433423 | E32: =IF(Assumptions!$B$64="Base Case",Scenarios!E36,IF(Assumptions!$B$64="Optimistic",Scenarios!E121,Scenarios!E206)) -> 0.05 | F32: =IF(Assumptions!$B$64="Base Case",Scenarios!F36,IF(Assumptions!$B$64="Optimistic",Scenarios!F121,Scenarios!F206)) -> 0.05 | G32: =IF(Assumptions!$B$64="Base Case",Scenarios!G36,IF(Assumptions!$B$64="Optimistic",Scenarios!G121,Scenarios!G206)) -> 0.05 | H32: =IF(Assumptions!$B$64="Base Case",Scenarios!H36,IF(Assumptions!$B$64="Optimistic",Scenarios!H121,Scenarios!H206)) -> 0.05 | I32: =IF(Assumptions!$B$64="Base Case",Scenarios!I36,IF(Assumptions!$B$64="Optimistic",Scenarios!I121,Scenarios!I206)) -> 0.05
A33: Share Repurchase Amount | B33: 0 | C33: 0 | D33: 0 | E33: =IF(Assumptions!$B$64="Base Case",Scenarios!E37,IF(Assumptions!$B$64="Optimistic",Scenarios!E122,Scenarios!E207)) -> 0 | F33: =IF(Assumptions!$B$64="Base Case",Scenarios!F37,IF(Assumptions!$B$64="Optimistic",Scenarios!F122,Scenarios!F207)) -> 0 | G33: =IF(Assumptions!$B$64="Base Case",Scenarios!G37,IF(Assumptions!$B$64="Optimistic",Scenarios!G122,Scenarios!G207)) -> 0 | H33: =IF(Assumptions!$B$64="Base Case",Scenarios!H37,IF(Assumptions!$B$64="Optimistic",Scenarios!H122,Scenarios!H207)) -> 0 | I33: =IF(Assumptions!$B$64="Base Case",Scenarios!I37,IF(Assumptions!$B$64="Optimistic",Scenarios!I122,Scenarios!I207)) -> 0
A34: Equity Issuance | B34: 0 | C34: 10000 | D34: 10000 | E34: =IF(Assumptions!$B$64="Base Case",Scenarios!E38,IF(Assumptions!$B$64="Optimistic",Scenarios!E123,Scenarios!E208)) -> 0 | F34: =IF(Assumptions!$B$64="Base Case",Scenarios!F38,IF(Assumptions!$B$64="Optimistic",Scenarios!F123,Scenarios!F208)) -> 0 | G34: =IF(Assumptions!$B$64="Base Case",Scenarios!G38,IF(Assumptions!$B$64="Optimistic",Scenarios!G123,Scenarios!G208)) -> 0 | H34: =IF(Assumptions!$B$64="Base Case",Scenarios!H38,IF(Assumptions!$B$64="Optimistic",Scenarios!H123,Scenarios!H208)) -> 0 | I34: =IF(Assumptions!$B$64="Base Case",Scenarios!I38,IF(Assumptions!$B$64="Optimistic",Scenarios!I123,Scenarios!I208)) -> 0
A35: ── BS / Equity Direct Values ──
A36: Goodwill | B36: 100000 | C36: 100000 | D36: 100000 | E36: =IF(Assumptions!$B$64="Base Case",Scenarios!E40,IF(Assumptions!$B$64="Optimistic",Scenarios!E125,Scenarios!E210)) -> 100000 | F36: =IF(Assumptions!$B$64="Base Case",Scenarios!F40,IF(Assumptions!$B$64="Optimistic",Scenarios!F125,Scenarios!F210)) -> 100000 | G36: =IF(Assumptions!$B$64="Base Case",Scenarios!G40,IF(Assumptions!$B$64="Optimistic",Scenarios!G125,Scenarios!G210)) -> 100000 | H36: =IF(Assumptions!$B$64="Base Case",Scenarios!H40,IF(Assumptions!$B$64="Optimistic",Scenarios!H125,Scenarios!H210)) -> 100000 | I36: =IF(Assumptions!$B$64="Base Case",Scenarios!I40,IF(Assumptions!$B$64="Optimistic",Scenarios!I125,Scenarios!I210)) -> 100000
A37: Other Current Assets | B37: 10000 | C37: 10000 | D37: 10000 | E37: =IF(Assumptions!$B$64="Base Case",Scenarios!E41,IF(Assumptions!$B$64="Optimistic",Scenarios!E126,Scenarios!E211)) -> 10000 | F37: =IF(Assumptions!$B$64="Base Case",Scenarios!F41,IF(Assumptions!$B$64="Optimistic",Scenarios!F126,Scenarios!F211)) -> 10000 | G37: =IF(Assumptions!$B$64="Base Case",Scenarios!G41,IF(Assumptions!$B$64="Optimistic",Scenarios!G126,Scenarios!G211)) -> 10000 | H37: =IF(Assumptions!$B$64="Base Case",Scenarios!H41,IF(Assumptions!$B$64="Optimistic",Scenarios!H126,Scenarios!H211)) -> 10000 | I37: =IF(Assumptions!$B$64="Base Case",Scenarios!I41,IF(Assumptions!$B$64="Optimistic",Scenarios!I126,Scenarios!I211)) -> 10000
A38: Other Long-Term Assets | B38: 20000 | C38: 20000 | D38: 20000 | E38: =IF(Assumptions!$B$64="Base Case",Scenarios!E42,IF(Assumptions!$B$64="Optimistic",Scenarios!E127,Scenarios!E212)) -> 20000 | F38: =IF(Assumptions!$B$64="Base Case",Scenarios!F42,IF(Assumptions!$B$64="Optimistic",Scenarios!F127,Scenarios!F212)) -> 20000 | G38: =IF(Assumptions!$B$64="Base Case",Scenarios!G42,IF(Assumptions!$B$64="Optimistic",Scenarios!G127,Scenarios!G212)) -> 20000 | H38: =IF(Assumptions!$B$64="Base Case",Scenarios!H42,IF(Assumptions!$B$64="Optimistic",Scenarios!H127,Scenarios!H212)) -> 20000 | I38: =IF(Assumptions!$B$64="Base Case",Scenarios!I42,IF(Assumptions!$B$64="Optimistic",Scenarios!I127,Scenarios!I212)) -> 20000
A39: Other Current Liabilities | B39: 15000 | C39: 15000 | D39: 15000 | E39: =IF(Assumptions!$B$64="Base Case",Scenarios!E43,IF(Assumptions!$B$64="Optimistic",Scenarios!E128,Scenarios!E213)) -> 15000 | F39: =IF(Assumptions!$B$64="Base Case",Scenarios!F43,IF(Assumptions!$B$64="Optimistic",Scenarios!F128,Scenarios!F213)) -> 15000 | G39: =IF(Assumptions!$B$64="Base Case",Scenarios!G43,IF(Assumptions!$B$64="Optimistic",Scenarios!G128,Scenarios!G213)) -> 15000 | H39: =IF(Assumptions!$B$64="Base Case",Scenarios!H43,IF(Assumptions!$B$64="Optimistic",Scenarios!H128,Scenarios!H213)) -> 15000 | I39: =IF(Assumptions!$B$64="Base Case",Scenarios!I43,IF(Assumptions!$B$64="Optimistic",Scenarios!I128,Scenarios!I213)) -> 15000
A40: Deferred Tax Liabilities | B40: 30000 | C40: 30000 | D40: 30000 | E40: =IF(Assumptions!$B$64="Base Case",Scenarios!E44,IF(Assumptions!$B$64="Optimistic",Scenarios!E129,Scenarios!E214)) -> 30000 | F40: =IF(Assumptions!$B$64="Base Case",Scenarios!F44,IF(Assumptions!$B$64="Optimistic",Scenarios!F129,Scenarios!F214)) -> 30000 | G40: =IF(Assumptions!$B$64="Base Case",Scenarios!G44,IF(Assumptions!$B$64="Optimistic",Scenarios!G129,Scenarios!G214)) -> 30000 | H40: =IF(Assumptions!$B$64="Base Case",Scenarios!H44,IF(Assumptions!$B$64="Optimistic",Scenarios!H129,Scenarios!H214)) -> 30000 | I40: =IF(Assumptions!$B$64="Base Case",Scenarios!I44,IF(Assumptions!$B$64="Optimistic",Scenarios!I129,Scenarios!I214)) -> 30000
A41: Other LT Liabilities | B41: 25000 | C41: 25000 | D41: 25000 | E41: =IF(Assumptions!$B$64="Base Case",Scenarios!E45,IF(Assumptions!$B$64="Optimistic",Scenarios!E130,Scenarios!E215)) -> 25000 | F41: =IF(Assumptions!$B$64="Base Case",Scenarios!F45,IF(Assumptions!$B$64="Optimistic",Scenarios!F130,Scenarios!F215)) -> 25000 | G41: =IF(Assumptions!$B$64="Base Case",Scenarios!G45,IF(Assumptions!$B$64="Optimistic",Scenarios!G130,Scenarios!G215)) -> 25000 | H41: =IF(Assumptions!$B$64="Base Case",Scenarios!H45,IF(Assumptions!$B$64="Optimistic",Scenarios!H130,Scenarios!H215)) -> 25000 | I41: =IF(Assumptions!$B$64="Base Case",Scenarios!I45,IF(Assumptions!$B$64="Optimistic",Scenarios!I130,Scenarios!I215)) -> 25000
A42: Common Stock | B42: 10000 | C42: 10000 | D42: 10000 | E42: =IF(Assumptions!$B$64="Base Case",Scenarios!E46,IF(Assumptions!$B$64="Optimistic",Scenarios!E131,Scenarios!E216)) -> 10000 | F42: =IF(Assumptions!$B$64="Base Case",Scenarios!F46,IF(Assumptions!$B$64="Optimistic",Scenarios!F131,Scenarios!F216)) -> 10000 | G42: =IF(Assumptions!$B$64="Base Case",Scenarios!G46,IF(Assumptions!$B$64="Optimistic",Scenarios!G131,Scenarios!G216)) -> 10000 | H42: =IF(Assumptions!$B$64="Base Case",Scenarios!H46,IF(Assumptions!$B$64="Optimistic",Scenarios!H131,Scenarios!H216)) -> 10000 | I42: =IF(Assumptions!$B$64="Base Case",Scenarios!I46,IF(Assumptions!$B$64="Optimistic",Scenarios!I131,Scenarios!I216)) -> 10000
A43: APIC | B43: 200000 | C43: 210000 | D43: 220000 | E43: =IF(Assumptions!$B$64="Base Case",Scenarios!E47,IF(Assumptions!$B$64="Optimistic",Scenarios!E132,Scenarios!E217)) -> 230000 | F43: =IF(Assumptions!$B$64="Base Case",Scenarios!F47,IF(Assumptions!$B$64="Optimistic",Scenarios!F132,Scenarios!F217)) -> 240000 | G43: =IF(Assumptions!$B$64="Base Case",Scenarios!G47,IF(Assumptions!$B$64="Optimistic",Scenarios!G132,Scenarios!G217)) -> 250000 | H43: =IF(Assumptions!$B$64="Base Case",Scenarios!H47,IF(Assumptions!$B$64="Optimistic",Scenarios!H132,Scenarios!H217)) -> 260000 | I43: =IF(Assumptions!$B$64="Base Case",Scenarios!I47,IF(Assumptions!$B$64="Optimistic",Scenarios!I132,Scenarios!I217)) -> 270000
A44: Other Comprehensive Income | B44: 0 | C44: 0 | D44: 0 | E44: =IF(Assumptions!$B$64="Base Case",Scenarios!E48,IF(Assumptions!$B$64="Optimistic",Scenarios!E133,Scenarios!E218)) -> 0 | F44: =IF(Assumptions!$B$64="Base Case",Scenarios!F48,IF(Assumptions!$B$64="Optimistic",Scenarios!F133,Scenarios!F218)) -> 0 | G44: =IF(Assumptions!$B$64="Base Case",Scenarios!G48,IF(Assumptions!$B$64="Optimistic",Scenarios!G133,Scenarios!G218)) -> 0 | H44: =IF(Assumptions!$B$64="Base Case",Scenarios!H48,IF(Assumptions!$B$64="Optimistic",Scenarios!H133,Scenarios!H218)) -> 0 | I44: =IF(Assumptions!$B$64="Base Case",Scenarios!I48,IF(Assumptions!$B$64="Optimistic",Scenarios!I133,Scenarios!I218)) -> 0
A45: ── Engine-Computed Values ──
A46: Interest Income (Computed) | B46: 2000 | C46: 2500 | D46: 3000 | E46: =IF(Assumptions!$B$64="Base Case",Scenarios!E50,IF(Assumptions!$B$64="Optimistic",Scenarios!E135,Scenarios!E220)) -> 4381.5518 | F46: =IF(Assumptions!$B$64="Base Case",Scenarios!F50,IF(Assumptions!$B$64="Optimistic",Scenarios!F135,Scenarios!F220)) -> 5271.6108 | G46: =IF(Assumptions!$B$64="Base Case",Scenarios!G50,IF(Assumptions!$B$64="Optimistic",Scenarios!G135,Scenarios!G220)) -> 6410.1322 | H46: =IF(Assumptions!$B$64="Base Case",Scenarios!H50,IF(Assumptions!$B$64="Optimistic",Scenarios!H135,Scenarios!H220)) -> 7790.3454 | I46: =IF(Assumptions!$B$64="Base Case",Scenarios!I50,IF(Assumptions!$B$64="Optimistic",Scenarios!I135,Scenarios!I220)) -> 9407.875
A47: Interest Expense (Computed) | B47: 15000 | C47: 14000 | D47: 13000 | E47: =IF(Assumptions!$B$64="Base Case",Scenarios!E51,IF(Assumptions!$B$64="Optimistic",Scenarios!E136,Scenarios!E221)) -> 54000 | F47: =IF(Assumptions!$B$64="Base Case",Scenarios!F51,IF(Assumptions!$B$64="Optimistic",Scenarios!F136,Scenarios!F221)) -> 50000 | G47: =IF(Assumptions!$B$64="Base Case",Scenarios!G51,IF(Assumptions!$B$64="Optimistic",Scenarios!G136,Scenarios!G221)) -> 46000 | H47: =IF(Assumptions!$B$64="Base Case",Scenarios!H51,IF(Assumptions!$B$64="Optimistic",Scenarios!H136,Scenarios!H221)) -> 42000 | I47: =IF(Assumptions!$B$64="Base Case",Scenarios!I51,IF(Assumptions!$B$64="Optimistic",Scenarios!I136,Scenarios!I221)) -> 38000
A48: Depreciation (Computed) | B48: 25000 | C48: 28000 | D48: 32000 | E48: =IF(Assumptions!$B$64="Base Case",Scenarios!E52,IF(Assumptions!$B$64="Optimistic",Scenarios!E137,Scenarios!E222)) -> 41112.5 | F48: =IF(Assumptions!$B$64="Base Case",Scenarios!F52,IF(Assumptions!$B$64="Optimistic",Scenarios!F137,Scenarios!F222)) -> 46546.5 | G48: =IF(Assumptions!$B$64="Base Case",Scenarios!G52,IF(Assumptions!$B$64="Optimistic",Scenarios!G137,Scenarios!G222)) -> 52387.005 | H48: =IF(Assumptions!$B$64="Base Case",Scenarios!H52,IF(Assumptions!$B$64="Optimistic",Scenarios!H137,Scenarios!H222)) -> 58606.155 | I48: =IF(Assumptions!$B$64="Base Case",Scenarios!I52,IF(Assumptions!$B$64="Optimistic",Scenarios!I137,Scenarios!I222)) -> 65166.453
A49: Gross PP&E (Computed) | B49: 300000 | C49: 340000 | D49: 385000 | E49: =IF(Assumptions!$B$64="Base Case",Scenarios!E53,IF(Assumptions!$B$64="Optimistic",Scenarios!E138,Scenarios!E223)) -> 437250 | F49: =IF(Assumptions!$B$64="Base Case",Scenarios!F53,IF(Assumptions!$B$64="Optimistic",Scenarios!F138,Scenarios!F223)) -> 493680 | G49: =IF(Assumptions!$B$64="Base Case",Scenarios!G53,IF(Assumptions!$B$64="Optimistic",Scenarios!G138,Scenarios!G223)) -> 554060.1 | H49: =IF(Assumptions!$B$64="Base Case",Scenarios!H53,IF(Assumptions!$B$64="Optimistic",Scenarios!H138,Scenarios!H223)) -> 618063.01 | I49: =IF(Assumptions!$B$64="Base Case",Scenarios!I53,IF(Assumptions!$B$64="Optimistic",Scenarios!I138,Scenarios!I223)) -> 685266.06
A50: Accum Depreciation (Computed) | B50: 100000 | C50: 128000 | D50: 160000 | E50: =IF(Assumptions!$B$64="Base Case",Scenarios!E54,IF(Assumptions!$B$64="Optimistic",Scenarios!E139,Scenarios!E224)) -> 201112.5 | F50: =IF(Assumptions!$B$64="Base Case",Scenarios!F54,IF(Assumptions!$B$64="Optimistic",Scenarios!F139,Scenarios!F224)) -> 247659 | G50: =IF(Assumptions!$B$64="Base Case",Scenarios!G54,IF(Assumptions!$B$64="Optimistic",Scenarios!G139,Scenarios!G224)) -> 300046.01 | H50: =IF(Assumptions!$B$64="Base Case",Scenarios!H54,IF(Assumptions!$B$64="Optimistic",Scenarios!H139,Scenarios!H224)) -> 358652.16 | I50: =IF(Assumptions!$B$64="Base Case",Scenarios!I54,IF(Assumptions!$B$64="Optimistic",Scenarios!I139,Scenarios!I224)) -> 423818.61
A51: Net PP&E (Computed) | B51: 200000 | C51: 212000 | D51: 225000 | E51: =IF(Assumptions!$B$64="Base Case",Scenarios!E55,IF(Assumptions!$B$64="Optimistic",Scenarios!E140,Scenarios!E225)) -> 236137.5 | F51: =IF(Assumptions!$B$64="Base Case",Scenarios!F55,IF(Assumptions!$B$64="Optimistic",Scenarios!F140,Scenarios!F225)) -> 246021 | G51: =IF(Assumptions!$B$64="Base Case",Scenarios!G55,IF(Assumptions!$B$64="Optimistic",Scenarios!G140,Scenarios!G225)) -> 254014.09 | H51: =IF(Assumptions!$B$64="Base Case",Scenarios!H55,IF(Assumptions!$B$64="Optimistic",Scenarios!H140,Scenarios!H225)) -> 259410.85 | I51: =IF(Assumptions!$B$64="Base Case",Scenarios!I55,IF(Assumptions!$B$64="Optimistic",Scenarios!I140,Scenarios!I225)) -> 261447.44
A52: Intangibles (Computed) | B52: 50000 | C52: 45000 | D52: 40000 | E52: =IF(Assumptions!$B$64="Base Case",Scenarios!E56,IF(Assumptions!$B$64="Optimistic",Scenarios!E141,Scenarios!E226)) -> 35000 | F52: =IF(Assumptions!$B$64="Base Case",Scenarios!F56,IF(Assumptions!$B$64="Optimistic",Scenarios!F141,Scenarios!F226)) -> 30000 | G52: =IF(Assumptions!$B$64="Base Case",Scenarios!G56,IF(Assumptions!$B$64="Optimistic",Scenarios!G141,Scenarios!G226)) -> 25000 | H52: =IF(Assumptions!$B$64="Base Case",Scenarios!H56,IF(Assumptions!$B$64="Optimistic",Scenarios!H141,Scenarios!H226)) -> 20000 | I52: =IF(Assumptions!$B$64="Base Case",Scenarios!I56,IF(Assumptions!$B$64="Optimistic",Scenarios!I141,Scenarios!I226)) -> 15000
A53: Long-Term Debt (Computed) | B53: 250000 | C53: 230000 | D53: 210000 | E53: =IF(Assumptions!$B$64="Base Case",Scenarios!E57,IF(Assumptions!$B$64="Optimistic",Scenarios!E142,Scenarios!E227)) -> 190000 | F53: =IF(Assumptions!$B$64="Base Case",Scenarios!F57,IF(Assumptions!$B$64="Optimistic",Scenarios!F142,Scenarios!F227)) -> 170000 | G53: =IF(Assumptions!$B$64="Base Case",Scenarios!G57,IF(Assumptions!$B$64="Optimistic",Scenarios!G142,Scenarios!G227)) -> 150000 | H53: =IF(Assumptions!$B$64="Base Case",Scenarios!H57,IF(Assumptions!$B$64="Optimistic",Scenarios!H142,Scenarios!H227)) -> 130000 | I53: =IF(Assumptions!$B$64="Base Case",Scenarios!I57,IF(Assumptions!$B$64="Optimistic",Scenarios!I142,Scenarios!I227)) -> 110000
A54: Retained Earnings (Computed) | B54: -19863 | C54: 28823 | D54: 78506 | E54: =IF(Assumptions!$B$64="Base Case",Scenarios!E58,IF(Assumptions!$B$64="Optimistic",Scenarios!E143,Scenarios!E228)) -> 139150.21 | F54: =IF(Assumptions!$B$64="Base Case",Scenarios!F58,IF(Assumptions!$B$64="Optimistic",Scenarios!F143,Scenarios!F228)) -> 210473.04 | G54: =IF(Assumptions!$B$64="Base Case",Scenarios!G58,IF(Assumptions!$B$64="Optimistic",Scenarios!G143,Scenarios!G228)) -> 291748.77 | H54: =IF(Assumptions!$B$64="Base Case",Scenarios!H58,IF(Assumptions!$B$64="Optimistic",Scenarios!H143,Scenarios!H228)) -> 382009.09 | I54: =IF(Assumptions!$B$64="Base Case",Scenarios!I58,IF(Assumptions!$B$64="Optimistic",Scenarios!I143,Scenarios!I228)) -> 480057.27
A55: Treasury Stock (Computed) | B55: 0 | C55: 0 | D55: 0 | E55: =IF(Assumptions!$B$64="Base Case",Scenarios!E59,IF(Assumptions!$B$64="Optimistic",Scenarios!E144,Scenarios!E229)) -> 0 | F55: =IF(Assumptions!$B$64="Base Case",Scenarios!F59,IF(Assumptions!$B$64="Optimistic",Scenarios!F144,Scenarios!F229)) -> 0 | G55: =IF(Assumptions!$B$64="Base Case",Scenarios!G59,IF(Assumptions!$B$64="Optimistic",Scenarios!G144,Scenarios!G229)) -> 0 | H55: =IF(Assumptions!$B$64="Base Case",Scenarios!H59,IF(Assumptions!$B$64="Optimistic",Scenarios!H144,Scenarios!H229)) -> 0 | I55: =IF(Assumptions!$B$64="Base Case",Scenarios!I59,IF(Assumptions!$B$64="Optimistic",Scenarios!I144,Scenarios!I229)) -> 0
A56: APIC (Computed) | B56: 200000 | C56: 210000 | D56: 220000 | E56: =IF(Assumptions!$B$64="Base Case",Scenarios!E60,IF(Assumptions!$B$64="Optimistic",Scenarios!E145,Scenarios!E230)) -> 230000 | F56: =IF(Assumptions!$B$64="Base Case",Scenarios!F60,IF(Assumptions!$B$64="Optimistic",Scenarios!F145,Scenarios!F230)) -> 240000 | G56: =IF(Assumptions!$B$64="Base Case",Scenarios!G60,IF(Assumptions!$B$64="Optimistic",Scenarios!G145,Scenarios!G230)) -> 250000 | H56: =IF(Assumptions!$B$64="Base Case",Scenarios!H60,IF(Assumptions!$B$64="Optimistic",Scenarios!H145,Scenarios!H230)) -> 260000 | I56: =IF(Assumptions!$B$64="Base Case",Scenarios!I60,IF(Assumptions!$B$64="Optimistic",Scenarios!I145,Scenarios!I230)) -> 270000
A57: Dividends Paid (Computed) | B57: 0 | C57: -32439 | D57: -43067 | E57: =IF(Assumptions!$B$64="Base Case",Scenarios!E61,IF(Assumptions!$B$64="Optimistic",Scenarios!E146,Scenarios!E231)) -> -3191.8008 | F57: =IF(Assumptions!$B$64="Base Case",Scenarios!F61,IF(Assumptions!$B$64="Optimistic",Scenarios!F146,Scenarios!F231)) -> -3753.833 | G57: =IF(Assumptions!$B$64="Base Case",Scenarios!G61,IF(Assumptions!$B$64="Optimistic",Scenarios!G146,Scenarios!G231)) -> -4277.6701 | H57: =IF(Assumptions!$B$64="Base Case",Scenarios!H61,IF(Assumptions!$B$64="Optimistic",Scenarios!H146,Scenarios!H231)) -> -4750.5428 | I57: =IF(Assumptions!$B$64="Base Case",Scenarios!I61,IF(Assumptions!$B$64="Optimistic",Scenarios!I146,Scenarios!I231)) -> -5160.4308
... A61: Asset Sales (Computed) | B61: 0 | C61: 0 | D61: 0 | E61: =IF(Assumptions!$B$64="Base Case",Scenarios!E65,IF(Assumptions!$B$64="Optimistic",Scenarios!E150,Scenarios!E235)) -> 0 | F61: =IF(Assumptions!$B$64="Base Case",Scenarios!F65,IF(Assumptions!$B$64="Optimistic",Scenarios!F150,Scenarios!F235)) -> 0 | G61: =IF(Assumptions!$B$64="Base Case",Scenarios!G65,IF(Assumptions!$B$64="Optimistic",Scenarios!G150,Scenarios!G235)) -> 0 | H61: =IF(Assumptions!$B$64="Base Case",Scenarios!H65,IF(Assumptions!$B$64="Optimistic",Scenarios!H150,Scenarios!H235)) -> 0 | I61: =IF(Assumptions!$B$64="Base Case",Scenarios!I65,IF(Assumptions!$B$64="Optimistic",Scenarios!I150,Scenarios!I235)) -> 0
A63: ── SCENARIO CONTROL ──
A64: Active Scenario | B64: =Dashboard!B6 -> Base Case
A65: ⚠ Change scenario via Dashboard!B6 dropdown only.

Sheet Income Statement
A1: WOLF — Income Statement | B1: 2021 (A) | C1: 2022 (A) | D1: 2023 (A) | E1: 2024E | F1: 2025E | G1: 2026E | H1: 2027E | I1: 2028E
A2: Revenue | B2: =Assumptions!B3 -> 750000 | C2: =B2*(1+Assumptions!C5) -> 850000 | D2: =C2*(1+Assumptions!D5) -> 950000 | E2: =D2*(1+Assumptions!E5) -> 1045000 | F2: =E2*(1+Assumptions!F5) -> 1128600 | G2: =F2*(1+Assumptions!G5) -> 1207602 | H2: =G2*(1+Assumptions!H5) -> 1280058.1 | I2: =H2*(1+Assumptions!I5) -> 1344061
A3: Revenue Growth % | B3: =Assumptions!B5 -> 0 | C3: =Assumptions!C5 -> 0.13333333 | D3: =Assumptions!D5 -> 0.11764706 | E3: =Assumptions!E5 -> 0.1 | F3: =Assumptions!F5 -> 0.08 | G3: =Assumptions!G5 -> 0.07 | H3: =Assumptions!H5 -> 0.06 | I3: =Assumptions!I5 -> 0.05
A4: Cost of Goods Sold | B4: =B2*Assumptions!B6 -> 450000 | C4: =C2*Assumptions!C6 -> 510000 | D4: =D2*Assumptions!D6 -> 570000 | E4: =E2*Assumptions!E6 -> 627000 | F4: =F2*Assumptions!F6 -> 677160 | G4: =G2*Assumptions!G6 -> 724561.2 | H4: =H2*Assumptions!H6 -> 768034.87 | I4: =I2*Assumptions!I6 -> 806436.62
A5: Gross Profit | B5: =B2-B4 -> 300000 | C5: =C2-C4 -> 340000 | D5: =D2-D4 -> 380000 | E5: =E2-E4 -> 418000 | F5: =F2-F4 -> 451440 | G5: =G2-G4 -> 483040.8 | H5: =H2-H4 -> 512023.25 | I5: =I2-I4 -> 537624.41
A6: Gross Margin | B6: =IF(B2=0,0,B5/B2) -> 0.4 | C6: =IF(C2=0,0,C5/C2) -> 0.4 | D6: =IF(D2=0,0,D5/D2) -> 0.4 | E6: =IF(E2=0,0,E5/E2) -> 0.4 | F6: =IF(F2=0,0,F5/F2) -> 0.4 | G6: =IF(G2=0,0,G5/G2) -> 0.4 | H6: =IF(H2=0,0,H5/H2) -> 0.4 | I6: =IF(I2=0,0,I5/I2) -> 0.4
A8: Operating Expenses
A9: SG&A | B9: =B2*Assumptions!B7 -> 112500 | C9: =C2*Assumptions!C7 -> 127500 | D9: =D2*Assumptions!D7 -> 142500 | E9: =E2*Assumptions!E7 -> 156750 | F9: =F2*Assumptions!F7 -> 169290 | G9: =G2*Assumptions!G7 -> 181140.3 | H9: =H2*Assumptions!H7 -> 192008.72 | I9: =I2*Assumptions!I7 -> 201609.15
A10: R&D | B10: =B2*Assumptions!B8 -> 37500 | C10: =C2*Assumptions!C8 -> 42500 | D10: =D2*Assumptions!D8 -> 47500 | E10: =E2*Assumptions!E8 -> 52250 | F10: =F2*Assumptions!F8 -> 56430 | G10: =G2*Assumptions!G8 -> 60380.1 | H10: =H2*Assumptions!H8 -> 64002.906 | I10: =I2*Assumptions!I8 -> 67203.051
A11: Depreciation | B11: =Assumptions!B48 -> 25000 | C11: =Assumptions!C48 -> 28000 | D11: =Assumptions!D48 -> 32000 | E11: =(Assumptions!D49+'Income Statement'!E2*Assumptions!E22/2)*Assumptions!E23 -> 41112.5 | F11: =(Assumptions!E49+'Income Statement'!F2*Assumptions!F22/2)*Assumptions!F23 -> 46546.5 | G11: =(Assumptions!F49+'Income Statement'!G2*Assumptions!G22/2)*Assumptions!G23 -> 52387.005 | H11: =(Assumptions!G49+'Income Statement'!H2*Assumptions!H22/2)*Assumptions!H23 -> 58606.155 | I11: =(Assumptions!H49+'Income Statement'!I2*Assumptions!I22/2)*Assumptions!I23 -> 65166.453
A12: Amortization | B12: =Assumptions!B24 -> 5000 | C12: =Assumptions!C24 -> 5000 | D12: =Assumptions!D24 -> 5000 | E12: =Assumptions!E24 -> 5000 | F12: =Assumptions!F24 -> 5000 | G12: =Assumptions!G24 -> 5000 | H12: =Assumptions!H24 -> 5000 | I12: =Assumptions!I24 -> 5000
A13: Other OpEx | B13: =B2*Assumptions!B9 -> 15000 | C13: =C2*Assumptions!C9 -> 17000 | D13: =D2*Assumptions!D9 -> 19000 | E13: =E2*Assumptions!E9 -> 20900 | F13: =F2*Assumptions!F9 -> 22572 | G13: =G2*Assumptions!G9 -> 24152.04 | H13: =H2*Assumptions!H9 -> 25601.162 | I13: =I2*Assumptions!I9 -> 26881.221
A14: Stock-Based Comp | B14: =Assumptions!B13 -> 0 | C14: =Assumptions!C13 -> 0 | D14: =Assumptions!D13 -> 0 | E14: =Assumptions!E13 -> 10000 | F14: =Assumptions!F13 -> 10000 | G14: =Assumptions!G13 -> 10000 | H14: =Assumptions!H13 -> 10000 | I14: =Assumptions!I13 -> 10000
A15: Total OpEx | B15: =B9+B10+B11+B12+B13+B14 -> 195000 | C15: =C9+C10+C11+C12+C13+C14 -> 220000 | D15: =D9+D10+D11+D12+D13+D14 -> 246000 | E15: =E9+E10+E11+E12+E13+E14 -> 286012.5 | F15: =F9+F10+F11+F12+F13+F14 -> 309838.5 | G15: =G9+G10+G11+G12+G13+G14 -> 333059.45 | H15: =H9+H10+H11+H12+H13+H14 -> 355218.94 | I15: =I9+I10+I11+I12+I13+I14 -> 375859.88
A17: EBIT | B17: =B5-B15 -> 105000 | C17: =C5-C15 -> 120000 | D17: =D5-D15 -> 134000 | E17: =E5-E15 -> 131987.5 | F17: =F5-F15 -> 141601.5 | G17: =G5-G15 -> 149981.36 | H17: =H5-H15 -> 156804.31 | I17: =I5-I15 -> 161764.53
A18: EBITDA | B18: =B17+B11+B12 -> 135000 | C18: =C17+C11+C12 -> 153000 | D18: =D17+D11+D12 -> 171000 | E18: =E17+E11+E12 -> 178100 | F18: =F17+F11+F12 -> 193148 | G18: =G17+G11+G12 -> 207368.36 | H18: =H17+H11+H12 -> 220410.46 | I18: =I17+I11+I12 -> 231930.98
A19: EBIT Margin | B19: =IF(B2=0,0,B17/B2) -> 0.14 | C19: =IF(C2=0,0,C17/C2) -> 0.14117647 | D19: =IF(D2=0,0,D17/D2) -> 0.14105263 | E19: =IF(E2=0,0,E17/E2) -> 0.12630383 | F19: =IF(F2=0,0,F17/F2) -> 0.12546651 | G19: =IF(G2=0,0,G17/G2) -> 0.12419767 | H19: =IF(H2=0,0,H17/H2) -> 0.1224978 | I19: =IF(I2=0,0,I17/I2) -> 0.12035505
A21: Interest Income | B21: =Assumptions!B46 -> 2000 | C21: =Assumptions!C46 -> 2500 | D21: =Assumptions!D46 -> 3000 | E21: =Assumptions!E46 -> 4381.5518 | F21: =Assumptions!F46 -> 5271.6108 | G21: =Assumptions!G46 -> 6410.1322 | H21: =Assumptions!H46 -> 7790.3454 | I21: =Assumptions!I46 -> 9407.875
A22: Interest Expense | B22: =Assumptions!B47 -> 15000 | C22: =Assumptions!C47 -> 14000 | D22: =Assumptions!D47 -> 13000 | E22: =Assumptions!E47 -> 54000 | F22: =Assumptions!F47 -> 50000 | G22: =Assumptions!G47 -> 46000 | H22: =Assumptions!H47 -> 42000 | I22: =Assumptions!I47 -> 38000
A23: Other Income/Expense | B23: =Assumptions!B11 -> 0 | C23: =Assumptions!C11 -> 0 | D23: =Assumptions!D11 -> 0 | E23: =Assumptions!E11 -> 0 | F23: =Assumptions!F11 -> 0 | G23: =Assumptions!G11 -> 0 | H23: =Assumptions!H11 -> 0 | I23: =Assumptions!I11 -> 0
A24: EBT | B24: =B17+B21-B22+B23 -> 92000 | C24: =C17+C21-C22+C23 -> 108500 | D24: =D17+D21-D22+D23 -> 124000 | E24: =E17+E21-E22+E23 -> 82369.052 | F24: =F17+F21-F22+F23 -> 96873.111 | G24: =G17+G21-G22+G23 -> 110391.49 | H24: =H17+H21-H22+H23 -> 122594.65 | I24: =I17+I21-I22+I23 -> 133172.41
A25: Tax Expense | B25: =MAX(0,B24*Assumptions!B10) -> 23125 | C25: =MAX(0,C24*Assumptions!C10) -> 27375 | D25: =MAX(0,D24*Assumptions!D10) -> 31250 | E25: =MAX(0,E24*Assumptions!E10) -> 18533.037 | F25: =MAX(0,F24*Assumptions!F10) -> 21796.45 | G25: =MAX(0,G24*Assumptions!G10) -> 24838.085 | H25: =MAX(0,H24*Assumptions!H10) -> 27583.797 | I25: =MAX(0,I24*Assumptions!I10) -> 29963.791
A26: Tax Rate | B26: =Assumptions!B10 -> 0.2513587 | C26: =Assumptions!C10 -> 0.25230415 | D26: =Assumptions!D10 -> 0.25201613 | E26: =Assumptions!E10 -> 0.225 | F26: =Assumptions!F10 -> 0.225 | G26: =Assumptions!G10 -> 0.225 | H26: =Assumptions!H10 -> 0.225 | I26: =Assumptions!I10 -> 0.225
A28: Net Income | B28: =B24-B25 -> 68875 | C28: =C24-C25 -> 81125 | D28: =D24-D25 -> 92750 | E28: =E24-E25 -> 63836.015 | F28: =F24-F25 -> 75076.661 | G28: =G24-G25 -> 85553.403 | H28: =H24-H25 -> 95010.855 | I28: =I24-I25 -> 103208.62
A29: Net Margin | B29: =IF(B2=0,0,B28/B2) -> 0.091833333 | C29: =IF(C2=0,0,C28/C2) -> 0.095441176 | D29: =IF(D2=0,0,D28/D2) -> 0.097631579 | E29: =IF(E2=0,0,E28/E2) -> 0.061087096 | F29: =IF(F2=0,0,F28/F2) -> 0.066521939 | G29: =IF(G2=0,0,G28/G2) -> 0.070845695 | H29: =IF(H2=0,0,H28/H2) -> 0.07422386 | I29: =IF(I2=0,0,I28/I2) -> 0.076788638
A30: EPS | B30: =IF(Assumptions!B12=0,0,B28/Assumptions!B12) -> 0.68875 | C30: =IF(Assumptions!C12=0,0,C28/Assumptions!C12) -> 0.81125 | D30: =IF(Assumptions!D12=0,0,D28/Assumptions!D12) -> 0.9275 | E30: =IF(Assumptions!E12=0,0,E28/Assumptions!E12) -> 0.63836015 | F30: =IF(Assumptions!F12=0,0,F28/Assumptions!F12) -> 0.75076661 | G30: =IF(Assumptions!G12=0,0,G28/Assumptions!G12) -> 0.85553403 | H30: =IF(Assumptions!H12=0,0,H28/Assumptions!H12) -> 0.95010855 | I30: =IF(Assumptions!I12=0,0,I28/Assumptions!I12) -> 1.0320862
A31: Stock-Based Compensation | B31: =Assumptions!B13 -> 0 | C31: =Assumptions!C13 -> 0 | D31: =Assumptions!D13 -> 0 | E31: =Assumptions!E13 -> 10000 | F31: =Assumptions!F13 -> 10000 | G31: =Assumptions!G13 -> 10000 | H31: =Assumptions!H13 -> 10000 | I31: =Assumptions!I13 -> 10000

Sheet Balance Sheet
A1: WOLF — Balance Sheet | B1: 2021 (A) | C1: 2022 (A) | D1: 2023 (A) | E1: 2024E | F1: 2025E | G1: 2026E | H1: 2027E | I1: 2028E
A2: ASSETS
A3: Cash & Equivalents | B3: =B42-B4-B5-B6-B7-B16 -> 150000 | C3: =C42-C4-C5-C6-C7-C16 -> 175000 | D3: =D42-D4-D5-D6-D7-D16 -> 200000 | E3: ='Cash Flow Statement'!D34 -> 238155.18 | F3: ='Cash Flow Statement'!E34 -> 289005.91 | G3: ='Cash Flow Statement'!F34 -> 352007.31 | H3: ='Cash Flow Statement'!G34 -> 427027.23 | I3: ='Cash Flow Statement'!H34 -> 513760.27
A4: Accounts Receivable | B4: ='Income Statement'!B2*Assumptions!B15/365 -> 92466 | C4: ='Income Statement'!C2*Assumptions!C15/365 -> 104795 | D4: ='Income Statement'!D2*Assumptions!D15/365 -> 117123 | E4: ='Income Statement'!E2*Assumptions!E15/365 -> 128835.62 | F4: ='Income Statement'!F2*Assumptions!F15/365 -> 139142.47 | G4: ='Income Statement'!G2*Assumptions!G15/365 -> 148882.44 | H4: ='Income Statement'!H2*Assumptions!H15/365 -> 157815.38 | I4: ='Income Statement'!I2*Assumptions!I15/365 -> 165706.15
A5: Inventory | B5: ='Income Statement'!B4*Assumptions!B16/365 -> 36986 | C5: ='Income Statement'!C4*Assumptions!C16/365 -> 41918 | D5: ='Income Statement'!D4*Assumptions!D16/365 -> 46849 | E5: ='Income Statement'!E4*Assumptions!E16/365 -> 51534.247 | F5: ='Income Statement'!F4*Assumptions!F16/365 -> 55656.986 | G5: ='Income Statement'!G4*Assumptions!G16/365 -> 59552.975 | H5: ='Income Statement'!H4*Assumptions!H16/365 -> 63126.154 | I5: ='Income Statement'!I4*Assumptions!I16/365 -> 66282.462
A6: Prepaid Expenses | B6: ='Income Statement'!B2*Assumptions!B18 -> 7500 | C6: ='Income Statement'!C2*Assumptions!C18 -> 8500 | D6: ='Income Statement'!D2*Assumptions!D18 -> 9500 | E6: ='Income Statement'!E2*Assumptions!E18 -> 10450 | F6: ='Income Statement'!F2*Assumptions!F18 -> 11286 | G6: ='Income Statement'!G2*Assumptions!G18 -> 12076.02 | H6: ='Income Statement'!H2*Assumptions!H18 -> 12800.581 | I6: ='Income Statement'!I2*Assumptions!I18 -> 13440.61
A7: Other Current Assets | B7: =Assumptions!B37 -> 10000 | C7: =Assumptions!C37 -> 10000 | D7: =Assumptions!D37 -> 10000 | E7: =Assumptions!E37 -> 10000 | F7: =Assumptions!F37 -> 10000 | G7: =Assumptions!G37 -> 10000 | H7: =Assumptions!H37 -> 10000 | I7: =Assumptions!I37 -> 10000
A8: Total Current Assets | B8: =SUM(B3:B7) -> 296952 | C8: =SUM(C3:C7) -> 340213 | D8: =SUM(D3:D7) -> 383472 | E8: =SUM(E3:E7) -> 438975.04 | F8: =SUM(F3:F7) -> 505091.36 | G8: =SUM(G3:G7) -> 582518.75 | H8: =SUM(H3:H7) -> 670769.35 | I8: =SUM(I3:I7) -> 769189.49
A10: Gross PP&E | B10: =Assumptions!B49 -> 300000 | C10: =Assumptions!C49 -> 340000 | D10: =Assumptions!D49 -> 385000 | E10: =D10+'Income Statement'!E2*Assumptions!E22 -> 437250 | F10: =E10+'Income Statement'!F2*Assumptions!F22 -> 493680 | G10: =F10+'Income Statement'!G2*Assumptions!G22 -> 554060.1 | H10: =G10+'Income Statement'!H2*Assumptions!H22 -> 618063.01 | I10: =H10+'Income Statement'!I2*Assumptions!I22 -> 685266.06
A11: Accumulated Depreciation | B11: =Assumptions!B50 -> 100000 | C11: =Assumptions!C50 -> 128000 | D11: =Assumptions!D50 -> 160000 | E11: =D11+'Income Statement'!E11 -> 201112.5 | F11: =E11+'Income Statement'!F11 -> 247659 | G11: =F11+'Income Statement'!G11 -> 300046.01 | H11: =G11+'Income Statement'!H11 -> 358652.16 | I11: =H11+'Income Statement'!I11 -> 423818.61
A12: Net PP&E | B12: =B10-B11 -> 200000 | C12: =C10-C11 -> 212000 | D12: =D10-D11 -> 225000 | E12: =E10-E11 -> 236137.5 | F12: =F10-F11 -> 246021 | G12: =G10-G11 -> 254014.09 | H12: =H10-H11 -> 259410.85 | I12: =I10-I11 -> 261447.44
A13: Intangibles | B13: =Assumptions!B52 -> 50000 | C13: =Assumptions!C52 -> 45000 | D13: =Assumptions!D52 -> 40000 | E13: =MAX(0,D13-'Income Statement'!E12) -> 35000 | F13: =MAX(0,E13-'Income Statement'!F12) -> 30000 | G13: =MAX(0,F13-'Income Statement'!G12) -> 25000 | H13: =MAX(0,G13-'Income Statement'!H12) -> 20000 | I13: =MAX(0,H13-'Income Statement'!I12) -> 15000
A14: Goodwill | B14: =Assumptions!B36 -> 100000 | C14: =Assumptions!C36 -> 100000 | D14: =Assumptions!D36 -> 100000 | E14: =Assumptions!E36 -> 100000 | F14: =Assumptions!F36 -> 100000 | G14: =Assumptions!G36 -> 100000 | H14: =Assumptions!H36 -> 100000 | I14: =Assumptions!I36 -> 100000
A15: Other Long-Term Assets | B15: =Assumptions!B38 -> 20000 | C15: =Assumptions!C38 -> 20000 | D15: =Assumptions!D38 -> 20000 | E15: =Assumptions!E38 -> 20000 | F15: =Assumptions!F38 -> 20000 | G15: =Assumptions!G38 -> 20000 | H15: =Assumptions!H38 -> 20000 | I15: =Assumptions!I38 -> 20000
A16: Total Non-Current Assets | B16: =B12+B13+B14+B15 -> 370000 | C16: =C12+C13+C14+C15 -> 377000 | D16: =D12+D13+D14+D15 -> 385000 | E16: =E12+E13+E14+E15 -> 391137.5 | F16: =F12+F13+F14+F15 -> 396021 | G16: =G12+G13+G14+G15 -> 399014.09 | H16: =H12+H13+H14+H15 -> 399410.85 | I16: =I12+I13+I14+I15 -> 396447.44
A17: Total Assets | B17: =B8+B16 -> 666952 | C17: =C8+C16 -> 717213 | D17: =D8+D16 -> 768472 | E17: =E8+E16 -> 830112.54 | F17: =F8+F16 -> 901112.36 | G17: =G8+G16 -> 981532.84 | H17: =H8+H16 -> 1070180.2 | I17: =I8+I16 -> 1165636.9
A19: LIABILITIES
A20: Accounts Payable | B20: ='Income Statement'!B4*Assumptions!B17/365 -> 49315 | C20: ='Income Statement'!C4*Assumptions!C17/365 -> 55890 | D20: ='Income Statement'!D4*Assumptions!D17/365 -> 62466 | E20: ='Income Statement'!E4*Assumptions!E17/365 -> 68712.329 | F20: ='Income Statement'!F4*Assumptions!F17/365 -> 74209.315 | G20: ='Income Statement'!G4*Assumptions!G17/365 -> 79403.967 | H20: ='Income Statement'!H4*Assumptions!H17/365 -> 84168.205 | I20: ='Income Statement'!I4*Assumptions!I17/365 -> 88376.615
A21: Accrued Expenses | B21: ='Income Statement'!B2*Assumptions!B19 -> 22500 | C21: ='Income Statement'!C2*Assumptions!C19 -> 25500 | D21: ='Income Statement'!D2*Assumptions!D19 -> 28500 | E21: ='Income Statement'!E2*Assumptions!E19 -> 31350 | F21: ='Income Statement'!F2*Assumptions!F19 -> 33858 | G21: ='Income Statement'!G2*Assumptions!G19 -> 36228.06 | H21: ='Income Statement'!H2*Assumptions!H19 -> 38401.744 | I21: ='Income Statement'!I2*Assumptions!I19 -> 40321.831
A22: Short-Term Debt | B22: =Assumptions!B28 -> 50000 | C22: =Assumptions!C28 -> 50000 | D22: =Assumptions!D28 -> 50000 | E22: =Assumptions!E28 -> 50000 | F22: =Assumptions!F28 -> 50000 | G22: =Assumptions!G28 -> 50000 | H22: =Assumptions!H28 -> 50000 | I22: =Assumptions!I28 -> 50000
A23: Current Portion LTD | B23: =Assumptions!B31 -> 20000 | C23: =Assumptions!C31 -> 20000 | D23: =Assumptions!D31 -> 20000 | E23: =Assumptions!E31 -> 20000 | F23: =Assumptions!F31 -> 20000 | G23: =Assumptions!G31 -> 20000 | H23: =Assumptions!H31 -> 20000 | I23: =Assumptions!I31 -> 20000
A24: Deferred Revenue | B24: ='Income Statement'!B2*Assumptions!B20 -> 15000 | C24: ='Income Statement'!C2*Assumptions!C20 -> 17000 | D24: ='Income Statement'!D2*Assumptions!D20 -> 19000 | E24: ='Income Statement'!E2*Assumptions!E20 -> 20900 | F24: ='Income Statement'!F2*Assumptions!F20 -> 22572 | G24: ='Income Statement'!G2*Assumptions!G20 -> 24152.04 | H24: ='Income Statement'!H2*Assumptions!H20 -> 25601.162 | I24: ='Income Statement'!I2*Assumptions!I20 -> 26881.221
A25: Other Current Liabilities | B25: =Assumptions!B39 -> 15000 | C25: =Assumptions!C39 -> 15000 | D25: =Assumptions!D39 -> 15000 | E25: =Assumptions!E39 -> 15000 | F25: =Assumptions!F39 -> 15000 | G25: =Assumptions!G39 -> 15000 | H25: =Assumptions!H39 -> 15000 | I25: =Assumptions!I39 -> 15000
A26: Total Current Liabilities | B26: =SUM(B20:B25) -> 171815 | C26: =SUM(C20:C25) -> 183390 | D26: =SUM(D20:D25) -> 194966 | E26: =SUM(E20:E25) -> 205962.33 | F26: =SUM(F20:F25) -> 215639.32 | G26: =SUM(G20:G25) -> 224784.07 | H26: =SUM(H20:H25) -> 233171.11 | I26: =SUM(I20:I25) -> 240579.67
A28: Long-Term Debt | B28: =Assumptions!B53 -> 250000 | C28: =Assumptions!C53 -> 230000 | D28: =Assumptions!D53 -> 210000 | E28: =D28+Assumptions!E29-Assumptions!E30 -> 190000 | F28: =E28+Assumptions!F29-Assumptions!F30 -> 170000 | G28: =F28+Assumptions!G29-Assumptions!G30 -> 150000 | H28: =G28+Assumptions!H29-Assumptions!H30 -> 130000 | I28: =H28+Assumptions!I29-Assumptions!I30 -> 110000
A29: Deferred Tax Liabilities | B29: =Assumptions!B40 -> 30000 | C29: =Assumptions!C40 -> 30000 | D29: =Assumptions!D40 -> 30000 | E29: =Assumptions!E40 -> 30000 | F29: =Assumptions!F40 -> 30000 | G29: =Assumptions!G40 -> 30000 | H29: =Assumptions!H40 -> 30000 | I29: =Assumptions!I40 -> 30000
A30: Other LT Liabilities | B30: =Assumptions!B41 -> 25000 | C30: =Assumptions!C41 -> 25000 | D30: =Assumptions!D41 -> 25000 | E30: =Assumptions!E41 -> 25000 | F30: =Assumptions!F41 -> 25000 | G30: =Assumptions!G41 -> 25000 | H30: =Assumptions!H41 -> 25000 | I30: =Assumptions!I41 -> 25000
A31: Total Non-Current Liabilities | B31: =SUM(B28:B30) -> 305000 | C31: =SUM(C28:C30) -> 285000 | D31: =SUM(D28:D30) -> 265000 | E31: =SUM(E28:E30) -> 245000 | F31: =SUM(F28:F30) -> 225000 | G31: =SUM(G28:G30) -> 205000 | H31: =SUM(H28:H30) -> 185000 | I31: =SUM(I28:I30) -> 165000
A32: Total Liabilities | B32: =B26+B31 -> 476815 | C32: =C26+C31 -> 468390 | D32: =D26+D31 -> 459966 | E32: =E26+E31 -> 450962.33 | F32: =F26+F31 -> 440639.32 | G32: =G26+G31 -> 429784.07 | H32: =H26+H31 -> 418171.11 | I32: =I26+I31 -> 405579.67
A34: EQUITY
A35: Common Stock | B35: =Assumptions!B42 -> 10000 | C35: =Assumptions!C42 -> 10000 | D35: =Assumptions!D42 -> 10000 | E35: =Assumptions!E42 -> 10000 | F35: =Assumptions!F42 -> 10000 | G35: =Assumptions!G42 -> 10000 | H35: =Assumptions!H42 -> 10000 | I35: =Assumptions!I42 -> 10000
A36: Additional Paid-in Capital | B36: =Assumptions!B56 -> 200000 | C36: =Assumptions!C56 -> 210000 | D36: =Assumptions!D56 -> 220000 | E36: =D36+Assumptions!E34+Assumptions!E13 -> 230000 | F36: =E36+Assumptions!F34+Assumptions!F13 -> 240000 | G36: =F36+Assumptions!G34+Assumptions!G13 -> 250000 | H36: =G36+Assumptions!H34+Assumptions!H13 -> 260000 | I36: =H36+Assumptions!I34+Assumptions!I13 -> 270000
A37: Retained Earnings | B37: =Assumptions!B54 -> -19863 | C37: =Assumptions!C54 -> 28823 | D37: =Assumptions!D54 -> 78506 | E37: =D37+'Income Statement'!E28-MAX(0,'Income Statement'!E28*Assumptions!E32) -> 139150.21 | F37: =E37+'Income Statement'!F28-MAX(0,'Income Statement'!F28*Assumptions!F32) -> 210473.04 | G37: =F37+'Income Statement'!G28-MAX(0,'Income Statement'!G28*Assumptions!G32) -> 291748.77 | H37: =G37+'Income Statement'!H28-MAX(0,'Income Statement'!H28*Assumptions!H32) -> 382009.09 | I37: =H37+'Income Statement'!I28-MAX(0,'Income Statement'!I28*Assumptions!I32) -> 480057.27
A38: Treasury Stock | B38: =Assumptions!B55 -> 0 | C38: =Assumptions!C55 -> 0 | D38: =Assumptions!D55 -> 0 | E38: =D38-Assumptions!E33 -> 0 | F38: =E38-Assumptions!F33 -> 0 | G38: =F38-Assumptions!G33 -> 0 | H38: =G38-Assumptions!H33 -> 0 | I38: =H38-Assumptions!I33 -> 0
A39: Other Comprehensive Income | B39: =Assumptions!B44 -> 0 | C39: =Assumptions!C44 -> 0 | D39: =Assumptions!D44 -> 0 | E39: =Assumptions!E44 -> 0 | F39: =Assumptions!F44 -> 0 | G39: =Assumptions!G44 -> 0 | H39: =Assumptions!H44 -> 0 | I39: =Assumptions!I44 -> 0
A40: Total Equity | B40: =SUM(B35:B39) -> 190137 | C40: =SUM(C35:C39) -> 248823 | D40: =SUM(D35:D39) -> 308506 | E40: =SUM(E35:E39) -> 379150.21 | F40: =SUM(F35:F39) -> 460473.04 | G40: =SUM(G35:G39) -> 551748.77 | H40: =SUM(H35:H39) -> 652009.09 | I40: =SUM(I35:I39) -> 760057.27
A42: Total Liabilities + Equity | B42: =B32+B40 -> 666952 | C42: =C32+C40 -> 717213 | D42: =D32+D40 -> 768472 | E42: =E32+E40 -> 830112.54 | F42: =F32+F40 -> 901112.36 | G42: =G32+G40 -> 981532.84 | H42: =H32+H40 -> 1070180.2 | I42: =I32+I40 -> 1165636.9
A43: Balance Check (A − L+E) | B43: =B17-B42 -> 0 | C43: =C17-C42 -> 0 | D43: =D17-D42 -> 0 | E43: =E17-E42 -> 0 | F43: =F17-F42 -> 0 | G43: =G17-G42 -> 0 | H43: =H17-H42 -> 0 | I43: =I17-I42 -> 0
A44: Balanced? | B44: =IF(ABS(B43)<1,"✓ Balanced","✗ Imbalanced") -> ✓ Balanced | C44: =IF(ABS(C43)<1,"✓ Balanced","✗ Imbalanced") -> ✓ Balanced | D44: =IF(ABS(D43)<1,"✓ Balanced","✗ Imbalanced") -> ✓ Balanced | E44: =IF(ABS(E43)<1,"✓ Balanced","✗ Imbalanced") -> ✓ Balanced | F44: =IF(ABS(F43)<1,"✓ Balanced","✗ Imbalanced") -> ✓ Balanced | G44: =IF(ABS(G43)<1,"✓ Balanced","✗ Imbalanced") -> ✓ Balanced | H44: =IF(ABS(H43)<1,"✓ Balanced","✗ Imbalanced") -> ✓ Balanced | I44: =IF(ABS(I43)<1,"✓ Balanced","✗ Imbalanced") -> ✓ Balanced

Sheet Cash Flow Statement
A1: WOLF — Cash Flow Statement | B1: 2022 (A) | C1: 2023 (A) | D1: 2024E | E1: 2025E | F1: 2026E | G1: 2027E | H1: 2028E
A2: Operating Activities
A3: Net Income | B3: ='Income Statement'!C28 -> 81125 | C3: ='Income Statement'!D28 -> 92750 | D3: ='Income Statement'!E28 -> 63836.015 | E3: ='Income Statement'!F28 -> 75076.661 | F3: ='Income Statement'!G28 -> 85553.403 | G3: ='Income Statement'!H28 -> 95010.855 | H3: ='Income Statement'!I28 -> 103208.62
A4: Depreciation | B4: ='Income Statement'!C11 -> 28000 | C4: ='Income Statement'!D11 -> 32000 | D4: ='Income Statement'!E11 -> 41112.5 | E4: ='Income Statement'!F11 -> 46546.5 | F4: ='Income Statement'!G11 -> 52387.005 | G4: ='Income Statement'!H11 -> 58606.155 | H4: ='Income Statement'!I11 -> 65166.453
A5: Amortization | B5: ='Income Statement'!C12 -> 5000 | C5: ='Income Statement'!D12 -> 5000 | D5: ='Income Statement'!E12 -> 5000 | E5: ='Income Statement'!F12 -> 5000 | F5: ='Income Statement'!G12 -> 5000 | G5: ='Income Statement'!H12 -> 5000 | H5: ='Income Statement'!I12 -> 5000
A6: Stock-Based Compensation | B6: ='Income Statement'!C31 -> 0 | C6: ='Income Statement'!D31 -> 0 | D6: ='Income Statement'!E31 -> 10000 | E6: ='Income Statement'!F31 -> 10000 | F6: ='Income Statement'!G31 -> 10000 | G6: ='Income Statement'!H31 -> 10000 | H6: ='Income Statement'!I31 -> 10000
A7: Deferred Taxes | B7: ='Balance Sheet'!C29-'Balance Sheet'!B29 -> 0 | C7: ='Balance Sheet'!D29-'Balance Sheet'!C29 -> 0 | D7: ='Balance Sheet'!E29-'Balance Sheet'!D29 -> 0 | E7: ='Balance Sheet'!F29-'Balance Sheet'!E29 -> 0 | F7: ='Balance Sheet'!G29-'Balance Sheet'!F29 -> 0 | G7: ='Balance Sheet'!H29-'Balance Sheet'!G29 -> 0 | H7: ='Balance Sheet'!I29-'Balance Sheet'!H29 -> 0
A8: Working Capital Changes
A9: Change in A/R | B9: =-('Balance Sheet'!C4-'Balance Sheet'!B4) -> -12329 | C9: =-('Balance Sheet'!D4-'Balance Sheet'!C4) -> -12328 | D9: =-('Balance Sheet'!E4-'Balance Sheet'!D4) -> -11712.616 | E9: =-('Balance Sheet'!F4-'Balance Sheet'!E4) -> -10306.849 | F9: =-('Balance Sheet'!G4-'Balance Sheet'!F4) -> -9739.9726 | G9: =-('Balance Sheet'!H4-'Balance Sheet'!G4) -> -8932.9463 | H9: =-('Balance Sheet'!I4-'Balance Sheet'!H4) -> -7890.7692
A10: Change in Inventory | B10: =-('Balance Sheet'!C5-'Balance Sheet'!B5) -> -4932 | C10: =-('Balance Sheet'!D5-'Balance Sheet'!C5) -> -4931 | D10: =-('Balance Sheet'!E5-'Balance Sheet'!D5) -> -4685.2466 | E10: =-('Balance Sheet'!F5-'Balance Sheet'!E5) -> -4122.7397 | F10: =-('Balance Sheet'!G5-'Balance Sheet'!F5) -> -3895.989 | G10: =-('Balance Sheet'!H5-'Balance Sheet'!G5) -> -3573.1785 | H10: =-('Balance Sheet'!I5-'Balance Sheet'!H5) -> -3156.3077
A11: Change in Prepaid | B11: =-('Balance Sheet'!C6-'Balance Sheet'!B6) -> -1000 | C11: =-('Balance Sheet'!D6-'Balance Sheet'!C6) -> -1000 | D11: =-('Balance Sheet'!E6-'Balance Sheet'!D6) -> -950 | E11: =-('Balance Sheet'!F6-'Balance Sheet'!E6) -> -836 | F11: =-('Balance Sheet'!G6-'Balance Sheet'!F6) -> -790.02 | G11: =-('Balance Sheet'!H6-'Balance Sheet'!G6) -> -724.5612 | H11: =-('Balance Sheet'!I6-'Balance Sheet'!H6) -> -640.02906
A12: Change in A/P | B12: ='Balance Sheet'!C20-'Balance Sheet'!B20 -> 6575 | C12: ='Balance Sheet'!D20-'Balance Sheet'!C20 -> 6576 | D12: ='Balance Sheet'!E20-'Balance Sheet'!D20 -> 6246.3288 | E12: ='Balance Sheet'!F20-'Balance Sheet'!E20 -> 5496.9863 | F12: ='Balance Sheet'!G20-'Balance Sheet'!F20 -> 5194.6521 | G12: ='Balance Sheet'!H20-'Balance Sheet'!G20 -> 4764.238 | H12: ='Balance Sheet'!I20-'Balance Sheet'!H20 -> 4208.4103
A13: Change in Accrued Exp | B13: ='Balance Sheet'!C21-'Balance Sheet'!B21 -> 3000 | C13: ='Balance Sheet'!D21-'Balance Sheet'!C21 -> 3000 | D13: ='Balance Sheet'!E21-'Balance Sheet'!D21 -> 2850 | E13: ='Balance Sheet'!F21-'Balance Sheet'!E21 -> 2508 | F13: ='Balance Sheet'!G21-'Balance Sheet'!F21 -> 2370.06 | G13: ='Balance Sheet'!H21-'Balance Sheet'!G21 -> 2173.6836 | H13: ='Balance Sheet'!I21-'Balance Sheet'!H21 -> 1920.0872
A14: Change in Deferred Rev | B14: ='Balance Sheet'!C24-'Balance Sheet'!B24 -> 2000 | C14: ='Balance Sheet'!D24-'Balance Sheet'!C24 -> 2000 | D14: ='Balance Sheet'!E24-'Balance Sheet'!D24 -> 1900 | E14: ='Balance Sheet'!F24-'Balance Sheet'!E24 -> 1672 | F14: ='Balance Sheet'!G24-'Balance Sheet'!F24 -> 1580.04 | G14: ='Balance Sheet'!H24-'Balance Sheet'!G24 -> 1449.1224 | H14: ='Balance Sheet'!I24-'Balance Sheet'!H24 -> 1280.0581
A15: Total WC Change | B15: =SUM(B9:B14) -> -6686 | C15: =SUM(C9:C14) -> -6683 | D15: =SUM(D9:D14) -> -6351.5342 | E15: =SUM(E9:E14) -> -5588.6027 | F15: =SUM(F9:F14) -> -5281.2296 | G15: =SUM(G9:G14) -> -4843.642 | H15: =SUM(H9:H14) -> -4278.5504
A16: Cash from Operations | B16: =B3+B4+B5+B6+B7+B15 -> 107439 | C16: =C3+C4+C5+C6+C7+C15 -> 123067 | D16: =D3+D4+D5+D6+D7+D15 -> 113596.98 | E16: =E3+E4+E5+E6+E7+E15 -> 131034.56 | F16: =F3+F4+F5+F6+F7+F15 -> 147659.18 | G16: =G3+G4+G5+G6+G7+G15 -> 163773.37 | H16: =H3+H4+H5+H6+H7+H15 -> 179096.52
A18: Investing Activities
A19: Capital Expenditures | B19: =-ABS('Income Statement'!C2*Assumptions!C22) -> -40000 | C19: =-ABS('Income Statement'!D2*Assumptions!D22) -> -45000 | D19: =-ABS('Income Statement'!E2*Assumptions!E22) -> -52250 | E19: =-ABS('Income Statement'!F2*Assumptions!F22) -> -56430 | F19: =-ABS('Income Statement'!G2*Assumptions!G22) -> -60380.1 | G19: =-ABS('Income Statement'!H2*Assumptions!H22) -> -64002.906 | H19: =-ABS('Income Statement'!I2*Assumptions!I22) -> -67203.051
A20: Acquisitions | B20: =Assumptions!C60 -> 0 | C20: =Assumptions!D60 -> 0 | D20: =Assumptions!E60 -> 0 | E20: =Assumptions!F60 -> 0 | F20: =Assumptions!G60 -> 0 | G20: =Assumptions!H60 -> 0 | H20: =Assumptions!I60 -> 0
A21: Asset Sales | B21: =Assumptions!C61 -> 0 | C21: =Assumptions!D61 -> 0 | D21: =Assumptions!E61 -> 0 | E21: =Assumptions!F61 -> 0 | F21: =Assumptions!G61 -> 0 | G21: =Assumptions!H61 -> 0 | H21: =Assumptions!I61 -> 0
A22: Cash from Investing | B22: =B19+B20+B21 -> -40000 | C22: =C19+C20+C21 -> -45000 | D22: =D19+D20+D21 -> -52250 | E22: =E19+E20+E21 -> -56430 | F22: =F19+F20+F21 -> -60380.1 | G22: =G19+G20+G21 -> -64002.906 | H22: =H19+H20+H21 -> -67203.051
A24: Financing Activities
A25: Debt Issuance | B25: =Assumptions!C29 -> 0 | C25: =Assumptions!D29 -> 0 | D25: =Assumptions!E29 -> 0 | E25: =Assumptions!F29 -> 0 | F25: =Assumptions!G29 -> 0 | G25: =Assumptions!H29 -> 0 | H25: =Assumptions!I29 -> 0
A26: Debt Repayment | B26: =-ABS(Assumptions!C30) -> -20000 | C26: =-ABS(Assumptions!D30) -> -20000 | D26: =-ABS(Assumptions!E30) -> -20000 | E26: =-ABS(Assumptions!F30) -> -20000 | F26: =-ABS(Assumptions!G30) -> -20000 | G26: =-ABS(Assumptions!H30) -> -20000 | H26: =-ABS(Assumptions!I30) -> -20000
A27: Dividends Paid | B27: =Assumptions!C57 -> -32439 | C27: =Assumptions!D57 -> -43067 | D27: =-MAX(0,'Income Statement'!E28*Assumptions!E32) -> -3191.8008 | E27: =-MAX(0,'Income Statement'!F28*Assumptions!F32) -> -3753.833 | F27: =-MAX(0,'Income Statement'!G28*Assumptions!G32) -> -4277.6701 | G27: =-MAX(0,'Income Statement'!H28*Assumptions!H32) -> -4750.5428 | H27: =-MAX(0,'Income Statement'!I28*Assumptions!I32) -> -5160.4308
A28: Equity Issuance | B28: =Assumptions!C58 -> 10000 | C28: =Assumptions!D58 -> 10000 | D28: =Assumptions!E34 -> 0 | E28: =Assumptions!F34 -> 0 | F28: =Assumptions!G34 -> 0 | G28: =Assumptions!H34 -> 0 | H28: =Assumptions!I34 -> 0
A29: Share Repurchases | B29: =Assumptions!C59 -> 0 | C29: =Assumptions!D59 -> 0 | D29: =-ABS(Assumptions!E33) -> 0 | E29: =-ABS(Assumptions!F33) -> 0 | F29: =-ABS(Assumptions!G33) -> 0 | G29: =-ABS(Assumptions!H33) -> 0 | H29: =-ABS(Assumptions!I33) -> 0
A30: Cash from Financing | B30: =B25+B26+B27+B28+B29 -> -42439 | C30: =C25+C26+C27+C28+C29 -> -53067 | D30: =D25+D26+D27+D28+D29 -> -23191.801 | E30: =E25+E26+E27+E28+E29 -> -23753.833 | F30: =F25+F26+F27+F28+F29 -> -24277.67 | G30: =G25+G26+G27+G28+G29 -> -24750.543 | H30: =H25+H26+H27+H28+H29 -> -25160.431
A32: Net Change in Cash | B32: =B16+B22+B30 -> 25000 | C32: =C16+C22+C30 -> 25000 | D32: =D16+D22+D30 -> 38155.18 | E32: =E16+E22+E30 -> 50850.725 | F32: =F16+F22+F30 -> 63001.408 | G32: =G16+G22+G30 -> 75019.92 | H32: =H16+H22+H30 -> 86733.036
A33: Beginning Cash | B33: ='Balance Sheet'!B3 -> 150000 | C33: ='Balance Sheet'!C3 -> 175000 | D33: ='Balance Sheet'!D3 -> 200000 | E33: ='Balance Sheet'!E3 -> 238155.18 | F33: ='Balance Sheet'!F3 -> 289005.91 | G33: ='Balance Sheet'!G3 -> 352007.31 | H33: ='Balance Sheet'!H3 -> 427027.23
A34: Ending Cash | B34: =B33+B32 -> 175000 | C34: =C33+C32 -> 200000 | D34: =D33+D32 -> 238155.18 | E34: =E33+E32 -> 289005.91 | F34: =F33+F32 -> 352007.31 | G34: =G33+G32 -> 427027.23 | H34: =H33+H32 -> 513760.27
A36: Free Cash Flow | B36: =B16+B19 -> 67439 | C36: =C16+C19 -> 78067 | D36: =D16+D19 -> 61346.981 | E36: =E16+E19 -> 74604.558 | F36: =F16+F19 -> 87279.078 | G36: =G16+G19 -> 99770.462 | H36: =H16+H19 -> 111893.47
A38: Reconciliation Check | B38: =IF(ABS(B34-'Balance Sheet'!C3)<0.01,"✓ Reconciles","✗ Error") -> ✓ Reconciles | C38: =IF(ABS(C34-'Balance Sheet'!D3)<0.01,"✓ Reconciles","✗ Error") -> ✓ Reconciles | D38: =IF(ABS(D34-'Balance Sheet'!E3)<0.01,"✓ Reconciles","✗ Error") -> ✓ Reconciles | E38: =IF(ABS(E34-'Balance Sheet'!F3)<0.01,"✓ Reconciles","✗ Error") -> ✓ Reconciles | F38: =IF(ABS(F34-'Balance Sheet'!G3)<0.01,"✓ Reconciles","✗ Error") -> ✓ Reconciles | G38: =IF(ABS(G34-'Balance Sheet'!H3)<0.01,"✓ Reconciles","✗ Error") -> ✓ Reconciles | H38: =IF(ABS(H34-'Balance Sheet'!I3)<0.01,"✓ Reconciles","✗ Error") -> ✓ Reconciles

Sheet Ratios
A1: Financial Ratios | B1: 2021 (A) | C1: 2022 (A) | D1: 2023 (A) | E1: 2024E | F1: 2025E | G1: 2026E | H1: 2027E | I1: 2028E
A2: ── Profitability ──
A3: Gross Margin | B3: =IF('Income Statement'!B2=0,0,'Income Statement'!B5/'Income Statement'!B2) -> 0.4 | C3: =IF('Income Statement'!C2=0,0,'Income Statement'!C5/'Income Statement'!C2) -> 0.4 | D3: =IF('Income Statement'!D2=0,0,'Income Statement'!D5/'Income Statement'!D2) -> 0.4 | E3: =IF('Income Statement'!E2=0,0,'Income Statement'!E5/'Income Statement'!E2) -> 0.4 | F3: =IF('Income Statement'!F2=0,0,'Income Statement'!F5/'Income Statement'!F2) -> 0.4 | G3: =IF('Income Statement'!G2=0,0,'Income Statement'!G5/'Income Statement'!G2) -> 0.4 | H3: =IF('Income Statement'!H2=0,0,'Income Statement'!H5/'Income Statement'!H2) -> 0.4 | I3: =IF('Income Statement'!I2=0,0,'Income Statement'!I5/'Income Statement'!I2) -> 0.4
A4: Operating Margin | B4: =IF('Income Statement'!B2=0,0,'Income Statement'!B17/'Income Statement'!B2) -> 0.14 | C4: =IF('Income Statement'!C2=0,0,'Income Statement'!C17/'Income Statement'!C2) -> 0.14117647 | D4: =IF('Income Statement'!D2=0,0,'Income Statement'!D17/'Income Statement'!D2) -> 0.14105263 | E4: =IF('Income Statement'!E2=0,0,'Income Statement'!E17/'Income Statement'!E2) -> 0.12630383 | F4: =IF('Income Statement'!F2=0,0,'Income Statement'!F17/'Income Statement'!F2) -> 0.12546651 | G4: =IF('Income Statement'!G2=0,0,'Income Statement'!G17/'Income Statement'!G2) -> 0.12419767 | H4: =IF('Income Statement'!H2=0,0,'Income Statement'!H17/'Income Statement'!H2) -> 0.1224978 | I4: =IF('Income Statement'!I2=0,0,'Income Statement'!I17/'Income Statement'!I2) -> 0.12035505
A5: Net Margin | B5: =IF('Income Statement'!B2=0,0,'Income Statement'!B28/'Income Statement'!B2) -> 0.091833333 | C5: =IF('Income Statement'!C2=0,0,'Income Statement'!C28/'Income Statement'!C2) -> 0.095441176 | D5: =IF('Income Statement'!D2=0,0,'Income Statement'!D28/'Income Statement'!D2) -> 0.097631579 | E5: =IF('Income Statement'!E2=0,0,'Income Statement'!E28/'Income Statement'!E2) -> 0.061087096 | F5: =IF('Income Statement'!F2=0,0,'Income Statement'!F28/'Income Statement'!F2) -> 0.066521939 | G5: =IF('Income Statement'!G2=0,0,'Income Statement'!G28/'Income Statement'!G2) -> 0.070845695 | H5: =IF('Income Statement'!H2=0,0,'Income Statement'!H28/'Income Statement'!H2) -> 0.07422386 | I5: =IF('Income Statement'!I2=0,0,'Income Statement'!I28/'Income Statement'!I2) -> 0.076788638
A6: ROA | B6: =IF('Balance Sheet'!B17=0,0,'Income Statement'!B28/'Balance Sheet'!B17) -> 0.1032683 | C6: =IF('Balance Sheet'!C17=0,0,'Income Statement'!C28/'Balance Sheet'!C17) -> 0.11721868 | D6: =IF('Balance Sheet'!D17=0,0,'Income Statement'!D28/'Balance Sheet'!D17) -> 0.12485823 | E6: =IF('Balance Sheet'!E17=0,0,'Income Statement'!E28/'Balance Sheet'!E17) -> 0.079865673 | F6: =IF('Balance Sheet'!F17=0,0,'Income Statement'!F28/'Balance Sheet'!F17) -> 0.086732418 | G6: =IF('Balance Sheet'!G17=0,0,'Income Statement'!G28/'Balance Sheet'!G17) -> 0.090886379 | H6: =IF('Balance Sheet'!H17=0,0,'Income Statement'!H28/'Balance Sheet'!H17) -> 0.092616124 | I6: =IF('Balance Sheet'!I17=0,0,'Income Statement'!I28/'Balance Sheet'!I17) -> 0.092322948
A7: ROE | B7: =IF('Balance Sheet'!B40=0,0,'Income Statement'!B28/'Balance Sheet'!B40) -> 0.36223881 | C7: =IF('Balance Sheet'!C40=0,0,'Income Statement'!C28/'Balance Sheet'!C40) -> 0.36962366 | D7: =IF('Balance Sheet'!D40=0,0,'Income Statement'!D28/'Balance Sheet'!D40) -> 0.33283752 | E7: =IF('Balance Sheet'!E40=0,0,'Income Statement'!E28/'Balance Sheet'!E40) -> 0.18566258 | F7: =IF('Balance Sheet'!F40=0,0,'Income Statement'!F28/'Balance Sheet'!F40) -> 0.17883416 | G7: =IF('Balance Sheet'!G40=0,0,'Income Statement'!G28/'Balance Sheet'!G40) -> 0.16904082 | H7: =IF('Balance Sheet'!H40=0,0,'Income Statement'!H28/'Balance Sheet'!H40) -> 0.15785709 | I7: =IF('Balance Sheet'!I40=0,0,'Income Statement'!I28/'Balance Sheet'!I40) -> 0.14618097
A8: ── Liquidity ──
A9: Current Ratio | B9: =IF('Balance Sheet'!B26=0,0,'Balance Sheet'!B8/'Balance Sheet'!B26) -> 1.7283241 | C9: =IF('Balance Sheet'!C26=0,0,'Balance Sheet'!C8/'Balance Sheet'!C26) -> 1.8551339 | D9: =IF('Balance Sheet'!D26=0,0,'Balance Sheet'!D8/'Balance Sheet'!D26) -> 1.966866 | E9: =IF('Balance Sheet'!E26=0,0,'Balance Sheet'!E8/'Balance Sheet'!E26) -> 2.1313366 | F9: =IF('Balance Sheet'!F26=0,0,'Balance Sheet'!F8/'Balance Sheet'!F26) -> 2.3422972 | G9: =IF('Balance Sheet'!G26=0,0,'Balance Sheet'!G8/'Balance Sheet'!G26) -> 2.5914592 | H9: =IF('Balance Sheet'!H26=0,0,'Balance Sheet'!H8/'Balance Sheet'!H26) -> 2.8767258 | I9: =IF('Balance Sheet'!I26=0,0,'Balance Sheet'!I8/'Balance Sheet'!I26) -> 3.197234
A10: Debt to Equity | B10: =IF('Balance Sheet'!B40=0,0,'Balance Sheet'!B32/'Balance Sheet'!B40) -> 1.682997 | C10: =IF('Balance Sheet'!C40=0,0,'Balance Sheet'!C32/'Balance Sheet'!C40) -> 1.2056763 | D10: =IF('Balance Sheet'!D40=0,0,'Balance Sheet'!D32/'Balance Sheet'!D40) -> 0.90759985 | E10: =IF('Balance Sheet'!E40=0,0,'Balance Sheet'!E32/'Balance Sheet'!E40) -> 0.68574404 | F10: =IF('Balance Sheet'!F40=0,0,'Balance Sheet'!F32/'Balance Sheet'!F40) -> 0.52120315 | G10: =IF('Balance Sheet'!G40=0,0,'Balance Sheet'!G32/'Balance Sheet'!G40) -> 0.39873219 | H10: =IF('Balance Sheet'!H40=0,0,'Balance Sheet'!H32/'Balance Sheet'!H40) -> 0.30674419 | I10: =IF('Balance Sheet'!I40=0,0,'Balance Sheet'!I32/'Balance Sheet'!I40) -> 0.23682426
A11: ── Efficiency ──
A12: Asset Turnover | B12: =IF('Balance Sheet'!B17=0,0,'Income Statement'!B2/'Balance Sheet'!B17) -> 1.1245187 | C12: =IF('Balance Sheet'!C17=0,0,'Income Statement'!C2/'Balance Sheet'!C17) -> 1.2281773 | D12: =IF('Balance Sheet'!D17=0,0,'Income Statement'!D2/'Balance Sheet'!D17) -> 1.2788714 | E12: =IF('Balance Sheet'!E17=0,0,'Income Statement'!E2/'Balance Sheet'!E17) -> 1.3074066 | F12: =IF('Balance Sheet'!F17=0,0,'Income Statement'!F2/'Balance Sheet'!F17) -> 1.3038167 | G12: =IF('Balance Sheet'!G17=0,0,'Income Statement'!G2/'Balance Sheet'!G17) -> 1.2828779 | H12: =IF('Balance Sheet'!H17=0,0,'Income Statement'!H2/'Balance Sheet'!H17) -> 1.2477945 | I12: =IF('Balance Sheet'!I17=0,0,'Income Statement'!I2/'Balance Sheet'!I17) -> 1.2022996

Sheet Working Capital
A1: WOLF — Working Capital Schedule | B1: 2021 (A) | C1: 2022 (A) | D1: 2023 (A) | E1: 2024E | F1: 2025E | G1: 2026E | H1: 2027E | I1: 2028E
A2: EFFICIENCY METRICS
A3: Days Sales Outstanding (DSO) | B3: =Assumptions!B15 -> 45.00012 | C3: =Assumptions!C15 -> 45.000206 | D3: =Assumptions!D15 -> 44.999889 | E3: =Assumptions!E15 -> 45 | F3: =Assumptions!F15 -> 45 | G3: =Assumptions!G15 -> 45 | H3: =Assumptions!H15 -> 45 | I3: =Assumptions!I15 -> 45
A4: Days Inventory Outstanding (DIO) | B4: =Assumptions!B16 -> 29.999756 | C4: =Assumptions!C16 -> 30.000137 | D4: =Assumptions!D16 -> 29.999798 | E4: =Assumptions!E16 -> 30 | F4: =Assumptions!F16 -> 30 | G4: =Assumptions!G16 -> 30 | H4: =Assumptions!H16 -> 30 | I4: =Assumptions!I16 -> 30
A5: Days Payables Outstanding (DPO) | B5: =Assumptions!B17 -> 39.999944 | C5: =Assumptions!C17 -> 39.999706 | D5: =Assumptions!D17 -> 40.000158 | E5: =Assumptions!E17 -> 40 | F5: =Assumptions!F17 -> 40 | G5: =Assumptions!G17 -> 40 | H5: =Assumptions!H17 -> 40 | I5: =Assumptions!I17 -> 40
A6: Cash Conversion Cycle (days) | B6: =B3+B4-B5 -> 34.999931 | C6: =C3+C4-C5 -> 35.000637 | D6: =D3+D4-D5 -> 34.99953 | E6: =E3+E4-E5 -> 35 | F6: =F3+F4-F5 -> 35 | G6: =G3+G4-G5 -> 35 | H6: =H3+H4-H5 -> 35 | I6: =I3+I4-I5 -> 35
A8: CURRENT ASSETS (excl. Cash)
A9: Accounts Receivable | B9: ='Balance Sheet'!B4 -> 92466 | C9: ='Balance Sheet'!C4 -> 104795 | D9: ='Balance Sheet'!D4 -> 117123 | E9: ='Balance Sheet'!E4 -> 128835.62 | F9: ='Balance Sheet'!F4 -> 139142.47 | G9: ='Balance Sheet'!G4 -> 148882.44 | H9: ='Balance Sheet'!H4 -> 157815.38 | I9: ='Balance Sheet'!I4 -> 165706.15
A10: Inventory | B10: ='Balance Sheet'!B5 -> 36986 | C10: ='Balance Sheet'!C5 -> 41918 | D10: ='Balance Sheet'!D5 -> 46849 | E10: ='Balance Sheet'!E5 -> 51534.247 | F10: ='Balance Sheet'!F5 -> 55656.986 | G10: ='Balance Sheet'!G5 -> 59552.975 | H10: ='Balance Sheet'!H5 -> 63126.154 | I10: ='Balance Sheet'!I5 -> 66282.462
A11: Prepaid Expenses | B11: ='Balance Sheet'!B6 -> 7500 | C11: ='Balance Sheet'!C6 -> 8500 | D11: ='Balance Sheet'!D6 -> 9500 | E11: ='Balance Sheet'!E6 -> 10450 | F11: ='Balance Sheet'!F6 -> 11286 | G11: ='Balance Sheet'!G6 -> 12076.02 | H11: ='Balance Sheet'!H6 -> 12800.581 | I11: ='Balance Sheet'!I6 -> 13440.61
A12: Other Current Assets | B12: ='Balance Sheet'!B7 -> 10000 | C12: ='Balance Sheet'!C7 -> 10000 | D12: ='Balance Sheet'!D7 -> 10000 | E12: ='Balance Sheet'!E7 -> 10000 | F12: ='Balance Sheet'!F7 -> 10000 | G12: ='Balance Sheet'!G7 -> 10000 | H12: ='Balance Sheet'!H7 -> 10000 | I12: ='Balance Sheet'!I7 -> 10000
A14: CURRENT LIABILITIES (excl. Debt)
A15: Accounts Payable | B15: ='Balance Sheet'!B20 -> 49315 | C15: ='Balance Sheet'!C20 -> 55890 | D15: ='Balance Sheet'!D20 -> 62466 | E15: ='Balance Sheet'!E20 -> 68712.329 | F15: ='Balance Sheet'!F20 -> 74209.315 | G15: ='Balance Sheet'!G20 -> 79403.967 | H15: ='Balance Sheet'!H20 -> 84168.205 | I15: ='Balance Sheet'!I20 -> 88376.615
A16: Accrued Expenses | B16: ='Balance Sheet'!B21 -> 22500 | C16: ='Balance Sheet'!C21 -> 25500 | D16: ='Balance Sheet'!D21 -> 28500 | E16: ='Balance Sheet'!E21 -> 31350 | F16: ='Balance Sheet'!F21 -> 33858 | G16: ='Balance Sheet'!G21 -> 36228.06 | H16: ='Balance Sheet'!H21 -> 38401.744 | I16: ='Balance Sheet'!I21 -> 40321.831
A17: Deferred Revenue | B17: ='Balance Sheet'!B24 -> 15000 | C17: ='Balance Sheet'!C24 -> 17000 | D17: ='Balance Sheet'!D24 -> 19000 | E17: ='Balance Sheet'!E24 -> 20900 | F17: ='Balance Sheet'!F24 -> 22572 | G17: ='Balance Sheet'!G24 -> 24152.04 | H17: ='Balance Sheet'!H24 -> 25601.162 | I17: ='Balance Sheet'!I24 -> 26881.221
A18: Other Current Liabilities | B18: ='Balance Sheet'!B25 -> 15000 | C18: ='Balance Sheet'!C25 -> 15000 | D18: ='Balance Sheet'!D25 -> 15000 | E18: ='Balance Sheet'!E25 -> 15000 | F18: ='Balance Sheet'!F25 -> 15000 | G18: ='Balance Sheet'!G25 -> 15000 | H18: ='Balance Sheet'!H25 -> 15000 | I18: ='Balance Sheet'!I25 -> 15000
A20: Net Working Capital | B20: =(B9+B10+B11+B12)-(B15+B16+B17+B18) -> 45137 | C20: =(C9+C10+C11+C12)-(C15+C16+C17+C18) -> 51823 | D20: =(D9+D10+D11+D12)-(D15+D16+D17+D18) -> 58506 | E20: =(E9+E10+E11+E12)-(E15+E16+E17+E18) -> 64857.534 | F20: =(F9+F10+F11+F12)-(F15+F16+F17+F18) -> 70446.137 | G20: =(G9+G10+G11+G12)-(G15+G16+G17+G18) -> 75727.367 | H20: =(H9+H10+H11+H12)-(H15+H16+H17+H18) -> 80571.009 | I20: =(I9+I10+I11+I12)-(I15+I16+I17+I18) -> 84849.559
A21: NWC Change | B21: =0 -> 0 | C21: =C20-B20 -> 6686 | D21: =D20-C20 -> 6683 | E21: =E20-D20 -> 6351.5342 | F21: =F20-E20 -> 5588.6027 | G21: =G20-F20 -> 5281.2296 | H21: =H20-G20 -> 4843.642 | I21: =I20-H20 -> 4278.5504
A22: NWC % of Revenue | B22: =IF('Income Statement'!B2=0,0,B20/'Income Statement'!B2) -> 0.060182667 | C22: =IF('Income Statement'!C2=0,0,C20/'Income Statement'!C2) -> 0.060968235 | D22: =IF('Income Statement'!D2=0,0,D20/'Income Statement'!D2) -> 0.061585263 | E22: =IF('Income Statement'!E2=0,0,E20/'Income Statement'!E2) -> 0.062064626 | F22: =IF('Income Statement'!F2=0,0,F20/'Income Statement'!F2) -> 0.062419047 | G22: =IF('Income Statement'!G2=0,0,G20/'Income Statement'!G2) -> 0.062708878 | H22: =IF('Income Statement'!H2=0,0,H20/'Income Statement'!H2) -> 0.062943242 | I22: =IF('Income Statement'!I2=0,0,I20/'Income Statement'!I2) -> 0.063129246

Sheet Depreciation Schedule
A1: WOLF — PP&E Rollforward | B1: 2021 (A) | C1: 2022 (A) | D1: 2023 (A) | E1: 2024E | F1: 2025E | G1: 2026E | H1: 2027E | I1: 2028E
A2: GROSS PP&E
A3: Beginning Gross PP&E | C3: ='Balance Sheet'!B10 -> 300000 | D3: ='Balance Sheet'!C10 -> 340000 | E3: ='Balance Sheet'!D10 -> 385000 | F3: ='Balance Sheet'!E10 -> 437250 | G3: ='Balance Sheet'!F10 -> 493680 | H3: ='Balance Sheet'!G10 -> 554060.1 | I3: ='Balance Sheet'!H10 -> 618063.01
A4: (+) Capital Expenditures | C4: =ABS('Income Statement'!C2*Assumptions!C22) -> 40000 | D4: =ABS('Income Statement'!D2*Assumptions!D22) -> 45000 | E4: =ABS('Income Statement'!E2*Assumptions!E22) -> 52250 | F4: =ABS('Income Statement'!F2*Assumptions!F22) -> 56430 | G4: =ABS('Income Statement'!G2*Assumptions!G22) -> 60380.1 | H4: =ABS('Income Statement'!H2*Assumptions!H22) -> 64002.906 | I4: =ABS('Income Statement'!I2*Assumptions!I22) -> 67203.051
A5: Ending Gross PP&E | B5: ='Balance Sheet'!B10 -> 300000 | C5: ='Balance Sheet'!C10 -> 340000 | D5: ='Balance Sheet'!D10 -> 385000 | E5: ='Balance Sheet'!E10 -> 437250 | F5: ='Balance Sheet'!F10 -> 493680 | G5: ='Balance Sheet'!G10 -> 554060.1 | H5: ='Balance Sheet'!H10 -> 618063.01 | I5: ='Balance Sheet'!I10 -> 685266.06
A7: ACCUMULATED DEPRECIATION
A8: Beginning Accum. Depreciation | C8: ='Balance Sheet'!B11 -> 100000 | D8: ='Balance Sheet'!C11 -> 128000 | E8: ='Balance Sheet'!D11 -> 160000 | F8: ='Balance Sheet'!E11 -> 201112.5 | G8: ='Balance Sheet'!F11 -> 247659 | H8: ='Balance Sheet'!G11 -> 300046.01 | I8: ='Balance Sheet'!H11 -> 358652.16
A9: (+) Depreciation Expense | B9: ='Income Statement'!B11 -> 25000 | C9: ='Income Statement'!C11 -> 28000 | D9: ='Income Statement'!D11 -> 32000 | E9: ='Income Statement'!E11 -> 41112.5 | F9: ='Income Statement'!F11 -> 46546.5 | G9: ='Income Statement'!G11 -> 52387.005 | H9: ='Income Statement'!H11 -> 58606.155 | I9: ='Income Statement'!I11 -> 65166.453
A10: Ending Accum. Depreciation | B10: ='Balance Sheet'!B11 -> 100000 | C10: ='Balance Sheet'!C11 -> 128000 | D10: ='Balance Sheet'!D11 -> 160000 | E10: ='Balance Sheet'!E11 -> 201112.5 | F10: ='Balance Sheet'!F11 -> 247659 | G10: ='Balance Sheet'!G11 -> 300046.01 | H10: ='Balance Sheet'!H11 -> 358652.16 | I10: ='Balance Sheet'!I11 -> 423818.61
A12: Net PP&E | B12: ='Balance Sheet'!B12 -> 200000 | C12: ='Balance Sheet'!C12 -> 212000 | D12: ='Balance Sheet'!D12 -> 225000 | E12: ='Balance Sheet'!E12 -> 236137.5 | F12: ='Balance Sheet'!F12 -> 246021 | G12: ='Balance Sheet'!G12 -> 254014.09 | H12: ='Balance Sheet'!H12 -> 259410.85 | I12: ='Balance Sheet'!I12 -> 261447.44
A14: KEY METRICS
A15: CapEx % of Revenue | C15: =IF('Income Statement'!C2=0,0,C4/'Income Statement'!C2) -> 0.047058824 | D15: =IF('Income Statement'!D2=0,0,D4/'Income Statement'!D2) -> 0.047368421 | E15: =IF('Income Statement'!E2=0,0,E4/'Income Statement'!E2) -> 0.05 | F15: =IF('Income Statement'!F2=0,0,F4/'Income Statement'!F2) -> 0.05 | G15: =IF('Income Statement'!G2=0,0,G4/'Income Statement'!G2) -> 0.05 | H15: =IF('Income Statement'!H2=0,0,H4/'Income Statement'!H2) -> 0.05 | I15: =IF('Income Statement'!I2=0,0,I4/'Income Statement'!I2) -> 0.05
A16: Depreciation Rate (% Gross PP&E) | B16: =IF(B5=0,0,B9/B5) -> 0.083333333 | C16: =IF(C5=0,0,C9/C5) -> 0.082352941 | D16: =IF(D5=0,0,D9/D5) -> 0.083116883 | E16: =IF(E5=0,0,E9/E5) -> 0.094025157 | F16: =IF(F5=0,0,F9/F5) -> 0.094284759 | G16: =IF(G5=0,0,G9/G5) -> 0.094551124 | H16: =IF(H5=0,0,H9/H5) -> 0.094822299 | I16: =IF(I5=0,0,I9/I5) -> 0.095096572
A17: Implied Useful Life (yrs) | B17: =IF(B16=0,0,1/B16) -> 12 | C17: =IF(C16=0,0,1/C16) -> 12.142857 | D17: =IF(D16=0,0,1/D16) -> 12.03125 | E17: =IF(E16=0,0,1/E16) -> 10.635452 | F17: =IF(F16=0,0,1/F16) -> 10.606168 | G17: =IF(G16=0,0,1/G16) -> 10.576289 | H17: =IF(H16=0,0,1/H16) -> 10.546043 | I17: =IF(I16=0,0,1/I16) -> 10.515626
A19: INTANGIBLES
A20: Amortization Expense | B20: ='Income Statement'!B12 -> 5000 | C20: ='Income Statement'!C12 -> 5000 | D20: ='Income Statement'!D12 -> 5000 | E20: ='Income Statement'!E12 -> 5000 | F20: ='Income Statement'!F12 -> 5000 | G20: ='Income Statement'!G12 -> 5000 | H20: ='Income Statement'!H12 -> 5000 | I20: ='Income Statement'!I12 -> 5000
A21: Net Intangibles | B21: ='Balance Sheet'!B13 -> 50000 | C21: ='Balance Sheet'!C13 -> 45000 | D21: ='Balance Sheet'!D13 -> 40000 | E21: ='Balance Sheet'!E13 -> 35000 | F21: ='Balance Sheet'!F13 -> 30000 | G21: ='Balance Sheet'!G13 -> 25000 | H21: ='Balance Sheet'!H13 -> 20000 | I21: ='Balance Sheet'!I13 -> 15000

Sheet Debt Schedule
A1: WOLF — Debt Schedule | B1: 2021 (A) | C1: 2022 (A) | D1: 2023 (A) | E1: 2024E | F1: 2025E | G1: 2026E | H1: 2027E | I1: 2028E
A2: LONG-TERM DEBT ROLLFORWARD
A3: Beginning Long-Term Debt | C3: ='Balance Sheet'!B28 -> 250000 | D3: ='Balance Sheet'!C28 -> 230000 | E3: ='Balance Sheet'!D28 -> 210000 | F3: ='Balance Sheet'!E28 -> 190000 | G3: ='Balance Sheet'!F28 -> 170000 | H3: ='Balance Sheet'!G28 -> 150000 | I3: ='Balance Sheet'!H28 -> 130000
A4: (+) New Issuance | C4: =Assumptions!C29 -> 0 | D4: =Assumptions!D29 -> 0 | E4: =Assumptions!E29 -> 0 | F4: =Assumptions!F29 -> 0 | G4: =Assumptions!G29 -> 0 | H4: =Assumptions!H29 -> 0 | I4: =Assumptions!I29 -> 0
A5: (-) Repayments | C5: =-ABS(Assumptions!C30) -> -20000 | D5: =-ABS(Assumptions!D30) -> -20000 | E5: =-ABS(Assumptions!E30) -> -20000 | F5: =-ABS(Assumptions!F30) -> -20000 | G5: =-ABS(Assumptions!G30) -> -20000 | H5: =-ABS(Assumptions!H30) -> -20000 | I5: =-ABS(Assumptions!I30) -> -20000
A6: Ending Long-Term Debt | B6: ='Balance Sheet'!B28 -> 250000 | C6: ='Balance Sheet'!C28 -> 230000 | D6: ='Balance Sheet'!D28 -> 210000 | E6: ='Balance Sheet'!E28 -> 190000 | F6: ='Balance Sheet'!F28 -> 170000 | G6: ='Balance Sheet'!G28 -> 150000 | H6: ='Balance Sheet'!H28 -> 130000 | I6: ='Balance Sheet'!I28 -> 110000
A8: DEBT SUMMARY
A9: Short-Term Debt | B9: ='Balance Sheet'!B22 -> 50000 | C9: ='Balance Sheet'!C22 -> 50000 | D9: ='Balance Sheet'!D22 -> 50000 | E9: ='Balance Sheet'!E22 -> 50000 | F9: ='Balance Sheet'!F22 -> 50000 | G9: ='Balance Sheet'!G22 -> 50000 | H9: ='Balance Sheet'!H22 -> 50000 | I9: ='Balance Sheet'!I22 -> 50000
A10: Current Portion of LTD | B10: ='Balance Sheet'!B23 -> 20000 | C10: ='Balance Sheet'!C23 -> 20000 | D10: ='Balance Sheet'!D23 -> 20000 | E10: ='Balance Sheet'!E23 -> 20000 | F10: ='Balance Sheet'!F23 -> 20000 | G10: ='Balance Sheet'!G23 -> 20000 | H10: ='Balance Sheet'!H23 -> 20000 | I10: ='Balance Sheet'!I23 -> 20000
A11: Long-Term Debt | B11: ='Balance Sheet'!B28 -> 250000 | C11: ='Balance Sheet'!C28 -> 230000 | D11: ='Balance Sheet'!D28 -> 210000 | E11: ='Balance Sheet'!E28 -> 190000 | F11: ='Balance Sheet'!F28 -> 170000 | G11: ='Balance Sheet'!G28 -> 150000 | H11: ='Balance Sheet'!H28 -> 130000 | I11: ='Balance Sheet'!I28 -> 110000
A12: Total Debt | B12: =B9+B10+B11 -> 320000 | C12: =C9+C10+C11 -> 300000 | D12: =D9+D10+D11 -> 280000 | E12: =E9+E10+E11 -> 260000 | F12: =F9+F10+F11 -> 240000 | G12: =G9+G10+G11 -> 220000 | H12: =H9+H10+H11 -> 200000 | I12: =I9+I10+I11 -> 180000
A14: INTEREST ANALYSIS
A15: Average Debt Balance | B15: =B12 -> 320000 | C15: =(C12+B12)/2 -> 310000 | D15: =(D12+C12)/2 -> 290000 | E15: =(E12+D12)/2 -> 270000 | F15: =(F12+E12)/2 -> 250000 | G15: =(G12+F12)/2 -> 230000 | H15: =(H12+G12)/2 -> 210000 | I15: =(I12+H12)/2 -> 190000
A16: Interest Expense | B16: ='Income Statement'!B22 -> 15000 | C16: ='Income Statement'!C22 -> 14000 | D16: ='Income Statement'!D22 -> 13000 | E16: ='Income Statement'!E22 -> 54000 | F16: ='Income Statement'!F22 -> 50000 | G16: ='Income Statement'!G22 -> 46000 | H16: ='Income Statement'!H22 -> 42000 | I16: ='Income Statement'!I22 -> 38000
A17: Interest Income | B17: ='Income Statement'!B21 -> 2000 | C17: ='Income Statement'!C21 -> 2500 | D17: ='Income Statement'!D21 -> 3000 | E17: ='Income Statement'!E21 -> 4381.5518 | F17: ='Income Statement'!F21 -> 5271.6108 | G17: ='Income Statement'!G21 -> 6410.1322 | H17: ='Income Statement'!H21 -> 7790.3454 | I17: ='Income Statement'!I21 -> 9407.875
A18: Net Interest | B18: =B16-B17 -> 13000 | C18: =C16-C17 -> 11500 | D18: =D16-D17 -> 10000 | E18: =E16-E17 -> 49618.448 | F18: =F16-F17 -> 44728.389 | G18: =G16-G17 -> 39589.868 | H18: =H16-H17 -> 34209.655 | I18: =I16-I17 -> 28592.125
A20: LEVERAGE RATIOS
A21: Interest Coverage (EBIT / Int Exp) | B21: =IF(B16=0,0,'Income Statement'!B17/B16) -> 7 | C21: =IF(C16=0,0,'Income Statement'!C17/C16) -> 8.5714286 | D21: =IF(D16=0,0,'Income Statement'!D17/D16) -> 10.307692 | E21: =IF(E16=0,0,'Income Statement'!E17/E16) -> 2.444213 | F21: =IF(F16=0,0,'Income Statement'!F17/F16) -> 2.83203 | G21: =IF(G16=0,0,'Income Statement'!G17/G16) -> 3.2604642 | H21: =IF(H16=0,0,'Income Statement'!H17/H16) -> 3.7334359 | I21: =IF(I16=0,0,'Income Statement'!I17/I16) -> 4.2569614
A22: Debt / Equity | B22: =IF('Balance Sheet'!B40=0,0,B12/'Balance Sheet'!B40) -> 1.682997 | C22: =IF('Balance Sheet'!C40=0,0,C12/'Balance Sheet'!C40) -> 1.2056763 | D22: =IF('Balance Sheet'!D40=0,0,D12/'Balance Sheet'!D40) -> 0.90759985 | E22: =IF('Balance Sheet'!E40=0,0,E12/'Balance Sheet'!E40) -> 0.68574404 | F22: =IF('Balance Sheet'!F40=0,0,F12/'Balance Sheet'!F40) -> 0.52120315 | G22: =IF('Balance Sheet'!G40=0,0,G12/'Balance Sheet'!G40) -> 0.39873219 | H22: =IF('Balance Sheet'!H40=0,0,H12/'Balance Sheet'!H40) -> 0.30674419 | I22: =IF('Balance Sheet'!I40=0,0,I12/'Balance Sheet'!I40) -> 0.23682426
A23: Debt / Total Assets | B23: =IF('Balance Sheet'!B17=0,0,B12/'Balance Sheet'!B17) -> 0.47979465 | C23: =IF('Balance Sheet'!C17=0,0,C12/'Balance Sheet'!C17) -> 0.41828578 | D23: =IF('Balance Sheet'!D17=0,0,D12/'Balance Sheet'!D17) -> 0.3643594 | E23: =IF('Balance Sheet'!E17=0,0,E12/'Balance Sheet'!E17) -> 0.31321054 | F23: =IF('Balance Sheet'!F17=0,0,F12/'Balance Sheet'!F17) -> 0.26633749 | G23: =IF('Balance Sheet'!G17=0,0,G12/'Balance Sheet'!G17) -> 0.22413921 | H23: =IF('Balance Sheet'!H17=0,0,H12/'Balance Sheet'!H17) -> 0.18688441 | I23: =IF('Balance Sheet'!I17=0,0,I12/'Balance Sheet'!I17) -> 0.15442201
A24: Debt / EBITDA | B24: =IF('Income Statement'!B18=0,0,B12/'Income Statement'!B18) -> 2.3703704 | C24: =IF('Income Statement'!C18=0,0,C12/'Income Statement'!C18) -> 1.9607843 | D24: =IF('Income Statement'!D18=0,0,D12/'Income Statement'!D18) -> 1.6374269 | E24: =IF('Income Statement'!E18=0,0,E12/'Income Statement'!E18) -> 1.459854 | F24: =IF('Income Statement'!F18=0,0,F12/'Income Statement'!F18) -> 1.2425705 | G24: =IF('Income Statement'!G18=0,0,G12/'Income Statement'!G18) -> 1.060914 | H24: =IF('Income Statement'!H18=0,0,H12/'Income Statement'!H18) -> 0.90739795 | I24: =IF('Income Statement'!I18=0,0,I12/'Income Statement'!I18) -> 0.77609294

Sheet CBE Banking Metrics
A1: CBE Compliance Metric | B1: 2021 (A) | C1: 2022 (A) | D1: 2023 (A) | E1: 2024E | F1: 2025E | G1: 2026E | H1: 2027E | I1: 2028E | J1: CBE Min | K1: CBE Max
A2: CBE COMPLIANCE DASHBOARD
A3: Current Ratio | B3: =IF('Balance Sheet'!B26=0,0,'Balance Sheet'!B8/'Balance Sheet'!B26) -> 1.7283241 | C3: =IF('Balance Sheet'!C26=0,0,'Balance Sheet'!C8/'Balance Sheet'!C26) -> 1.8551339 | D3: =IF('Balance Sheet'!D26=0,0,'Balance Sheet'!D8/'Balance Sheet'!D26) -> 1.966866 | E3: =IF('Balance Sheet'!E26=0,0,'Balance Sheet'!E8/'Balance Sheet'!E26) -> 2.1313366 | F3: =IF('Balance Sheet'!F26=0,0,'Balance Sheet'!F8/'Balance Sheet'!F26) -> 2.3422972 | G3: =IF('Balance Sheet'!G26=0,0,'Balance Sheet'!G8/'Balance Sheet'!G26) -> 2.5914592 | H3: =IF('Balance Sheet'!H26=0,0,'Balance Sheet'!H8/'Balance Sheet'!H26) -> 2.8767258 | I3: =IF('Balance Sheet'!I26=0,0,'Balance Sheet'!I8/'Balance Sheet'!I26) -> 3.197234 | J3: 1.20x | K3: —
A4: └ Status | B4: ✓ PASS | C4: ✓ PASS | D4: ✓ PASS | E4: ✓ PASS | F4: ✓ PASS | G4: ✓ PASS | H4: ✓ PASS | I4: ✓ PASS
A6: Debt-to-Equity | B6: =IF('Balance Sheet'!B40=0,0,'Debt Schedule'!B12/'Balance Sheet'!B40) -> 1.682997 | C6: =IF('Balance Sheet'!C40=0,0,'Debt Schedule'!C12/'Balance Sheet'!C40) -> 1.2056763 | D6: =IF('Balance Sheet'!D40=0,0,'Debt Schedule'!D12/'Balance Sheet'!D40) -> 0.90759985 | E6: =IF('Balance Sheet'!E40=0,0,'Debt Schedule'!E12/'Balance Sheet'!E40) -> 0.68574404 | F6: =IF('Balance Sheet'!F40=0,0,'Debt Schedule'!F12/'Balance Sheet'!F40) -> 0.52120315 | G6: =IF('Balance Sheet'!G40=0,0,'Debt Schedule'!G12/'Balance Sheet'!G40) -> 0.39873219 | H6: =IF('Balance Sheet'!H40=0,0,'Debt Schedule'!H12/'Balance Sheet'!H40) -> 0.30674419 | I6: =IF('Balance Sheet'!I40=0,0,'Debt Schedule'!I12/'Balance Sheet'!I40) -> 0.23682426 | J6: — | K6: 2.50x
A7: └ Status | B7: ✓ PASS | C7: ✓ PASS | D7: ✓ PASS | E7: ✓ PASS | F7: ✓ PASS | G7: ✓ PASS | H7: ✓ PASS | I7: ✓ PASS
A9: Interest Coverage (EBIT / Interest Expense) | B9: =IF('Income Statement'!B22=0,0,'Income Statement'!B17/'Income Statement'!B22) -> 7 | C9: =IF('Income Statement'!C22=0,0,'Income Statement'!C17/'Income Statement'!C22) -> 8.5714286 | D9: =IF('Income Statement'!D22=0,0,'Income Statement'!D17/'Income Statement'!D22) -> 10.307692 | E9: =IF('Income Statement'!E22=0,0,'Income Statement'!E17/'Income Statement'!E22) -> 2.444213 | F9: =IF('Income Statement'!F22=0,0,'Income Statement'!F17/'Income Statement'!F22) -> 2.83203 | G9: =IF('Income Statement'!G22=0,0,'Income Statement'!G17/'Income Statement'!G22) -> 3.2604642 | H9: =IF('Income Statement'!H22=0,0,'Income Statement'!H17/'Income Statement'!H22) -> 3.7334359 | I9: =IF('Income Statement'!I22=0,0,'Income Statement'!I17/'Income Statement'!I22) -> 4.2569614 | J9: 2.00x | K9: —
A10: └ Status | B10: ✓ PASS | C10: ✓ PASS | D10: ✓ PASS | E10: ✓ PASS | F10: ✓ PASS | G10: ✓ PASS | H10: ✓ PASS | I10: ✓ PASS
A12: OVERALL COMPLIANCE
A13: Compliance Score | B13: 3/3 | C13: 3/3 | D13: 3/3 | E13: 3/3 | F13: 3/3 | G13: 3/3 | H13: 3/3 | I13: 3/3

Sheet _Calc_Base
A1: _Calc_Base — Full 3-Statement Model | B1: 2021 | C1: 2022 | D1: 2023 | E1: 2024E | F1: 2025E | G1: 2026E | H1: 2027E | I1: 2028E
A2: Revenue | B2: ='Income Statement'!B2 -> 750000 | C2: ='Income Statement'!C2 -> 850000 | D2: ='Income Statement'!D2 -> 950000 | E2: =D2*(1+Scenarios!E9) -> 1045000 | F2: =E2*(1+Scenarios!F9) -> 1128600 | G2: =F2*(1+Scenarios!G9) -> 1207602 | H2: =G2*(1+Scenarios!H9) -> 1280058.1 | I2: =H2*(1+Scenarios!I9) -> 1344061
A3: Revenue Growth % | B3: =0 -> 0 | C3: =(C2-B2)/B2 -> 0 | D3: =(D2-C2)/C2 -> 0 | E3: =Scenarios!E9 -> 0 | F3: =Scenarios!F9 -> 0 | G3: =Scenarios!G9 -> 0 | H3: =Scenarios!H9 -> 0 | I3: =Scenarios!I9 -> 0
A4: COGS | B4: ='Income Statement'!B4 -> 450000 | C4: ='Income Statement'!C4 -> 510000 | D4: ='Income Statement'!D4 -> 570000 | E4: =E2*Scenarios!E10 -> 627000 | F4: =F2*Scenarios!F10 -> 677160 | G4: =G2*Scenarios!G10 -> 724561.2 | H4: =H2*Scenarios!H10 -> 768034.87 | I4: =I2*Scenarios!I10 -> 806436.62
A5: Gross Profit | B5: =B2-B4 -> 300000 | C5: =C2-C4 -> 340000 | D5: =D2-D4 -> 380000 | E5: =E2-E4 -> 418000 | F5: =F2-F4 -> 451440 | G5: =G2-G4 -> 483040.8 | H5: =H2-H4 -> 512023.25 | I5: =I2-I4 -> 537624.41
A6: SG&A | B6: ='Income Statement'!B9 -> 112500 | C6: ='Income Statement'!C9 -> 127500 | D6: ='Income Statement'!D9 -> 142500 | E6: =E2*Scenarios!E11 -> 156750 | F6: =F2*Scenarios!F11 -> 169290 | G6: =G2*Scenarios!G11 -> 181140.3 | H6: =H2*Scenarios!H11 -> 192008.72 | I6: =I2*Scenarios!I11 -> 201609.15
A7: R&D | B7: ='Income Statement'!B10 -> 37500 | C7: ='Income Statement'!C10 -> 42500 | D7: ='Income Statement'!D10 -> 47500 | E7: =E2*Scenarios!E12 -> 52250 | F7: =F2*Scenarios!F12 -> 56430 | G7: =G2*Scenarios!G12 -> 60380.1 | H7: =H2*Scenarios!H12 -> 64002.906 | I7: =I2*Scenarios!I12 -> 67203.051
A8: Depreciation | B8: ='Income Statement'!B11 -> 25000 | C8: ='Income Statement'!C11 -> 28000 | D8: ='Income Statement'!D11 -> 32000 | E8: =(D28+E2*Scenarios!E26/2)*Scenarios!E27 -> 41112.5 | F8: =(E28+F2*Scenarios!F26/2)*Scenarios!F27 -> 46546.5 | G8: =(F28+G2*Scenarios!G26/2)*Scenarios!G27 -> 52387.005 | H8: =(G28+H2*Scenarios!H26/2)*Scenarios!H27 -> 58606.155 | I8: =(H28+I2*Scenarios!I26/2)*Scenarios!I27 -> 65166.453
A9: Amortization | B9: ='Income Statement'!B12 -> 5000 | C9: ='Income Statement'!C12 -> 5000 | D9: ='Income Statement'!D12 -> 5000 | E9: =Scenarios!E28 -> 5000 | F9: =Scenarios!F28 -> 5000 | G9: =Scenarios!G28 -> 5000 | H9: =Scenarios!H28 -> 5000 | I9: =Scenarios!I28 -> 5000
A10: Other OpEx | B10: ='Income Statement'!B13 -> 15000 | C10: ='Income Statement'!C13 -> 17000 | D10: ='Income Statement'!D13 -> 19000 | E10: =E2*Scenarios!E13 -> 20900 | F10: =F2*Scenarios!F13 -> 22572 | G10: =G2*Scenarios!G13 -> 24152.04 | H10: =H2*Scenarios!H13 -> 25601.162 | I10: =I2*Scenarios!I13 -> 26881.221
A11: SBC | B11: ='Income Statement'!B14 -> 0 | C11: ='Income Statement'!C14 -> 0 | D11: ='Income Statement'!D14 -> 0 | E11: =Scenarios!E17 -> 10000 | F11: =Scenarios!F17 -> 10000 | G11: =Scenarios!G17 -> 10000 | H11: =Scenarios!H17 -> 10000 | I11: =Scenarios!I17 -> 10000
A12: Total OpEx | B12: =B6+B7+B8+B9+B10+B11 -> 195000 | C12: =C6+C7+C8+C9+C10+C11 -> 220000 | D12: =D6+D7+D8+D9+D10+D11 -> 246000 | E12: =E6+E7+E8+E9+E10+E11 -> 286012.5 | F12: =F6+F7+F8+F9+F10+F11 -> 309838.5 | G12: =G6+G7+G8+G9+G10+G11 -> 333059.45 | H12: =H6+H7+H8+H9+H10+H11 -> 355218.94 | I12: =I6+I7+I8+I9+I10+I11 -> 375859.88
A13: EBIT | B13: =B5-B12 -> 105000 | C13: =C5-C12 -> 120000 | D13: =D5-D12 -> 134000 | E13: =E5-E12 -> 131987.5 | F13: =F5-F12 -> 141601.5 | G13: =G5-G12 -> 149981.36 | H13: =H5-H12 -> 156804.31 | I13: =I5-I12 -> 161764.53
A14: Interest Income | B14: ='Income Statement'!B21 -> 2000 | C14: ='Income Statement'!C21 -> 2500 | D14: ='Income Statement'!D21 -> 3000 | E14: =D21*Scenarios!E31 -> 4381.5518 | F14: =E21*Scenarios!F31 -> 5271.6108 | G14: =F21*Scenarios!G31 -> 6410.1322 | H14: =G21*Scenarios!H31 -> 7790.3454 | I14: =H21*Scenarios!I31 -> 9407.875
A15: Interest Expense | B15: ='Income Statement'!B22 -> 15000 | C15: ='Income Statement'!C22 -> 14000 | D15: ='Income Statement'!D22 -> 13000 | E15: =(D45+E45)/2*Scenarios!E30 -> 54000 | F15: =(E45+F45)/2*Scenarios!F30 -> 50000 | G15: =(F45+G45)/2*Scenarios!G30 -> 46000 | H15: =(G45+H45)/2*Scenarios!H30 -> 42000 | I15: =(H45+I45)/2*Scenarios!I30 -> 38000
A16: Other Income/Expense | B16: ='Income Statement'!B23 -> 0 | C16: ='Income Statement'!C23 -> 0 | D16: ='Income Statement'!D23 -> 0 | E16: =Scenarios!E15 -> 0 | F16: =Scenarios!F15 -> 0 | G16: =Scenarios!G15 -> 0 | H16: =Scenarios!H15 -> 0 | I16: =Scenarios!I15 -> 0
A17: EBT | B17: =B13+B14-B15+B16 -> 92000 | C17: =C13+C14-C15+C16 -> 108500 | D17: =D13+D14-D15+D16 -> 124000 | E17: =E13+E14-E15+E16 -> 82369.052 | F17: =F13+F14-F15+F16 -> 96873.111 | G17: =G13+G14-G15+G16 -> 110391.49 | H17: =H13+H14-H15+H16 -> 122594.65 | I17: =I13+I14-I15+I16 -> 133172.41
A18: Tax Expense | B18: ='Income Statement'!B25 -> 23125 | C18: ='Income Statement'!C25 -> 27375 | D18: ='Income Statement'!D25 -> 31250 | E18: =MAX(0,E17*Scenarios!E14) -> 18533.037 | F18: =MAX(0,F17*Scenarios!F14) -> 21796.45 | G18: =MAX(0,G17*Scenarios!G14) -> 24838.085 | H18: =MAX(0,H17*Scenarios!H14) -> 27583.797 | I18: =MAX(0,I17*Scenarios!I14) -> 29963.791
A19: Net Income | B19: =B17-B18 -> 68875 | C19: =C17-C18 -> 81125 | D19: =D17-D18 -> 92750 | E19: =E17-E18 -> 63836.015 | F19: =F17-F18 -> 75076.661 | G19: =G17-G18 -> 85553.403 | H19: =H17-H18 -> 95010.855 | I19: =I17-I18 -> 103208.62
A20: ── Balance Sheet ──
A21: Cash & Equivalents | B21: ='Balance Sheet'!B3 -> 150000 | C21: ='Balance Sheet'!C3 -> 175000 | D21: ='Balance Sheet'!D3 -> 200000 | E21: =D21+E73+E78+E85 -> 238155.18 | F21: =E21+F73+F78+F85 -> 289005.91 | G21: =F21+G73+G78+G85 -> 352007.31 | H21: =G21+H73+H78+H85 -> 427027.23 | I21: =H21+I73+I78+I85 -> 513760.27
A22: Accounts Receivable | B22: ='Balance Sheet'!B4 -> 92466 | C22: ='Balance Sheet'!C4 -> 104795 | D22: ='Balance Sheet'!D4 -> 117123 | E22: =E2*Scenarios!E19/365 -> 128835.62 | F22: =F2*Scenarios!F19/365 -> 139142.47 | G22: =G2*Scenarios!G19/365 -> 148882.44 | H22: =H2*Scenarios!H19/365 -> 157815.38 | I22: =I2*Scenarios!I19/365 -> 165706.15
A23: Inventory | B23: ='Balance Sheet'!B5 -> 36986 | C23: ='Balance Sheet'!C5 -> 41918 | D23: ='Balance Sheet'!D5 -> 46849 | E23: =E4*Scenarios!E20/365 -> 51534.247 | F23: =F4*Scenarios!F20/365 -> 55656.986 | G23: =G4*Scenarios!G20/365 -> 59552.975 | H23: =H4*Scenarios!H20/365 -> 63126.154 | I23: =I4*Scenarios!I20/365 -> 66282.462
A24: Prepaid Expenses | B24: ='Balance Sheet'!B6 -> 7500 | C24: ='Balance Sheet'!C6 -> 8500 | D24: ='Balance Sheet'!D6 -> 9500 | E24: =E2*Scenarios!E22 -> 10450 | F24: =F2*Scenarios!F22 -> 11286 | G24: =G2*Scenarios!G22 -> 12076.02 | H24: =H2*Scenarios!H22 -> 12800.581 | I24: =I2*Scenarios!I22 -> 13440.61
A25: Other Current Assets | B25: ='Balance Sheet'!B7 -> 10000 | C25: ='Balance Sheet'!C7 -> 10000 | D25: ='Balance Sheet'!D7 -> 10000 | E25: =Scenarios!E41 -> 10000 | F25: =Scenarios!F41 -> 10000 | G25: =Scenarios!G41 -> 10000 | H25: =Scenarios!H41 -> 10000 | I25: =Scenarios!I41 -> 10000
A26: Total Current Assets | B26: =SUM(B21:B25) -> 296952 | C26: =SUM(C21:C25) -> 340213 | D26: =SUM(D21:D25) -> 383472 | E26: =SUM(E21:E25) -> 438975.04 | F26: =SUM(F21:F25) -> 505091.36 | G26: =SUM(G21:G25) -> 582518.75 | H26: =SUM(H21:H25) -> 670769.35 | I26: =SUM(I21:I25) -> 769189.49
A28: Gross PP&E | B28: ='Balance Sheet'!B10 -> 300000 | C28: ='Balance Sheet'!C10 -> 340000 | D28: ='Balance Sheet'!D10 -> 385000 | E28: =D28+E2*Scenarios!E26 -> 437250 | F28: =E28+F2*Scenarios!F26 -> 493680 | G28: =F28+G2*Scenarios!G26 -> 554060.1 | H28: =G28+H2*Scenarios!H26 -> 618063.01 | I28: =H28+I2*Scenarios!I26 -> 685266.06
A29: Accumulated Depreciation | B29: ='Balance Sheet'!B11 -> 100000 | C29: ='Balance Sheet'!C11 -> 128000 | D29: ='Balance Sheet'!D11 -> 160000 | E29: =D29+E8 -> 201112.5 | F29: =E29+F8 -> 247659 | G29: =F29+G8 -> 300046.01 | H29: =G29+H8 -> 358652.16 | I29: =H29+I8 -> 423818.61
A30: Net PP&E | B30: =B28-B29 -> 200000 | C30: =C28-C29 -> 212000 | D30: =D28-D29 -> 225000 | E30: =E28-E29 -> 236137.5 | F30: =F28-F29 -> 246021 | G30: =G28-G29 -> 254014.09 | H30: =H28-H29 -> 259410.85 | I30: =I28-I29 -> 261447.44
A31: Intangibles | B31: ='Balance Sheet'!B13 -> 50000 | C31: ='Balance Sheet'!C13 -> 45000 | D31: ='Balance Sheet'!D13 -> 40000 | E31: =MAX(0,D31-E9) -> 35000 | F31: =MAX(0,E31-F9) -> 30000 | G31: =MAX(0,F31-G9) -> 25000 | H31: =MAX(0,G31-H9) -> 20000 | I31: =MAX(0,H31-I9) -> 15000
A32: Goodwill | B32: ='Balance Sheet'!B14 -> 100000 | C32: ='Balance Sheet'!C14 -> 100000 | D32: ='Balance Sheet'!D14 -> 100000 | E32: =Scenarios!E40 -> 100000 | F32: =Scenarios!F40 -> 100000 | G32: =Scenarios!G40 -> 100000 | H32: =Scenarios!H40 -> 100000 | I32: =Scenarios!I40 -> 100000
A33: Other LT Assets | B33: ='Balance Sheet'!B15 -> 20000 | C33: ='Balance Sheet'!C15 -> 20000 | D33: ='Balance Sheet'!D15 -> 20000 | E33: =Scenarios!E42 -> 20000 | F33: =Scenarios!F42 -> 20000 | G33: =Scenarios!G42 -> 20000 | H33: =Scenarios!H42 -> 20000 | I33: =Scenarios!I42 -> 20000
A34: Total Non-Current Assets | B34: =B30+B31+B32+B33 -> 370000 | C34: =C30+C31+C32+C33 -> 377000 | D34: =D30+D31+D32+D33 -> 385000 | E34: =E30+E31+E32+E33 -> 391137.5 | F34: =F30+F31+F32+F33 -> 396021 | G34: =G30+G31+G32+G33 -> 399014.09 | H34: =H30+H31+H32+H33 -> 399410.85 | I34: =I30+I31+I32+I33 -> 396447.44
A35: Total Assets | B35: =B26+B34 -> 666952 | C35: =C26+C34 -> 717213 | D35: =D26+D34 -> 768472 | E35: =E26+E34 -> 830112.54 | F35: =F26+F34 -> 901112.36 | G35: =G26+G34 -> 981532.84 | H35: =H26+H34 -> 1070180.2 | I35: =I26+I34 -> 1165636.9
A37: Accounts Payable | B37: ='Balance Sheet'!B20 -> 49315 | C37: ='Balance Sheet'!C20 -> 55890 | D37: ='Balance Sheet'!D20 -> 62466 | E37: =E4*Scenarios!E21/365 -> 68712.329 | F37: =F4*Scenarios!F21/365 -> 74209.315 | G37: =G4*Scenarios!G21/365 -> 79403.967 | H37: =H4*Scenarios!H21/365 -> 84168.205 | I37: =I4*Scenarios!I21/365 -> 88376.615
A38: Accrued Expenses | B38: ='Balance Sheet'!B21 -> 22500 | C38: ='Balance Sheet'!C21 -> 25500 | D38: ='Balance Sheet'!D21 -> 28500 | E38: =E2*Scenarios!E23 -> 31350 | F38: =F2*Scenarios!F23 -> 33858 | G38: =G2*Scenarios!G23 -> 36228.06 | H38: =H2*Scenarios!H23 -> 38401.744 | I38: =I2*Scenarios!I23 -> 40321.831
A39: Short-Term Debt | B39: ='Balance Sheet'!B22 -> 50000 | C39: ='Balance Sheet'!C22 -> 50000 | D39: ='Balance Sheet'!D22 -> 50000 | E39: =Scenarios!E32 -> 50000 | F39: =Scenarios!F32 -> 50000 | G39: =Scenarios!G32 -> 50000 | H39: =Scenarios!H32 -> 50000 | I39: =Scenarios!I32 -> 50000
A40: Current Portion LTD | B40: ='Balance Sheet'!B23 -> 20000 | C40: ='Balance Sheet'!C23 -> 20000 | D40: ='Balance Sheet'!D23 -> 20000 | E40: =Scenarios!E35 -> 20000 | F40: =Scenarios!F35 -> 20000 | G40: =Scenarios!G35 -> 20000 | H40: =Scenarios!H35 -> 20000 | I40: =Scenarios!I35 -> 20000
A41: Deferred Revenue | B41: ='Balance Sheet'!B24 -> 15000 | C41: ='Balance Sheet'!C24 -> 17000 | D41: ='Balance Sheet'!D24 -> 19000 | E41: =E2*Scenarios!E24 -> 20900 | F41: =F2*Scenarios!F24 -> 22572 | G41: =G2*Scenarios!G24 -> 24152.04 | H41: =H2*Scenarios!H24 -> 25601.162 | I41: =I2*Scenarios!I24 -> 26881.221
A42: Other Current Liabilities | B42: ='Balance Sheet'!B25 -> 15000 | C42: ='Balance Sheet'!C25 -> 15000 | D42: ='Balance Sheet'!D25 -> 15000 | E42: =Scenarios!E43 -> 15000 | F42: =Scenarios!F43 -> 15000 | G42: =Scenarios!G43 -> 15000 | H42: =Scenarios!H43 -> 15000 | I42: =Scenarios!I43 -> 15000
A43: Total Current Liabilities | B43: =SUM(B37:B42) -> 171815 | C43: =SUM(C37:C42) -> 183390 | D43: =SUM(D37:D42) -> 194966 | E43: =SUM(E37:E42) -> 205962.33 | F43: =SUM(F37:F42) -> 215639.32 | G43: =SUM(G37:G42) -> 224784.07 | H43: =SUM(H37:H42) -> 233171.11 | I43: =SUM(I37:I42) -> 240579.67
A45: Long-Term Debt | B45: ='Balance Sheet'!B28 -> 250000 | C45: ='Balance Sheet'!C28 -> 230000 | D45: ='Balance Sheet'!D28 -> 210000 | E45: =D45+Scenarios!E33-Scenarios!E34 -> 190000 | F45: =E45+Scenarios!F33-Scenarios!F34 -> 170000 | G45: =F45+Scenarios!G33-Scenarios!G34 -> 150000 | H45: =G45+Scenarios!H33-Scenarios!H34 -> 130000 | I45: =H45+Scenarios!I33-Scenarios!I34 -> 110000
A46: Deferred Tax Liabilities | B46: ='Balance Sheet'!B29 -> 30000 | C46: ='Balance Sheet'!C29 -> 30000 | D46: ='Balance Sheet'!D29 -> 30000 | E46: =Scenarios!E44 -> 30000 | F46: =Scenarios!F44 -> 30000 | G46: =Scenarios!G44 -> 30000 | H46: =Scenarios!H44 -> 30000 | I46: =Scenarios!I44 -> 30000
A47: Other LT Liabilities | B47: ='Balance Sheet'!B30 -> 25000 | C47: ='Balance Sheet'!C30 -> 25000 | D47: ='Balance Sheet'!D30 -> 25000 | E47: =Scenarios!E45 -> 25000 | F47: =Scenarios!F45 -> 25000 | G47: =Scenarios!G45 -> 25000 | H47: =Scenarios!H45 -> 25000 | I47: =Scenarios!I45 -> 25000
A48: Total Non-Current Liabilities | B48: =SUM(B45:B47) -> 305000 | C48: =SUM(C45:C47) -> 285000 | D48: =SUM(D45:D47) -> 265000 | E48: =SUM(E45:E47) -> 245000 | F48: =SUM(F45:F47) -> 225000 | G48: =SUM(G45:G47) -> 205000 | H48: =SUM(H45:H47) -> 185000 | I48: =SUM(I45:I47) -> 165000
A49: Total Liabilities | B49: =B43+B48 -> 476815 | C49: =C43+C48 -> 468390 | D49: =D43+D48 -> 459966 | E49: =E43+E48 -> 450962.33 | F49: =F43+F48 -> 440639.32 | G49: =G43+G48 -> 429784.07 | H49: =H43+H48 -> 418171.11 | I49: =I43+I48 -> 405579.67
A51: Common Stock | B51: ='Balance Sheet'!B35 -> 10000 | C51: ='Balance Sheet'!C35 -> 10000 | D51: ='Balance Sheet'!D35 -> 10000 | E51: =Scenarios!E46 -> 10000 | F51: =Scenarios!F46 -> 10000 | G51: =Scenarios!G46 -> 10000 | H51: =Scenarios!H46 -> 10000 | I51: =Scenarios!I46 -> 10000
A52: APIC | B52: ='Balance Sheet'!B36 -> 200000 | C52: ='Balance Sheet'!C36 -> 210000 | D52: ='Balance Sheet'!D36 -> 220000 | E52: =D52+Scenarios!E38+Scenarios!E17 -> 230000 | F52: =E52+Scenarios!F38+Scenarios!F17 -> 240000 | G52: =F52+Scenarios!G38+Scenarios!G17 -> 250000 | H52: =G52+Scenarios!H38+Scenarios!H17 -> 260000 | I52: =H52+Scenarios!I38+Scenarios!I17 -> 270000
A53: Retained Earnings | B53: ='Balance Sheet'!B37 -> -19863 | C53: ='Balance Sheet'!C37 -> 28823 | D53: ='Balance Sheet'!D37 -> 78506 | E53: =D53+E19-MAX(0,E19*Scenarios!E36) -> 139150.21 | F53: =E53+F19-MAX(0,F19*Scenarios!F36) -> 210473.04 | G53: =F53+G19-MAX(0,G19*Scenarios!G36) -> 291748.77 | H53: =G53+H19-MAX(0,H19*Scenarios!H36) -> 382009.09 | I53: =H53+I19-MAX(0,I19*Scenarios!I36) -> 480057.27
A54: Treasury Stock | B54: ='Balance Sheet'!B38 -> 0 | C54: ='Balance Sheet'!C38 -> 0 | D54: ='Balance Sheet'!D38 -> 0 | E54: =D54-Scenarios!E37 -> 0 | F54: =E54-Scenarios!F37 -> 0 | G54: =F54-Scenarios!G37 -> 0 | H54: =G54-Scenarios!H37 -> 0 | I54: =H54-Scenarios!I37 -> 0
A55: Other Comprehensive Income | B55: ='Balance Sheet'!B39 -> 0 | C55: ='Balance Sheet'!C39 -> 0 | D55: ='Balance Sheet'!D39 -> 0 | E55: =Scenarios!E48 -> 0 | F55: =Scenarios!F48 -> 0 | G55: =Scenarios!G48 -> 0 | H55: =Scenarios!H48 -> 0 | I55: =Scenarios!I48 -> 0
A56: Total Equity | B56: =SUM(B51:B55) -> 190137 | C56: =SUM(C51:C55) -> 248823 | D56: =SUM(D51:D55) -> 308506 | E56: =SUM(E51:E55) -> 379150.21 | F56: =SUM(F51:F55) -> 460473.04 | G56: =SUM(G51:G55) -> 551748.77 | H56: =SUM(H51:H55) -> 652009.09 | I56: =SUM(I51:I55) -> 760057.27
A58: Total Liabilities + Equity | B58: =B49+B56 -> 666952 | C58: =C49+C56 -> 717213 | D58: =D49+D56 -> 768472 | E58: =E49+E56 -> 830112.54 | F58: =F49+F56 -> 901112.36 | G58: =G49+G56 -> 981532.84 | H58: =H49+H56 -> 1070180.2 | I58: =I49+I56 -> 1165636.9
A59: Balance Check (TA - TLE) | B59: =B35-B58 -> 0 | C59: =C35-C58 -> 0 | D59: =D35-D58 -> 0 | E59: =E35-E58 -> 0 | F59: =F35-F58 -> 0 | G59: =G35-G58 -> 0 | H59: =H35-H58 -> 0 | I59: =I35-I58 -> 0
A60: ── Cash Flow ──
A61: Net Income | C61: =C19 -> 81125 | D61: =D19 -> 92750 | E61: =E19 -> 63836.015 | F61: =F19 -> 75076.661 | G61: =G19 -> 85553.403 | H61: =H19 -> 95010.855 | I61: =I19 -> 103208.62
A62: + Depreciation | C62: =C8 -> 28000 | D62: =D8 -> 32000 | E62: =E8 -> 41112.5 | F62: =F8 -> 46546.5 | G62: =G8 -> 52387.005 | H62: =H8 -> 58606.155 | I62: =I8 -> 65166.453
A63: + Amortization | C63: =C9 -> 5000 | D63: =D9 -> 5000 | E63: =E9 -> 5000 | F63: =F9 -> 5000 | G63: =G9 -> 5000 | H63: =H9 -> 5000 | I63: =I9 -> 5000
A64: + SBC | C64: =C11 -> 0 | D64: =D11 -> 0 | E64: =E11 -> 10000 | F64: =F11 -> 10000 | G64: =G11 -> 10000 | H64: =H11 -> 10000 | I64: =I11 -> 10000
A65: Deferred Taxes | C65: =C46-B46 -> 0 | D65: =D46-C46 -> 0 | E65: =E46-D46 -> 0 | F65: =F46-E46 -> 0 | G65: =G46-F46 -> 0 | H65: =H46-G46 -> 0 | I65: =I46-H46 -> 0
A66: Δ A/R | C66: =-(C22-B22) -> -12329 | D66: =-(D22-C22) -> -12328 | E66: =-(E22-D22) -> -11712.616 | F66: =-(F22-E22) -> -10306.849 | G66: =-(G22-F22) -> -9739.9726 | H66: =-(H22-G22) -> -8932.9463 | I66: =-(I22-H22) -> -7890.7692
A67: Δ Inventory | C67: =-(C23-B23) -> -4932 | D67: =-(D23-C23) -> -4931 | E67: =-(E23-D23) -> -4685.2466 | F67: =-(F23-E23) -> -4122.7397 | G67: =-(G23-F23) -> -3895.989 | H67: =-(H23-G23) -> -3573.1785 | I67: =-(I23-H23) -> -3156.3077
A68: Δ Prepaid | C68: =-(C24-B24) -> -1000 | D68: =-(D24-C24) -> -1000 | E68: =-(E24-D24) -> -950 | F68: =-(F24-E24) -> -836 | G68: =-(G24-F24) -> -790.02 | H68: =-(H24-G24) -> -724.5612 | I68: =-(I24-H24) -> -640.02906
A69: Δ A/P | C69: =C37-B37 -> 6575 | D69: =D37-C37 -> 6576 | E69: =E37-D37 -> 6246.3288 | F69: =F37-E37 -> 5496.9863 | G69: =G37-F37 -> 5194.6521 | H69: =H37-G37 -> 4764.238 | I69: =I37-H37 -> 4208.4103
A70: Δ Accrued Exp | C70: =C38-B38 -> 3000 | D70: =D38-C38 -> 3000 | E70: =E38-D38 -> 2850 | F70: =F38-E38 -> 2508 | G70: =G38-F38 -> 2370.06 | H70: =H38-G38 -> 2173.6836 | I70: =I38-H38 -> 1920.0872
A71: Δ Deferred Revenue | C71: =C41-B41 -> 2000 | D71: =D41-C41 -> 2000 | E71: =E41-D41 -> 1900 | F71: =F41-E41 -> 1672 | G71: =G41-F41 -> 1580.04 | H71: =H41-G41 -> 1449.1224 | I71: =I41-H41 -> 1280.0581
A72: Total WC Change | C72: =SUM(C66:C71) -> -6686 | D72: =SUM(D66:D71) -> -6683 | E72: =SUM(E66:E71) -> -6351.5342 | F72: =SUM(F66:F71) -> -5588.6027 | G72: =SUM(G66:G71) -> -5281.2296 | H72: =SUM(H66:H71) -> -4843.642 | I72: =SUM(I66:I71) -> -4278.5504
A73: Cash from Operations | C73: =C61+C62+C63+C64+C65+C72 -> 107439 | D73: =D61+D62+D63+D64+D65+D72 -> 123067 | E73: =E61+E62+E63+E64+E65+E72 -> 113596.98 | F73: =F61+F62+F63+F64+F65+F72 -> 131034.56 | G73: =G61+G62+G63+G64+G65+G72 -> 147659.18 | H73: =H61+H62+H63+H64+H65+H72 -> 163773.37 | I73: =I61+I62+I63+I64+I65+I72 -> 179096.52
A75: Capital Expenditures | C75: =-ABS(C2*Scenarios!C26) -> -40000 | D75: =-ABS(D2*Scenarios!D26) -> -45000 | E75: =-ABS(E2*Scenarios!E26) -> -52250 | F75: =-ABS(F2*Scenarios!F26) -> -56430 | G75: =-ABS(G2*Scenarios!G26) -> -60380.1 | H75: =-ABS(H2*Scenarios!H26) -> -64002.906 | I75: =-ABS(I2*Scenarios!I26) -> -67203.051
A76: Acquisitions | C76: =Scenarios!C64 -> 0 | D76: =Scenarios!D64 -> 0 | E76: =0 -> 0 | F76: =0 -> 0 | G76: =0 -> 0 | H76: =0 -> 0 | I76: =0 -> 0
A77: Asset Sales | C77: =Scenarios!C65 -> 0 | D77: =Scenarios!D65 -> 0 | E77: =0 -> 0 | F77: =0 -> 0 | G77: =0 -> 0 | H77: =0 -> 0 | I77: =0 -> 0
A78: Cash from Investing | C78: =C75+C76+C77 -> -40000 | D78: =D75+D76+D77 -> -45000 | E78: =E75+E76+E77 -> -52250 | F78: =F75+F76+F77 -> -56430 | G78: =G75+G76+G77 -> -60380.1 | H78: =H75+H76+H77 -> -64002.906 | I78: =I75+I76+I77 -> -67203.051
A80: Debt Issuance | C80: =Scenarios!C33 -> 0 | D80: =Scenarios!D33 -> 0 | E80: =Scenarios!E33 -> 0 | F80: =Scenarios!F33 -> 0 | G80: =Scenarios!G33 -> 0 | H80: =Scenarios!H33 -> 0 | I80: =Scenarios!I33 -> 0
A81: Debt Repayment | C81: =-ABS(Scenarios!C34) -> -20000 | D81: =-ABS(Scenarios!D34) -> -20000 | E81: =-ABS(Scenarios!E34) -> -20000 | F81: =-ABS(Scenarios!F34) -> -20000 | G81: =-ABS(Scenarios!G34) -> -20000 | H81: =-ABS(Scenarios!H34) -> -20000 | I81: =-ABS(Scenarios!I34) -> -20000
A82: Dividends Paid | C82: =Scenarios!C61 -> -32439 | D82: =Scenarios!D61 -> -43067 | E82: =-MAX(0,E19*Scenarios!E36) -> -3191.8008 | F82: =-MAX(0,F19*Scenarios!F36) -> -3753.833 | G82: =-MAX(0,G19*Scenarios!G36) -> -4277.6701 | H82: =-MAX(0,H19*Scenarios!H36) -> -4750.5428 | I82: =-MAX(0,I19*Scenarios!I36) -> -5160.4308
A83: Equity Issuance | C83: =Scenarios!C62 -> 10000 | D83: =Scenarios!D62 -> 10000 | E83: =Scenarios!E38 -> 0 | F83: =Scenarios!F38 -> 0 | G83: =Scenarios!G38 -> 0 | H83: =Scenarios!H38 -> 0 | I83: =Scenarios!I38 -> 0
A84: Share Repurchases | C84: =Scenarios!C63 -> 0 | D84: =Scenarios!D63 -> 0 | E84: =-ABS(Scenarios!E37) -> 0 | F84: =-ABS(Scenarios!F37) -> 0 | G84: =-ABS(Scenarios!G37) -> 0 | H84: =-ABS(Scenarios!H37) -> 0 | I84: =-ABS(Scenarios!I37) -> 0
A85: Cash from Financing | C85: =C80+C81+C82+C83+C84 -> -42439 | D85: =D80+D81+D82+D83+D84 -> -53067 | E85: =E80+E81+E82+E83+E84 -> -23191.801 | F85: =F80+F81+F82+F83+F84 -> -23753.833 | G85: =G80+G81+G82+G83+G84 -> -24277.67 | H85: =H80+H81+H82+H83+H84 -> -24750.543 | I85: =I80+I81+I82+I83+I84 -> -25160.431
A87: Net Change in Cash | C87: =C73+C78+C85 -> 25000 | D87: =D73+D78+D85 -> 25000 | E87: =E73+E78+E85 -> 38155.18 | F87: =F73+F78+F85 -> 50850.725 | G87: =G73+G78+G85 -> 63001.408 | H87: =H73+H78+H85 -> 75019.92 | I87: =I73+I78+I85 -> 86733.036
A88: Beginning Cash | C88: =B21 -> 150000 | D88: =C21 -> 175000 | E88: =D21 -> 200000 | F88: =E21 -> 238155.18 | G88: =F21 -> 289005.91 | H88: =G21 -> 352007.31 | I88: =H21 -> 427027.23
A89: Ending Cash | C89: =C88+C87 -> 175000 | D89: =D88+D87 -> 200000 | E89: =E88+E87 -> 238155.18 | F89: =F88+F87 -> 289005.91 | G89: =G88+G87 -> 352007.31 | H89: =H88+H87 -> 427027.23 | I89: =I88+I87 -> 513760.27
A90: Free Cash Flow | C90: =C73+C75 -> 67439 | D90: =D73+D75 -> 78067 | E90: =E73+E75 -> 61346.981 | F90: =F73+F75 -> 74604.558 | G90: =G73+G75 -> 87279.078 | H90: =H73+H75 -> 99770.462 | I90: =I73+I75 -> 111893.47

Sheet _Calc_Opt
A1: _Calc_Opt — Full 3-Statement Model | B1: 2021 | C1: 2022 | D1: 2023 | E1: 2024E | F1: 2025E | G1: 2026E | H1: 2027E | I1: 2028E
A2: Revenue | B2: ='Income Statement'!B2 -> 750000 | C2: ='Income Statement'!C2 -> 850000 | D2: ='Income Statement'!D2 -> 950000 | E2: =D2*(1+Scenarios!E94) -> 1092500 | F2: =E2*(1+Scenarios!F94) -> 1223600 | G2: =F2*(1+Scenarios!G94) -> 1345960 | H2: =G2*(1+Scenarios!H94) -> 1467096.4 | I2: =H2*(1+Scenarios!I94) -> 1584464.1
A3: Revenue Growth % | B3: =0 -> 0 | C3: =(C2-B2)/B2 -> 0 | D3: =(D2-C2)/C2 -> 0 | E3: =Scenarios!E94 -> 0 | F3: =Scenarios!F94 -> 0 | G3: =Scenarios!G94 -> 0 | H3: =Scenarios!H94 -> 0 | I3: =Scenarios!I94 -> 0
A4: COGS | B4: ='Income Statement'!B4 -> 450000 | C4: ='Income Statement'!C4 -> 510000 | D4: ='Income Statement'!D4 -> 570000 | E4: =E2*Scenarios!E95 -> 600875 | F4: =F2*Scenarios!F95 -> 660744 | G4: =G2*Scenarios!G95 -> 713358.8 | H4: =H2*Scenarios!H95 -> 762890.13 | I4: =I2*Scenarios!I95 -> 808076.7
A5: Gross Profit | B5: =B2-B4 -> 300000 | C5: =C2-C4 -> 340000 | D5: =D2-D4 -> 380000 | E5: =E2-E4 -> 491625 | F5: =F2-F4 -> 562856 | G5: =G2-G4 -> 632601.2 | H5: =H2-H4 -> 704206.27 | I5: =I2-I4 -> 776387.41
A6: SG&A | B6: ='Income Statement'!B9 -> 112500 | C6: ='Income Statement'!C9 -> 127500 | D6: ='Income Statement'!D9 -> 142500 | E6: =E2*Scenarios!E96 -> 142025 | F6: =F2*Scenarios!F96 -> 146832 | G6: =G2*Scenarios!G96 -> 161515.2 | H6: =H2*Scenarios!H96 -> 161380.6 | I6: =I2*Scenarios!I96 -> 174291.05
A7: R&D | B7: ='Income Statement'!B10 -> 37500 | C7: ='Income Statement'!C10 -> 42500 | D7: ='Income Statement'!D10 -> 47500 | E7: =E2*Scenarios!E97 -> 54625 | F7: =F2*Scenarios!F97 -> 61180 | G7: =G2*Scenarios!G97 -> 67298 | H7: =H2*Scenarios!H97 -> 73354.82 | I7: =I2*Scenarios!I97 -> 79223.206
A8: Depreciation | B8: ='Income Statement'!B11 -> 25000 | C8: ='Income Statement'!C11 -> 28000 | D8: ='Income Statement'!D11 -> 32000 | E8: =(D28+E2*Scenarios!E111/2)*Scenarios!E112 -> 41231.25 | F8: =(E28+F2*Scenarios!F111/2)*Scenarios!F112 -> 47021.5 | G8: =(F28+G2*Scenarios!G111/2)*Scenarios!G112 -> 53445.4 | H8: =(G28+H2*Scenarios!H111/2)*Scenarios!H112 -> 60478.041 | I8: =(H28+I2*Scenarios!I111/2)*Scenarios!I112 -> 68106.942
A9: Amortization | B9: ='Income Statement'!B12 -> 5000 | C9: ='Income Statement'!C12 -> 5000 | D9: ='Income Statement'!D12 -> 5000 | E9: =Scenarios!E113 -> 5000 | F9: =Scenarios!F113 -> 5000 | G9: =Scenarios!G113 -> 5000 | H9: =Scenarios!H113 -> 5000 | I9: =Scenarios!I113 -> 5000
A10: Other OpEx | B10: ='Income Statement'!B13 -> 15000 | C10: ='Income Statement'!C13 -> 17000 | D10: ='Income Statement'!D13 -> 19000 | E10: =E2*Scenarios!E98 -> 21850 | F10: =F2*Scenarios!F98 -> 24472 | G10: =G2*Scenarios!G98 -> 26919.2 | H10: =H2*Scenarios!H98 -> 29341.928 | I10: =I2*Scenarios!I98 -> 31689.282
A11: SBC | B11: ='Income Statement'!B14 -> 0 | C11: ='Income Statement'!C14 -> 0 | D11: ='Income Statement'!D14 -> 0 | E11: =Scenarios!E102 -> 10000 | F11: =Scenarios!F102 -> 10000 | G11: =Scenarios!G102 -> 10000 | H11: =Scenarios!H102 -> 10000 | I11: =Scenarios!I102 -> 10000
A12: Total OpEx | B12: =B6+B7+B8+B9+B10+B11 -> 195000 | C12: =C6+C7+C8+C9+C10+C11 -> 220000 | D12: =D6+D7+D8+D9+D10+D11 -> 246000 | E12: =E6+E7+E8+E9+E10+E11 -> 274731.25 | F12: =F6+F7+F8+F9+F10+F11 -> 294505.5 | G12: =G6+G7+G8+G9+G10+G11 -> 324177.8 | H12: =H6+H7+H8+H9+H10+H11 -> 339555.39 | I12: =I6+I7+I8+I9+I10+I11 -> 368310.48
A13: EBIT | B13: =B5-B12 -> 105000 | C13: =C5-C12 -> 120000 | D13: =D5-D12 -> 134000 | E13: =E5-E12 -> 216893.75 | F13: =F5-F12 -> 268350.5 | G13: =G5-G12 -> 308423.4 | H13: =H5-H12 -> 364650.88 | I13: =I5-I12 -> 408076.93
A14: Interest Income | B14: ='Income Statement'!B21 -> 2000 | C14: ='Income Statement'!C21 -> 2500 | D14: ='Income Statement'!D21 -> 3000 | E14: =D21*Scenarios!E116 -> 4835.4715 | F14: =E21*Scenarios!F116 -> 6811.5117 | G14: =F21*Scenarios!G116 -> 9337.5242 | H14: =G21*Scenarios!H116 -> 12445.665 | I14: =H21*Scenarios!I116 -> 16171.838
A15: Interest Expense | B15: ='Income Statement'!B22 -> 15000 | C15: ='Income Statement'!C22 -> 14000 | D15: ='Income Statement'!D22 -> 13000 | E15: =(D45+E45)/2*Scenarios!E115 -> 13500 | F15: =(E45+F45)/2*Scenarios!F115 -> 12500 | G15: =(F45+G45)/2*Scenarios!G115 -> 11500 | H15: =(G45+H45)/2*Scenarios!H115 -> 10500 | I15: =(H45+I45)/2*Scenarios!I115 -> 9500
A16: Other Income/Expense | B16: ='Income Statement'!B23 -> 0 | C16: ='Income Statement'!C23 -> 0 | D16: ='Income Statement'!D23 -> 0 | E16: =Scenarios!E100 -> 0 | F16: =Scenarios!F100 -> 0 | G16: =Scenarios!G100 -> 0 | H16: =Scenarios!H100 -> 0 | I16: =Scenarios!I100 -> 0
A17: EBT | B17: =B13+B14-B15+B16 -> 92000 | C17: =C13+C14-C15+C16 -> 108500 | D17: =D13+D14-D15+D16 -> 124000 | E17: =E13+E14-E15+E16 -> 208229.22 | F17: =F13+F14-F15+F16 -> 262662.01 | G17: =G13+G14-G15+G16 -> 306260.92 | H17: =H13+H14-H15+H16 -> 366596.54 | I17: =I13+I14-I15+I16 -> 414748.77
A18: Tax Expense | B18: ='Income Statement'!B25 -> 23125 | C18: ='Income Statement'!C25 -> 27375 | D18: ='Income Statement'!D25 -> 31250 | E18: =MAX(0,E17*Scenarios!E99) -> 46851.575 | F18: =MAX(0,F17*Scenarios!F99) -> 59098.953 | G18: =MAX(0,G17*Scenarios!G99) -> 68908.708 | H18: =MAX(0,H17*Scenarios!H99) -> 82484.222 | I18: =MAX(0,I17*Scenarios!I99) -> 93318.473
A19: Net Income | B19: =B17-B18 -> 68875 | C19: =C17-C18 -> 81125 | D19: =D17-D18 -> 92750 | E19: =E17-E18 -> 161377.65 | F19: =F17-F18 -> 203563.06 | G19: =G17-G18 -> 237352.22 | H19: =H17-H18 -> 284112.32 | I19: =I17-I18 -> 321430.3
A20: ── Balance Sheet ──
A21: Cash & Equivalents | B21: ='Balance Sheet'!B3 -> 150000 | C21: ='Balance Sheet'!C3 -> 175000 | D21: ='Balance Sheet'!D3 -> 200000 | E21: =D21+E73+E78+E85 -> 283547.15 | F21: =E21+F73+F78+F85 -> 397604.02 | G21: =F21+G73+G78+G85 -> 536148.4 | H21: =G21+H73+H78+H85 -> 708418.1 | I21: =H21+I73+I78+I85 -> 908765.75
A22: Accounts Receivable | B22: ='Balance Sheet'!B4 -> 92466 | C22: ='Balance Sheet'!C4 -> 104795 | D22: ='Balance Sheet'!D4 -> 117123 | E22: =E2*Scenarios!E104/365 -> 134691.78 | F22: =F2*Scenarios!F104/365 -> 150854.79 | G22: =G2*Scenarios!G104/365 -> 165940.27 | H22: =H2*Scenarios!H104/365 -> 180874.9 | I22: =I2*Scenarios!I104/365 -> 195344.89
A23: Inventory | B23: ='Balance Sheet'!B5 -> 36986 | C23: ='Balance Sheet'!C5 -> 41918 | D23: ='Balance Sheet'!D5 -> 46849 | E23: =E4*Scenarios!E105/365 -> 49386.986 | F23: =F4*Scenarios!F105/365 -> 54307.726 | G23: =G4*Scenarios!G105/365 -> 58632.23 | H23: =H4*Scenarios!H105/365 -> 62703.298 | I23: =I4*Scenarios!I105/365 -> 66417.263
A24: Prepaid Expenses | B24: ='Balance Sheet'!B6 -> 7500 | C24: ='Balance Sheet'!C6 -> 8500 | D24: ='Balance Sheet'!D6 -> 9500 | E24: =E2*Scenarios!E107 -> 10925 | F24: =F2*Scenarios!F107 -> 12236 | G24: =G2*Scenarios!G107 -> 13459.6 | H24: =H2*Scenarios!H107 -> 14670.964 | I24: =I2*Scenarios!I107 -> 15844.641
A25: Other Current Assets | B25: ='Balance Sheet'!B7 -> 10000 | C25: ='Balance Sheet'!C7 -> 10000 | D25: ='Balance Sheet'!D7 -> 10000 | E25: =Scenarios!E126 -> 10000 | F25: =Scenarios!F126 -> 10000 | G25: =Scenarios!G126 -> 10000 | H25: =Scenarios!H126 -> 10000 | I25: =Scenarios!I126 -> 10000
A26: Total Current Assets | B26: =SUM(B21:B25) -> 296952 | C26: =SUM(C21:C25) -> 340213 | D26: =SUM(D21:D25) -> 383472 | E26: =SUM(E21:E25) -> 488550.92 | F26: =SUM(F21:F25) -> 625002.55 | G26: =SUM(G21:G25) -> 784180.5 | H26: =SUM(H21:H25) -> 976667.26 | I26: =SUM(I21:I25) -> 1196372.5
A28: Gross PP&E | B28: ='Balance Sheet'!B10 -> 300000 | C28: ='Balance Sheet'!C10 -> 340000 | D28: ='Balance Sheet'!D10 -> 385000 | E28: =D28+E2*Scenarios!E111 -> 439625 | F28: =E28+F2*Scenarios!F111 -> 500805 | G28: =F28+G2*Scenarios!G111 -> 568103 | H28: =G28+H2*Scenarios!H111 -> 641457.82 | I28: =H28+I2*Scenarios!I111 -> 720681.03
A29: Accumulated Depreciation | B29: ='Balance Sheet'!B11 -> 100000 | C29: ='Balance Sheet'!C11 -> 128000 | D29: ='Balance Sheet'!D11 -> 160000 | E29: =D29+E8 -> 201231.25 | F29: =E29+F8 -> 248252.75 | G29: =F29+G8 -> 301698.15 | H29: =G29+H8 -> 362176.19 | I29: =H29+I8 -> 430283.13
A30: Net PP&E | B30: =B28-B29 -> 200000 | C30: =C28-C29 -> 212000 | D30: =D28-D29 -> 225000 | E30: =E28-E29 -> 238393.75 | F30: =F28-F29 -> 252552.25 | G30: =G28-G29 -> 266404.85 | H30: =H28-H29 -> 279281.63 | I30: =I28-I29 -> 290397.89
A31: Intangibles | B31: ='Balance Sheet'!B13 -> 50000 | C31: ='Balance Sheet'!C13 -> 45000 | D31: ='Balance Sheet'!D13 -> 40000 | E31: =MAX(0,D31-E9) -> 35000 | F31: =MAX(0,E31-F9) -> 30000 | G31: =MAX(0,F31-G9) -> 25000 | H31: =MAX(0,G31-H9) -> 20000 | I31: =MAX(0,H31-I9) -> 15000
A32: Goodwill | B32: ='Balance Sheet'!B14 -> 100000 | C32: ='Balance Sheet'!C14 -> 100000 | D32: ='Balance Sheet'!D14 -> 100000 | E32: =Scenarios!E125 -> 100000 | F32: =Scenarios!F125 -> 100000 | G32: =Scenarios!G125 -> 100000 | H32: =Scenarios!H125 -> 100000 | I32: =Scenarios!I125 -> 100000
A33: Other LT Assets | B33: ='Balance Sheet'!B15 -> 20000 | C33: ='Balance Sheet'!C15 -> 20000 | D33: ='Balance Sheet'!D15 -> 20000 | E33: =Scenarios!E127 -> 20000 | F33: =Scenarios!F127 -> 20000 | G33: =Scenarios!G127 -> 20000 | H33: =Scenarios!H127 -> 20000 | I33: =Scenarios!I127 -> 20000
A34: Total Non-Current Assets | B34: =B30+B31+B32+B33 -> 370000 | C34: =C30+C31+C32+C33 -> 377000 | D34: =D30+D31+D32+D33 -> 385000 | E34: =E30+E31+E32+E33 -> 393393.75 | F34: =F30+F31+F32+F33 -> 402552.25 | G34: =G30+G31+G32+G33 -> 411404.85 | H34: =H30+H31+H32+H33 -> 419281.63 | I34: =I30+I31+I32+I33 -> 425397.89
A35: Total Assets | B35: =B26+B34 -> 666952 | C35: =C26+C34 -> 717213 | D35: =D26+D34 -> 768472 | E35: =E26+E34 -> 881944.67 | F35: =F26+F34 -> 1027554.8 | G35: =G26+G34 -> 1195585.4 | H35: =H26+H34 -> 1395948.9 | I35: =I26+I34 -> 1621770.4
A37: Accounts Payable | B37: ='Balance Sheet'!B20 -> 49315 | C37: ='Balance Sheet'!C20 -> 55890 | D37: ='Balance Sheet'!D20 -> 62466 | E37: =E4*Scenarios!E106/365 -> 65849.315 | F37: =F4*Scenarios!F106/365 -> 72410.301 | G37: =G4*Scenarios!G106/365 -> 78176.307 | H37: =H4*Scenarios!H106/365 -> 83604.398 | I37: =I4*Scenarios!I106/365 -> 88556.35
A38: Accrued Expenses | B38: ='Balance Sheet'!B21 -> 22500 | C38: ='Balance Sheet'!C21 -> 25500 | D38: ='Balance Sheet'!D21 -> 28500 | E38: =E2*Scenarios!E108 -> 32775 | F38: =F2*Scenarios!F108 -> 36708 | G38: =G2*Scenarios!G108 -> 40378.8 | H38: =H2*Scenarios!H108 -> 44012.892 | I38: =I2*Scenarios!I108 -> 47533.923
A39: Short-Term Debt | B39: ='Balance Sheet'!B22 -> 50000 | C39: ='Balance Sheet'!C22 -> 50000 | D39: ='Balance Sheet'!D22 -> 50000 | E39: =Scenarios!E117 -> 50000 | F39: =Scenarios!F117 -> 50000 | G39: =Scenarios!G117 -> 50000 | H39: =Scenarios!H117 -> 50000 | I39: =Scenarios!I117 -> 50000
A40: Current Portion LTD | B40: ='Balance Sheet'!B23 -> 20000 | C40: ='Balance Sheet'!C23 -> 20000 | D40: ='Balance Sheet'!D23 -> 20000 | E40: =Scenarios!E120 -> 20000 | F40: =Scenarios!F120 -> 20000 | G40: =Scenarios!G120 -> 20000 | H40: =Scenarios!H120 -> 20000 | I40: =Scenarios!I120 -> 20000
A41: Deferred Revenue | B41: ='Balance Sheet'!B24 -> 15000 | C41: ='Balance Sheet'!C24 -> 17000 | D41: ='Balance Sheet'!D24 -> 19000 | E41: =E2*Scenarios!E109 -> 21850 | F41: =F2*Scenarios!F109 -> 24472 | G41: =G2*Scenarios!G109 -> 26919.2 | H41: =H2*Scenarios!H109 -> 29341.928 | I41: =I2*Scenarios!I109 -> 31689.282
A42: Other Current Liabilities | B42: ='Balance Sheet'!B25 -> 15000 | C42: ='Balance Sheet'!C25 -> 15000 | D42: ='Balance Sheet'!D25 -> 15000 | E42: =Scenarios!E128 -> 15000 | F42: =Scenarios!F128 -> 15000 | G42: =Scenarios!G128 -> 15000 | H42: =Scenarios!H128 -> 15000 | I42: =Scenarios!I128 -> 15000
A43: Total Current Liabilities | B43: =SUM(B37:B42) -> 171815 | C43: =SUM(C37:C42) -> 183390 | D43: =SUM(D37:D42) -> 194966 | E43: =SUM(E37:E42) -> 205474.32 | F43: =SUM(F37:F42) -> 218590.3 | G43: =SUM(G37:G42) -> 230474.31 | H43: =SUM(H37:H42) -> 241959.22 | I43: =SUM(I37:I42) -> 252779.56
A45: Long-Term Debt | B45: ='Balance Sheet'!B28 -> 250000 | C45: ='Balance Sheet'!C28 -> 230000 | D45: ='Balance Sheet'!D28 -> 210000 | E45: =D45+Scenarios!E118-Scenarios!E119 -> 190000 | F45: =E45+Scenarios!F118-Scenarios!F119 -> 170000 | G45: =F45+Scenarios!G118-Scenarios!G119 -> 150000 | H45: =G45+Scenarios!H118-Scenarios!H119 -> 130000 | I45: =H45+Scenarios!I118-Scenarios!I119 -> 110000
A46: Deferred Tax Liabilities | B46: ='Balance Sheet'!B29 -> 30000 | C46: ='Balance Sheet'!C29 -> 30000 | D46: ='Balance Sheet'!D29 -> 30000 | E46: =Scenarios!E129 -> 30000 | F46: =Scenarios!F129 -> 30000 | G46: =Scenarios!G129 -> 30000 | H46: =Scenarios!H129 -> 30000 | I46: =Scenarios!I129 -> 30000
A47: Other LT Liabilities | B47: ='Balance Sheet'!B30 -> 25000 | C47: ='Balance Sheet'!C30 -> 25000 | D47: ='Balance Sheet'!D30 -> 25000 | E47: =Scenarios!E130 -> 25000 | F47: =Scenarios!F130 -> 25000 | G47: =Scenarios!G130 -> 25000 | H47: =Scenarios!H130 -> 25000 | I47: =Scenarios!I130 -> 25000
A48: Total Non-Current Liabilities | B48: =SUM(B45:B47) -> 305000 | C48: =SUM(C45:C47) -> 285000 | D48: =SUM(D45:D47) -> 265000 | E48: =SUM(E45:E47) -> 245000 | F48: =SUM(F45:F47) -> 225000 | G48: =SUM(G45:G47) -> 205000 | H48: =SUM(H45:H47) -> 185000 | I48: =SUM(I45:I47) -> 165000
A49: Total Liabilities | B49: =B43+B48 -> 476815 | C49: =C43+C48 -> 468390 | D49: =D43+D48 -> 459966 | E49: =E43+E48 -> 450474.32 | F49: =F43+F48 -> 443590.3 | G49: =G43+G48 -> 435474.31 | H49: =H43+H48 -> 426959.22 | I49: =I43+I48 -> 417779.56
A51: Common Stock | B51: ='Balance Sheet'!B35 -> 10000 | C51: ='Balance Sheet'!C35 -> 10000 | D51: ='Balance Sheet'!D35 -> 10000 | E51: =Scenarios!E131 -> 10000 | F51: =Scenarios!F131 -> 10000 | G51: =Scenarios!G131 -> 10000 | H51: =Scenarios!H131 -> 10000 | I51: =Scenarios!I131 -> 10000
A52: APIC | B52: ='Balance Sheet'!B36 -> 200000 | C52: ='Balance Sheet'!C36 -> 210000 | D52: ='Balance Sheet'!D36 -> 220000 | E52: =D52+Scenarios!E123+Scenarios!E102 -> 230000 | F52: =E52+Scenarios!F123+Scenarios!F102 -> 240000 | G52: =F52+Scenarios!G123+Scenarios!G102 -> 250000 | H52: =G52+Scenarios!H123+Scenarios!H102 -> 260000 | I52: =H52+Scenarios!I123+Scenarios!I102 -> 270000
A53: Retained Earnings | B53: ='Balance Sheet'!B37 -> -19863 | C53: ='Balance Sheet'!C37 -> 28823 | D53: ='Balance Sheet'!D37 -> 78506 | E53: =D53+E19-MAX(0,E19*Scenarios!E121) -> 191470.35 | F53: =E53+F19-MAX(0,F19*Scenarios!F121) -> 333964.49 | G53: =F53+G19-MAX(0,G19*Scenarios!G121) -> 500111.05 | H53: =G53+H19-MAX(0,H19*Scenarios!H121) -> 698989.67 | I53: =H53+I19-MAX(0,I19*Scenarios!I121) -> 923990.88
A54: Treasury Stock | B54: ='Balance Sheet'!B38 -> 0 | C54: ='Balance Sheet'!C38 -> 0 | D54: ='Balance Sheet'!D38 -> 0 | E54: =D54-Scenarios!E122 -> 0 | F54: =E54-Scenarios!F122 -> 0 | G54: =F54-Scenarios!G122 -> 0 | H54: =G54-Scenarios!H122 -> 0 | I54: =H54-Scenarios!I122 -> 0
A55: Other Comprehensive Income | B55: ='Balance Sheet'!B39 -> 0 | C55: ='Balance Sheet'!C39 -> 0 | D55: ='Balance Sheet'!D39 -> 0 | E55: =Scenarios!E133 -> 0 | F55: =Scenarios!F133 -> 0 | G55: =Scenarios!G133 -> 0 | H55: =Scenarios!H133 -> 0 | I55: =Scenarios!I133 -> 0
A56: Total Equity | B56: =SUM(B51:B55) -> 190137 | C56: =SUM(C51:C55) -> 248823 | D56: =SUM(D51:D55) -> 308506 | E56: =SUM(E51:E55) -> 431470.35 | F56: =SUM(F51:F55) -> 583964.49 | G56: =SUM(G51:G55) -> 760111.05 | H56: =SUM(H51:H55) -> 968989.67 | I56: =SUM(I51:I55) -> 1203990.9
A58: Total Liabilities + Equity | B58: =B49+B56 -> 666952 | C58: =C49+C56 -> 717213 | D58: =D49+D56 -> 768472 | E58: =E49+E56 -> 881944.67 | F58: =F49+F56 -> 1027554.8 | G58: =G49+G56 -> 1195585.4 | H58: =H49+H56 -> 1395948.9 | I58: =I49+I56 -> 1621770.4
A59: Balance Check (TA - TLE) | B59: =B35-B58 -> 0 | C59: =C35-C58 -> 0 | D59: =D35-D58 -> 0 | E59: =E35-E58 -> 0 | F59: =F35-F58 -> 0 | G59: =G35-G58 -> 0 | H59: =H35-H58 -> 0 | I59: =I35-I58 -> 0
A60: ── Cash Flow ──
A61: Net Income | C61: =C19 -> 81125 | D61: =D19 -> 92750 | E61: =E19 -> 161377.65 | F61: =F19 -> 203563.06 | G61: =G19 -> 237352.22 | H61: =H19 -> 284112.32 | I61: =I19 -> 321430.3
A62: + Depreciation | C62: =C8 -> 28000 | D62: =D8 -> 32000 | E62: =E8 -> 41231.25 | F62: =F8 -> 47021.5 | G62: =G8 -> 53445.4 | H62: =H8 -> 60478.041 | I62: =I8 -> 68106.942
A63: + Amortization | C63: =C9 -> 5000 | D63: =D9 -> 5000 | E63: =E9 -> 5000 | F63: =F9 -> 5000 | G63: =G9 -> 5000 | H63: =H9 -> 5000 | I63: =I9 -> 5000
A64: + SBC | C64: =C11 -> 0 | D64: =D11 -> 0 | E64: =E11 -> 10000 | F64: =F11 -> 10000 | G64: =G11 -> 10000 | H64: =H11 -> 10000 | I64: =I11 -> 10000
A65: Deferred Taxes | C65: =C46-B46 -> 0 | D65: =D46-C46 -> 0 | E65: =E46-D46 -> 0 | F65: =F46-E46 -> 0 | G65: =G46-F46 -> 0 | H65: =H46-G46 -> 0 | I65: =I46-H46 -> 0
A66: Δ A/R | C66: =-(C22-B22) -> -12329 | D66: =-(D22-C22) -> -12328 | E66: =-(E22-D22) -> -17568.781 | F66: =-(F22-E22) -> -16163.014 | G66: =-(G22-F22) -> -15085.479 | H66: =-(H22-G22) -> -14934.625 | I66: =-(I22-H22) -> -14469.992
A67: Δ Inventory | C67: =-(C23-B23) -> -4932 | D67: =-(D23-C23) -> -4931 | E67: =-(E23-D23) -> -2537.9863 | F67: =-(F23-E23) -> -4920.7397 | G67: =-(G23-F23) -> -4324.5041 | H67: =-(H23-G23) -> -4071.0681 | I67: =-(I23-H23) -> -3713.9646
A68: Δ Prepaid | C68: =-(C24-B24) -> -1000 | D68: =-(D24-C24) -> -1000 | E68: =-(E24-D24) -> -1425 | F68: =-(F24-E24) -> -1311 | G68: =-(G24-F24) -> -1223.6 | H68: =-(H24-G24) -> -1211.364 | I68: =-(I24-H24) -> -1173.6771
A69: Δ A/P | C69: =C37-B37 -> 6575 | D69: =D37-C37 -> 6576 | E69: =E37-D37 -> 3383.3151 | F69: =F37-E37 -> 6560.9863 | G69: =G37-F37 -> 5766.0055 | H69: =H37-G37 -> 5428.0907 | I69: =I37-H37 -> 4951.9528
A70: Δ Accrued Exp | C70: =C38-B38 -> 3000 | D70: =D38-C38 -> 3000 | E70: =E38-D38 -> 4275 | F70: =F38-E38 -> 3933 | G70: =G38-F38 -> 3670.8 | H70: =H38-G38 -> 3634.092 | I70: =I38-H38 -> 3521.0314
A71: Δ Deferred Revenue | C71: =C41-B41 -> 2000 | D71: =D41-C41 -> 2000 | E71: =E41-D41 -> 2850 | F71: =F41-E41 -> 2622 | G71: =G41-F41 -> 2447.2 | H71: =H41-G41 -> 2422.728 | I71: =I41-H41 -> 2347.3542
A72: Total WC Change | C72: =SUM(C66:C71) -> -6686 | D72: =SUM(D66:D71) -> -6683 | E72: =SUM(E66:E71) -> -11023.452 | F72: =SUM(F66:F71) -> -9278.7671 | G72: =SUM(G66:G71) -> -8749.5781 | H72: =SUM(H66:H71) -> -8732.146 | I72: =SUM(I66:I71) -> -8537.2952
A73: Cash from Operations | C73: =C61+C62+C63+C64+C65+C72 -> 107439 | D73: =D61+D62+D63+D64+D65+D72 -> 123067 | E73: =E61+E62+E63+E64+E65+E72 -> 206585.44 | F73: =F61+F62+F63+F64+F65+F72 -> 256305.79 | G73: =G61+G62+G63+G64+G65+G72 -> 297048.04 | H73: =H61+H62+H63+H64+H65+H72 -> 350858.22 | I73: =I61+I62+I63+I64+I65+I72 -> 395999.94
A75: Capital Expenditures | C75: =-ABS(C2*Scenarios!C111) -> -40000 | D75: =-ABS(D2*Scenarios!D111) -> -45000 | E75: =-ABS(E2*Scenarios!E111) -> -54625 | F75: =-ABS(F2*Scenarios!F111) -> -61180 | G75: =-ABS(G2*Scenarios!G111) -> -67298 | H75: =-ABS(H2*Scenarios!H111) -> -73354.82 | I75: =-ABS(I2*Scenarios!I111) -> -79223.206
A76: Acquisitions | C76: =Scenarios!C149 -> 0 | D76: =Scenarios!D149 -> 0 | E76: =0 -> 0 | F76: =0 -> 0 | G76: =0 -> 0 | H76: =0 -> 0 | I76: =0 -> 0
A77: Asset Sales | C77: =Scenarios!C150 -> 0 | D77: =Scenarios!D150 -> 0 | E77: =0 -> 0 | F77: =0 -> 0 | G77: =0 -> 0 | H77: =0 -> 0 | I77: =0 -> 0
A78: Cash from Investing | C78: =C75+C76+C77 -> -40000 | D78: =D75+D76+D77 -> -45000 | E78: =E75+E76+E77 -> -54625 | F78: =F75+F76+F77 -> -61180 | G78: =G75+G76+G77 -> -67298 | H78: =H75+H76+H77 -> -73354.82 | I78: =I75+I76+I77 -> -79223.206
A80: Debt Issuance | C80: =Scenarios!C118 -> 0 | D80: =Scenarios!D118 -> 0 | E80: =Scenarios!E118 -> 0 | F80: =Scenarios!F118 -> 0 | G80: =Scenarios!G118 -> 0 | H80: =Scenarios!H118 -> 0 | I80: =Scenarios!I118 -> 0
A81: Debt Repayment | C81: =-ABS(Scenarios!C119) -> -20000 | D81: =-ABS(Scenarios!D119) -> -20000 | E81: =-ABS(Scenarios!E119) -> -20000 | F81: =-ABS(Scenarios!F119) -> -20000 | G81: =-ABS(Scenarios!G119) -> -20000 | H81: =-ABS(Scenarios!H119) -> -20000 | I81: =-ABS(Scenarios!I119) -> -20000
A82: Dividends Paid | C82: =Scenarios!C146 -> -32439 | D82: =Scenarios!D146 -> -43067 | E82: =-MAX(0,E19*Scenarios!E121) -> -48413.294 | F82: =-MAX(0,F19*Scenarios!F121) -> -61068.918 | G82: =-MAX(0,G19*Scenarios!G121) -> -71205.665 | H82: =-MAX(0,H19*Scenarios!H121) -> -85233.696 | I82: =-MAX(0,I19*Scenarios!I121) -> -96429.089
A83: Equity Issuance | C83: =Scenarios!C147 -> 10000 | D83: =Scenarios!D147 -> 10000 | E83: =Scenarios!E123 -> 0 | F83: =Scenarios!F123 -> 0 | G83: =Scenarios!G123 -> 0 | H83: =Scenarios!H123 -> 0 | I83: =Scenarios!I123 -> 0
A84: Share Repurchases | C84: =Scenarios!C148 -> 0 | D84: =Scenarios!D148 -> 0 | E84: =-ABS(Scenarios!E122) -> 0 | F84: =-ABS(Scenarios!F122) -> 0 | G84: =-ABS(Scenarios!G122) -> 0 | H84: =-ABS(Scenarios!H122) -> 0 | I84: =-ABS(Scenarios!I122) -> 0
A85: Cash from Financing | C85: =C80+C81+C82+C83+C84 -> -42439 | D85: =D80+D81+D82+D83+D84 -> -53067 | E85: =E80+E81+E82+E83+E84 -> -68413.294 | F85: =F80+F81+F82+F83+F84 -> -81068.918 | G85: =G80+G81+G82+G83+G84 -> -91205.665 | H85: =H80+H81+H82+H83+H84 -> -105233.7 | I85: =I80+I81+I82+I83+I84 -> -116429.09
A87: Net Change in Cash | C87: =C73+C78+C85 -> 25000 | D87: =D73+D78+D85 -> 25000 | E87: =E73+E78+E85 -> 83547.151 | F87: =F73+F78+F85 -> 114056.87 | G87: =G73+G78+G85 -> 138544.37 | H87: =H73+H78+H85 -> 172269.7 | I87: =I73+I78+I85 -> 200347.65
A88: Beginning Cash | C88: =B21 -> 150000 | D88: =C21 -> 175000 | E88: =D21 -> 200000 | F88: =E21 -> 283547.15 | G88: =F21 -> 397604.02 | H88: =G21 -> 536148.4 | I88: =H21 -> 708418.1
A89: Ending Cash | C89: =C88+C87 -> 175000 | D89: =D88+D87 -> 200000 | E89: =E88+E87 -> 283547.15 | F89: =F88+F87 -> 397604.02 | G89: =G88+G87 -> 536148.4 | H89: =H88+H87 -> 708418.1 | I89: =I88+I87 -> 908765.75
A90: Free Cash Flow | C90: =C73+C75 -> 67439 | D90: =D73+D75 -> 78067 | E90: =E73+E75 -> 151960.44 | F90: =F73+F75 -> 195125.79 | G90: =G73+G75 -> 229750.04 | H90: =H73+H75 -> 277503.4 | I90: =I73+I75 -> 316776.74

Sheet _Calc_Con
A1: _Calc_Con — Full 3-Statement Model | B1: 2021 | C1: 2022 | D1: 2023 | E1: 2024E | F1: 2025E | G1: 2026E | H1: 2027E | I1: 2028E
A2: Revenue | B2: ='Income Statement'!B2 -> 750000 | C2: ='Income Statement'!C2 -> 850000 | D2: ='Income Statement'!D2 -> 950000 | E2: =D2*(1+Scenarios!E179) -> 978500 | F2: =E2*(1+Scenarios!F179) -> 998070 | G2: =F2*(1+Scenarios!G179) -> 1018031.4 | H2: =G2*(1+Scenarios!H179) -> 1028211.7 | I2: =H2*(1+Scenarios!I179) -> 1038493.8
A3: Revenue Growth % | B3: =0 -> 0 | C3: =(C2-B2)/B2 -> 0 | D3: =(D2-C2)/C2 -> 0 | E3: =Scenarios!E179 -> 0 | F3: =Scenarios!F179 -> 0 | G3: =Scenarios!G179 -> 0 | H3: =Scenarios!H179 -> 0 | I3: =Scenarios!I179 -> 0
A4: COGS | B4: ='Income Statement'!B4 -> 450000 | C4: ='Income Statement'!C4 -> 510000 | D4: ='Income Statement'!D4 -> 570000 | E4: =E2*Scenarios!E180 -> 636025 | F4: =F2*Scenarios!F180 -> 658726.2 | G4: =G2*Scenarios!G180 -> 682081.04 | H4: =H2*Scenarios!H180 -> 688901.85 | I4: =I2*Scenarios!I180 -> 706175.81
A5: Gross Profit | B5: =B2-B4 -> 300000 | C5: =C2-C4 -> 340000 | D5: =D2-D4 -> 380000 | E5: =E2-E4 -> 342475 | F5: =F2-F4 -> 339343.8 | G5: =G2-G4 -> 335950.36 | H5: =H2-H4 -> 339309.87 | I5: =I2-I4 -> 332318.03
A6: SG&A | B6: ='Income Statement'!B9 -> 112500 | C6: ='Income Statement'!C9 -> 127500 | D6: ='Income Statement'!D9 -> 142500 | E6: =E2*Scenarios!E181 -> 176130 | F6: =F2*Scenarios!F181 -> 189633.3 | G6: =G2*Scenarios!G181 -> 193425.97 | H6: =H2*Scenarios!H181 -> 205642.34 | I6: =I2*Scenarios!I181 -> 207698.77
A7: R&D | B7: ='Income Statement'!B10 -> 37500 | C7: ='Income Statement'!C10 -> 42500 | D7: ='Income Statement'!D10 -> 47500 | E7: =E2*Scenarios!E182 -> 48925 | F7: =F2*Scenarios!F182 -> 49903.5 | G7: =G2*Scenarios!G182 -> 50901.57 | H7: =H2*Scenarios!H182 -> 51410.586 | I7: =I2*Scenarios!I182 -> 51924.692
A8: Depreciation | B8: ='Income Statement'!B11 -> 25000 | C8: ='Income Statement'!C11 -> 28000 | D8: ='Income Statement'!D11 -> 32000 | E8: =(D28+E2*Scenarios!E196/2)*Scenarios!E197 -> 40946.25 | F8: =(E28+F2*Scenarios!F196/2)*Scenarios!F197 -> 45887.675 | G8: =(F28+G2*Scenarios!G196/2)*Scenarios!G197 -> 50927.929 | H8: =(G28+H2*Scenarios!H196/2)*Scenarios!H197 -> 56043.536 | I8: =(H28+I2*Scenarios!I196/2)*Scenarios!I197 -> 61210.3
A9: Amortization | B9: ='Income Statement'!B12 -> 5000 | C9: ='Income Statement'!C12 -> 5000 | D9: ='Income Statement'!D12 -> 5000 | E9: =Scenarios!E198 -> 5000 | F9: =Scenarios!F198 -> 5000 | G9: =Scenarios!G198 -> 5000 | H9: =Scenarios!H198 -> 5000 | I9: =Scenarios!I198 -> 5000
A10: Other OpEx | B10: ='Income Statement'!B13 -> 15000 | C10: ='Income Statement'!C13 -> 17000 | D10: ='Income Statement'!D13 -> 19000 | E10: =E2*Scenarios!E183 -> 19570 | F10: =F2*Scenarios!F183 -> 19961.4 | G10: =G2*Scenarios!G183 -> 20360.628 | H10: =H2*Scenarios!H183 -> 20564.234 | I10: =I2*Scenarios!I183 -> 20769.877
A11: SBC | B11: ='Income Statement'!B14 -> 0 | C11: ='Income Statement'!C14 -> 0 | D11: ='Income Statement'!D14 -> 0 | E11: =Scenarios!E187 -> 10000 | F11: =Scenarios!F187 -> 10000 | G11: =Scenarios!G187 -> 10000 | H11: =Scenarios!H187 -> 10000 | I11: =Scenarios!I187 -> 10000
A12: Total OpEx | B12: =B6+B7+B8+B9+B10+B11 -> 195000 | C12: =C6+C7+C8+C9+C10+C11 -> 220000 | D12: =D6+D7+D8+D9+D10+D11 -> 246000 | E12: =E6+E7+E8+E9+E10+E11 -> 300571.25 | F12: =F6+F7+F8+F9+F10+F11 -> 320385.88 | G12: =G6+G7+G8+G9+G10+G11 -> 330616.09 | H12: =H6+H7+H8+H9+H10+H11 -> 348660.7 | I12: =I6+I7+I8+I9+I10+I11 -> 356603.63
A13: EBIT | B13: =B5-B12 -> 105000 | C13: =C5-C12 -> 120000 | D13: =D5-D12 -> 134000 | E13: =E5-E12 -> 41903.75 | F13: =F5-F12 -> 18957.925 | G13: =G5-G12 -> 5334.2695 | H13: =H5-H12 -> -9350.8334 | I13: =I5-I12 -> -24285.609
A14: Interest Income | B14: ='Income Statement'!B21 -> 2000 | C14: ='Income Statement'!C21 -> 2500 | D14: ='Income Statement'!D21 -> 3000 | E14: =D21*Scenarios!E201 -> 4040.5665 | F14: =E21*Scenarios!F201 -> 4037.8343 | G14: =F21*Scenarios!G201 -> 3912.0355 | H14: =G21*Scenarios!H201 -> 3657.3195 | I14: =H21*Scenarios!I201 -> 3218.457
A15: Interest Expense | B15: ='Income Statement'!B22 -> 15000 | C15: ='Income Statement'!C22 -> 14000 | D15: ='Income Statement'!D22 -> 13000 | E15: =(D45+E45)/2*Scenarios!E200 -> 13500 | F15: =(E45+F45)/2*Scenarios!F200 -> 12500 | G15: =(F45+G45)/2*Scenarios!G200 -> 11500 | H15: =(G45+H45)/2*Scenarios!H200 -> 10500 | I15: =(H45+I45)/2*Scenarios!I200 -> 9500
A16: Other Income/Expense | B16: ='Income Statement'!B23 -> 0 | C16: ='Income Statement'!C23 -> 0 | D16: ='Income Statement'!D23 -> 0 | E16: =Scenarios!E185 -> 0 | F16: =Scenarios!F185 -> 0 | G16: =Scenarios!G185 -> 0 | H16: =Scenarios!H185 -> 0 | I16: =Scenarios!I185 -> 0
A17: EBT | B17: =B13+B14-B15+B16 -> 92000 | C17: =C13+C14-C15+C16 -> 108500 | D17: =D13+D14-D15+D16 -> 124000 | E17: =E13+E14-E15+E16 -> 32444.316 | F17: =F13+F14-F15+F16 -> 10495.759 | G17: =G13+G14-G15+G16 -> -2253.695 | H17: =H13+H14-H15+H16 -> -16193.514 | I17: =I13+I14-I15+I16 -> -30567.152
A18: Tax Expense | B18: ='Income Statement'!B25 -> 23125 | C18: ='Income Statement'!C25 -> 27375 | D18: ='Income Statement'!D25 -> 31250 | E18: =MAX(0,E17*Scenarios!E184) -> 7299.9712 | F18: =MAX(0,F17*Scenarios!F184) -> 2361.5458 | G18: =MAX(0,G17*Scenarios!G184) -> 0 | H18: =MAX(0,H17*Scenarios!H184) -> 0 | I18: =MAX(0,I17*Scenarios!I184) -> 0
A19: Net Income | B19: =B17-B18 -> 68875 | C19: =C17-C18 -> 81125 | D19: =D17-D18 -> 92750 | E19: =E17-E18 -> 25144.345 | F19: =F17-F18 -> 8134.2135 | G19: =G17-G18 -> -2253.695 | H19: =H17-H18 -> -16193.514 | I19: =I17-I18 -> -30567.152
A20: ── Balance Sheet ──
A21: Cash & Equivalents | B21: ='Balance Sheet'!B3 -> 150000 | C21: ='Balance Sheet'!C3 -> 175000 | D21: ='Balance Sheet'!D3 -> 200000 | E21: =D21+E73+E78+E85 -> 204056.65 | F21: =E21+F73+F78+F85 -> 199726.78 | G21: =F21+G73+G78+G85 -> 191476.77 | H21: =G21+H73+H78+H85 -> 174255.18 | I21: =H21+I73+I78+I85 -> 147590.52
A22: Accounts Receivable | B22: ='Balance Sheet'!B4 -> 92466 | C22: ='Balance Sheet'!C4 -> 104795 | D22: ='Balance Sheet'!D4 -> 117123 | E22: =E2*Scenarios!E189/365 -> 120636.99 | F22: =F2*Scenarios!F189/365 -> 123049.73 | G22: =G2*Scenarios!G189/365 -> 125510.72 | H22: =H2*Scenarios!H189/365 -> 126765.83 | I22: =I2*Scenarios!I189/365 -> 128033.49
A23: Inventory | B23: ='Balance Sheet'!B5 -> 36986 | C23: ='Balance Sheet'!C5 -> 41918 | D23: ='Balance Sheet'!D5 -> 46849 | E23: =E4*Scenarios!E190/365 -> 52276.027 | F23: =F4*Scenarios!F190/365 -> 54141.879 | G23: =G4*Scenarios!G190/365 -> 56061.455 | H23: =H4*Scenarios!H190/365 -> 56622.07 | I23: =I4*Scenarios!I190/365 -> 58041.847
A24: Prepaid Expenses | B24: ='Balance Sheet'!B6 -> 7500 | C24: ='Balance Sheet'!C6 -> 8500 | D24: ='Balance Sheet'!D6 -> 9500 | E24: =E2*Scenarios!E192 -> 9785 | F24: =F2*Scenarios!F192 -> 9980.7 | G24: =G2*Scenarios!G192 -> 10180.314 | H24: =H2*Scenarios!H192 -> 10282.117 | I24: =I2*Scenarios!I192 -> 10384.938
A25: Other Current Assets | B25: ='Balance Sheet'!B7 -> 10000 | C25: ='Balance Sheet'!C7 -> 10000 | D25: ='Balance Sheet'!D7 -> 10000 | E25: =Scenarios!E211 -> 10000 | F25: =Scenarios!F211 -> 10000 | G25: =Scenarios!G211 -> 10000 | H25: =Scenarios!H211 -> 10000 | I25: =Scenarios!I211 -> 10000
A26: Total Current Assets | B26: =SUM(B21:B25) -> 296952 | C26: =SUM(C21:C25) -> 340213 | D26: =SUM(D21:D25) -> 383472 | E26: =SUM(E21:E25) -> 396754.66 | F26: =SUM(F21:F25) -> 396899.09 | G26: =SUM(G21:G25) -> 393229.26 | H26: =SUM(H21:H25) -> 377925.19 | I26: =SUM(I21:I25) -> 354050.79
A28: Gross PP&E | B28: ='Balance Sheet'!B10 -> 300000 | C28: ='Balance Sheet'!C10 -> 340000 | D28: ='Balance Sheet'!D10 -> 385000 | E28: =D28+E2*Scenarios!E196 -> 433925 | F28: =E28+F2*Scenarios!F196 -> 483828.5 | G28: =F28+G2*Scenarios!G196 -> 534730.07 | H28: =G28+H2*Scenarios!H196 -> 586140.66 | I28: =H28+I2*Scenarios!I196 -> 638065.35
A29: Accumulated Depreciation | B29: ='Balance Sheet'!B11 -> 100000 | C29: ='Balance Sheet'!C11 -> 128000 | D29: ='Balance Sheet'!D11 -> 160000 | E29: =D29+E8 -> 200946.25 | F29: =E29+F8 -> 246833.92 | G29: =F29+G8 -> 297761.85 | H29: =G29+H8 -> 353805.39 | I29: =H29+I8 -> 415015.69
A30: Net PP&E | B30: =B28-B29 -> 200000 | C30: =C28-C29 -> 212000 | D30: =D28-D29 -> 225000 | E30: =E28-E29 -> 232978.75 | F30: =F28-F29 -> 236994.58 | G30: =G28-G29 -> 236968.22 | H30: =H28-H29 -> 232335.27 | I30: =I28-I29 -> 223049.66
A31: Intangibles | B31: ='Balance Sheet'!B13 -> 50000 | C31: ='Balance Sheet'!C13 -> 45000 | D31: ='Balance Sheet'!D13 -> 40000 | E31: =MAX(0,D31-E9) -> 35000 | F31: =MAX(0,E31-F9) -> 30000 | G31: =MAX(0,F31-G9) -> 25000 | H31: =MAX(0,G31-H9) -> 20000 | I31: =MAX(0,H31-I9) -> 15000
A32: Goodwill | B32: ='Balance Sheet'!B14 -> 100000 | C32: ='Balance Sheet'!C14 -> 100000 | D32: ='Balance Sheet'!D14 -> 100000 | E32: =Scenarios!E210 -> 100000 | F32: =Scenarios!F210 -> 100000 | G32: =Scenarios!G210 -> 100000 | H32: =Scenarios!H210 -> 100000 | I32: =Scenarios!I210 -> 100000
A33: Other LT Assets | B33: ='Balance Sheet'!B15 -> 20000 | C33: ='Balance Sheet'!C15 -> 20000 | D33: ='Balance Sheet'!D15 -> 20000 | E33: =Scenarios!E212 -> 20000 | F33: =Scenarios!F212 -> 20000 | G33: =Scenarios!G212 -> 20000 | H33: =Scenarios!H212 -> 20000 | I33: =Scenarios!I212 -> 20000
A34: Total Non-Current Assets | B34: =B30+B31+B32+B33 -> 370000 | C34: =C30+C31+C32+C33 -> 377000 | D34: =D30+D31+D32+D33 -> 385000 | E34: =E30+E31+E32+E33 -> 387978.75 | F34: =F30+F31+F32+F33 -> 386994.58 | G34: =G30+G31+G32+G33 -> 381968.22 | H34: =H30+H31+H32+H33 -> 372335.27 | I34: =I30+I31+I32+I33 -> 358049.66
A35: Total Assets | B35: =B26+B34 -> 666952 | C35: =C26+C34 -> 717213 | D35: =D26+D34 -> 768472 | E35: =E26+E34 -> 784733.41 | F35: =F26+F34 -> 783893.66 | G35: =G26+G34 -> 775197.47 | H35: =H26+H34 -> 750260.46 | I35: =I26+I34 -> 712100.45
A37: Accounts Payable | B37: ='Balance Sheet'!B20 -> 49315 | C37: ='Balance Sheet'!C20 -> 55890 | D37: ='Balance Sheet'!D20 -> 62466 | E37: =E4*Scenarios!E191/365 -> 69701.37 | F37: =F4*Scenarios!F191/365 -> 72189.173 | G37: =G4*Scenarios!G191/365 -> 74748.607 | H37: =H4*Scenarios!H191/365 -> 75496.093 | I37: =I4*Scenarios!I191/365 -> 77389.129
A38: Accrued Expenses | B38: ='Balance Sheet'!B21 -> 22500 | C38: ='Balance Sheet'!C21 -> 25500 | D38: ='Balance Sheet'!D21 -> 28500 | E38: =E2*Scenarios!E193 -> 29355 | F38: =F2*Scenarios!F193 -> 29942.1 | G38: =G2*Scenarios!G193 -> 30540.942 | H38: =H2*Scenarios!H193 -> 30846.351 | I38: =I2*Scenarios!I193 -> 31154.815
A39: Short-Term Debt | B39: ='Balance Sheet'!B22 -> 50000 | C39: ='Balance Sheet'!C22 -> 50000 | D39: ='Balance Sheet'!D22 -> 50000 | E39: =Scenarios!E202 -> 50000 | F39: =Scenarios!F202 -> 50000 | G39: =Scenarios!G202 -> 50000 | H39: =Scenarios!H202 -> 50000 | I39: =Scenarios!I202 -> 50000
A40: Current Portion LTD | B40: ='Balance Sheet'!B23 -> 20000 | C40: ='Balance Sheet'!C23 -> 20000 | D40: ='Balance Sheet'!D23 -> 20000 | E40: =Scenarios!E205 -> 20000 | F40: =Scenarios!F205 -> 20000 | G40: =Scenarios!G205 -> 20000 | H40: =Scenarios!H205 -> 20000 | I40: =Scenarios!I205 -> 20000
A41: Deferred Revenue | B41: ='Balance Sheet'!B24 -> 15000 | C41: ='Balance Sheet'!C24 -> 17000 | D41: ='Balance Sheet'!D24 -> 19000 | E41: =E2*Scenarios!E194 -> 19570 | F41: =F2*Scenarios!F194 -> 19961.4 | G41: =G2*Scenarios!G194 -> 20360.628 | H41: =H2*Scenarios!H194 -> 20564.234 | I41: =I2*Scenarios!I194 -> 20769.877
A42: Other Current Liabilities | B42: ='Balance Sheet'!B25 -> 15000 | C42: ='Balance Sheet'!C25 -> 15000 | D42: ='Balance Sheet'!D25 -> 15000 | E42: =Scenarios!E213 -> 15000 | F42: =Scenarios!F213 -> 15000 | G42: =Scenarios!G213 -> 15000 | H42: =Scenarios!H213 -> 15000 | I42: =Scenarios!I213 -> 15000
A43: Total Current Liabilities | B43: =SUM(B37:B42) -> 171815 | C43: =SUM(C37:C42) -> 183390 | D43: =SUM(D37:D42) -> 194966 | E43: =SUM(E37:E42) -> 203626.37 | F43: =SUM(F37:F42) -> 207092.67 | G43: =SUM(G37:G42) -> 210650.18 | H43: =SUM(H37:H42) -> 211906.68 | I43: =SUM(I37:I42) -> 214313.82
A45: Long-Term Debt | B45: ='Balance Sheet'!B28 -> 250000 | C45: ='Balance Sheet'!C28 -> 230000 | D45: ='Balance Sheet'!D28 -> 210000 | E45: =D45+Scenarios!E203-Scenarios!E204 -> 190000 | F45: =E45+Scenarios!F203-Scenarios!F204 -> 170000 | G45: =F45+Scenarios!G203-Scenarios!G204 -> 150000 | H45: =G45+Scenarios!H203-Scenarios!H204 -> 130000 | I45: =H45+Scenarios!I203-Scenarios!I204 -> 110000
A46: Deferred Tax Liabilities | B46: ='Balance Sheet'!B29 -> 30000 | C46: ='Balance Sheet'!C29 -> 30000 | D46: ='Balance Sheet'!D29 -> 30000 | E46: =Scenarios!E214 -> 30000 | F46: =Scenarios!F214 -> 30000 | G46: =Scenarios!G214 -> 30000 | H46: =Scenarios!H214 -> 30000 | I46: =Scenarios!I214 -> 30000
A47: Other LT Liabilities | B47: ='Balance Sheet'!B30 -> 25000 | C47: ='Balance Sheet'!C30 -> 25000 | D47: ='Balance Sheet'!D30 -> 25000 | E47: =Scenarios!E215 -> 25000 | F47: =Scenarios!F215 -> 25000 | G47: =Scenarios!G215 -> 25000 | H47: =Scenarios!H215 -> 25000 | I47: =Scenarios!I215 -> 25000
A48: Total Non-Current Liabilities | B48: =SUM(B45:B47) -> 305000 | C48: =SUM(C45:C47) -> 285000 | D48: =SUM(D45:D47) -> 265000 | E48: =SUM(E45:E47) -> 245000 | F48: =SUM(F45:F47) -> 225000 | G48: =SUM(G45:G47) -> 205000 | H48: =SUM(H45:H47) -> 185000 | I48: =SUM(I45:I47) -> 165000
A49: Total Liabilities | B49: =B43+B48 -> 476815 | C49: =C43+C48 -> 468390 | D49: =D43+D48 -> 459966 | E49: =E43+E48 -> 448626.37 | F49: =F43+F48 -> 432092.67 | G49: =G43+G48 -> 415650.18 | H49: =H43+H48 -> 396906.68 | I49: =I43+I48 -> 379313.82
A51: Common Stock | B51: ='Balance Sheet'!B35 -> 10000 | C51: ='Balance Sheet'!C35 -> 10000 | D51: ='Balance Sheet'!D35 -> 10000 | E51: =Scenarios!E216 -> 10000 | F51: =Scenarios!F216 -> 10000 | G51: =Scenarios!G216 -> 10000 | H51: =Scenarios!H216 -> 10000 | I51: =Scenarios!I216 -> 10000
A52: APIC | B52: ='Balance Sheet'!B36 -> 200000 | C52: ='Balance Sheet'!C36 -> 210000 | D52: ='Balance Sheet'!D36 -> 220000 | E52: =D52+Scenarios!E208+Scenarios!E187 -> 230000 | F52: =E52+Scenarios!F208+Scenarios!F187 -> 240000 | G52: =F52+Scenarios!G208+Scenarios!G187 -> 250000 | H52: =G52+Scenarios!H208+Scenarios!H187 -> 260000 | I52: =H52+Scenarios!I208+Scenarios!I187 -> 270000
A53: Retained Earnings | B53: ='Balance Sheet'!B37 -> -19863 | C53: ='Balance Sheet'!C37 -> 28823 | D53: ='Balance Sheet'!D37 -> 78506 | E53: =D53+E19-MAX(0,E19*Scenarios!E206) -> 96107.042 | F53: =E53+F19-MAX(0,F19*Scenarios!F206) -> 101800.99 | G53: =F53+G19-MAX(0,G19*Scenarios!G206) -> 99547.296 | H53: =G53+H19-MAX(0,H19*Scenarios!H206) -> 83353.782 | I53: =H53+I19-MAX(0,I19*Scenarios!I206) -> 52786.631
A54: Treasury Stock | B54: ='Balance Sheet'!B38 -> 0 | C54: ='Balance Sheet'!C38 -> 0 | D54: ='Balance Sheet'!D38 -> 0 | E54: =D54-Scenarios!E207 -> 0 | F54: =E54-Scenarios!F207 -> 0 | G54: =F54-Scenarios!G207 -> 0 | H54: =G54-Scenarios!H207 -> 0 | I54: =H54-Scenarios!I207 -> 0
A55: Other Comprehensive Income | B55: ='Balance Sheet'!B39 -> 0 | C55: ='Balance Sheet'!C39 -> 0 | D55: ='Balance Sheet'!D39 -> 0 | E55: =Scenarios!E218 -> 0 | F55: =Scenarios!F218 -> 0 | G55: =Scenarios!G218 -> 0 | H55: =Scenarios!H218 -> 0 | I55: =Scenarios!I218 -> 0
A56: Total Equity | B56: =SUM(B51:B55) -> 190137 | C56: =SUM(C51:C55) -> 248823 | D56: =SUM(D51:D55) -> 308506 | E56: =SUM(E51:E55) -> 336107.04 | F56: =SUM(F51:F55) -> 351800.99 | G56: =SUM(G51:G55) -> 359547.3 | H56: =SUM(H51:H55) -> 353353.78 | I56: =SUM(I51:I55) -> 332786.63
A58: Total Liabilities + Equity | B58: =B49+B56 -> 666952 | C58: =C49+C56 -> 717213 | D58: =D49+D56 -> 768472 | E58: =E49+E56 -> 784733.41 | F58: =F49+F56 -> 783893.66 | G58: =G49+G56 -> 775197.47 | H58: =H49+H56 -> 750260.46 | I58: =I49+I56 -> 712100.45
A59: Balance Check (TA - TLE) | B59: =B35-B58 -> 0 | C59: =C35-C58 -> 0 | D59: =D35-D58 -> 0 | E59: =E35-E58 -> 0 | F59: =F35-F58 -> 0 | G59: =G35-G58 -> 0 | H59: =H35-H58 -> 0 | I59: =I35-I58 -> 0
A60: ── Cash Flow ──
A61: Net Income | C61: =C19 -> 81125 | D61: =D19 -> 92750 | E61: =E19 -> 25144.345 | F61: =F19 -> 8134.2135 | G61: =G19 -> -2253.695 | H61: =H19 -> -16193.514 | I61: =I19 -> -30567.152
A62: + Depreciation | C62: =C8 -> 28000 | D62: =D8 -> 32000 | E62: =E8 -> 40946.25 | F62: =F8 -> 45887.675 | G62: =G8 -> 50927.929 | H62: =H8 -> 56043.536 | I62: =I8 -> 61210.3
A63: + Amortization | C63: =C9 -> 5000 | D63: =D9 -> 5000 | E63: =E9 -> 5000 | F63: =F9 -> 5000 | G63: =G9 -> 5000 | H63: =H9 -> 5000 | I63: =I9 -> 5000
A64: + SBC | C64: =C11 -> 0 | D64: =D11 -> 0 | E64: =E11 -> 10000 | F64: =F11 -> 10000 | G64: =G11 -> 10000 | H64: =H11 -> 10000 | I64: =I11 -> 10000
A65: Deferred Taxes | C65: =C46-B46 -> 0 | D65: =D46-C46 -> 0 | E65: =E46-D46 -> 0 | F65: =F46-E46 -> 0 | G65: =G46-F46 -> 0 | H65: =H46-G46 -> 0 | I65: =I46-H46 -> 0
A66: Δ A/R | C66: =-(C22-B22) -> -12329 | D66: =-(D22-C22) -> -12328 | E66: =-(E22-D22) -> -3513.9863 | F66: =-(F22-E22) -> -2412.7397 | G66: =-(G22-F22) -> -2460.9945 | H66: =-(H22-G22) -> -1255.1072 | I66: =-(I22-H22) -> -1267.6583
A67: Δ Inventory | C67: =-(C23-B23) -> -4932 | D67: =-(D23-C23) -> -4931 | E67: =-(E23-D23) -> -5427.0274 | F67: =-(F23-E23) -> -1865.8521 | G67: =-(G23-F23) -> -1919.5757 | H67: =-(H23-G23) -> -560.61455 | I67: =-(I23-H23) -> -1419.7773
A68: Δ Prepaid | C68: =-(C24-B24) -> -1000 | D68: =-(D24-C24) -> -1000 | E68: =-(E24-D24) -> -285 | F68: =-(F24-E24) -> -195.7 | G68: =-(G24-F24) -> -199.614 | H68: =-(H24-G24) -> -101.80314 | I68: =-(I24-H24) -> -102.82117
A69: Δ A/P | C69: =C37-B37 -> 6575 | D69: =D37-C37 -> 6576 | E69: =E37-D37 -> 7235.3699 | F69: =F37-E37 -> 2487.8027 | G69: =G37-F37 -> 2559.4343 | H69: =H37-G37 -> 747.48607 | I69: =I37-H37 -> 1893.0364
A70: Δ Accrued Exp | C70: =C38-B38 -> 3000 | D70: =D38-C38 -> 3000 | E70: =E38-D38 -> 855 | F70: =F38-E38 -> 587.1 | G70: =G38-F38 -> 598.842 | H70: =H38-G38 -> 305.40942 | I70: =I38-H38 -> 308.46351
A71: Δ Deferred Revenue | C71: =C41-B41 -> 2000 | D71: =D41-C41 -> 2000 | E71: =E41-D41 -> 570 | F71: =F41-E41 -> 391.4 | G71: =G41-F41 -> 399.228 | H71: =H41-G41 -> 203.60628 | I71: =I41-H41 -> 205.64234
A72: Total WC Change | C72: =SUM(C66:C71) -> -6686 | D72: =SUM(D66:D71) -> -6683 | E72: =SUM(E66:E71) -> -565.64384 | F72: =SUM(F66:F71) -> -1007.989 | G72: =SUM(G66:G71) -> -1022.6799 | H72: =SUM(H66:H71) -> -661.02313 | I72: =SUM(I66:I71) -> -383.1145
A73: Cash from Operations | C73: =C61+C62+C63+C64+C65+C72 -> 107439 | D73: =D61+D62+D63+D64+D65+D72 -> 123067 | E73: =E61+E62+E63+E64+E65+E72 -> 80524.951 | F73: =F61+F62+F63+F64+F65+F72 -> 68013.899 | G73: =G61+G62+G63+G64+G65+G72 -> 62651.554 | H73: =H61+H62+H63+H64+H65+H72 -> 54188.999 | I73: =I61+I62+I63+I64+I65+I72 -> 45260.034
A75: Capital Expenditures | C75: =-ABS(C2*Scenarios!C196) -> -40000 | D75: =-ABS(D2*Scenarios!D196) -> -45000 | E75: =-ABS(E2*Scenarios!E196) -> -48925 | F75: =-ABS(F2*Scenarios!F196) -> -49903.5 | G75: =-ABS(G2*Scenarios!G196) -> -50901.57 | H75: =-ABS(H2*Scenarios!H196) -> -51410.586 | I75: =-ABS(I2*Scenarios!I196) -> -51924.692
A76: Acquisitions | C76: =Scenarios!C234 -> 0 | D76: =Scenarios!D234 -> 0 | E76: =0 -> 0 | F76: =0 -> 0 | G76: =0 -> 0 | H76: =0 -> 0 | I76: =0 -> 0
A77: Asset Sales | C77: =Scenarios!C235 -> 0 | D77: =Scenarios!D235 -> 0 | E77: =0 -> 0 | F77: =0 -> 0 | G77: =0 -> 0 | H77: =0 -> 0 | I77: =0 -> 0
A78: Cash from Investing | C78: =C75+C76+C77 -> -40000 | D78: =D75+D76+D77 -> -45000 | E78: =E75+E76+E77 -> -48925 | F78: =F75+F76+F77 -> -49903.5 | G78: =G75+G76+G77 -> -50901.57 | H78: =H75+H76+H77 -> -51410.586 | I78: =I75+I76+I77 -> -51924.692
A80: Debt Issuance | C80: =Scenarios!C203 -> 0 | D80: =Scenarios!D203 -> 0 | E80: =Scenarios!E203 -> 0 | F80: =Scenarios!F203 -> 0 | G80: =Scenarios!G203 -> 0 | H80: =Scenarios!H203 -> 0 | I80: =Scenarios!I203 -> 0
A81: Debt Repayment | C81: =-ABS(Scenarios!C204) -> -20000 | D81: =-ABS(Scenarios!D204) -> -20000 | E81: =-ABS(Scenarios!E204) -> -20000 | F81: =-ABS(Scenarios!F204) -> -20000 | G81: =-ABS(Scenarios!G204) -> -20000 | H81: =-ABS(Scenarios!H204) -> -20000 | I81: =-ABS(Scenarios!I204) -> -20000
A82: Dividends Paid | C82: =Scenarios!C231 -> -32439 | D82: =Scenarios!D231 -> -43067 | E82: =-MAX(0,E19*Scenarios!E206) -> -7543.3036 | F82: =-MAX(0,F19*Scenarios!F206) -> -2440.264 | G82: =-MAX(0,G19*Scenarios!G206) -> 0 | H82: =-MAX(0,H19*Scenarios!H206) -> 0 | I82: =-MAX(0,I19*Scenarios!I206) -> 0
A83: Equity Issuance | C83: =Scenarios!C232 -> 10000 | D83: =Scenarios!D232 -> 10000 | E83: =Scenarios!E208 -> 0 | F83: =Scenarios!F208 -> 0 | G83: =Scenarios!G208 -> 0 | H83: =Scenarios!H208 -> 0 | I83: =Scenarios!I208 -> 0
A84: Share Repurchases | C84: =Scenarios!C233 -> 0 | D84: =Scenarios!D233 -> 0 | E84: =-ABS(Scenarios!E207) -> 0 | F84: =-ABS(Scenarios!F207) -> 0 | G84: =-ABS(Scenarios!G207) -> 0 | H84: =-ABS(Scenarios!H207) -> 0 | I84: =-ABS(Scenarios!I207) -> 0
A85: Cash from Financing | C85: =C80+C81+C82+C83+C84 -> -42439 | D85: =D80+D81+D82+D83+D84 -> -53067 | E85: =E80+E81+E82+E83+E84 -> -27543.304 | F85: =F80+F81+F82+F83+F84 -> -22440.264 | G85: =G80+G81+G82+G83+G84 -> -20000 | H85: =H80+H81+H82+H83+H84 -> -20000 | I85: =I80+I81+I82+I83+I84 -> -20000
A87: Net Change in Cash | C87: =C73+C78+C85 -> 25000 | D87: =D73+D78+D85 -> 25000 | E87: =E73+E78+E85 -> 4056.6479 | F87: =F73+F78+F85 -> -4329.8646 | G87: =G73+G78+G85 -> -8250.0165 | H87: =H73+H78+H85 -> -17221.587 | I87: =I73+I78+I85 -> -26664.657
A88: Beginning Cash | C88: =B21 -> 150000 | D88: =C21 -> 175000 | E88: =D21 -> 200000 | F88: =E21 -> 204056.65 | G88: =F21 -> 199726.78 | H88: =G21 -> 191476.77 | I88: =H21 -> 174255.18
A89: Ending Cash | C89: =C88+C87 -> 175000 | D89: =D88+D87 -> 200000 | E89: =E88+E87 -> 204056.65 | F89: =F88+F87 -> 199726.78 | G89: =G88+G87 -> 191476.77 | H89: =H88+H87 -> 174255.18 | I89: =I88+I87 -> 147590.52
